machinery.pyc (Python 3.10)
[Code]
    File Name: importlib/machinery.py
    Object Name: <module>
    Arg Count: 0
    Pos Only Arg Count: 0
    KW Only Arg Count: 0
    Locals: 0
    Stack Size: 2
    Flags: 0x00000040 (CO_NOFREE)
    [Names]
        '__doc__'
        '_bootstrap'
        'ModuleSpec'
        'BuiltinImporter'
        'FrozenImporter'
        '_bootstrap_external'
        'SOURCE_SUFFIXES'
        'DEBUG_BYTECODE_SUFFIXES'
        'OPTIMIZED_BYTECODE_SUFFIXES'
        'BYTECODE_SUFFIXES'
        'EXTENSION_SUFFIXES'
        'WindowsRegistryFinder'
        'PathFinder'
        'FileFinder'
        'SourceFileLoader'
        'SourcelessFileLoader'
        'ExtensionFileLoader'
        'all_suffixes'
    [Var Names]
    [Free Vars]
    [Cell Vars]
    [Constants]
        'The machinery of importlib: finders, loaders, hooks, etc.'
        1
        (
            'ModuleSpec'
        )
        (
            'BuiltinImporter'
        )
        (
            'FrozenImporter'
        )
        (
            'SOURCE_SUFFIXES'
            'DEBUG_BYTECODE_SUFFIXES'
            'OPTIMIZED_BYTECODE_SUFFIXES'
            'BYTECODE_SUFFIXES'
            'EXTENSION_SUFFIXES'
        )
        (
            'WindowsRegistryFinder'
        )
        (
            'PathFinder'
        )
        (
            'FileFinder'
        )
        (
            'SourceFileLoader'
        )
        (
            'SourcelessFileLoader'
        )
        (
            'ExtensionFileLoader'
        )
        [Code]
            File Name: importlib/machinery.py
            Object Name: all_suffixes
            Arg Count: 0
            Pos Only Arg Count: 0
            KW Only Arg Count: 0
            Locals: 0
            Stack Size: 2
            Flags: 0x00000043 (CO_OPTIMIZED | CO_NEWLOCALS | CO_NOFREE)
            [Names]
                'SOURCE_SUFFIXES'
                'BYTECODE_SUFFIXES'
                'EXTENSION_SUFFIXES'
            [Var Names]
            [Free Vars]
            [Cell Vars]
            [Constants]
                'Returns a list of all recognized module suffixes for this process'
            [Disassembly]
                0       LOAD_GLOBAL                     0: SOURCE_SUFFIXES
                2       LOAD_GLOBAL                     1: BYTECODE_SUFFIXES
                4       BINARY_ADD                      
                6       LOAD_GLOBAL                     2: EXTENSION_SUFFIXES
                8       BINARY_ADD                      
                10      RETURN_VALUE                    
        'all_suffixes'
        None
    [Disassembly]
        0       LOAD_CONST                      0: 'The machinery of importlib: finders, loaders, hooks, etc.'
        2       STORE_NAME                      0: __doc__
        4       LOAD_CONST                      1: 1
        6       LOAD_CONST                      2: ('ModuleSpec',)
        8       IMPORT_NAME                     1: _bootstrap
        10      IMPORT_FROM                     2: ModuleSpec
        12      STORE_NAME                      2: ModuleSpec
        14      POP_TOP                         
        16      LOAD_CONST                      1: 1
        18      LOAD_CONST                      3: ('BuiltinImporter',)
        20      IMPORT_NAME                     1: _bootstrap
        22      IMPORT_FROM                     3: BuiltinImporter
        24      STORE_NAME                      3: BuiltinImporter
        26      POP_TOP                         
        28      LOAD_CONST                      1: 1
        30      LOAD_CONST                      4: ('FrozenImporter',)
        32      IMPORT_NAME                     1: _bootstrap
        34      IMPORT_FROM                     4: FrozenImporter
        36      STORE_NAME                      4: FrozenImporter
        38      POP_TOP                         
        40      LOAD_CONST                      1: 1
        42      LOAD_CONST                      5: ('SOURCE_SUFFIXES', 'DEBUG_BYTECODE_SUFFIXES', 'OPTIMIZED_BYTECODE_SUFFIXES', 'BYTECODE_SUFFIXES', 'EXTENSION_SUFFIXES')
        44      IMPORT_NAME                     5: _bootstrap_external
        46      IMPORT_FROM                     6: SOURCE_SUFFIXES
        48      STORE_NAME                      6: SOURCE_SUFFIXES
        50      IMPORT_FROM                     7: DEBUG_BYTECODE_SUFFIXES
        52      STORE_NAME                      7: DEBUG_BYTECODE_SUFFIXES
        54      IMPORT_FROM                     8: OPTIMIZED_BYTECODE_SUFFIXES
        56      STORE_NAME                      8: OPTIMIZED_BYTECODE_SUFFIXES
        58      IMPORT_FROM                     9: BYTECODE_SUFFIXES
        60      STORE_NAME                      9: BYTECODE_SUFFIXES
        62      IMPORT_FROM                     10: EXTENSION_SUFFIXES
        64      STORE_NAME                      10: EXTENSION_SUFFIXES
        66      POP_TOP                         
        68      LOAD_CONST                      1: 1
        70      LOAD_CONST                      6: ('WindowsRegistryFinder',)
        72      IMPORT_NAME                     5: _bootstrap_external
        74      IMPORT_FROM                     11: WindowsRegistryFinder
        76      STORE_NAME                      11: WindowsRegistryFinder
        78      POP_TOP                         
        80      LOAD_CONST                      1: 1
        82      LOAD_CONST                      7: ('PathFinder',)
        84      IMPORT_NAME                     5: _bootstrap_external
        86      IMPORT_FROM                     12: PathFinder
        88      STORE_NAME                      12: PathFinder
        90      POP_TOP                         
        92      LOAD_CONST                      1: 1
        94      LOAD_CONST                      8: ('FileFinder',)
        96      IMPORT_NAME                     5: _bootstrap_external
        98      IMPORT_FROM                     13: FileFinder
        100     STORE_NAME                      13: FileFinder
        102     POP_TOP                         
        104     LOAD_CONST                      1: 1
        106     LOAD_CONST                      9: ('SourceFileLoader',)
        108     IMPORT_NAME                     5: _bootstrap_external
        110     IMPORT_FROM                     14: SourceFileLoader
        112     STORE_NAME                      14: SourceFileLoader
        114     POP_TOP                         
        116     LOAD_CONST                      1: 1
        118     LOAD_CONST                      10: ('SourcelessFileLoader',)
        120     IMPORT_NAME                     5: _bootstrap_external
        122     IMPORT_FROM                     15: SourcelessFileLoader
        124     STORE_NAME                      15: SourcelessFileLoader
        126     POP_TOP                         
        128     LOAD_CONST                      1: 1
        130     LOAD_CONST                      11: ('ExtensionFileLoader',)
        132     IMPORT_NAME                     5: _bootstrap_external
        134     IMPORT_FROM                     16: ExtensionFileLoader
        136     STORE_NAME                      16: ExtensionFileLoader
        138     POP_TOP                         
        140     LOAD_CONST                      12: <CODE> all_suffixes
        142     LOAD_CONST                      13: 'all_suffixes'
        144     MAKE_FUNCTION                   0
        146     STORE_NAME                      17: all_suffixes
        148     LOAD_CONST                      14: None
        150     RETURN_VALUE                    
