gzip.pyc (Python 3.10)
[Code]
    File Name: gzip.py
    Object Name: <module>
    Arg Count: 0
    Pos Only Arg Count: 0
    KW Only Arg Count: 0
    Locals: 0
    Stack Size: 5
    Flags: 0x00000040 (CO_NOFREE)
    [Names]
        '__doc__'
        'struct'
        'sys'
        'time'
        'os'
        'zlib'
        'builtins'
        'io'
        '_compression'
        '__all__'
        'FTEXT'
        'FHCRC'
        'FEXTRA'
        'FNAME'
        'FCOMMENT'
        'READ'
        'WRITE'
        '_COMPRESS_LEVEL_FAST'
        '_COMPRESS_LEVEL_TRADEOFF'
        '_COMPRESS_LEVEL_BEST'
        'open'
        'write32u'
        '_PaddedFile'
        'OSError'
        'BadGzipFile'
        'BaseStream'
        'GzipFile'
        'DecompressReader'
        '_GzipReader'
        'compress'
        'decompress'
        'main'
        '__name__'
    [Var Names]
    [Free Vars]
    [Cell Vars]
    [Constants]
        "Functions that read and write gzipped files.\n\nThe user of the file doesn't have to worry about the compression,\nbut random access is not allowed."
        0
        None
        (
            'BadGzipFile'
            'GzipFile'
            'open'
            'compress'
            'decompress'
        )
        (
            1
            2
            4
            8
            16
        )
        (
            1
            2
        )
        1
        6
        9
        'rb'
        [Code]
            File Name: gzip.py
            Object Name: open
            Arg Count: 6
            Pos Only Arg Count: 0
            KW Only Arg Count: 0
            Locals: 8
            Stack Size: 6
            Flags: 0x00000043 (CO_OPTIMIZED | CO_NEWLOCALS | CO_NOFREE)
            [Names]
                'ValueError'
                'replace'
                'isinstance'
                'str'
                'bytes'
                'os'
                'PathLike'
                'GzipFile'
                'hasattr'
                'TypeError'
                'io'
                'text_encoding'
                'TextIOWrapper'
            [Var Names]
                'filename'
                'mode'
                'compresslevel'
                'encoding'
                'errors'
                'newline'
                'gz_mode'
                'binary_file'
            [Free Vars]
            [Cell Vars]
            [Constants]
                'Open a gzip-compressed file in binary or text mode.\n\n    The filename argument can be an actual filename (a str or bytes object), or\n    an existing file object to read from or write to.\n\n    The mode argument can be "r", "rb", "w", "wb", "x", "xb", "a" or "ab" for\n    binary mode, or "rt", "wt", "xt" or "at" for text mode. The default mode is\n    "rb", and the default compresslevel is 9.\n\n    For binary mode, this function is equivalent to the GzipFile constructor:\n    GzipFile(filename, mode, compresslevel). In this case, the encoding, errors\n    and newline arguments must not be provided.\n\n    For text mode, a GzipFile object is created, and wrapped in an\n    io.TextIOWrapper instance with the specified encoding, error handling\n    behavior, and line ending(s).\n\n    '
                't'
                'b'
                'Invalid mode: %r'
                None
                "Argument 'encoding' not supported in binary mode"
                "Argument 'errors' not supported in binary mode"
                "Argument 'newline' not supported in binary mode"
                ''
                'read'
                'write'
                'filename must be a str or bytes object, or a file'
            [Disassembly]
                0       LOAD_CONST                      1: 't'
                2       LOAD_FAST                       1: mode
                4       CONTAINS_OP                     0 (in)
                6       POP_JUMP_IF_FALSE               16 (to 32)
                8       LOAD_CONST                      2: 'b'
                10      LOAD_FAST                       1: mode
                12      CONTAINS_OP                     0 (in)
                14      POP_JUMP_IF_FALSE               15 (to 30)
                16      LOAD_GLOBAL                     0: ValueError
                18      LOAD_CONST                      3: 'Invalid mode: %r'
                20      LOAD_FAST                       1: mode
                22      BUILD_TUPLE                     1
                24      BINARY_MODULO                   
                26      CALL_FUNCTION                   1
                28      RAISE_VARARGS                   1
                30      JUMP_FORWARD                    24 (to 80)
                32      LOAD_FAST                       3: encoding
                34      LOAD_CONST                      4: None
                36      IS_OP                           1 (is not)
                38      POP_JUMP_IF_FALSE               24 (to 48)
                40      LOAD_GLOBAL                     0: ValueError
                42      LOAD_CONST                      5: "Argument 'encoding' not supported in binary mode"
                44      CALL_FUNCTION                   1
                46      RAISE_VARARGS                   1
                48      LOAD_FAST                       4: errors
                50      LOAD_CONST                      4: None
                52      IS_OP                           1 (is not)
                54      POP_JUMP_IF_FALSE               32 (to 64)
                56      LOAD_GLOBAL                     0: ValueError
                58      LOAD_CONST                      6: "Argument 'errors' not supported in binary mode"
                60      CALL_FUNCTION                   1
                62      RAISE_VARARGS                   1
                64      LOAD_FAST                       5: newline
                66      LOAD_CONST                      4: None
                68      IS_OP                           1 (is not)
                70      POP_JUMP_IF_FALSE               40 (to 80)
                72      LOAD_GLOBAL                     0: ValueError
                74      LOAD_CONST                      7: "Argument 'newline' not supported in binary mode"
                76      CALL_FUNCTION                   1
                78      RAISE_VARARGS                   1
                80      LOAD_FAST                       1: mode
                82      LOAD_METHOD                     1: replace
                84      LOAD_CONST                      1: 't'
                86      LOAD_CONST                      8: ''
                88      CALL_METHOD                     2
                90      STORE_FAST                      6: gz_mode
                92      LOAD_GLOBAL                     2: isinstance
                94      LOAD_FAST                       0: filename
                96      LOAD_GLOBAL                     3: str
                98      LOAD_GLOBAL                     4: bytes
                100     LOAD_GLOBAL                     5: os
                102     LOAD_ATTR                       6: PathLike
                104     BUILD_TUPLE                     3
                106     CALL_FUNCTION                   2
                108     POP_JUMP_IF_FALSE               62 (to 124)
                110     LOAD_GLOBAL                     7: GzipFile
                112     LOAD_FAST                       0: filename
                114     LOAD_FAST                       6: gz_mode
                116     LOAD_FAST                       2: compresslevel
                118     CALL_FUNCTION                   3
                120     STORE_FAST                      7: binary_file
                122     JUMP_FORWARD                    22 (to 168)
                124     LOAD_GLOBAL                     8: hasattr
                126     LOAD_FAST                       0: filename
                128     LOAD_CONST                      9: 'read'
                130     CALL_FUNCTION                   2
                132     POP_JUMP_IF_TRUE                72 (to 144)
                134     LOAD_GLOBAL                     8: hasattr
                136     LOAD_FAST                       0: filename
                138     LOAD_CONST                      10: 'write'
                140     CALL_FUNCTION                   2
                142     POP_JUMP_IF_FALSE               80 (to 160)
                144     LOAD_GLOBAL                     7: GzipFile
                146     LOAD_CONST                      4: None
                148     LOAD_FAST                       6: gz_mode
                150     LOAD_FAST                       2: compresslevel
                152     LOAD_FAST                       0: filename
                154     CALL_FUNCTION                   4
                156     STORE_FAST                      7: binary_file
                158     JUMP_FORWARD                    4 (to 168)
                160     LOAD_GLOBAL                     9: TypeError
                162     LOAD_CONST                      11: 'filename must be a str or bytes object, or a file'
                164     CALL_FUNCTION                   1
                166     RAISE_VARARGS                   1
                168     LOAD_CONST                      1: 't'
                170     LOAD_FAST                       1: mode
                172     CONTAINS_OP                     0 (in)
                174     POP_JUMP_IF_FALSE               101 (to 202)
                176     LOAD_GLOBAL                     10: io
                178     LOAD_METHOD                     11: text_encoding
                180     LOAD_FAST                       3: encoding
                182     CALL_METHOD                     1
                184     STORE_FAST                      3: encoding
                186     LOAD_GLOBAL                     10: io
                188     LOAD_METHOD                     12: TextIOWrapper
                190     LOAD_FAST                       7: binary_file
                192     LOAD_FAST                       3: encoding
                194     LOAD_FAST                       4: errors
                196     LOAD_FAST                       5: newline
                198     CALL_METHOD                     4
                200     RETURN_VALUE                    
                202     LOAD_FAST                       7: binary_file
                204     RETURN_VALUE                    
        'open'
        [Code]
            File Name: gzip.py
            Object Name: write32u
            Arg Count: 2
            Pos Only Arg Count: 0
            KW Only Arg Count: 0
            Locals: 2
            Stack Size: 6
            Flags: 0x00000043 (CO_OPTIMIZED | CO_NEWLOCALS | CO_NOFREE)
            [Names]
                'write'
                'struct'
                'pack'
            [Var Names]
                'output'
                'value'
            [Free Vars]
            [Cell Vars]
            [Constants]
                None
                '<L'
            [Disassembly]
                0       LOAD_FAST                       0: output
                2       LOAD_METHOD                     0: write
                4       LOAD_GLOBAL                     1: struct
                6       LOAD_METHOD                     2: pack
                8       LOAD_CONST                      1: '<L'
                10      LOAD_FAST                       1: value
                12      CALL_METHOD                     2
                14      CALL_METHOD                     1
                16      POP_TOP                         
                18      LOAD_CONST                      0: None
                20      RETURN_VALUE                    
        'write32u'
        [Code]
            File Name: gzip.py
            Object Name: _PaddedFile
            Arg Count: 0
            Pos Only Arg Count: 0
            KW Only Arg Count: 0
            Locals: 0
            Stack Size: 3
            Flags: 0x00000040 (CO_NOFREE)
            [Names]
                '__name__'
                '__module__'
                '__qualname__'
                '__doc__'
                '__init__'
                'read'
                'prepend'
                'seek'
                'seekable'
            [Var Names]
            [Free Vars]
            [Cell Vars]
            [Constants]
                '_PaddedFile'
                "Minimal read-only file object that prepends a string to the contents\n    of an actual file. Shouldn't be used outside of gzip.py, as it lacks\n    essential functionality."
                b''
                [Code]
                    File Name: gzip.py
                    Object Name: __init__
                    Arg Count: 3
                    Pos Only Arg Count: 0
                    KW Only Arg Count: 0
                    Locals: 3
                    Stack Size: 2
                    Flags: 0x00000043 (CO_OPTIMIZED | CO_NEWLOCALS | CO_NOFREE)
                    [Names]
                        '_buffer'
                        'len'
                        '_length'
                        'file'
                        '_read'
                    [Var Names]
                        'self'
                        'f'
                        'prepend'
                    [Free Vars]
                    [Cell Vars]
                    [Constants]
                        None
                        0
                    [Disassembly]
                        0       LOAD_FAST                       2: prepend
                        2       LOAD_FAST                       0: self
                        4       STORE_ATTR                      0: _buffer
                        6       LOAD_GLOBAL                     1: len
                        8       LOAD_FAST                       2: prepend
                        10      CALL_FUNCTION                   1
                        12      LOAD_FAST                       0: self
                        14      STORE_ATTR                      2: _length
                        16      LOAD_FAST                       1: f
                        18      LOAD_FAST                       0: self
                        20      STORE_ATTR                      3: file
                        22      LOAD_CONST                      1: 0
                        24      LOAD_FAST                       0: self
                        26      STORE_ATTR                      4: _read
                        28      LOAD_CONST                      0: None
                        30      RETURN_VALUE                    
                '_PaddedFile.__init__'
                [Code]
                    File Name: gzip.py
                    Object Name: read
                    Arg Count: 2
                    Pos Only Arg Count: 0
                    KW Only Arg Count: 0
                    Locals: 3
                    Stack Size: 5
                    Flags: 0x00000043 (CO_OPTIMIZED | CO_NEWLOCALS | CO_NOFREE)
                    [Names]
                        '_read'
                        'file'
                        'read'
                        '_length'
                        '_buffer'
                    [Var Names]
                        'self'
                        'size'
                        'read'
                    [Free Vars]
                    [Cell Vars]
                    [Constants]
                        None
                    [Disassembly]
                        0       LOAD_FAST                       0: self
                        2       LOAD_ATTR                       0: _read
                        4       LOAD_CONST                      0: None
                        6       IS_OP                           0 (is)
                        8       POP_JUMP_IF_FALSE               11 (to 22)
                        10      LOAD_FAST                       0: self
                        12      LOAD_ATTR                       1: file
                        14      LOAD_METHOD                     2: read
                        16      LOAD_FAST                       1: size
                        18      CALL_METHOD                     1
                        20      RETURN_VALUE                    
                        22      LOAD_FAST                       0: self
                        24      LOAD_ATTR                       0: _read
                        26      LOAD_FAST                       1: size
                        28      BINARY_ADD                      
                        30      LOAD_FAST                       0: self
                        32      LOAD_ATTR                       3: _length
                        34      COMPARE_OP                      1 (<=)
                        36      POP_JUMP_IF_FALSE               37 (to 74)
                        38      LOAD_FAST                       0: self
                        40      LOAD_ATTR                       0: _read
                        42      STORE_FAST                      2: read
                        44      LOAD_FAST                       0: self
                        46      DUP_TOP                         
                        48      LOAD_ATTR                       0: _read
                        50      LOAD_FAST                       1: size
                        52      INPLACE_ADD                     
                        54      ROT_TWO                         
                        56      STORE_ATTR                      0: _read
                        58      LOAD_FAST                       0: self
                        60      LOAD_ATTR                       4: _buffer
                        62      LOAD_FAST                       2: read
                        64      LOAD_FAST                       0: self
                        66      LOAD_ATTR                       0: _read
                        68      BUILD_SLICE                     2
                        70      BINARY_SUBSCR                   
                        72      RETURN_VALUE                    
                        74      LOAD_FAST                       0: self
                        76      LOAD_ATTR                       0: _read
                        78      STORE_FAST                      2: read
                        80      LOAD_CONST                      0: None
                        82      LOAD_FAST                       0: self
                        84      STORE_ATTR                      0: _read
                        86      LOAD_FAST                       0: self
                        88      LOAD_ATTR                       4: _buffer
                        90      LOAD_FAST                       2: read
                        92      LOAD_CONST                      0: None
                        94      BUILD_SLICE                     2
                        96      BINARY_SUBSCR                   
                        98      LOAD_FAST                       0: self
                        100     LOAD_ATTR                       1: file
                        102     LOAD_METHOD                     2: read
                        104     LOAD_FAST                       1: size
                        106     LOAD_FAST                       0: self
                        108     LOAD_ATTR                       3: _length
                        110     BINARY_SUBTRACT                 
                        112     LOAD_FAST                       2: read
                        114     BINARY_ADD                      
                        116     CALL_METHOD                     1
                        118     BINARY_ADD                      
                        120     RETURN_VALUE                    
                '_PaddedFile.read'
                [Code]
                    File Name: gzip.py
                    Object Name: prepend
                    Arg Count: 2
                    Pos Only Arg Count: 0
                    KW Only Arg Count: 0
                    Locals: 2
                    Stack Size: 4
                    Flags: 0x00000043 (CO_OPTIMIZED | CO_NEWLOCALS | CO_NOFREE)
                    [Names]
                        '_read'
                        '_buffer'
                        'len'
                        '_length'
                    [Var Names]
                        'self'
                        'prepend'
                    [Free Vars]
                    [Cell Vars]
                    [Constants]
                        None
                        0
                    [Disassembly]
                        0       LOAD_FAST                       0: self
                        2       LOAD_ATTR                       0: _read
                        4       LOAD_CONST                      0: None
                        6       IS_OP                           0 (is)
                        8       POP_JUMP_IF_FALSE               9 (to 18)
                        10      LOAD_FAST                       1: prepend
                        12      LOAD_FAST                       0: self
                        14      STORE_ATTR                      1: _buffer
                        16      JUMP_FORWARD                    11 (to 40)
                        18      LOAD_FAST                       0: self
                        20      DUP_TOP                         
                        22      LOAD_ATTR                       0: _read
                        24      LOAD_GLOBAL                     2: len
                        26      LOAD_FAST                       1: prepend
                        28      CALL_FUNCTION                   1
                        30      INPLACE_SUBTRACT                
                        32      ROT_TWO                         
                        34      STORE_ATTR                      0: _read
                        36      LOAD_CONST                      0: None
                        38      RETURN_VALUE                    
                        40      LOAD_GLOBAL                     2: len
                        42      LOAD_FAST                       0: self
                        44      LOAD_ATTR                       1: _buffer
                        46      CALL_FUNCTION                   1
                        48      LOAD_FAST                       0: self
                        50      STORE_ATTR                      3: _length
                        52      LOAD_CONST                      1: 0
                        54      LOAD_FAST                       0: self
                        56      STORE_ATTR                      0: _read
                        58      LOAD_CONST                      0: None
                        60      RETURN_VALUE                    
                '_PaddedFile.prepend'
                [Code]
                    File Name: gzip.py
                    Object Name: seek
                    Arg Count: 2
                    Pos Only Arg Count: 0
                    KW Only Arg Count: 0
                    Locals: 2
                    Stack Size: 3
                    Flags: 0x00000043 (CO_OPTIMIZED | CO_NEWLOCALS | CO_NOFREE)
                    [Names]
                        '_read'
                        '_buffer'
                        'file'
                        'seek'
                    [Var Names]
                        'self'
                        'off'
                    [Free Vars]
                    [Cell Vars]
                    [Constants]
                        None
                    [Disassembly]
                        0       LOAD_CONST                      0: None
                        2       LOAD_FAST                       0: self
                        4       STORE_ATTR                      0: _read
                        6       LOAD_CONST                      0: None
                        8       LOAD_FAST                       0: self
                        10      STORE_ATTR                      1: _buffer
                        12      LOAD_FAST                       0: self
                        14      LOAD_ATTR                       2: file
                        16      LOAD_METHOD                     3: seek
                        18      LOAD_FAST                       1: off
                        20      CALL_METHOD                     1
                        22      RETURN_VALUE                    
                '_PaddedFile.seek'
                [Code]
                    File Name: gzip.py
                    Object Name: seekable
                    Arg Count: 1
                    Pos Only Arg Count: 0
                    KW Only Arg Count: 0
                    Locals: 1
                    Stack Size: 1
                    Flags: 0x00000043 (CO_OPTIMIZED | CO_NEWLOCALS | CO_NOFREE)
                    [Names]
                    [Var Names]
                        'self'
                    [Free Vars]
                    [Cell Vars]
                    [Constants]
                        None
                        True
                    [Disassembly]
                        0       LOAD_CONST                      1: True
                        2       RETURN_VALUE                    
                '_PaddedFile.seekable'
                None
                (
                    b''
                )
            [Disassembly]
                0       LOAD_NAME                       0: __name__
                2       STORE_NAME                      1: __module__
                4       LOAD_CONST                      0: '_PaddedFile'
                6       STORE_NAME                      2: __qualname__
                8       LOAD_CONST                      1: "Minimal read-only file object that prepends a string to the contents\n    of an actual file. Shouldn't be used outside of gzip.py, as it lacks\n    essential functionality."
                10      STORE_NAME                      3: __doc__
                12      LOAD_CONST                      14: (b'',)
                14      LOAD_CONST                      3: <CODE> __init__
                16      LOAD_CONST                      4: '_PaddedFile.__init__'
                18      MAKE_FUNCTION                   1
                20      STORE_NAME                      4: __init__
                22      LOAD_CONST                      5: <CODE> read
                24      LOAD_CONST                      6: '_PaddedFile.read'
                26      MAKE_FUNCTION                   0
                28      STORE_NAME                      5: read
                30      LOAD_CONST                      14: (b'',)
                32      LOAD_CONST                      7: <CODE> prepend
                34      LOAD_CONST                      8: '_PaddedFile.prepend'
                36      MAKE_FUNCTION                   1
                38      STORE_NAME                      6: prepend
                40      LOAD_CONST                      9: <CODE> seek
                42      LOAD_CONST                      10: '_PaddedFile.seek'
                44      MAKE_FUNCTION                   0
                46      STORE_NAME                      7: seek
                48      LOAD_CONST                      11: <CODE> seekable
                50      LOAD_CONST                      12: '_PaddedFile.seekable'
                52      MAKE_FUNCTION                   0
                54      STORE_NAME                      8: seekable
                56      LOAD_CONST                      13: None
                58      RETURN_VALUE                    
        '_PaddedFile'
        [Code]
            File Name: gzip.py
            Object Name: BadGzipFile
            Arg Count: 0
            Pos Only Arg Count: 0
            KW Only Arg Count: 0
            Locals: 0
            Stack Size: 1
            Flags: 0x00000040 (CO_NOFREE)
            [Names]
                '__name__'
                '__module__'
                '__qualname__'
                '__doc__'
            [Var Names]
            [Free Vars]
            [Cell Vars]
            [Constants]
                'BadGzipFile'
                'Exception raised in some cases for invalid gzip files.'
                None
            [Disassembly]
                0       LOAD_NAME                       0: __name__
                2       STORE_NAME                      1: __module__
                4       LOAD_CONST                      0: 'BadGzipFile'
                6       STORE_NAME                      2: __qualname__
                8       LOAD_CONST                      1: 'Exception raised in some cases for invalid gzip files.'
                10      STORE_NAME                      3: __doc__
                12      LOAD_CONST                      2: None
                14      RETURN_VALUE                    
        'BadGzipFile'
        [Code]
            File Name: gzip.py
            Object Name: GzipFile
            Arg Count: 0
            Pos Only Arg Count: 0
            KW Only Arg Count: 0
            Locals: 0
            Stack Size: 5
            Flags: 0x00000040 (CO_NOFREE)
            [Names]
                '__name__'
                '__module__'
                '__qualname__'
                '__doc__'
                'myfileobj'
                '_COMPRESS_LEVEL_BEST'
                '__init__'
                'property'
                'filename'
                'mtime'
                '__repr__'
                '_init_write'
                '_write_gzip_header'
                'write'
                'read'
                'read1'
                'peek'
                'closed'
                'close'
                'zlib'
                'Z_SYNC_FLUSH'
                'flush'
                'fileno'
                'rewind'
                'readable'
                'writable'
                'seekable'
                'io'
                'SEEK_SET'
                'seek'
                'readline'
            [Var Names]
            [Free Vars]
            [Cell Vars]
            [Constants]
                'GzipFile'
                'The GzipFile class simulates most of the methods of a file object with\n    the exception of the truncate() method.\n\n    This class only supports opening files in binary mode. If you need to open a\n    compressed file in text mode, use the gzip.open() function.\n\n    '
                None
                [Code]
                    File Name: gzip.py
                    Object Name: __init__
                    Arg Count: 6
                    Pos Only Arg Count: 0
                    KW Only Arg Count: 0
                    Locals: 9
                    Stack Size: 7
                    Flags: 0x00000043 (CO_OPTIMIZED | CO_NEWLOCALS | CO_NOFREE)
                    [Names]
                        'ValueError'
                        'format'
                        'builtins'
                        'open'
                        'myfileobj'
                        'getattr'
                        'isinstance'
                        'str'
                        'bytes'
                        'os'
                        'fspath'
                        'startswith'
                        'READ'
                        'mode'
                        '_GzipReader'
                        'io'
                        'BufferedReader'
                        '_buffer'
                        'name'
                        'warnings'
                        'warn'
                        'FutureWarning'
                        'WRITE'
                        '_init_write'
                        'zlib'
                        'compressobj'
                        'DEFLATED'
                        'MAX_WBITS'
                        'DEF_MEM_LEVEL'
                        'compress'
                        '_write_mtime'
                        'fileobj'
                        '_write_gzip_header'
                    [Var Names]
                        'self'
                        'filename'
                        'mode'
                        'compresslevel'
                        'fileobj'
                        'mtime'
                        'origmode'
                        'raw'
                        'warnings'
                    [Free Vars]
                    [Cell Vars]
                    [Constants]
                        "Constructor for the GzipFile class.\n\n        At least one of fileobj and filename must be given a\n        non-trivial value.\n\n        The new class instance is based on fileobj, which can be a regular\n        file, an io.BytesIO object, or any other object which simulates a file.\n        It defaults to None, in which case filename is opened to provide\n        a file object.\n\n        When fileobj is not None, the filename argument is only used to be\n        included in the gzip file header, which may include the original\n        filename of the uncompressed file.  It defaults to the filename of\n        fileobj, if discernible; otherwise, it defaults to the empty string,\n        and in this case the original filename is not included in the header.\n\n        The mode argument can be any of 'r', 'rb', 'a', 'ab', 'w', 'wb', 'x', or\n        'xb' depending on whether the file will be read or written.  The default\n        is the mode of fileobj if discernible; otherwise, the default is 'rb'.\n        A mode of 'r' is equivalent to one of 'rb', and similarly for 'w' and\n        'wb', 'a' and 'ab', and 'x' and 'xb'.\n\n        The compresslevel argument is an integer from 0 to 9 controlling the\n        level of compression; 1 is fastest and produces the least compression,\n        and 9 is slowest and produces the most compression. 0 is no compression\n        at all. The default is 9.\n\n        The mtime argument is an optional numeric timestamp to be written\n        to the last modification time field in the stream when compressing.\n        If omitted or None, the current time is used.\n\n        "
                        't'
                        'U'
                        'Invalid mode: {!r}'
                        'b'
                        None
                        'rb'
                        'name'
                        ''
                        'mode'
                        'r'
                        (
                            'w'
                            'a'
                            'x'
                        )
                        0
                        'GzipFile was opened for writing, but this will change in future Python releases.  Specify the mode argument for opening it for writing.'
                        2
                    [Disassembly]
                        0       LOAD_FAST                       2: mode
                        2       POP_JUMP_IF_FALSE               17 (to 34)
                        4       LOAD_CONST                      1: 't'
                        6       LOAD_FAST                       2: mode
                        8       CONTAINS_OP                     0 (in)
                        10      POP_JUMP_IF_TRUE                10 (to 20)
                        12      LOAD_CONST                      2: 'U'
                        14      LOAD_FAST                       2: mode
                        16      CONTAINS_OP                     0 (in)
                        18      POP_JUMP_IF_FALSE               17 (to 34)
                        20      LOAD_GLOBAL                     0: ValueError
                        22      LOAD_CONST                      3: 'Invalid mode: {!r}'
                        24      LOAD_METHOD                     1: format
                        26      LOAD_FAST                       2: mode
                        28      CALL_METHOD                     1
                        30      CALL_FUNCTION                   1
                        32      RAISE_VARARGS                   1
                        34      LOAD_FAST                       2: mode
                        36      POP_JUMP_IF_FALSE               27 (to 54)
                        38      LOAD_CONST                      4: 'b'
                        40      LOAD_FAST                       2: mode
                        42      CONTAINS_OP                     1 (not in)
                        44      POP_JUMP_IF_FALSE               27 (to 54)
                        46      LOAD_FAST                       2: mode
                        48      LOAD_CONST                      4: 'b'
                        50      INPLACE_ADD                     
                        52      STORE_FAST                      2: mode
                        54      LOAD_FAST                       4: fileobj
                        56      LOAD_CONST                      5: None
                        58      IS_OP                           0 (is)
                        60      POP_JUMP_IF_FALSE               42 (to 84)
                        62      LOAD_GLOBAL                     2: builtins
                        64      LOAD_METHOD                     3: open
                        66      LOAD_FAST                       1: filename
                        68      LOAD_FAST                       2: mode
                        70      JUMP_IF_TRUE_OR_POP             37 (to 74)
                        72      LOAD_CONST                      6: 'rb'
                        74      CALL_METHOD                     2
                        76      DUP_TOP                         
                        78      STORE_FAST                      4: fileobj
                        80      LOAD_FAST                       0: self
                        82      STORE_ATTR                      4: myfileobj
                        84      LOAD_FAST                       1: filename
                        86      LOAD_CONST                      5: None
                        88      IS_OP                           0 (is)
                        90      POP_JUMP_IF_FALSE               62 (to 124)
                        92      LOAD_GLOBAL                     5: getattr
                        94      LOAD_FAST                       4: fileobj
                        96      LOAD_CONST                      7: 'name'
                        98      LOAD_CONST                      8: ''
                        100     CALL_FUNCTION                   3
                        102     STORE_FAST                      1: filename
                        104     LOAD_GLOBAL                     6: isinstance
                        106     LOAD_FAST                       1: filename
                        108     LOAD_GLOBAL                     7: str
                        110     LOAD_GLOBAL                     8: bytes
                        112     BUILD_TUPLE                     2
                        114     CALL_FUNCTION                   2
                        116     POP_JUMP_IF_TRUE                61 (to 122)
                        118     LOAD_CONST                      8: ''
                        120     STORE_FAST                      1: filename
                        122     JUMP_FORWARD                    5 (to 134)
                        124     LOAD_GLOBAL                     9: os
                        126     LOAD_METHOD                     10: fspath
                        128     LOAD_FAST                       1: filename
                        130     CALL_METHOD                     1
                        132     STORE_FAST                      1: filename
                        134     LOAD_FAST                       2: mode
                        136     STORE_FAST                      6: origmode
                        138     LOAD_FAST                       2: mode
                        140     LOAD_CONST                      5: None
                        142     IS_OP                           0 (is)
                        144     POP_JUMP_IF_FALSE               79 (to 158)
                        146     LOAD_GLOBAL                     5: getattr
                        148     LOAD_FAST                       4: fileobj
                        150     LOAD_CONST                      9: 'mode'
                        152     LOAD_CONST                      6: 'rb'
                        154     CALL_FUNCTION                   3
                        156     STORE_FAST                      2: mode
                        158     LOAD_FAST                       2: mode
                        160     LOAD_METHOD                     11: startswith
                        162     LOAD_CONST                      10: 'r'
                        164     CALL_METHOD                     1
                        166     POP_JUMP_IF_FALSE               101 (to 202)
                        168     LOAD_GLOBAL                     12: READ
                        170     LOAD_FAST                       0: self
                        172     STORE_ATTR                      13: mode
                        174     LOAD_GLOBAL                     14: _GzipReader
                        176     LOAD_FAST                       4: fileobj
                        178     CALL_FUNCTION                   1
                        180     STORE_FAST                      7: raw
                        182     LOAD_GLOBAL                     15: io
                        184     LOAD_METHOD                     16: BufferedReader
                        186     LOAD_FAST                       7: raw
                        188     CALL_METHOD                     1
                        190     LOAD_FAST                       0: self
                        192     STORE_ATTR                      17: _buffer
                        194     LOAD_FAST                       1: filename
                        196     LOAD_FAST                       0: self
                        198     STORE_ATTR                      18: name
                        200     JUMP_FORWARD                    53 (to 308)
                        202     LOAD_FAST                       2: mode
                        204     LOAD_METHOD                     11: startswith
                        206     LOAD_CONST                      11: ('w', 'a', 'x')
                        208     CALL_METHOD                     1
                        210     POP_JUMP_IF_FALSE               147 (to 294)
                        212     LOAD_FAST                       6: origmode
                        214     LOAD_CONST                      5: None
                        216     IS_OP                           0 (is)
                        218     POP_JUMP_IF_FALSE               121 (to 242)
                        220     LOAD_CONST                      12: 0
                        222     LOAD_CONST                      5: None
                        224     IMPORT_NAME                     19: warnings
                        226     STORE_FAST                      8: warnings
                        228     LOAD_FAST                       8: warnings
                        230     LOAD_METHOD                     20: warn
                        232     LOAD_CONST                      13: 'GzipFile was opened for writing, but this will change in future Python releases.  Specify the mode argument for opening it for writing.'
                        234     LOAD_GLOBAL                     21: FutureWarning
                        236     LOAD_CONST                      14: 2
                        238     CALL_METHOD                     3
                        240     POP_TOP                         
                        242     LOAD_GLOBAL                     22: WRITE
                        244     LOAD_FAST                       0: self
                        246     STORE_ATTR                      13: mode
                        248     LOAD_FAST                       0: self
                        250     LOAD_METHOD                     23: _init_write
                        252     LOAD_FAST                       1: filename
                        254     CALL_METHOD                     1
                        256     POP_TOP                         
                        258     LOAD_GLOBAL                     24: zlib
                        260     LOAD_METHOD                     25: compressobj
                        262     LOAD_FAST                       3: compresslevel
                        264     LOAD_GLOBAL                     24: zlib
                        266     LOAD_ATTR                       26: DEFLATED
                        268     LOAD_GLOBAL                     24: zlib
                        270     LOAD_ATTR                       27: MAX_WBITS
                        272     UNARY_NEGATIVE                  
                        274     LOAD_GLOBAL                     24: zlib
                        276     LOAD_ATTR                       28: DEF_MEM_LEVEL
                        278     LOAD_CONST                      12: 0
                        280     CALL_METHOD                     5
                        282     LOAD_FAST                       0: self
                        284     STORE_ATTR                      29: compress
                        286     LOAD_FAST                       5: mtime
                        288     LOAD_FAST                       0: self
                        290     STORE_ATTR                      30: _write_mtime
                        292     JUMP_FORWARD                    7 (to 308)
                        294     LOAD_GLOBAL                     0: ValueError
                        296     LOAD_CONST                      3: 'Invalid mode: {!r}'
                        298     LOAD_METHOD                     1: format
                        300     LOAD_FAST                       2: mode
                        302     CALL_METHOD                     1
                        304     CALL_FUNCTION                   1
                        306     RAISE_VARARGS                   1
                        308     LOAD_FAST                       4: fileobj
                        310     LOAD_FAST                       0: self
                        312     STORE_ATTR                      31: fileobj
                        314     LOAD_FAST                       0: self
                        316     LOAD_ATTR                       13: mode
                        318     LOAD_GLOBAL                     22: WRITE
                        320     COMPARE_OP                      2 (==)
                        322     POP_JUMP_IF_FALSE               169 (to 338)
                        324     LOAD_FAST                       0: self
                        326     LOAD_METHOD                     32: _write_gzip_header
                        328     LOAD_FAST                       3: compresslevel
                        330     CALL_METHOD                     1
                        332     POP_TOP                         
                        334     LOAD_CONST                      5: None
                        336     RETURN_VALUE                    
                        338     LOAD_CONST                      5: None
                        340     RETURN_VALUE                    
                'GzipFile.__init__'
                [Code]
                    File Name: gzip.py
                    Object Name: filename
                    Arg Count: 1
                    Pos Only Arg Count: 0
                    KW Only Arg Count: 0
                    Locals: 2
                    Stack Size: 5
                    Flags: 0x00000043 (CO_OPTIMIZED | CO_NEWLOCALS | CO_NOFREE)
                    [Names]
                        'warnings'
                        'warn'
                        'DeprecationWarning'
                        'mode'
                        'WRITE'
                        'name'
                    [Var Names]
                        'self'
                        'warnings'
                    [Free Vars]
                    [Cell Vars]
                    [Constants]
                        None
                        0
                        'use the name attribute'
                        2
                        -3
                        '.gz'
                    [Disassembly]
                        0       LOAD_CONST                      1: 0
                        2       LOAD_CONST                      0: None
                        4       IMPORT_NAME                     0: warnings
                        6       STORE_FAST                      1: warnings
                        8       LOAD_FAST                       1: warnings
                        10      LOAD_METHOD                     1: warn
                        12      LOAD_CONST                      2: 'use the name attribute'
                        14      LOAD_GLOBAL                     2: DeprecationWarning
                        16      LOAD_CONST                      3: 2
                        18      CALL_METHOD                     3
                        20      POP_TOP                         
                        22      LOAD_FAST                       0: self
                        24      LOAD_ATTR                       3: mode
                        26      LOAD_GLOBAL                     4: WRITE
                        28      COMPARE_OP                      2 (==)
                        30      POP_JUMP_IF_FALSE               30 (to 60)
                        32      LOAD_FAST                       0: self
                        34      LOAD_ATTR                       5: name
                        36      LOAD_CONST                      4: -3
                        38      LOAD_CONST                      0: None
                        40      BUILD_SLICE                     2
                        42      BINARY_SUBSCR                   
                        44      LOAD_CONST                      5: '.gz'
                        46      COMPARE_OP                      3 (!=)
                        48      POP_JUMP_IF_FALSE               30 (to 60)
                        50      LOAD_FAST                       0: self
                        52      LOAD_ATTR                       5: name
                        54      LOAD_CONST                      5: '.gz'
                        56      BINARY_ADD                      
                        58      RETURN_VALUE                    
                        60      LOAD_FAST                       0: self
                        62      LOAD_ATTR                       5: name
                        64      RETURN_VALUE                    
                'GzipFile.filename'
                [Code]
                    File Name: gzip.py
                    Object Name: mtime
                    Arg Count: 1
                    Pos Only Arg Count: 0
                    KW Only Arg Count: 0
                    Locals: 1
                    Stack Size: 1
                    Flags: 0x00000043 (CO_OPTIMIZED | CO_NEWLOCALS | CO_NOFREE)
                    [Names]
                        '_buffer'
                        'raw'
                        '_last_mtime'
                    [Var Names]
                        'self'
                    [Free Vars]
                    [Cell Vars]
                    [Constants]
                        'Last modification time read from stream, or None'
                    [Disassembly]
                        0       LOAD_FAST                       0: self
                        2       LOAD_ATTR                       0: _buffer
                        4       LOAD_ATTR                       1: raw
                        6       LOAD_ATTR                       2: _last_mtime
                        8       RETURN_VALUE                    
                'GzipFile.mtime'
                [Code]
                    File Name: gzip.py
                    Object Name: __repr__
                    Arg Count: 1
                    Pos Only Arg Count: 0
                    KW Only Arg Count: 0
                    Locals: 2
                    Stack Size: 4
                    Flags: 0x00000043 (CO_OPTIMIZED | CO_NEWLOCALS | CO_NOFREE)
                    [Names]
                        'repr'
                        'fileobj'
                        'hex'
                        'id'
                    [Var Names]
                        'self'
                        's'
                    [Free Vars]
                    [Cell Vars]
                    [Constants]
                        None
                        '<gzip '
                        1
                        -1
                        ' '
                        '>'
                    [Disassembly]
                        0       LOAD_GLOBAL                     0: repr
                        2       LOAD_FAST                       0: self
                        4       LOAD_ATTR                       1: fileobj
                        6       CALL_FUNCTION                   1
                        8       STORE_FAST                      1: s
                        10      LOAD_CONST                      1: '<gzip '
                        12      LOAD_FAST                       1: s
                        14      LOAD_CONST                      2: 1
                        16      LOAD_CONST                      3: -1
                        18      BUILD_SLICE                     2
                        20      BINARY_SUBSCR                   
                        22      BINARY_ADD                      
                        24      LOAD_CONST                      4: ' '
                        26      BINARY_ADD                      
                        28      LOAD_GLOBAL                     2: hex
                        30      LOAD_GLOBAL                     3: id
                        32      LOAD_FAST                       0: self
                        34      CALL_FUNCTION                   1
                        36      CALL_FUNCTION                   1
                        38      BINARY_ADD                      
                        40      LOAD_CONST                      5: '>'
                        42      BINARY_ADD                      
                        44      RETURN_VALUE                    
                'GzipFile.__repr__'
                [Code]
                    File Name: gzip.py
                    Object Name: _init_write
                    Arg Count: 2
                    Pos Only Arg Count: 0
                    KW Only Arg Count: 0
                    Locals: 2
                    Stack Size: 3
                    Flags: 0x00000043 (CO_OPTIMIZED | CO_NEWLOCALS | CO_NOFREE)
                    [Names]
                        'name'
                        'zlib'
                        'crc32'
                        'crc'
                        'size'
                        'writebuf'
                        'bufsize'
                        'offset'
                    [Var Names]
                        'self'
                        'filename'
                    [Free Vars]
                    [Cell Vars]
                    [Constants]
                        None
                        b''
                        0
                    [Disassembly]
                        0       LOAD_FAST                       1: filename
                        2       LOAD_FAST                       0: self
                        4       STORE_ATTR                      0: name
                        6       LOAD_GLOBAL                     1: zlib
                        8       LOAD_METHOD                     2: crc32
                        10      LOAD_CONST                      1: b''
                        12      CALL_METHOD                     1
                        14      LOAD_FAST                       0: self
                        16      STORE_ATTR                      3: crc
                        18      LOAD_CONST                      2: 0
                        20      LOAD_FAST                       0: self
                        22      STORE_ATTR                      4: size
                        24      BUILD_LIST                      0
                        26      LOAD_FAST                       0: self
                        28      STORE_ATTR                      5: writebuf
                        30      LOAD_CONST                      2: 0
                        32      LOAD_FAST                       0: self
                        34      STORE_ATTR                      6: bufsize
                        36      LOAD_CONST                      2: 0
                        38      LOAD_FAST                       0: self
                        40      STORE_ATTR                      7: offset
                        42      LOAD_CONST                      0: None
                        44      RETURN_VALUE                    
                'GzipFile._init_write'
                [Code]
                    File Name: gzip.py
                    Object Name: _write_gzip_header
                    Arg Count: 2
                    Pos Only Arg Count: 0
                    KW Only Arg Count: 0
                    Locals: 6
                    Stack Size: 8
                    Flags: 0x00000043 (CO_OPTIMIZED | CO_NEWLOCALS | CO_NOFREE)
                    [Names]
                        'fileobj'
                        'write'
                        'os'
                        'path'
                        'basename'
                        'name'
                        'isinstance'
                        'bytes'
                        'encode'
                        'endswith'
                        'UnicodeEncodeError'
                        'FNAME'
                        'chr'
                        '_write_mtime'
                        'time'
                        'write32u'
                        'int'
                        '_COMPRESS_LEVEL_BEST'
                        '_COMPRESS_LEVEL_FAST'
                    [Var Names]
                        'self'
                        'compresslevel'
                        'fname'
                        'flags'
                        'mtime'
                        'xfl'
                    [Free Vars]
                    [Cell Vars]
                    [Constants]
                        None
                        b'\x1f\x8b'
                        b'\x08'
                        'latin-1'
                        b'.gz'
                        -3
                        b''
                        0
                        b'\x02'
                        b'\x04'
                        b'\x00'
                        b'\xff'
                    [Disassembly]
                        0       LOAD_FAST                       0: self
                        2       LOAD_ATTR                       0: fileobj
                        4       LOAD_METHOD                     1: write
                        6       LOAD_CONST                      1: b'\x1f\x8b'
                        8       CALL_METHOD                     1
                        10      POP_TOP                         
                        12      LOAD_FAST                       0: self
                        14      LOAD_ATTR                       0: fileobj
                        16      LOAD_METHOD                     1: write
                        18      LOAD_CONST                      2: b'\x08'
                        20      CALL_METHOD                     1
                        22      POP_TOP                         
                        24      SETUP_FINALLY                   30 (to 86)
                        26      LOAD_GLOBAL                     2: os
                        28      LOAD_ATTR                       3: path
                        30      LOAD_METHOD                     4: basename
                        32      LOAD_FAST                       0: self
                        34      LOAD_ATTR                       5: name
                        36      CALL_METHOD                     1
                        38      STORE_FAST                      2: fname
                        40      LOAD_GLOBAL                     6: isinstance
                        42      LOAD_FAST                       2: fname
                        44      LOAD_GLOBAL                     7: bytes
                        46      CALL_FUNCTION                   2
                        48      POP_JUMP_IF_TRUE                30 (to 60)
                        50      LOAD_FAST                       2: fname
                        52      LOAD_METHOD                     8: encode
                        54      LOAD_CONST                      3: 'latin-1'
                        56      CALL_METHOD                     1
                        58      STORE_FAST                      2: fname
                        60      LOAD_FAST                       2: fname
                        62      LOAD_METHOD                     9: endswith
                        64      LOAD_CONST                      4: b'.gz'
                        66      CALL_METHOD                     1
                        68      POP_JUMP_IF_FALSE               41 (to 82)
                        70      LOAD_FAST                       2: fname
                        72      LOAD_CONST                      0: None
                        74      LOAD_CONST                      5: -3
                        76      BUILD_SLICE                     2
                        78      BINARY_SUBSCR                   
                        80      STORE_FAST                      2: fname
                        82      POP_BLOCK                       
                        84      JUMP_FORWARD                    11 (to 108)
                        86      DUP_TOP                         
                        88      LOAD_GLOBAL                     10: UnicodeEncodeError
                        90      JUMP_IF_NOT_EXC_MATCH           53 (to 106)
                        92      POP_TOP                         
                        94      POP_TOP                         
                        96      POP_TOP                         
                        98      LOAD_CONST                      6: b''
                        100     STORE_FAST                      2: fname
                        102     POP_EXCEPT                      
                        104     JUMP_FORWARD                    1 (to 108)
                        106     RERAISE                         0
                        108     LOAD_CONST                      7: 0
                        110     STORE_FAST                      3: flags
                        112     LOAD_FAST                       2: fname
                        114     POP_JUMP_IF_FALSE               60 (to 120)
                        116     LOAD_GLOBAL                     11: FNAME
                        118     STORE_FAST                      3: flags
                        120     LOAD_FAST                       0: self
                        122     LOAD_ATTR                       0: fileobj
                        124     LOAD_METHOD                     1: write
                        126     LOAD_GLOBAL                     12: chr
                        128     LOAD_FAST                       3: flags
                        130     CALL_FUNCTION                   1
                        132     LOAD_METHOD                     8: encode
                        134     LOAD_CONST                      3: 'latin-1'
                        136     CALL_METHOD                     1
                        138     CALL_METHOD                     1
                        140     POP_TOP                         
                        142     LOAD_FAST                       0: self
                        144     LOAD_ATTR                       13: _write_mtime
                        146     STORE_FAST                      4: mtime
                        148     LOAD_FAST                       4: mtime
                        150     LOAD_CONST                      0: None
                        152     IS_OP                           0 (is)
                        154     POP_JUMP_IF_FALSE               82 (to 164)
                        156     LOAD_GLOBAL                     14: time
                        158     LOAD_METHOD                     14: time
                        160     CALL_METHOD                     0
                        162     STORE_FAST                      4: mtime
                        164     LOAD_GLOBAL                     15: write32u
                        166     LOAD_FAST                       0: self
                        168     LOAD_ATTR                       0: fileobj
                        170     LOAD_GLOBAL                     16: int
                        172     LOAD_FAST                       4: mtime
                        174     CALL_FUNCTION                   1
                        176     CALL_FUNCTION                   2
                        178     POP_TOP                         
                        180     LOAD_FAST                       1: compresslevel
                        182     LOAD_GLOBAL                     17: _COMPRESS_LEVEL_BEST
                        184     COMPARE_OP                      2 (==)
                        186     POP_JUMP_IF_FALSE               97 (to 194)
                        188     LOAD_CONST                      8: b'\x02'
                        190     STORE_FAST                      5: xfl
                        192     JUMP_FORWARD                    9 (to 212)
                        194     LOAD_FAST                       1: compresslevel
                        196     LOAD_GLOBAL                     18: _COMPRESS_LEVEL_FAST
                        198     COMPARE_OP                      2 (==)
                        200     POP_JUMP_IF_FALSE               104 (to 208)
                        202     LOAD_CONST                      9: b'\x04'
                        204     STORE_FAST                      5: xfl
                        206     JUMP_FORWARD                    2 (to 212)
                        208     LOAD_CONST                      10: b'\x00'
                        210     STORE_FAST                      5: xfl
                        212     LOAD_FAST                       0: self
                        214     LOAD_ATTR                       0: fileobj
                        216     LOAD_METHOD                     1: write
                        218     LOAD_FAST                       5: xfl
                        220     CALL_METHOD                     1
                        222     POP_TOP                         
                        224     LOAD_FAST                       0: self
                        226     LOAD_ATTR                       0: fileobj
                        228     LOAD_METHOD                     1: write
                        230     LOAD_CONST                      11: b'\xff'
                        232     CALL_METHOD                     1
                        234     POP_TOP                         
                        236     LOAD_FAST                       2: fname
                        238     POP_JUMP_IF_FALSE               130 (to 260)
                        240     LOAD_FAST                       0: self
                        242     LOAD_ATTR                       0: fileobj
                        244     LOAD_METHOD                     1: write
                        246     LOAD_FAST                       2: fname
                        248     LOAD_CONST                      10: b'\x00'
                        250     BINARY_ADD                      
                        252     CALL_METHOD                     1
                        254     POP_TOP                         
                        256     LOAD_CONST                      0: None
                        258     RETURN_VALUE                    
                        260     LOAD_CONST                      0: None
                        262     RETURN_VALUE                    
                'GzipFile._write_gzip_header'
                [Code]
                    File Name: gzip.py
                    Object Name: write
                    Arg Count: 2
                    Pos Only Arg Count: 0
                    KW Only Arg Count: 0
                    Locals: 4
                    Stack Size: 5
                    Flags: 0x00000043 (CO_OPTIMIZED | CO_NEWLOCALS | CO_NOFREE)
                    [Names]
                        '_check_not_closed'
                        'mode'
                        'WRITE'
                        'errno'
                        'OSError'
                        'EBADF'
                        'fileobj'
                        'ValueError'
                        'isinstance'
                        'bytes'
                        'bytearray'
                        'len'
                        'memoryview'
                        'nbytes'
                        'write'
                        'compress'
                        'size'
                        'zlib'
                        'crc32'
                        'crc'
                        'offset'
                    [Var Names]
                        'self'
                        'data'
                        'errno'
                        'length'
                    [Free Vars]
                    [Cell Vars]
                    [Constants]
                        None
                        0
                        'write() on read-only GzipFile object'
                        'write() on closed GzipFile object'
                    [Disassembly]
                        0       LOAD_FAST                       0: self
                        2       LOAD_METHOD                     0: _check_not_closed
                        4       CALL_METHOD                     0
                        6       POP_TOP                         
                        8       LOAD_FAST                       0: self
                        10      LOAD_ATTR                       1: mode
                        12      LOAD_GLOBAL                     2: WRITE
                        14      COMPARE_OP                      3 (!=)
                        16      POP_JUMP_IF_FALSE               19 (to 38)
                        18      LOAD_CONST                      1: 0
                        20      LOAD_CONST                      0: None
                        22      IMPORT_NAME                     3: errno
                        24      STORE_FAST                      2: errno
                        26      LOAD_GLOBAL                     4: OSError
                        28      LOAD_FAST                       2: errno
                        30      LOAD_ATTR                       5: EBADF
                        32      LOAD_CONST                      2: 'write() on read-only GzipFile object'
                        34      CALL_FUNCTION                   2
                        36      RAISE_VARARGS                   1
                        38      LOAD_FAST                       0: self
                        40      LOAD_ATTR                       6: fileobj
                        42      LOAD_CONST                      0: None
                        44      IS_OP                           0 (is)
                        46      POP_JUMP_IF_FALSE               28 (to 56)
                        48      LOAD_GLOBAL                     7: ValueError
                        50      LOAD_CONST                      3: 'write() on closed GzipFile object'
                        52      CALL_FUNCTION                   1
                        54      RAISE_VARARGS                   1
                        56      LOAD_GLOBAL                     8: isinstance
                        58      LOAD_FAST                       1: data
                        60      LOAD_GLOBAL                     9: bytes
                        62      LOAD_GLOBAL                     10: bytearray
                        64      BUILD_TUPLE                     2
                        66      CALL_FUNCTION                   2
                        68      POP_JUMP_IF_FALSE               40 (to 80)
                        70      LOAD_GLOBAL                     11: len
                        72      LOAD_FAST                       1: data
                        74      CALL_FUNCTION                   1
                        76      STORE_FAST                      3: length
                        78      JUMP_FORWARD                    7 (to 94)
                        80      LOAD_GLOBAL                     12: memoryview
                        82      LOAD_FAST                       1: data
                        84      CALL_FUNCTION                   1
                        86      STORE_FAST                      1: data
                        88      LOAD_FAST                       1: data
                        90      LOAD_ATTR                       13: nbytes
                        92      STORE_FAST                      3: length
                        94      LOAD_FAST                       3: length
                        96      LOAD_CONST                      1: 0
                        98      COMPARE_OP                      4 (>)
                        100     POP_JUMP_IF_FALSE               83 (to 166)
                        102     LOAD_FAST                       0: self
                        104     LOAD_ATTR                       6: fileobj
                        106     LOAD_METHOD                     14: write
                        108     LOAD_FAST                       0: self
                        110     LOAD_ATTR                       15: compress
                        112     LOAD_METHOD                     15: compress
                        114     LOAD_FAST                       1: data
                        116     CALL_METHOD                     1
                        118     CALL_METHOD                     1
                        120     POP_TOP                         
                        122     LOAD_FAST                       0: self
                        124     DUP_TOP                         
                        126     LOAD_ATTR                       16: size
                        128     LOAD_FAST                       3: length
                        130     INPLACE_ADD                     
                        132     ROT_TWO                         
                        134     STORE_ATTR                      16: size
                        136     LOAD_GLOBAL                     17: zlib
                        138     LOAD_METHOD                     18: crc32
                        140     LOAD_FAST                       1: data
                        142     LOAD_FAST                       0: self
                        144     LOAD_ATTR                       19: crc
                        146     CALL_METHOD                     2
                        148     LOAD_FAST                       0: self
                        150     STORE_ATTR                      19: crc
                        152     LOAD_FAST                       0: self
                        154     DUP_TOP                         
                        156     LOAD_ATTR                       20: offset
                        158     LOAD_FAST                       3: length
                        160     INPLACE_ADD                     
                        162     ROT_TWO                         
                        164     STORE_ATTR                      20: offset
                        166     LOAD_FAST                       3: length
                        168     RETURN_VALUE                    
                'GzipFile.write'
                -1
                [Code]
                    File Name: gzip.py
                    Object Name: read
                    Arg Count: 2
                    Pos Only Arg Count: 0
                    KW Only Arg Count: 0
                    Locals: 3
                    Stack Size: 3
                    Flags: 0x00000043 (CO_OPTIMIZED | CO_NEWLOCALS | CO_NOFREE)
                    [Names]
                        '_check_not_closed'
                        'mode'
                        'READ'
                        'errno'
                        'OSError'
                        'EBADF'
                        '_buffer'
                        'read'
                    [Var Names]
                        'self'
                        'size'
                        'errno'
                    [Free Vars]
                    [Cell Vars]
                    [Constants]
                        None
                        0
                        'read() on write-only GzipFile object'
                    [Disassembly]
                        0       LOAD_FAST                       0: self
                        2       LOAD_METHOD                     0: _check_not_closed
                        4       CALL_METHOD                     0
                        6       POP_TOP                         
                        8       LOAD_FAST                       0: self
                        10      LOAD_ATTR                       1: mode
                        12      LOAD_GLOBAL                     2: READ
                        14      COMPARE_OP                      3 (!=)
                        16      POP_JUMP_IF_FALSE               19 (to 38)
                        18      LOAD_CONST                      1: 0
                        20      LOAD_CONST                      0: None
                        22      IMPORT_NAME                     3: errno
                        24      STORE_FAST                      2: errno
                        26      LOAD_GLOBAL                     4: OSError
                        28      LOAD_FAST                       2: errno
                        30      LOAD_ATTR                       5: EBADF
                        32      LOAD_CONST                      2: 'read() on write-only GzipFile object'
                        34      CALL_FUNCTION                   2
                        36      RAISE_VARARGS                   1
                        38      LOAD_FAST                       0: self
                        40      LOAD_ATTR                       6: _buffer
                        42      LOAD_METHOD                     7: read
                        44      LOAD_FAST                       1: size
                        46      CALL_METHOD                     1
                        48      RETURN_VALUE                    
                'GzipFile.read'
                [Code]
                    File Name: gzip.py
                    Object Name: read1
                    Arg Count: 2
                    Pos Only Arg Count: 0
                    KW Only Arg Count: 0
                    Locals: 3
                    Stack Size: 3
                    Flags: 0x00000043 (CO_OPTIMIZED | CO_NEWLOCALS | CO_NOFREE)
                    [Names]
                        '_check_not_closed'
                        'mode'
                        'READ'
                        'errno'
                        'OSError'
                        'EBADF'
                        'io'
                        'DEFAULT_BUFFER_SIZE'
                        '_buffer'
                        'read1'
                    [Var Names]
                        'self'
                        'size'
                        'errno'
                    [Free Vars]
                    [Cell Vars]
                    [Constants]
                        "Implements BufferedIOBase.read1()\n\n        Reads up to a buffer's worth of data if size is negative."
                        0
                        None
                        'read1() on write-only GzipFile object'
                    [Disassembly]
                        0       LOAD_FAST                       0: self
                        2       LOAD_METHOD                     0: _check_not_closed
                        4       CALL_METHOD                     0
                        6       POP_TOP                         
                        8       LOAD_FAST                       0: self
                        10      LOAD_ATTR                       1: mode
                        12      LOAD_GLOBAL                     2: READ
                        14      COMPARE_OP                      3 (!=)
                        16      POP_JUMP_IF_FALSE               19 (to 38)
                        18      LOAD_CONST                      1: 0
                        20      LOAD_CONST                      2: None
                        22      IMPORT_NAME                     3: errno
                        24      STORE_FAST                      2: errno
                        26      LOAD_GLOBAL                     4: OSError
                        28      LOAD_FAST                       2: errno
                        30      LOAD_ATTR                       5: EBADF
                        32      LOAD_CONST                      3: 'read1() on write-only GzipFile object'
                        34      CALL_FUNCTION                   2
                        36      RAISE_VARARGS                   1
                        38      LOAD_FAST                       1: size
                        40      LOAD_CONST                      1: 0
                        42      COMPARE_OP                      0 (<)
                        44      POP_JUMP_IF_FALSE               26 (to 52)
                        46      LOAD_GLOBAL                     6: io
                        48      LOAD_ATTR                       7: DEFAULT_BUFFER_SIZE
                        50      STORE_FAST                      1: size
                        52      LOAD_FAST                       0: self
                        54      LOAD_ATTR                       8: _buffer
                        56      LOAD_METHOD                     9: read1
                        58      LOAD_FAST                       1: size
                        60      CALL_METHOD                     1
                        62      RETURN_VALUE                    
                'GzipFile.read1'
                [Code]
                    File Name: gzip.py
                    Object Name: peek
                    Arg Count: 2
                    Pos Only Arg Count: 0
                    KW Only Arg Count: 0
                    Locals: 3
                    Stack Size: 3
                    Flags: 0x00000043 (CO_OPTIMIZED | CO_NEWLOCALS | CO_NOFREE)
                    [Names]
                        '_check_not_closed'
                        'mode'
                        'READ'
                        'errno'
                        'OSError'
                        'EBADF'
                        '_buffer'
                        'peek'
                    [Var Names]
                        'self'
                        'n'
                        'errno'
                    [Free Vars]
                    [Cell Vars]
                    [Constants]
                        None
                        0
                        'peek() on write-only GzipFile object'
                    [Disassembly]
                        0       LOAD_FAST                       0: self
                        2       LOAD_METHOD                     0: _check_not_closed
                        4       CALL_METHOD                     0
                        6       POP_TOP                         
                        8       LOAD_FAST                       0: self
                        10      LOAD_ATTR                       1: mode
                        12      LOAD_GLOBAL                     2: READ
                        14      COMPARE_OP                      3 (!=)
                        16      POP_JUMP_IF_FALSE               19 (to 38)
                        18      LOAD_CONST                      1: 0
                        20      LOAD_CONST                      0: None
                        22      IMPORT_NAME                     3: errno
                        24      STORE_FAST                      2: errno
                        26      LOAD_GLOBAL                     4: OSError
                        28      LOAD_FAST                       2: errno
                        30      LOAD_ATTR                       5: EBADF
                        32      LOAD_CONST                      2: 'peek() on write-only GzipFile object'
                        34      CALL_FUNCTION                   2
                        36      RAISE_VARARGS                   1
                        38      LOAD_FAST                       0: self
                        40      LOAD_ATTR                       6: _buffer
                        42      LOAD_METHOD                     7: peek
                        44      LOAD_FAST                       1: n
                        46      CALL_METHOD                     1
                        48      RETURN_VALUE                    
                'GzipFile.peek'
                [Code]
                    File Name: gzip.py
                    Object Name: closed
                    Arg Count: 1
                    Pos Only Arg Count: 0
                    KW Only Arg Count: 0
                    Locals: 1
                    Stack Size: 2
                    Flags: 0x00000043 (CO_OPTIMIZED | CO_NEWLOCALS | CO_NOFREE)
                    [Names]
                        'fileobj'
                    [Var Names]
                        'self'
                    [Free Vars]
                    [Cell Vars]
                    [Constants]
                        None
                    [Disassembly]
                        0       LOAD_FAST                       0: self
                        2       LOAD_ATTR                       0: fileobj
                        4       LOAD_CONST                      0: None
                        6       IS_OP                           0 (is)
                        8       RETURN_VALUE                    
                'GzipFile.closed'
                [Code]
                    File Name: gzip.py
                    Object Name: close
                    Arg Count: 1
                    Pos Only Arg Count: 0
                    KW Only Arg Count: 0
                    Locals: 3
                    Stack Size: 8
                    Flags: 0x00000043 (CO_OPTIMIZED | CO_NEWLOCALS | CO_NOFREE)
                    [Names]
                        'fileobj'
                        'mode'
                        'WRITE'
                        'write'
                        'compress'
                        'flush'
                        'write32u'
                        'crc'
                        'size'
                        'READ'
                        '_buffer'
                        'close'
                        'myfileobj'
                    [Var Names]
                        'self'
                        'fileobj'
                        'myfileobj'
                    [Free Vars]
                    [Cell Vars]
                    [Constants]
                        None
                        0xFFFFFFFF
                    [Disassembly]
                        0       LOAD_FAST                       0: self
                        2       LOAD_ATTR                       0: fileobj
                        4       STORE_FAST                      1: fileobj
                        6       LOAD_FAST                       1: fileobj
                        8       LOAD_CONST                      0: None
                        10      IS_OP                           0 (is)
                        12      POP_JUMP_IF_FALSE               9 (to 18)
                        14      LOAD_CONST                      0: None
                        16      RETURN_VALUE                    
                        18      LOAD_CONST                      0: None
                        20      LOAD_FAST                       0: self
                        22      STORE_ATTR                      0: fileobj
                        24      SETUP_FINALLY                   55 (to 136)
                        26      LOAD_FAST                       0: self
                        28      LOAD_ATTR                       1: mode
                        30      LOAD_GLOBAL                     2: WRITE
                        32      COMPARE_OP                      2 (==)
                        34      POP_JUMP_IF_FALSE               41 (to 82)
                        36      LOAD_FAST                       1: fileobj
                        38      LOAD_METHOD                     3: write
                        40      LOAD_FAST                       0: self
                        42      LOAD_ATTR                       4: compress
                        44      LOAD_METHOD                     5: flush
                        46      CALL_METHOD                     0
                        48      CALL_METHOD                     1
                        50      POP_TOP                         
                        52      LOAD_GLOBAL                     6: write32u
                        54      LOAD_FAST                       1: fileobj
                        56      LOAD_FAST                       0: self
                        58      LOAD_ATTR                       7: crc
                        60      CALL_FUNCTION                   2
                        62      POP_TOP                         
                        64      LOAD_GLOBAL                     6: write32u
                        66      LOAD_FAST                       1: fileobj
                        68      LOAD_FAST                       0: self
                        70      LOAD_ATTR                       8: size
                        72      LOAD_CONST                      1: 0xFFFFFFFF
                        74      BINARY_AND                      
                        76      CALL_FUNCTION                   2
                        78      POP_TOP                         
                        80      JUMP_FORWARD                    10 (to 102)
                        82      LOAD_FAST                       0: self
                        84      LOAD_ATTR                       1: mode
                        86      LOAD_GLOBAL                     9: READ
                        88      COMPARE_OP                      2 (==)
                        90      POP_JUMP_IF_FALSE               51 (to 102)
                        92      LOAD_FAST                       0: self
                        94      LOAD_ATTR                       10: _buffer
                        96      LOAD_METHOD                     11: close
                        98      CALL_METHOD                     0
                        100     POP_TOP                         
                        102     POP_BLOCK                       
                        104     LOAD_FAST                       0: self
                        106     LOAD_ATTR                       12: myfileobj
                        108     STORE_FAST                      2: myfileobj
                        110     LOAD_FAST                       2: myfileobj
                        112     POP_JUMP_IF_FALSE               66 (to 132)
                        114     LOAD_CONST                      0: None
                        116     LOAD_FAST                       0: self
                        118     STORE_ATTR                      12: myfileobj
                        120     LOAD_FAST                       2: myfileobj
                        122     LOAD_METHOD                     11: close
                        124     CALL_METHOD                     0
                        126     POP_TOP                         
                        128     LOAD_CONST                      0: None
                        130     RETURN_VALUE                    
                        132     LOAD_CONST                      0: None
                        134     RETURN_VALUE                    
                        136     LOAD_FAST                       0: self
                        138     LOAD_ATTR                       12: myfileobj
                        140     STORE_FAST                      2: myfileobj
                        142     LOAD_FAST                       2: myfileobj
                        144     POP_JUMP_IF_FALSE               81 (to 162)
                        146     LOAD_CONST                      0: None
                        148     LOAD_FAST                       0: self
                        150     STORE_ATTR                      12: myfileobj
                        152     LOAD_FAST                       2: myfileobj
                        154     LOAD_METHOD                     11: close
                        156     CALL_METHOD                     0
                        158     POP_TOP                         
                        160     RERAISE                         0
                        162     RERAISE                         0
                'GzipFile.close'
                [Code]
                    File Name: gzip.py
                    Object Name: flush
                    Arg Count: 2
                    Pos Only Arg Count: 0
                    KW Only Arg Count: 0
                    Locals: 2
                    Stack Size: 5
                    Flags: 0x00000043 (CO_OPTIMIZED | CO_NEWLOCALS | CO_NOFREE)
                    [Names]
                        '_check_not_closed'
                        'mode'
                        'WRITE'
                        'fileobj'
                        'write'
                        'compress'
                        'flush'
                    [Var Names]
                        'self'
                        'zlib_mode'
                    [Free Vars]
                    [Cell Vars]
                    [Constants]
                        None
                    [Disassembly]
                        0       LOAD_FAST                       0: self
                        2       LOAD_METHOD                     0: _check_not_closed
                        4       CALL_METHOD                     0
                        6       POP_TOP                         
                        8       LOAD_FAST                       0: self
                        10      LOAD_ATTR                       1: mode
                        12      LOAD_GLOBAL                     2: WRITE
                        14      COMPARE_OP                      2 (==)
                        16      POP_JUMP_IF_FALSE               26 (to 52)
                        18      LOAD_FAST                       0: self
                        20      LOAD_ATTR                       3: fileobj
                        22      LOAD_METHOD                     4: write
                        24      LOAD_FAST                       0: self
                        26      LOAD_ATTR                       5: compress
                        28      LOAD_METHOD                     6: flush
                        30      LOAD_FAST                       1: zlib_mode
                        32      CALL_METHOD                     1
                        34      CALL_METHOD                     1
                        36      POP_TOP                         
                        38      LOAD_FAST                       0: self
                        40      LOAD_ATTR                       3: fileobj
                        42      LOAD_METHOD                     6: flush
                        44      CALL_METHOD                     0
                        46      POP_TOP                         
                        48      LOAD_CONST                      0: None
                        50      RETURN_VALUE                    
                        52      LOAD_CONST                      0: None
                        54      RETURN_VALUE                    
                'GzipFile.flush'
                [Code]
                    File Name: gzip.py
                    Object Name: fileno
                    Arg Count: 1
                    Pos Only Arg Count: 0
                    KW Only Arg Count: 0
                    Locals: 1
                    Stack Size: 2
                    Flags: 0x00000043 (CO_OPTIMIZED | CO_NEWLOCALS | CO_NOFREE)
                    [Names]
                        'fileobj'
                        'fileno'
                    [Var Names]
                        'self'
                    [Free Vars]
                    [Cell Vars]
                    [Constants]
                        "Invoke the underlying file object's fileno() method.\n\n        This will raise AttributeError if the underlying file object\n        doesn't support fileno().\n        "
                    [Disassembly]
                        0       LOAD_FAST                       0: self
                        2       LOAD_ATTR                       0: fileobj
                        4       LOAD_METHOD                     1: fileno
                        6       CALL_METHOD                     0
                        8       RETURN_VALUE                    
                'GzipFile.fileno'
                [Code]
                    File Name: gzip.py
                    Object Name: rewind
                    Arg Count: 1
                    Pos Only Arg Count: 0
                    KW Only Arg Count: 0
                    Locals: 1
                    Stack Size: 3
                    Flags: 0x00000043 (CO_OPTIMIZED | CO_NEWLOCALS | CO_NOFREE)
                    [Names]
                        'mode'
                        'READ'
                        'OSError'
                        '_buffer'
                        'seek'
                    [Var Names]
                        'self'
                    [Free Vars]
                    [Cell Vars]
                    [Constants]
                        'Return the uncompressed stream file position indicator to the\n        beginning of the file'
                        "Can't rewind in write mode"
                        0
                        None
                    [Disassembly]
                        0       LOAD_FAST                       0: self
                        2       LOAD_ATTR                       0: mode
                        4       LOAD_GLOBAL                     1: READ
                        6       COMPARE_OP                      3 (!=)
                        8       POP_JUMP_IF_FALSE               9 (to 18)
                        10      LOAD_GLOBAL                     2: OSError
                        12      LOAD_CONST                      1: "Can't rewind in write mode"
                        14      CALL_FUNCTION                   1
                        16      RAISE_VARARGS                   1
                        18      LOAD_FAST                       0: self
                        20      LOAD_ATTR                       3: _buffer
                        22      LOAD_METHOD                     4: seek
                        24      LOAD_CONST                      2: 0
                        26      CALL_METHOD                     1
                        28      POP_TOP                         
                        30      LOAD_CONST                      3: None
                        32      RETURN_VALUE                    
                'GzipFile.rewind'
                [Code]
                    File Name: gzip.py
                    Object Name: readable
                    Arg Count: 1
                    Pos Only Arg Count: 0
                    KW Only Arg Count: 0
                    Locals: 1
                    Stack Size: 2
                    Flags: 0x00000043 (CO_OPTIMIZED | CO_NEWLOCALS | CO_NOFREE)
                    [Names]
                        'mode'
                        'READ'
                    [Var Names]
                        'self'
                    [Free Vars]
                    [Cell Vars]
                    [Constants]
                        None
                    [Disassembly]
                        0       LOAD_FAST                       0: self
                        2       LOAD_ATTR                       0: mode
                        4       LOAD_GLOBAL                     1: READ
                        6       COMPARE_OP                      2 (==)
                        8       RETURN_VALUE                    
                'GzipFile.readable'
                [Code]
                    File Name: gzip.py
                    Object Name: writable
                    Arg Count: 1
                    Pos Only Arg Count: 0
                    KW Only Arg Count: 0
                    Locals: 1
                    Stack Size: 2
                    Flags: 0x00000043 (CO_OPTIMIZED | CO_NEWLOCALS | CO_NOFREE)
                    [Names]
                        'mode'
                        'WRITE'
                    [Var Names]
                        'self'
                    [Free Vars]
                    [Cell Vars]
                    [Constants]
                        None
                    [Disassembly]
                        0       LOAD_FAST                       0: self
                        2       LOAD_ATTR                       0: mode
                        4       LOAD_GLOBAL                     1: WRITE
                        6       COMPARE_OP                      2 (==)
                        8       RETURN_VALUE                    
                'GzipFile.writable'
                [Code]
                    File Name: gzip.py
                    Object Name: seekable
                    Arg Count: 1
                    Pos Only Arg Count: 0
                    KW Only Arg Count: 0
                    Locals: 1
                    Stack Size: 1
                    Flags: 0x00000043 (CO_OPTIMIZED | CO_NEWLOCALS | CO_NOFREE)
                    [Names]
                    [Var Names]
                        'self'
                    [Free Vars]
                    [Cell Vars]
                    [Constants]
                        None
                        True
                    [Disassembly]
                        0       LOAD_CONST                      1: True
                        2       RETURN_VALUE                    
                'GzipFile.seekable'
                [Code]
                    File Name: gzip.py
                    Object Name: seek
                    Arg Count: 3
                    Pos Only Arg Count: 0
                    KW Only Arg Count: 0
                    Locals: 6
                    Stack Size: 5
                    Flags: 0x00000043 (CO_OPTIMIZED | CO_NEWLOCALS | CO_NOFREE)
                    [Names]
                        'mode'
                        'WRITE'
                        'io'
                        'SEEK_SET'
                        'SEEK_CUR'
                        'offset'
                        'ValueError'
                        'OSError'
                        'range'
                        'write'
                        'READ'
                        '_check_not_closed'
                        '_buffer'
                        'seek'
                    [Var Names]
                        'self'
                        'offset'
                        'whence'
                        'count'
                        'chunk'
                        'i'
                    [Free Vars]
                    [Cell Vars]
                    [Constants]
                        None
                        'Seek from end not supported'
                        'Negative seek in write mode'
                        b'\x00\x00\x00\x00\x00\x00\x00\x00\x00\x00\x00\x00\x00\x00\x00\x00\x00\x00\x00\x00\x00\x00\x00\x00\x00\x00\x00\x00\x00\x00\x00\x00\x00\x00\x00\x00\x00\x00\x00\x00\x00\x00\x00\x00\x00\x00\x00\x00\x00\x00\x00\x00\x00\x00\x00\x00\x00\x00\x00\x00\x00\x00\x00\x00\x00\x00\x00\x00\x00\x00\x00\x00\x00\x00\x00\x00\x00\x00\x00\x00\x00\x00\x00\x00\x00\x00\x00\x00\x00\x00\x00\x00\x00\x00\x00\x00\x00\x00\x00\x00\x00\x00\x00\x00\x00\x00\x00\x00\x00\x00\x00\x00\x00\x00\x00\x00\x00\x00\x00\x00\x00\x00\x00\x00\x00\x00\x00\x00\x00\x00\x00\x00\x00\x00\x00\x00\x00\x00\x00\x00\x00\x00\x00\x00\x00\x00\x00\x00\x00\x00\x00\x00\x00\x00\x00\x00\x00\x00\x00\x00\x00\x00\x00\x00\x00\x00\x00\x00\x00\x00\x00\x00\x00\x00\x00\x00\x00\x00\x00\x00\x00\x00\x00\x00\x00\x00\x00\x00\x00\x00\x00\x00\x00\x00\x00\x00\x00\x00\x00\x00\x00\x00\x00\x00\x00\x00\x00\x00\x00\x00\x00\x00\x00\x00\x00\x00\x00\x00\x00\x00\x00\x00\x00\x00\x00\x00\x00\x00\x00\x00\x00\x00\x00\x00\x00\x00\x00\x00\x00\x00\x00\x00\x00\x00\x00\x00\x00\x00\x00\x00\x00\x00\x00\x00\x00\x00\x00\x00\x00\x00\x00\x00\x00\x00\x00\x00\x00\x00\x00\x00\x00\x00\x00\x00\x00\x00\x00\x00\x00\x00\x00\x00\x00\x00\x00\x00\x00\x00\x00\x00\x00\x00\x00\x00\x00\x00\x00\x00\x00\x00\x00\x00\x00\x00\x00\x00\x00\x00\x00\x00\x00\x00\x00\x00\x00\x00\x00\x00\x00\x00\x00\x00\x00\x00\x00\x00\x00\x00\x00\x00\x00\x00\x00\x00\x00\x00\x00\x00\x00\x00\x00\x00\x00\x00\x00\x00\x00\x00\x00\x00\x00\x00\x00\x00\x00\x00\x00\x00\x00\x00\x00\x00\x00\x00\x00\x00\x00\x00\x00\x00\x00\x00\x00\x00\x00\x00\x00\x00\x00\x00\x00\x00\x00\x00\x00\x00\x00\x00\x00\x00\x00\x00\x00\x00\x00\x00\x00\x00\x00\x00\x00\x00\x00\x00\x00\x00\x00\x00\x00\x00\x00\x00\x00\x00\x00\x00\x00\x00\x00\x00\x00\x00\x00\x00\x00\x00\x00\x00\x00\x00\x00\x00\x00\x00\x00\x00\x00\x00\x00\x00\x00\x00\x00\x00\x00\x00\x00\x00\x00\x00\x00\x00\x00\x00\x00\x00\x00\x00\x00\x00\x00\x00\x00\x00\x00\x00\x00\x00\x00\x00\x00\x00\x00\x00\x00\x00\x00\x00\x00\x00\x00\x00\x00\x00\x00\x00\x00\x00\x00\x00\x00\x00\x00\x00\x00\x00\x00\x00\x00\x00\x00\x00\x00\x00\x00\x00\x00\x00\x00\x00\x00\x00\x00\x00\x00\x00\x00\x00\x00\x00\x00\x00\x00\x00\x00\x00\x00\x00\x00\x00\x00\x00\x00\x00\x00\x00\x00\x00\x00\x00\x00\x00\x00\x00\x00\x00\x00\x00\x00\x00\x00\x00\x00\x00\x00\x00\x00\x00\x00\x00\x00\x00\x00\x00\x00\x00\x00\x00\x00\x00\x00\x00\x00\x00\x00\x00\x00\x00\x00\x00\x00\x00\x00\x00\x00\x00\x00\x00\x00\x00\x00\x00\x00\x00\x00\x00\x00\x00\x00\x00\x00\x00\x00\x00\x00\x00\x00\x00\x00\x00\x00\x00\x00\x00\x00\x00\x00\x00\x00\x00\x00\x00\x00\x00\x00\x00\x00\x00\x00\x00\x00\x00\x00\x00\x00\x00\x00\x00\x00\x00\x00\x00\x00\x00\x00\x00\x00\x00\x00\x00\x00\x00\x00\x00\x00\x00\x00\x00\x00\x00\x00\x00\x00\x00\x00\x00\x00\x00\x00\x00\x00\x00\x00\x00\x00\x00\x00\x00\x00\x00\x00\x00\x00\x00\x00\x00\x00\x00\x00\x00\x00\x00\x00\x00\x00\x00\x00\x00\x00\x00\x00\x00\x00\x00\x00\x00\x00\x00\x00\x00\x00\x00\x00\x00\x00\x00\x00\x00\x00\x00\x00\x00\x00\x00\x00\x00\x00\x00\x00\x00\x00\x00\x00\x00\x00\x00\x00\x00\x00\x00\x00\x00\x00\x00\x00\x00\x00\x00\x00\x00\x00\x00\x00\x00\x00\x00\x00\x00\x00\x00\x00\x00\x00\x00\x00\x00\x00\x00\x00\x00\x00\x00\x00\x00\x00\x00\x00\x00\x00\x00\x00\x00\x00\x00\x00\x00\x00\x00\x00\x00\x00\x00\x00\x00\x00\x00\x00\x00\x00\x00\x00\x00\x00\x00\x00\x00\x00\x00\x00\x00\x00\x00\x00\x00\x00\x00\x00\x00\x00\x00\x00\x00\x00\x00\x00\x00\x00\x00\x00\x00\x00\x00\x00\x00\x00\x00\x00\x00\x00\x00\x00\x00\x00\x00\x00\x00\x00\x00\x00\x00\x00\x00\x00\x00\x00\x00\x00\x00\x00\x00\x00\x00\x00\x00\x00\x00\x00\x00\x00\x00\x00\x00\x00\x00\x00\x00\x00\x00\x00\x00\x00\x00\x00\x00\x00\x00\x00\x00\x00\x00\x00\x00\x00\x00\x00\x00\x00\x00\x00\x00\x00\x00\x00\x00\x00\x00\x00\x00\x00\x00\x00\x00\x00\x00\x00\x00\x00\x00\x00\x00\x00\x00\x00\x00\x00\x00\x00\x00\x00\x00\x00\x00\x00\x00\x00\x00\x00\x00\x00\x00\x00\x00\x00\x00\x00\x00\x00\x00\x00\x00\x00\x00\x00\x00\x00\x00\x00\x00\x00\x00\x00\x00\x00\x00\x00\x00\x00\x00\x00\x00\x00\x00\x00\x00\x00\x00\x00\x00\x00\x00\x00\x00\x00\x00\x00\x00\x00\x00\x00\x00\x00\x00\x00\x00\x00\x00\x00\x00\x00\x00\x00\x00\x00\x00\x00\x00\x00\x00\x00\x00\x00\x00\x00\x00\x00\x00\x00\x00\x00\x00\x00\x00\x00\x00'
                        1024
                        b'\x00'
                    [Disassembly]
                        0       LOAD_FAST                       0: self
                        2       LOAD_ATTR                       0: mode
                        4       LOAD_GLOBAL                     1: WRITE
                        6       COMPARE_OP                      2 (==)
                        8       POP_JUMP_IF_FALSE               67 (to 134)
                        10      LOAD_FAST                       2: whence
                        12      LOAD_GLOBAL                     2: io
                        14      LOAD_ATTR                       3: SEEK_SET
                        16      COMPARE_OP                      3 (!=)
                        18      POP_JUMP_IF_FALSE               25 (to 50)
                        20      LOAD_FAST                       2: whence
                        22      LOAD_GLOBAL                     2: io
                        24      LOAD_ATTR                       4: SEEK_CUR
                        26      COMPARE_OP                      2 (==)
                        28      POP_JUMP_IF_FALSE               21 (to 42)
                        30      LOAD_FAST                       0: self
                        32      LOAD_ATTR                       5: offset
                        34      LOAD_FAST                       1: offset
                        36      BINARY_ADD                      
                        38      STORE_FAST                      1: offset
                        40      JUMP_FORWARD                    4 (to 50)
                        42      LOAD_GLOBAL                     6: ValueError
                        44      LOAD_CONST                      1: 'Seek from end not supported'
                        46      CALL_FUNCTION                   1
                        48      RAISE_VARARGS                   1
                        50      LOAD_FAST                       1: offset
                        52      LOAD_FAST                       0: self
                        54      LOAD_ATTR                       5: offset
                        56      COMPARE_OP                      0 (<)
                        58      POP_JUMP_IF_FALSE               34 (to 68)
                        60      LOAD_GLOBAL                     7: OSError
                        62      LOAD_CONST                      2: 'Negative seek in write mode'
                        64      CALL_FUNCTION                   1
                        66      RAISE_VARARGS                   1
                        68      LOAD_FAST                       1: offset
                        70      LOAD_FAST                       0: self
                        72      LOAD_ATTR                       5: offset
                        74      BINARY_SUBTRACT                 
                        76      STORE_FAST                      3: count
                        78      LOAD_CONST                      3: b'\x00\x00\x00\x00\x00\x00\x00\x00\x00\x00\x00\x00\x00\x00\x00\x00\x00\x00\x00\x00\x00\x00\x00\x00\x00\x00\x00\x00\x00\x00\x00\x00\x00\x00\x00\x00\x00\x00\x00\x00\x00\x00\x00\x00\x00\x00\x00\x00\x00\x00\x00\x00\x00\x00\x00\x00\x00\x00\x00\x00\x00\x00\x00\x00\x00\x00\x00\x00\x00\x00\x00\x00\x00\x00\x00\x00\x00\x00\x00\x00\x00\x00\x00\x00\x00\x00\x00\x00\x00\x00\x00\x00\x00\x00\x00\x00\x00\x00\x00\x00\x00\x00\x00\x00\x00\x00\x00\x00\x00\x00\x00\x00\x00\x00\x00\x00\x00\x00\x00\x00\x00\x00\x00\x00\x00\x00\x00\x00\x00\x00\x00\x00\x00\x00\x00\x00\x00\x00\x00\x00\x00\x00\x00\x00\x00\x00\x00\x00\x00\x00\x00\x00\x00\x00\x00\x00\x00\x00\x00\x00\x00\x00\x00\x00\x00\x00\x00\x00\x00\x00\x00\x00\x00\x00\x00\x00\x00\x00\x00\x00\x00\x00\x00\x00\x00\x00\x00\x00\x00\x00\x00\x00\x00\x00\x00\x00\x00\x00\x00\x00\x00\x00\x00\x00\x00\x00\x00\x00\x00\x00\x00\x00\x00\x00\x00\x00\x00\x00\x00\x00\x00\x00\x00\x00\x00\x00\x00\x00\x00\x00\x00\x00\x00\x00\x00\x00\x00\x00\x00\x00\x00\x00\x00\x00\x00\x00\x00\x00\x00\x00\x00\x00\x00\x00\x00\x00\x00\x00\x00\x00\x00\x00\x00\x00\x00\x00\x00\x00\x00\x00\x00\x00\x00\x00\x00\x00\x00\x00\x00\x00\x00\x00\x00\x00\x00\x00\x00\x00\x00\x00\x00\x00\x00\x00\x00\x00\x00\x00\x00\x00\x00\x00\x00\x00\x00\x00\x00\x00\x00\x00\x00\x00\x00\x00\x00\x00\x00\x00\x00\x00\x00\x00\x00\x00\x00\x00\x00\x00\x00\x00\x00\x00\x00\x00\x00\x00\x00\x00\x00\x00\x00\x00\x00\x00\x00\x00\x00\x00\x00\x00\x00\x00\x00\x00\x00\x00\x00\x00\x00\x00\x00\x00\x00\x00\x00\x00\x00\x00\x00\x00\x00\x00\x00\x00\x00\x00\x00\x00\x00\x00\x00\x00\x00\x00\x00\x00\x00\x00\x00\x00\x00\x00\x00\x00\x00\x00\x00\x00\x00\x00\x00\x00\x00\x00\x00\x00\x00\x00\x00\x00\x00\x00\x00\x00\x00\x00\x00\x00\x00\x00\x00\x00\x00\x00\x00\x00\x00\x00\x00\x00\x00\x00\x00\x00\x00\x00\x00\x00\x00\x00\x00\x00\x00\x00\x00\x00\x00\x00\x00\x00\x00\x00\x00\x00\x00\x00\x00\x00\x00\x00\x00\x00\x00\x00\x00\x00\x00\x00\x00\x00\x00\x00\x00\x00\x00\x00\x00\x00\x00\x00\x00\x00\x00\x00\x00\x00\x00\x00\x00\x00\x00\x00\x00\x00\x00\x00\x00\x00\x00\x00\x00\x00\x00\x00\x00\x00\x00\x00\x00\x00\x00\x00\x00\x00\x00\x00\x00\x00\x00\x00\x00\x00\x00\x00\x00\x00\x00\x00\x00\x00\x00\x00\x00\x00\x00\x00\x00\x00\x00\x00\x00\x00\x00\x00\x00\x00\x00\x00\x00\x00\x00\x00\x00\x00\x00\x00\x00\x00\x00\x00\x00\x00\x00\x00\x00\x00\x00\x00\x00\x00\x00\x00\x00\x00\x00\x00\x00\x00\x00\x00\x00\x00\x00\x00\x00\x00\x00\x00\x00\x00\x00\x00\x00\x00\x00\x00\x00\x00\x00\x00\x00\x00\x00\x00\x00\x00\x00\x00\x00\x00\x00\x00\x00\x00\x00\x00\x00\x00\x00\x00\x00\x00\x00\x00\x00\x00\x00\x00\x00\x00\x00\x00\x00\x00\x00\x00\x00\x00\x00\x00\x00\x00\x00\x00\x00\x00\x00\x00\x00\x00\x00\x00\x00\x00\x00\x00\x00\x00\x00\x00\x00\x00\x00\x00\x00\x00\x00\x00\x00\x00\x00\x00\x00\x00\x00\x00\x00\x00\x00\x00\x00\x00\x00\x00\x00\x00\x00\x00\x00\x00\x00\x00\x00\x00\x00\x00\x00\x00\x00\x00\x00\x00\x00\x00\x00\x00\x00\x00\x00\x00\x00\x00\x00\x00\x00\x00\x00\x00\x00\x00\x00\x00\x00\x00\x00\x00\x00\x00\x00\x00\x00\x00\x00\x00\x00\x00\x00\x00\x00\x00\x00\x00\x00\x00\x00\x00\x00\x00\x00\x00\x00\x00\x00\x00\x00\x00\x00\x00\x00\x00\x00\x00\x00\x00\x00\x00\x00\x00\x00\x00\x00\x00\x00\x00\x00\x00\x00\x00\x00\x00\x00\x00\x00\x00\x00\x00\x00\x00\x00\x00\x00\x00\x00\x00\x00\x00\x00\x00\x00\x00\x00\x00\x00\x00\x00\x00\x00\x00\x00\x00\x00\x00\x00\x00\x00\x00\x00\x00\x00\x00\x00\x00\x00\x00\x00\x00\x00\x00\x00\x00\x00\x00\x00\x00\x00\x00\x00\x00\x00\x00\x00\x00\x00\x00\x00\x00\x00\x00\x00\x00\x00\x00\x00\x00\x00\x00\x00\x00\x00\x00\x00\x00\x00\x00\x00\x00\x00\x00\x00\x00\x00\x00\x00\x00\x00\x00\x00\x00\x00\x00\x00\x00\x00\x00\x00\x00\x00\x00\x00\x00\x00\x00\x00\x00\x00\x00\x00\x00\x00\x00\x00\x00\x00\x00\x00\x00\x00\x00\x00\x00\x00\x00\x00\x00\x00\x00\x00\x00\x00\x00\x00\x00\x00\x00\x00\x00\x00\x00\x00\x00\x00\x00\x00\x00\x00\x00\x00\x00\x00\x00\x00\x00\x00\x00\x00\x00\x00\x00\x00\x00\x00\x00\x00\x00\x00\x00\x00\x00\x00\x00\x00\x00\x00\x00\x00\x00\x00\x00\x00\x00\x00\x00\x00\x00\x00\x00\x00\x00\x00\x00\x00\x00\x00\x00\x00\x00\x00\x00\x00\x00\x00\x00\x00\x00\x00\x00\x00\x00\x00\x00\x00\x00\x00\x00\x00\x00\x00\x00\x00\x00\x00\x00\x00\x00\x00\x00\x00\x00\x00\x00\x00\x00\x00\x00'
                        80      STORE_FAST                      4: chunk
                        82      LOAD_GLOBAL                     8: range
                        84      LOAD_FAST                       3: count
                        86      LOAD_CONST                      4: 1024
                        88      BINARY_FLOOR_DIVIDE             
                        90      CALL_FUNCTION                   1
                        92      GET_ITER                        
                        94      FOR_ITER                        7 (to 110)
                        96      STORE_FAST                      5: i
                        98      LOAD_FAST                       0: self
                        100     LOAD_METHOD                     9: write
                        102     LOAD_FAST                       4: chunk
                        104     CALL_METHOD                     1
                        106     POP_TOP                         
                        108     JUMP_ABSOLUTE                   47 (to 94)
                        110     LOAD_FAST                       0: self
                        112     LOAD_METHOD                     9: write
                        114     LOAD_CONST                      5: b'\x00'
                        116     LOAD_FAST                       3: count
                        118     LOAD_CONST                      4: 1024
                        120     BINARY_MODULO                   
                        122     BINARY_MULTIPLY                 
                        124     CALL_METHOD                     1
                        126     POP_TOP                         
                        128     LOAD_FAST                       0: self
                        130     LOAD_ATTR                       5: offset
                        132     RETURN_VALUE                    
                        134     LOAD_FAST                       0: self
                        136     LOAD_ATTR                       0: mode
                        138     LOAD_GLOBAL                     10: READ
                        140     COMPARE_OP                      2 (==)
                        142     POP_JUMP_IF_FALSE               83 (to 166)
                        144     LOAD_FAST                       0: self
                        146     LOAD_METHOD                     11: _check_not_closed
                        148     CALL_METHOD                     0
                        150     POP_TOP                         
                        152     LOAD_FAST                       0: self
                        154     LOAD_ATTR                       12: _buffer
                        156     LOAD_METHOD                     13: seek
                        158     LOAD_FAST                       1: offset
                        160     LOAD_FAST                       2: whence
                        162     CALL_METHOD                     2
                        164     RETURN_VALUE                    
                        166     LOAD_FAST                       0: self
                        168     LOAD_ATTR                       5: offset
                        170     RETURN_VALUE                    
                'GzipFile.seek'
                [Code]
                    File Name: gzip.py
                    Object Name: readline
                    Arg Count: 2
                    Pos Only Arg Count: 0
                    KW Only Arg Count: 0
                    Locals: 2
                    Stack Size: 3
                    Flags: 0x00000043 (CO_OPTIMIZED | CO_NEWLOCALS | CO_NOFREE)
                    [Names]
                        '_check_not_closed'
                        '_buffer'
                        'readline'
                    [Var Names]
                        'self'
                        'size'
                    [Free Vars]
                    [Cell Vars]
                    [Constants]
                        None
                    [Disassembly]
                        0       LOAD_FAST                       0: self
                        2       LOAD_METHOD                     0: _check_not_closed
                        4       CALL_METHOD                     0
                        6       POP_TOP                         
                        8       LOAD_FAST                       0: self
                        10      LOAD_ATTR                       1: _buffer
                        12      LOAD_METHOD                     2: readline
                        14      LOAD_FAST                       1: size
                        16      CALL_METHOD                     1
                        18      RETURN_VALUE                    
                'GzipFile.readline'
                (
                    -1
                )
            [Disassembly]
                0       LOAD_NAME                       0: __name__
                2       STORE_NAME                      1: __module__
                4       LOAD_CONST                      0: 'GzipFile'
                6       STORE_NAME                      2: __qualname__
                8       LOAD_CONST                      1: 'The GzipFile class simulates most of the methods of a file object with\n    the exception of the truncate() method.\n\n    This class only supports opening files in binary mode. If you need to open a\n    compressed file in text mode, use the gzip.open() function.\n\n    '
                10      STORE_NAME                      3: __doc__
                12      LOAD_CONST                      2: None
                14      STORE_NAME                      4: myfileobj
                16      LOAD_CONST                      2: None
                18      LOAD_CONST                      2: None
                20      LOAD_NAME                       5: _COMPRESS_LEVEL_BEST
                22      LOAD_CONST                      2: None
                24      LOAD_CONST                      2: None
                26      BUILD_TUPLE                     5
                28      LOAD_CONST                      3: <CODE> __init__
                30      LOAD_CONST                      4: 'GzipFile.__init__'
                32      MAKE_FUNCTION                   1
                34      STORE_NAME                      6: __init__
                36      LOAD_NAME                       7: property
                38      LOAD_CONST                      5: <CODE> filename
                40      LOAD_CONST                      6: 'GzipFile.filename'
                42      MAKE_FUNCTION                   0
                44      CALL_FUNCTION                   1
                46      STORE_NAME                      8: filename
                48      LOAD_NAME                       7: property
                50      LOAD_CONST                      7: <CODE> mtime
                52      LOAD_CONST                      8: 'GzipFile.mtime'
                54      MAKE_FUNCTION                   0
                56      CALL_FUNCTION                   1
                58      STORE_NAME                      9: mtime
                60      LOAD_CONST                      9: <CODE> __repr__
                62      LOAD_CONST                      10: 'GzipFile.__repr__'
                64      MAKE_FUNCTION                   0
                66      STORE_NAME                      10: __repr__
                68      LOAD_CONST                      11: <CODE> _init_write
                70      LOAD_CONST                      12: 'GzipFile._init_write'
                72      MAKE_FUNCTION                   0
                74      STORE_NAME                      11: _init_write
                76      LOAD_CONST                      13: <CODE> _write_gzip_header
                78      LOAD_CONST                      14: 'GzipFile._write_gzip_header'
                80      MAKE_FUNCTION                   0
                82      STORE_NAME                      12: _write_gzip_header
                84      LOAD_CONST                      15: <CODE> write
                86      LOAD_CONST                      16: 'GzipFile.write'
                88      MAKE_FUNCTION                   0
                90      STORE_NAME                      13: write
                92      LOAD_CONST                      44: (-1,)
                94      LOAD_CONST                      18: <CODE> read
                96      LOAD_CONST                      19: 'GzipFile.read'
                98      MAKE_FUNCTION                   1
                100     STORE_NAME                      14: read
                102     LOAD_CONST                      44: (-1,)
                104     LOAD_CONST                      20: <CODE> read1
                106     LOAD_CONST                      21: 'GzipFile.read1'
                108     MAKE_FUNCTION                   1
                110     STORE_NAME                      15: read1
                112     LOAD_CONST                      22: <CODE> peek
                114     LOAD_CONST                      23: 'GzipFile.peek'
                116     MAKE_FUNCTION                   0
                118     STORE_NAME                      16: peek
                120     LOAD_NAME                       7: property
                122     LOAD_CONST                      24: <CODE> closed
                124     LOAD_CONST                      25: 'GzipFile.closed'
                126     MAKE_FUNCTION                   0
                128     CALL_FUNCTION                   1
                130     STORE_NAME                      17: closed
                132     LOAD_CONST                      26: <CODE> close
                134     LOAD_CONST                      27: 'GzipFile.close'
                136     MAKE_FUNCTION                   0
                138     STORE_NAME                      18: close
                140     LOAD_NAME                       19: zlib
                142     LOAD_ATTR                       20: Z_SYNC_FLUSH
                144     BUILD_TUPLE                     1
                146     LOAD_CONST                      28: <CODE> flush
                148     LOAD_CONST                      29: 'GzipFile.flush'
                150     MAKE_FUNCTION                   1
                152     STORE_NAME                      21: flush
                154     LOAD_CONST                      30: <CODE> fileno
                156     LOAD_CONST                      31: 'GzipFile.fileno'
                158     MAKE_FUNCTION                   0
                160     STORE_NAME                      22: fileno
                162     LOAD_CONST                      32: <CODE> rewind
                164     LOAD_CONST                      33: 'GzipFile.rewind'
                166     MAKE_FUNCTION                   0
                168     STORE_NAME                      23: rewind
                170     LOAD_CONST                      34: <CODE> readable
                172     LOAD_CONST                      35: 'GzipFile.readable'
                174     MAKE_FUNCTION                   0
                176     STORE_NAME                      24: readable
                178     LOAD_CONST                      36: <CODE> writable
                180     LOAD_CONST                      37: 'GzipFile.writable'
                182     MAKE_FUNCTION                   0
                184     STORE_NAME                      25: writable
                186     LOAD_CONST                      38: <CODE> seekable
                188     LOAD_CONST                      39: 'GzipFile.seekable'
                190     MAKE_FUNCTION                   0
                192     STORE_NAME                      26: seekable
                194     LOAD_NAME                       27: io
                196     LOAD_ATTR                       28: SEEK_SET
                198     BUILD_TUPLE                     1
                200     LOAD_CONST                      40: <CODE> seek
                202     LOAD_CONST                      41: 'GzipFile.seek'
                204     MAKE_FUNCTION                   1
                206     STORE_NAME                      29: seek
                208     LOAD_CONST                      44: (-1,)
                210     LOAD_CONST                      42: <CODE> readline
                212     LOAD_CONST                      43: 'GzipFile.readline'
                214     MAKE_FUNCTION                   1
                216     STORE_NAME                      30: readline
                218     LOAD_CONST                      2: None
                220     RETURN_VALUE                    
        'GzipFile'
        [Code]
            File Name: gzip.py
            Object Name: _GzipReader
            Arg Count: 0
            Pos Only Arg Count: 0
            KW Only Arg Count: 0
            Locals: 0
            Stack Size: 3
            Flags: 0x00000000
            [Names]
                '__name__'
                '__module__'
                '__qualname__'
                '__init__'
                '_init_read'
                '_read_exact'
                '_read_gzip_header'
                'read'
                '_add_read_data'
                '_read_eof'
                '_rewind'
                '__classcell__'
            [Var Names]
            [Free Vars]
            [Cell Vars]
                '__class__'
            [Constants]
                '_GzipReader'
                [Code]
                    File Name: gzip.py
                    Object Name: __init__
                    Arg Count: 2
                    Pos Only Arg Count: 0
                    KW Only Arg Count: 0
                    Locals: 2
                    Stack Size: 5
                    Flags: 0x00000003 (CO_OPTIMIZED | CO_NEWLOCALS)
                    [Names]
                        'super'
                        '__init__'
                        '_PaddedFile'
                        'zlib'
                        'decompressobj'
                        'MAX_WBITS'
                        '_new_member'
                        '_last_mtime'
                    [Var Names]
                        'self'
                        'fp'
                    [Free Vars]
                        '__class__'
                    [Cell Vars]
                    [Constants]
                        None
                        (
                            'wbits'
                        )
                        True
                    [Disassembly]
                        0       LOAD_GLOBAL                     0: super
                        2       CALL_FUNCTION                   0
                        4       LOAD_ATTR                       1: __init__
                        6       LOAD_GLOBAL                     2: _PaddedFile
                        8       LOAD_FAST                       1: fp
                        10      CALL_FUNCTION                   1
                        12      LOAD_GLOBAL                     3: zlib
                        14      LOAD_ATTR                       4: decompressobj
                        16      LOAD_GLOBAL                     3: zlib
                        18      LOAD_ATTR                       5: MAX_WBITS
                        20      UNARY_NEGATIVE                  
                        22      LOAD_CONST                      1: ('wbits',)
                        24      CALL_FUNCTION_KW                3
                        26      POP_TOP                         
                        28      LOAD_CONST                      2: True
                        30      LOAD_FAST                       0: self
                        32      STORE_ATTR                      6: _new_member
                        34      LOAD_CONST                      0: None
                        36      LOAD_FAST                       0: self
                        38      STORE_ATTR                      7: _last_mtime
                        40      LOAD_CONST                      0: None
                        42      RETURN_VALUE                    
                '_GzipReader.__init__'
                [Code]
                    File Name: gzip.py
                    Object Name: _init_read
                    Arg Count: 1
                    Pos Only Arg Count: 0
                    KW Only Arg Count: 0
                    Locals: 1
                    Stack Size: 3
                    Flags: 0x00000043 (CO_OPTIMIZED | CO_NEWLOCALS | CO_NOFREE)
                    [Names]
                        'zlib'
                        'crc32'
                        '_crc'
                        '_stream_size'
                    [Var Names]
                        'self'
                    [Free Vars]
                    [Cell Vars]
                    [Constants]
                        None
                        b''
                        0
                    [Disassembly]
                        0       LOAD_GLOBAL                     0: zlib
                        2       LOAD_METHOD                     1: crc32
                        4       LOAD_CONST                      1: b''
                        6       CALL_METHOD                     1
                        8       LOAD_FAST                       0: self
                        10      STORE_ATTR                      2: _crc
                        12      LOAD_CONST                      2: 0
                        14      LOAD_FAST                       0: self
                        16      STORE_ATTR                      3: _stream_size
                        18      LOAD_CONST                      0: None
                        20      RETURN_VALUE                    
                '_GzipReader._init_read'
                [Code]
                    File Name: gzip.py
                    Object Name: _read_exact
                    Arg Count: 2
                    Pos Only Arg Count: 0
                    KW Only Arg Count: 0
                    Locals: 4
                    Stack Size: 5
                    Flags: 0x00000043 (CO_OPTIMIZED | CO_NEWLOCALS | CO_NOFREE)
                    [Names]
                        '_fp'
                        'read'
                        'len'
                        'EOFError'
                    [Var Names]
                        'self'
                        'n'
                        'data'
                        'b'
                    [Free Vars]
                    [Cell Vars]
                    [Constants]
                        'Read exactly *n* bytes from `self._fp`\n\n        This method is required because self._fp may be unbuffered,\n        i.e. return short reads.\n        '
                        'Compressed file ended before the end-of-stream marker was reached'
                    [Disassembly]
                        0       LOAD_FAST                       0: self
                        2       LOAD_ATTR                       0: _fp
                        4       LOAD_METHOD                     1: read
                        6       LOAD_FAST                       1: n
                        8       CALL_METHOD                     1
                        10      STORE_FAST                      2: data
                        12      LOAD_GLOBAL                     2: len
                        14      LOAD_FAST                       2: data
                        16      CALL_FUNCTION                   1
                        18      LOAD_FAST                       1: n
                        20      COMPARE_OP                      0 (<)
                        22      POP_JUMP_IF_FALSE               38 (to 76)
                        24      LOAD_FAST                       0: self
                        26      LOAD_ATTR                       0: _fp
                        28      LOAD_METHOD                     1: read
                        30      LOAD_FAST                       1: n
                        32      LOAD_GLOBAL                     2: len
                        34      LOAD_FAST                       2: data
                        36      CALL_FUNCTION                   1
                        38      BINARY_SUBTRACT                 
                        40      CALL_METHOD                     1
                        42      STORE_FAST                      3: b
                        44      LOAD_FAST                       3: b
                        46      POP_JUMP_IF_TRUE                28 (to 56)
                        48      LOAD_GLOBAL                     3: EOFError
                        50      LOAD_CONST                      1: 'Compressed file ended before the end-of-stream marker was reached'
                        52      CALL_FUNCTION                   1
                        54      RAISE_VARARGS                   1
                        56      LOAD_FAST                       2: data
                        58      LOAD_FAST                       3: b
                        60      INPLACE_ADD                     
                        62      STORE_FAST                      2: data
                        64      LOAD_GLOBAL                     2: len
                        66      LOAD_FAST                       2: data
                        68      CALL_FUNCTION                   1
                        70      LOAD_FAST                       1: n
                        72      COMPARE_OP                      0 (<)
                        74      POP_JUMP_IF_TRUE                12 (to 24)
                        76      LOAD_FAST                       2: data
                        78      RETURN_VALUE                    
                '_GzipReader._read_exact'
                [Code]
                    File Name: gzip.py
                    Object Name: _read_gzip_header
                    Arg Count: 1
                    Pos Only Arg Count: 0
                    KW Only Arg Count: 0
                    Locals: 6
                    Stack Size: 6
                    Flags: 0x00000043 (CO_OPTIMIZED | CO_NEWLOCALS | CO_NOFREE)
                    [Names]
                        '_fp'
                        'read'
                        'BadGzipFile'
                        'struct'
                        'unpack'
                        '_read_exact'
                        '_last_mtime'
                        'FEXTRA'
                        'FNAME'
                        'FCOMMENT'
                        'FHCRC'
                    [Var Names]
                        'self'
                        'magic'
                        'method'
                        'flag'
                        'extra_len'
                        's'
                    [Free Vars]
                    [Cell Vars]
                    [Constants]
                        None
                        2
                        b''
                        False
                        b'\x1f\x8b'
                        'Not a gzipped file (%r)'
                        '<BBIxx'
                        8
                        'Unknown compression method'
                        '<H'
                        True
                        1
                        b'\x00'
                    [Disassembly]
                        0       LOAD_FAST                       0: self
                        2       LOAD_ATTR                       0: _fp
                        4       LOAD_METHOD                     1: read
                        6       LOAD_CONST                      1: 2
                        8       CALL_METHOD                     1
                        10      STORE_FAST                      1: magic
                        12      LOAD_FAST                       1: magic
                        14      LOAD_CONST                      2: b''
                        16      COMPARE_OP                      2 (==)
                        18      POP_JUMP_IF_FALSE               12 (to 24)
                        20      LOAD_CONST                      3: False
                        22      RETURN_VALUE                    
                        24      LOAD_FAST                       1: magic
                        26      LOAD_CONST                      4: b'\x1f\x8b'
                        28      COMPARE_OP                      3 (!=)
                        30      POP_JUMP_IF_FALSE               22 (to 44)
                        32      LOAD_GLOBAL                     2: BadGzipFile
                        34      LOAD_CONST                      5: 'Not a gzipped file (%r)'
                        36      LOAD_FAST                       1: magic
                        38      BINARY_MODULO                   
                        40      CALL_FUNCTION                   1
                        42      RAISE_VARARGS                   1
                        44      LOAD_GLOBAL                     3: struct
                        46      LOAD_METHOD                     4: unpack
                        48      LOAD_CONST                      6: '<BBIxx'
                        50      LOAD_FAST                       0: self
                        52      LOAD_METHOD                     5: _read_exact
                        54      LOAD_CONST                      7: 8
                        56      CALL_METHOD                     1
                        58      CALL_METHOD                     2
                        60      UNPACK_SEQUENCE                 3
                        62      STORE_FAST                      2: method
                        64      STORE_FAST                      3: flag
                        66      LOAD_FAST                       0: self
                        68      STORE_ATTR                      6: _last_mtime
                        70      LOAD_FAST                       2: method
                        72      LOAD_CONST                      7: 8
                        74      COMPARE_OP                      3 (!=)
                        76      POP_JUMP_IF_FALSE               43 (to 86)
                        78      LOAD_GLOBAL                     2: BadGzipFile
                        80      LOAD_CONST                      8: 'Unknown compression method'
                        82      CALL_FUNCTION                   1
                        84      RAISE_VARARGS                   1
                        86      LOAD_FAST                       3: flag
                        88      LOAD_GLOBAL                     7: FEXTRA
                        90      BINARY_AND                      
                        92      POP_JUMP_IF_FALSE               62 (to 124)
                        94      LOAD_GLOBAL                     3: struct
                        96      LOAD_METHOD                     4: unpack
                        98      LOAD_CONST                      9: '<H'
                        100     LOAD_FAST                       0: self
                        102     LOAD_METHOD                     5: _read_exact
                        104     LOAD_CONST                      1: 2
                        106     CALL_METHOD                     1
                        108     CALL_METHOD                     2
                        110     UNPACK_SEQUENCE                 1
                        112     STORE_FAST                      4: extra_len
                        114     LOAD_FAST                       0: self
                        116     LOAD_METHOD                     5: _read_exact
                        118     LOAD_FAST                       4: extra_len
                        120     CALL_METHOD                     1
                        122     POP_TOP                         
                        124     LOAD_FAST                       3: flag
                        126     LOAD_GLOBAL                     8: FNAME
                        128     BINARY_AND                      
                        130     POP_JUMP_IF_FALSE               81 (to 162)
                        132     NOP                             
                        134     LOAD_FAST                       0: self
                        136     LOAD_ATTR                       0: _fp
                        138     LOAD_METHOD                     1: read
                        140     LOAD_CONST                      11: 1
                        142     CALL_METHOD                     1
                        144     STORE_FAST                      5: s
                        146     LOAD_FAST                       5: s
                        148     POP_JUMP_IF_FALSE               79 (to 158)
                        150     LOAD_FAST                       5: s
                        152     LOAD_CONST                      12: b'\x00'
                        154     COMPARE_OP                      2 (==)
                        156     POP_JUMP_IF_FALSE               80 (to 160)
                        158     JUMP_FORWARD                    1 (to 162)
                        160     JUMP_ABSOLUTE                   67 (to 134)
                        162     LOAD_FAST                       3: flag
                        164     LOAD_GLOBAL                     9: FCOMMENT
                        166     BINARY_AND                      
                        168     POP_JUMP_IF_FALSE               100 (to 200)
                        170     NOP                             
                        172     LOAD_FAST                       0: self
                        174     LOAD_ATTR                       0: _fp
                        176     LOAD_METHOD                     1: read
                        178     LOAD_CONST                      11: 1
                        180     CALL_METHOD                     1
                        182     STORE_FAST                      5: s
                        184     LOAD_FAST                       5: s
                        186     POP_JUMP_IF_FALSE               98 (to 196)
                        188     LOAD_FAST                       5: s
                        190     LOAD_CONST                      12: b'\x00'
                        192     COMPARE_OP                      2 (==)
                        194     POP_JUMP_IF_FALSE               99 (to 198)
                        196     JUMP_FORWARD                    1 (to 200)
                        198     JUMP_ABSOLUTE                   86 (to 172)
                        200     LOAD_FAST                       3: flag
                        202     LOAD_GLOBAL                     10: FHCRC
                        204     BINARY_AND                      
                        206     POP_JUMP_IF_FALSE               109 (to 218)
                        208     LOAD_FAST                       0: self
                        210     LOAD_METHOD                     5: _read_exact
                        212     LOAD_CONST                      1: 2
                        214     CALL_METHOD                     1
                        216     POP_TOP                         
                        218     LOAD_CONST                      10: True
                        220     RETURN_VALUE                    
                '_GzipReader._read_gzip_header'
                -1
                [Code]
                    File Name: gzip.py
                    Object Name: read
                    Arg Count: 2
                    Pos Only Arg Count: 0
                    KW Only Arg Count: 0
                    Locals: 4
                    Stack Size: 4
                    Flags: 0x00000043 (CO_OPTIMIZED | CO_NEWLOCALS | CO_NOFREE)
                    [Names]
                        'readall'
                        '_decompressor'
                        'eof'
                        '_read_eof'
                        '_new_member'
                        '_decomp_factory'
                        '_decomp_args'
                        '_init_read'
                        '_read_gzip_header'
                        '_pos'
                        '_size'
                        '_fp'
                        'read'
                        'io'
                        'DEFAULT_BUFFER_SIZE'
                        'decompress'
                        'unconsumed_tail'
                        'prepend'
                        'unused_data'
                        'EOFError'
                        '_add_read_data'
                        'len'
                    [Var Names]
                        'self'
                        'size'
                        'buf'
                        'uncompress'
                    [Free Vars]
                    [Cell Vars]
                    [Constants]
                        None
                        0
                        b''
                        True
                        False
                        'Compressed file ended before the end-of-stream marker was reached'
                        (
                        )
                    [Disassembly]
                        0       LOAD_FAST                       1: size
                        2       LOAD_CONST                      1: 0
                        4       COMPARE_OP                      0 (<)
                        6       POP_JUMP_IF_FALSE               8 (to 16)
                        8       LOAD_FAST                       0: self
                        10      LOAD_METHOD                     0: readall
                        12      CALL_METHOD                     0
                        14      RETURN_VALUE                    
                        16      LOAD_FAST                       1: size
                        18      POP_JUMP_IF_TRUE                12 (to 24)
                        20      LOAD_CONST                      2: b''
                        22      RETURN_VALUE                    
                        24      NOP                             
                        26      LOAD_FAST                       0: self
                        28      LOAD_ATTR                       1: _decompressor
                        30      LOAD_ATTR                       2: eof
                        32      POP_JUMP_IF_FALSE               34 (to 68)
                        34      LOAD_FAST                       0: self
                        36      LOAD_METHOD                     3: _read_eof
                        38      CALL_METHOD                     0
                        40      POP_TOP                         
                        42      LOAD_CONST                      3: True
                        44      LOAD_FAST                       0: self
                        46      STORE_ATTR                      4: _new_member
                        48      LOAD_FAST                       0: self
                        50      LOAD_ATTR                       5: _decomp_factory
                        52      LOAD_CONST                      6: ()
                        54      BUILD_MAP                       0
                        56      LOAD_FAST                       0: self
                        58      LOAD_ATTR                       6: _decomp_args
                        60      DICT_MERGE                      1
                        62      CALL_FUNCTION_EX                1
                        64      LOAD_FAST                       0: self
                        66      STORE_ATTR                      1: _decompressor
                        68      LOAD_FAST                       0: self
                        70      LOAD_ATTR                       4: _new_member
                        72      POP_JUMP_IF_FALSE               54 (to 108)
                        74      LOAD_FAST                       0: self
                        76      LOAD_METHOD                     7: _init_read
                        78      CALL_METHOD                     0
                        80      POP_TOP                         
                        82      LOAD_FAST                       0: self
                        84      LOAD_METHOD                     8: _read_gzip_header
                        86      CALL_METHOD                     0
                        88      POP_JUMP_IF_TRUE                51 (to 102)
                        90      LOAD_FAST                       0: self
                        92      LOAD_ATTR                       9: _pos
                        94      LOAD_FAST                       0: self
                        96      STORE_ATTR                      10: _size
                        98      LOAD_CONST                      2: b''
                        100     RETURN_VALUE                    
                        102     LOAD_CONST                      4: False
                        104     LOAD_FAST                       0: self
                        106     STORE_ATTR                      4: _new_member
                        108     LOAD_FAST                       0: self
                        110     LOAD_ATTR                       11: _fp
                        112     LOAD_METHOD                     12: read
                        114     LOAD_GLOBAL                     13: io
                        116     LOAD_ATTR                       14: DEFAULT_BUFFER_SIZE
                        118     CALL_METHOD                     1
                        120     STORE_FAST                      2: buf
                        122     LOAD_FAST                       0: self
                        124     LOAD_ATTR                       1: _decompressor
                        126     LOAD_METHOD                     15: decompress
                        128     LOAD_FAST                       2: buf
                        130     LOAD_FAST                       1: size
                        132     CALL_METHOD                     2
                        134     STORE_FAST                      3: uncompress
                        136     LOAD_FAST                       0: self
                        138     LOAD_ATTR                       1: _decompressor
                        140     LOAD_ATTR                       16: unconsumed_tail
                        142     LOAD_CONST                      2: b''
                        144     COMPARE_OP                      3 (!=)
                        146     POP_JUMP_IF_FALSE               83 (to 166)
                        148     LOAD_FAST                       0: self
                        150     LOAD_ATTR                       11: _fp
                        152     LOAD_METHOD                     17: prepend
                        154     LOAD_FAST                       0: self
                        156     LOAD_ATTR                       1: _decompressor
                        158     LOAD_ATTR                       16: unconsumed_tail
                        160     CALL_METHOD                     1
                        162     POP_TOP                         
                        164     JUMP_FORWARD                    14 (to 194)
                        166     LOAD_FAST                       0: self
                        168     LOAD_ATTR                       1: _decompressor
                        170     LOAD_ATTR                       18: unused_data
                        172     LOAD_CONST                      2: b''
                        174     COMPARE_OP                      3 (!=)
                        176     POP_JUMP_IF_FALSE               97 (to 194)
                        178     LOAD_FAST                       0: self
                        180     LOAD_ATTR                       11: _fp
                        182     LOAD_METHOD                     17: prepend
                        184     LOAD_FAST                       0: self
                        186     LOAD_ATTR                       1: _decompressor
                        188     LOAD_ATTR                       18: unused_data
                        190     CALL_METHOD                     1
                        192     POP_TOP                         
                        194     LOAD_FAST                       3: uncompress
                        196     LOAD_CONST                      2: b''
                        198     COMPARE_OP                      3 (!=)
                        200     POP_JUMP_IF_FALSE               102 (to 204)
                        202     JUMP_FORWARD                    9 (to 222)
                        204     LOAD_FAST                       2: buf
                        206     LOAD_CONST                      2: b''
                        208     COMPARE_OP                      2 (==)
                        210     POP_JUMP_IF_FALSE               110 (to 220)
                        212     LOAD_GLOBAL                     19: EOFError
                        214     LOAD_CONST                      5: 'Compressed file ended before the end-of-stream marker was reached'
                        216     CALL_FUNCTION                   1
                        218     RAISE_VARARGS                   1
                        220     JUMP_ABSOLUTE                   13 (to 26)
                        222     LOAD_FAST                       0: self
                        224     LOAD_METHOD                     20: _add_read_data
                        226     LOAD_FAST                       3: uncompress
                        228     CALL_METHOD                     1
                        230     POP_TOP                         
                        232     LOAD_FAST                       0: self
                        234     DUP_TOP                         
                        236     LOAD_ATTR                       9: _pos
                        238     LOAD_GLOBAL                     21: len
                        240     LOAD_FAST                       3: uncompress
                        242     CALL_FUNCTION                   1
                        244     INPLACE_ADD                     
                        246     ROT_TWO                         
                        248     STORE_ATTR                      9: _pos
                        250     LOAD_FAST                       3: uncompress
                        252     RETURN_VALUE                    
                '_GzipReader.read'
                [Code]
                    File Name: gzip.py
                    Object Name: _add_read_data
                    Arg Count: 2
                    Pos Only Arg Count: 0
                    KW Only Arg Count: 0
                    Locals: 2
                    Stack Size: 4
                    Flags: 0x00000043 (CO_OPTIMIZED | CO_NEWLOCALS | CO_NOFREE)
                    [Names]
                        'zlib'
                        'crc32'
                        '_crc'
                        '_stream_size'
                        'len'
                    [Var Names]
                        'self'
                        'data'
                    [Free Vars]
                    [Cell Vars]
                    [Constants]
                        None
                    [Disassembly]
                        0       LOAD_GLOBAL                     0: zlib
                        2       LOAD_METHOD                     1: crc32
                        4       LOAD_FAST                       1: data
                        6       LOAD_FAST                       0: self
                        8       LOAD_ATTR                       2: _crc
                        10      CALL_METHOD                     2
                        12      LOAD_FAST                       0: self
                        14      STORE_ATTR                      2: _crc
                        16      LOAD_FAST                       0: self
                        18      LOAD_ATTR                       3: _stream_size
                        20      LOAD_GLOBAL                     4: len
                        22      LOAD_FAST                       1: data
                        24      CALL_FUNCTION                   1
                        26      BINARY_ADD                      
                        28      LOAD_FAST                       0: self
                        30      STORE_ATTR                      3: _stream_size
                        32      LOAD_CONST                      0: None
                        34      RETURN_VALUE                    
                '_GzipReader._add_read_data'
                [Code]
                    File Name: gzip.py
                    Object Name: _read_eof
                    Arg Count: 1
                    Pos Only Arg Count: 0
                    KW Only Arg Count: 0
                    Locals: 4
                    Stack Size: 6
                    Flags: 0x00000043 (CO_OPTIMIZED | CO_NEWLOCALS | CO_NOFREE)
                    [Names]
                        'struct'
                        'unpack'
                        '_read_exact'
                        '_crc'
                        'BadGzipFile'
                        'hex'
                        '_stream_size'
                        '_fp'
                        'read'
                        'prepend'
                    [Var Names]
                        'self'
                        'crc32'
                        'isize'
                        'c'
                    [Free Vars]
                    [Cell Vars]
                    [Constants]
                        None
                        '<II'
                        8
                        'CRC check failed %s != %s'
                        0xFFFFFFFF
                        'Incorrect length of data produced'
                        b'\x00'
                        1
                    [Disassembly]
                        0       LOAD_GLOBAL                     0: struct
                        2       LOAD_METHOD                     1: unpack
                        4       LOAD_CONST                      1: '<II'
                        6       LOAD_FAST                       0: self
                        8       LOAD_METHOD                     2: _read_exact
                        10      LOAD_CONST                      2: 8
                        12      CALL_METHOD                     1
                        14      CALL_METHOD                     2
                        16      UNPACK_SEQUENCE                 2
                        18      STORE_FAST                      1: crc32
                        20      STORE_FAST                      2: isize
                        22      LOAD_FAST                       1: crc32
                        24      LOAD_FAST                       0: self
                        26      LOAD_ATTR                       3: _crc
                        28      COMPARE_OP                      3 (!=)
                        30      POP_JUMP_IF_FALSE               29 (to 58)
                        32      LOAD_GLOBAL                     4: BadGzipFile
                        34      LOAD_CONST                      3: 'CRC check failed %s != %s'
                        36      LOAD_GLOBAL                     5: hex
                        38      LOAD_FAST                       1: crc32
                        40      CALL_FUNCTION                   1
                        42      LOAD_GLOBAL                     5: hex
                        44      LOAD_FAST                       0: self
                        46      LOAD_ATTR                       3: _crc
                        48      CALL_FUNCTION                   1
                        50      BUILD_TUPLE                     2
                        52      BINARY_MODULO                   
                        54      CALL_FUNCTION                   1
                        56      RAISE_VARARGS                   1
                        58      LOAD_FAST                       2: isize
                        60      LOAD_FAST                       0: self
                        62      LOAD_ATTR                       6: _stream_size
                        64      LOAD_CONST                      4: 0xFFFFFFFF
                        66      BINARY_AND                      
                        68      COMPARE_OP                      3 (!=)
                        70      POP_JUMP_IF_FALSE               40 (to 80)
                        72      LOAD_GLOBAL                     4: BadGzipFile
                        74      LOAD_CONST                      5: 'Incorrect length of data produced'
                        76      CALL_FUNCTION                   1
                        78      RAISE_VARARGS                   1
                        80      LOAD_CONST                      6: b'\x00'
                        82      STORE_FAST                      3: c
                        84      LOAD_FAST                       3: c
                        86      LOAD_CONST                      6: b'\x00'
                        88      COMPARE_OP                      2 (==)
                        90      POP_JUMP_IF_FALSE               56 (to 112)
                        92      LOAD_FAST                       0: self
                        94      LOAD_ATTR                       7: _fp
                        96      LOAD_METHOD                     8: read
                        98      LOAD_CONST                      7: 1
                        100     CALL_METHOD                     1
                        102     STORE_FAST                      3: c
                        104     LOAD_FAST                       3: c
                        106     LOAD_CONST                      6: b'\x00'
                        108     COMPARE_OP                      2 (==)
                        110     POP_JUMP_IF_TRUE                46 (to 92)
                        112     LOAD_FAST                       3: c
                        114     POP_JUMP_IF_FALSE               66 (to 132)
                        116     LOAD_FAST                       0: self
                        118     LOAD_ATTR                       7: _fp
                        120     LOAD_METHOD                     9: prepend
                        122     LOAD_FAST                       3: c
                        124     CALL_METHOD                     1
                        126     POP_TOP                         
                        128     LOAD_CONST                      0: None
                        130     RETURN_VALUE                    
                        132     LOAD_CONST                      0: None
                        134     RETURN_VALUE                    
                '_GzipReader._read_eof'
                [Code]
                    File Name: gzip.py
                    Object Name: _rewind
                    Arg Count: 1
                    Pos Only Arg Count: 0
                    KW Only Arg Count: 0
                    Locals: 1
                    Stack Size: 2
                    Flags: 0x00000003 (CO_OPTIMIZED | CO_NEWLOCALS)
                    [Names]
                        'super'
                        '_rewind'
                        '_new_member'
                    [Var Names]
                        'self'
                    [Free Vars]
                        '__class__'
                    [Cell Vars]
                    [Constants]
                        None
                        True
                    [Disassembly]
                        0       LOAD_GLOBAL                     0: super
                        2       CALL_FUNCTION                   0
                        4       LOAD_METHOD                     1: _rewind
                        6       CALL_METHOD                     0
                        8       POP_TOP                         
                        10      LOAD_CONST                      1: True
                        12      LOAD_FAST                       0: self
                        14      STORE_ATTR                      2: _new_member
                        16      LOAD_CONST                      0: None
                        18      RETURN_VALUE                    
                '_GzipReader._rewind'
                (
                    -1
                )
            [Disassembly]
                0       LOAD_NAME                       0: __name__
                2       STORE_NAME                      1: __module__
                4       LOAD_CONST                      0: '_GzipReader'
                6       STORE_NAME                      2: __qualname__
                8       LOAD_CLOSURE                    0: __class__
                10      BUILD_TUPLE                     1
                12      LOAD_CONST                      1: <CODE> __init__
                14      LOAD_CONST                      2: '_GzipReader.__init__'
                16      MAKE_FUNCTION                   8
                18      STORE_NAME                      3: __init__
                20      LOAD_CONST                      3: <CODE> _init_read
                22      LOAD_CONST                      4: '_GzipReader._init_read'
                24      MAKE_FUNCTION                   0
                26      STORE_NAME                      4: _init_read
                28      LOAD_CONST                      5: <CODE> _read_exact
                30      LOAD_CONST                      6: '_GzipReader._read_exact'
                32      MAKE_FUNCTION                   0
                34      STORE_NAME                      5: _read_exact
                36      LOAD_CONST                      7: <CODE> _read_gzip_header
                38      LOAD_CONST                      8: '_GzipReader._read_gzip_header'
                40      MAKE_FUNCTION                   0
                42      STORE_NAME                      6: _read_gzip_header
                44      LOAD_CONST                      18: (-1,)
                46      LOAD_CONST                      10: <CODE> read
                48      LOAD_CONST                      11: '_GzipReader.read'
                50      MAKE_FUNCTION                   1
                52      STORE_NAME                      7: read
                54      LOAD_CONST                      12: <CODE> _add_read_data
                56      LOAD_CONST                      13: '_GzipReader._add_read_data'
                58      MAKE_FUNCTION                   0
                60      STORE_NAME                      8: _add_read_data
                62      LOAD_CONST                      14: <CODE> _read_eof
                64      LOAD_CONST                      15: '_GzipReader._read_eof'
                66      MAKE_FUNCTION                   0
                68      STORE_NAME                      9: _read_eof
                70      LOAD_CLOSURE                    0: __class__
                72      BUILD_TUPLE                     1
                74      LOAD_CONST                      16: <CODE> _rewind
                76      LOAD_CONST                      17: '_GzipReader._rewind'
                78      MAKE_FUNCTION                   8
                80      STORE_NAME                      10: _rewind
                82      LOAD_CLOSURE                    0: __class__
                84      DUP_TOP                         
                86      STORE_NAME                      11: __classcell__
                88      RETURN_VALUE                    
        '_GzipReader'
        (
            'mtime'
        )
        [Code]
            File Name: gzip.py
            Object Name: compress
            Arg Count: 2
            Pos Only Arg Count: 0
            KW Only Arg Count: 1
            Locals: 5
            Stack Size: 8
            Flags: 0x00000043 (CO_OPTIMIZED | CO_NEWLOCALS | CO_NOFREE)
            [Names]
                'io'
                'BytesIO'
                'GzipFile'
                'write'
                'getvalue'
            [Var Names]
                'data'
                'compresslevel'
                'mtime'
                'buf'
                'f'
            [Free Vars]
            [Cell Vars]
            [Constants]
                'Compress data in one shot and return the compressed string.\n    Optional argument is the compression level, in range of 0-9.\n    '
                'wb'
                (
                    'fileobj'
                    'mode'
                    'compresslevel'
                    'mtime'
                )
                None
            [Disassembly]
                0       LOAD_GLOBAL                     0: io
                2       LOAD_METHOD                     1: BytesIO
                4       CALL_METHOD                     0
                6       STORE_FAST                      3: buf
                8       LOAD_GLOBAL                     2: GzipFile
                10      LOAD_FAST                       3: buf
                12      LOAD_CONST                      1: 'wb'
                14      LOAD_FAST                       1: compresslevel
                16      LOAD_FAST                       2: mtime
                18      LOAD_CONST                      2: ('fileobj', 'mode', 'compresslevel', 'mtime')
                20      CALL_FUNCTION_KW                4
                22      SETUP_WITH                      16 (to 56)
                24      STORE_FAST                      4: f
                26      LOAD_FAST                       4: f
                28      LOAD_METHOD                     3: write
                30      LOAD_FAST                       0: data
                32      CALL_METHOD                     1
                34      POP_TOP                         
                36      POP_BLOCK                       
                38      LOAD_CONST                      3: None
                40      DUP_TOP                         
                42      DUP_TOP                         
                44      CALL_FUNCTION                   3
                46      POP_TOP                         
                48      LOAD_FAST                       3: buf
                50      LOAD_METHOD                     4: getvalue
                52      CALL_METHOD                     0
                54      RETURN_VALUE                    
                56      WITH_EXCEPT_START               
                58      POP_JUMP_IF_TRUE                31 (to 62)
                60      RERAISE                         1
                62      POP_TOP                         
                64      POP_TOP                         
                66      POP_TOP                         
                68      POP_EXCEPT                      
                70      POP_TOP                         
                72      LOAD_FAST                       3: buf
                74      LOAD_METHOD                     4: getvalue
                76      CALL_METHOD                     0
                78      RETURN_VALUE                    
        'compress'
        [Code]
            File Name: gzip.py
            Object Name: decompress
            Arg Count: 1
            Pos Only Arg Count: 0
            KW Only Arg Count: 0
            Locals: 2
            Stack Size: 8
            Flags: 0x00000043 (CO_OPTIMIZED | CO_NEWLOCALS | CO_NOFREE)
            [Names]
                'GzipFile'
                'io'
                'BytesIO'
                'read'
            [Var Names]
                'data'
                'f'
            [Free Vars]
            [Cell Vars]
            [Constants]
                'Decompress a gzip compressed string in one shot.\n    Return the decompressed string.\n    '
                (
                    'fileobj'
                )
                None
            [Disassembly]
                0       LOAD_GLOBAL                     0: GzipFile
                2       LOAD_GLOBAL                     1: io
                4       LOAD_METHOD                     2: BytesIO
                6       LOAD_FAST                       0: data
                8       CALL_METHOD                     1
                10      LOAD_CONST                      1: ('fileobj',)
                12      CALL_FUNCTION_KW                1
                14      SETUP_WITH                      12 (to 40)
                16      STORE_FAST                      1: f
                18      LOAD_FAST                       1: f
                20      LOAD_METHOD                     3: read
                22      CALL_METHOD                     0
                24      POP_BLOCK                       
                26      ROT_TWO                         
                28      LOAD_CONST                      2: None
                30      DUP_TOP                         
                32      DUP_TOP                         
                34      CALL_FUNCTION                   3
                36      POP_TOP                         
                38      RETURN_VALUE                    
                40      WITH_EXCEPT_START               
                42      POP_JUMP_IF_TRUE                23 (to 46)
                44      RERAISE                         1
                46      POP_TOP                         
                48      POP_TOP                         
                50      POP_TOP                         
                52      POP_EXCEPT                      
                54      POP_TOP                         
                56      LOAD_CONST                      2: None
                58      RETURN_VALUE                    
        'decompress'
        [Code]
            File Name: gzip.py
            Object Name: main
            Arg Count: 0
            Pos Only Arg Count: 0
            KW Only Arg Count: 0
            Locals: 9
            Stack Size: 7
            Flags: 0x00000043 (CO_OPTIMIZED | CO_NEWLOCALS | CO_NOFREE)
            [Names]
                'argparse'
                'ArgumentParser'
                'add_mutually_exclusive_group'
                'add_argument'
                'parse_args'
                '_COMPRESS_LEVEL_TRADEOFF'
                'fast'
                '_COMPRESS_LEVEL_FAST'
                'best'
                '_COMPRESS_LEVEL_BEST'
                'args'
                'decompress'
                'GzipFile'
                'sys'
                'stdin'
                'buffer'
                'stdout'
                'exit'
                'open'
                'builtins'
                'read'
                'io'
                'DEFAULT_BUFFER_SIZE'
                'write'
                'close'
            [Var Names]
                'ArgumentParser'
                'parser'
                'group'
                'args'
                'compresslevel'
                'arg'
                'f'
                'g'
                'chunk'
            [Free Vars]
            [Cell Vars]
            [Constants]
                None
                0
                (
                    'ArgumentParser'
                )
                'A simple command line interface for the gzip module: act like gzip, but do not delete the input file.'
                (
                    'description'
                )
                '--fast'
                'store_true'
                'compress faster'
                (
                    'action'
                    'help'
                )
                '--best'
                'compress better'
                '-d'
                '--decompress'
                'act like gunzip instead of gzip'
                'args'
                '*'
                '-'
                'file'
                (
                    'nargs'
                    'default'
                    'metavar'
                )
                ''
                'rb'
                (
                    'filename'
                    'mode'
                    'fileobj'
                )
                -3
                '.gz'
                "filename doesn't end in .gz: "
                'wb'
                (
                    'filename'
                    'mode'
                    'fileobj'
                    'compresslevel'
                )
            [Disassembly]
                0       LOAD_CONST                      1: 0
                2       LOAD_CONST                      2: ('ArgumentParser',)
                4       IMPORT_NAME                     0: argparse
                6       IMPORT_FROM                     1: ArgumentParser
                8       STORE_FAST                      0: ArgumentParser
                10      POP_TOP                         
                12      LOAD_FAST                       0: ArgumentParser
                14      LOAD_CONST                      3: 'A simple command line interface for the gzip module: act like gzip, but do not delete the input file.'
                16      LOAD_CONST                      4: ('description',)
                18      CALL_FUNCTION_KW                1
                20      STORE_FAST                      1: parser
                22      LOAD_FAST                       1: parser
                24      LOAD_METHOD                     2: add_mutually_exclusive_group
                26      CALL_METHOD                     0
                28      STORE_FAST                      2: group
                30      LOAD_FAST                       2: group
                32      LOAD_ATTR                       3: add_argument
                34      LOAD_CONST                      5: '--fast'
                36      LOAD_CONST                      6: 'store_true'
                38      LOAD_CONST                      7: 'compress faster'
                40      LOAD_CONST                      8: ('action', 'help')
                42      CALL_FUNCTION_KW                3
                44      POP_TOP                         
                46      LOAD_FAST                       2: group
                48      LOAD_ATTR                       3: add_argument
                50      LOAD_CONST                      9: '--best'
                52      LOAD_CONST                      6: 'store_true'
                54      LOAD_CONST                      10: 'compress better'
                56      LOAD_CONST                      8: ('action', 'help')
                58      CALL_FUNCTION_KW                3
                60      POP_TOP                         
                62      LOAD_FAST                       2: group
                64      LOAD_ATTR                       3: add_argument
                66      LOAD_CONST                      11: '-d'
                68      LOAD_CONST                      12: '--decompress'
                70      LOAD_CONST                      6: 'store_true'
                72      LOAD_CONST                      13: 'act like gunzip instead of gzip'
                74      LOAD_CONST                      8: ('action', 'help')
                76      CALL_FUNCTION_KW                4
                78      POP_TOP                         
                80      LOAD_FAST                       1: parser
                82      LOAD_ATTR                       3: add_argument
                84      LOAD_CONST                      14: 'args'
                86      LOAD_CONST                      15: '*'
                88      LOAD_CONST                      16: '-'
                90      BUILD_LIST                      1
                92      LOAD_CONST                      17: 'file'
                94      LOAD_CONST                      18: ('nargs', 'default', 'metavar')
                96      CALL_FUNCTION_KW                4
                98      POP_TOP                         
                100     LOAD_FAST                       1: parser
                102     LOAD_METHOD                     4: parse_args
                104     CALL_METHOD                     0
                106     STORE_FAST                      3: args
                108     LOAD_GLOBAL                     5: _COMPRESS_LEVEL_TRADEOFF
                110     STORE_FAST                      4: compresslevel
                112     LOAD_FAST                       3: args
                114     LOAD_ATTR                       6: fast
                116     POP_JUMP_IF_FALSE               62 (to 124)
                118     LOAD_GLOBAL                     7: _COMPRESS_LEVEL_FAST
                120     STORE_FAST                      4: compresslevel
                122     JUMP_FORWARD                    5 (to 134)
                124     LOAD_FAST                       3: args
                126     LOAD_ATTR                       8: best
                128     POP_JUMP_IF_FALSE               67 (to 134)
                130     LOAD_GLOBAL                     9: _COMPRESS_LEVEL_BEST
                132     STORE_FAST                      4: compresslevel
                134     LOAD_FAST                       3: args
                136     LOAD_ATTR                       10: args
                138     GET_ITER                        
                140     FOR_ITER                        123 (to 388)
                142     STORE_FAST                      5: arg
                144     LOAD_FAST                       3: args
                146     LOAD_ATTR                       11: decompress
                148     POP_JUMP_IF_FALSE               125 (to 250)
                150     LOAD_FAST                       5: arg
                152     LOAD_CONST                      16: '-'
                154     COMPARE_OP                      2 (==)
                156     POP_JUMP_IF_FALSE               93 (to 186)
                158     LOAD_GLOBAL                     12: GzipFile
                160     LOAD_CONST                      19: ''
                162     LOAD_CONST                      20: 'rb'
                164     LOAD_GLOBAL                     13: sys
                166     LOAD_ATTR                       14: stdin
                168     LOAD_ATTR                       15: buffer
                170     LOAD_CONST                      21: ('filename', 'mode', 'fileobj')
                172     CALL_FUNCTION_KW                3
                174     STORE_FAST                      6: f
                176     LOAD_GLOBAL                     13: sys
                178     LOAD_ATTR                       16: stdout
                180     LOAD_ATTR                       15: buffer
                182     STORE_FAST                      7: g
                184     JUMP_FORWARD                    64 (to 314)
                186     LOAD_FAST                       5: arg
                188     LOAD_CONST                      22: -3
                190     LOAD_CONST                      0: None
                192     BUILD_SLICE                     2
                194     BINARY_SUBSCR                   
                196     LOAD_CONST                      23: '.gz'
                198     COMPARE_OP                      3 (!=)
                200     POP_JUMP_IF_FALSE               109 (to 218)
                202     LOAD_GLOBAL                     13: sys
                204     LOAD_METHOD                     17: exit
                206     LOAD_CONST                      24: "filename doesn't end in .gz: "
                208     LOAD_FAST                       5: arg
                210     FORMAT_VALUE                    2 (FVC_REPR)
                212     BUILD_STRING                    2
                214     CALL_METHOD                     1
                216     POP_TOP                         
                218     LOAD_GLOBAL                     18: open
                220     LOAD_FAST                       5: arg
                222     LOAD_CONST                      20: 'rb'
                224     CALL_FUNCTION                   2
                226     STORE_FAST                      6: f
                228     LOAD_GLOBAL                     19: builtins
                230     LOAD_METHOD                     18: open
                232     LOAD_FAST                       5: arg
                234     LOAD_CONST                      0: None
                236     LOAD_CONST                      22: -3
                238     BUILD_SLICE                     2
                240     BINARY_SUBSCR                   
                242     LOAD_CONST                      25: 'wb'
                244     CALL_METHOD                     2
                246     STORE_FAST                      7: g
                248     JUMP_FORWARD                    32 (to 314)
                250     LOAD_FAST                       5: arg
                252     LOAD_CONST                      16: '-'
                254     COMPARE_OP                      2 (==)
                256     POP_JUMP_IF_FALSE               144 (to 288)
                258     LOAD_GLOBAL                     13: sys
                260     LOAD_ATTR                       14: stdin
                262     LOAD_ATTR                       15: buffer
                264     STORE_FAST                      6: f
                266     LOAD_GLOBAL                     12: GzipFile
                268     LOAD_CONST                      19: ''
                270     LOAD_CONST                      25: 'wb'
                272     LOAD_GLOBAL                     13: sys
                274     LOAD_ATTR                       16: stdout
                276     LOAD_ATTR                       15: buffer
                278     LOAD_FAST                       4: compresslevel
                280     LOAD_CONST                      26: ('filename', 'mode', 'fileobj', 'compresslevel')
                282     CALL_FUNCTION_KW                4
                284     STORE_FAST                      7: g
                286     JUMP_FORWARD                    13 (to 314)
                288     LOAD_GLOBAL                     19: builtins
                290     LOAD_METHOD                     18: open
                292     LOAD_FAST                       5: arg
                294     LOAD_CONST                      20: 'rb'
                296     CALL_METHOD                     2
                298     STORE_FAST                      6: f
                300     LOAD_GLOBAL                     18: open
                302     LOAD_FAST                       5: arg
                304     LOAD_CONST                      23: '.gz'
                306     BINARY_ADD                      
                308     LOAD_CONST                      25: 'wb'
                310     CALL_FUNCTION                   2
                312     STORE_FAST                      7: g
                314     NOP                             
                316     LOAD_FAST                       6: f
                318     LOAD_METHOD                     20: read
                320     LOAD_GLOBAL                     21: io
                322     LOAD_ATTR                       22: DEFAULT_BUFFER_SIZE
                324     CALL_METHOD                     1
                326     STORE_FAST                      8: chunk
                328     LOAD_FAST                       8: chunk
                330     POP_JUMP_IF_TRUE                167 (to 334)
                332     JUMP_FORWARD                    6 (to 346)
                334     LOAD_FAST                       7: g
                336     LOAD_METHOD                     23: write
                338     LOAD_FAST                       8: chunk
                340     CALL_METHOD                     1
                342     POP_TOP                         
                344     JUMP_ABSOLUTE                   158 (to 316)
                346     LOAD_FAST                       7: g
                348     LOAD_GLOBAL                     13: sys
                350     LOAD_ATTR                       16: stdout
                352     LOAD_ATTR                       15: buffer
                354     IS_OP                           1 (is not)
                356     POP_JUMP_IF_FALSE               183 (to 366)
                358     LOAD_FAST                       7: g
                360     LOAD_METHOD                     24: close
                362     CALL_METHOD                     0
                364     POP_TOP                         
                366     LOAD_FAST                       6: f
                368     LOAD_GLOBAL                     13: sys
                370     LOAD_ATTR                       14: stdin
                372     LOAD_ATTR                       15: buffer
                374     IS_OP                           1 (is not)
                376     POP_JUMP_IF_FALSE               193 (to 386)
                378     LOAD_FAST                       6: f
                380     LOAD_METHOD                     24: close
                382     CALL_METHOD                     0
                384     POP_TOP                         
                386     JUMP_ABSOLUTE                   70 (to 140)
                388     LOAD_CONST                      0: None
                390     RETURN_VALUE                    
        'main'
        '__main__'
    [Disassembly]
        0       LOAD_CONST                      0: "Functions that read and write gzipped files.\n\nThe user of the file doesn't have to worry about the compression,\nbut random access is not allowed."
        2       STORE_NAME                      0: __doc__
        4       LOAD_CONST                      1: 0
        6       LOAD_CONST                      2: None
        8       IMPORT_NAME                     1: struct
        10      STORE_NAME                      1: struct
        12      LOAD_CONST                      1: 0
        14      LOAD_CONST                      2: None
        16      IMPORT_NAME                     2: sys
        18      STORE_NAME                      2: sys
        20      LOAD_CONST                      1: 0
        22      LOAD_CONST                      2: None
        24      IMPORT_NAME                     3: time
        26      STORE_NAME                      3: time
        28      LOAD_CONST                      1: 0
        30      LOAD_CONST                      2: None
        32      IMPORT_NAME                     4: os
        34      STORE_NAME                      4: os
        36      LOAD_CONST                      1: 0
        38      LOAD_CONST                      2: None
        40      IMPORT_NAME                     5: zlib
        42      STORE_NAME                      5: zlib
        44      LOAD_CONST                      1: 0
        46      LOAD_CONST                      2: None
        48      IMPORT_NAME                     6: builtins
        50      STORE_NAME                      6: builtins
        52      LOAD_CONST                      1: 0
        54      LOAD_CONST                      2: None
        56      IMPORT_NAME                     7: io
        58      STORE_NAME                      7: io
        60      LOAD_CONST                      1: 0
        62      LOAD_CONST                      2: None
        64      IMPORT_NAME                     8: _compression
        66      STORE_NAME                      8: _compression
        68      BUILD_LIST                      0
        70      LOAD_CONST                      3: ('BadGzipFile', 'GzipFile', 'open', 'compress', 'decompress')
        72      LIST_EXTEND                     1
        74      STORE_NAME                      9: __all__
        76      LOAD_CONST                      4: (1, 2, 4, 8, 16)
        78      UNPACK_SEQUENCE                 5
        80      STORE_NAME                      10: FTEXT
        82      STORE_NAME                      11: FHCRC
        84      STORE_NAME                      12: FEXTRA
        86      STORE_NAME                      13: FNAME
        88      STORE_NAME                      14: FCOMMENT
        90      LOAD_CONST                      5: (1, 2)
        92      UNPACK_SEQUENCE                 2
        94      STORE_NAME                      15: READ
        96      STORE_NAME                      16: WRITE
        98      LOAD_CONST                      6: 1
        100     STORE_NAME                      17: _COMPRESS_LEVEL_FAST
        102     LOAD_CONST                      7: 6
        104     STORE_NAME                      18: _COMPRESS_LEVEL_TRADEOFF
        106     LOAD_CONST                      8: 9
        108     STORE_NAME                      19: _COMPRESS_LEVEL_BEST
        110     LOAD_CONST                      9: 'rb'
        112     LOAD_NAME                       19: _COMPRESS_LEVEL_BEST
        114     LOAD_CONST                      2: None
        116     LOAD_CONST                      2: None
        118     LOAD_CONST                      2: None
        120     BUILD_TUPLE                     5
        122     LOAD_CONST                      10: <CODE> open
        124     LOAD_CONST                      11: 'open'
        126     MAKE_FUNCTION                   1
        128     STORE_NAME                      20: open
        130     LOAD_CONST                      12: <CODE> write32u
        132     LOAD_CONST                      13: 'write32u'
        134     MAKE_FUNCTION                   0
        136     STORE_NAME                      21: write32u
        138     LOAD_BUILD_CLASS                
        140     LOAD_CONST                      14: <CODE> _PaddedFile
        142     LOAD_CONST                      15: '_PaddedFile'
        144     MAKE_FUNCTION                   0
        146     LOAD_CONST                      15: '_PaddedFile'
        148     CALL_FUNCTION                   2
        150     STORE_NAME                      22: _PaddedFile
        152     LOAD_BUILD_CLASS                
        154     LOAD_CONST                      16: <CODE> BadGzipFile
        156     LOAD_CONST                      17: 'BadGzipFile'
        158     MAKE_FUNCTION                   0
        160     LOAD_CONST                      17: 'BadGzipFile'
        162     LOAD_NAME                       23: OSError
        164     CALL_FUNCTION                   3
        166     STORE_NAME                      24: BadGzipFile
        168     LOAD_BUILD_CLASS                
        170     LOAD_CONST                      18: <CODE> GzipFile
        172     LOAD_CONST                      19: 'GzipFile'
        174     MAKE_FUNCTION                   0
        176     LOAD_CONST                      19: 'GzipFile'
        178     LOAD_NAME                       8: _compression
        180     LOAD_ATTR                       25: BaseStream
        182     CALL_FUNCTION                   3
        184     STORE_NAME                      26: GzipFile
        186     LOAD_BUILD_CLASS                
        188     LOAD_CONST                      20: <CODE> _GzipReader
        190     LOAD_CONST                      21: '_GzipReader'
        192     MAKE_FUNCTION                   0
        194     LOAD_CONST                      21: '_GzipReader'
        196     LOAD_NAME                       8: _compression
        198     LOAD_ATTR                       27: DecompressReader
        200     CALL_FUNCTION                   3
        202     STORE_NAME                      28: _GzipReader
        204     LOAD_NAME                       19: _COMPRESS_LEVEL_BEST
        206     BUILD_TUPLE                     1
        208     LOAD_CONST                      2: None
        210     LOAD_CONST                      22: ('mtime',)
        212     BUILD_CONST_KEY_MAP             1
        214     LOAD_CONST                      23: <CODE> compress
        216     LOAD_CONST                      24: 'compress'
        218     MAKE_FUNCTION                   3
        220     STORE_NAME                      29: compress
        222     LOAD_CONST                      25: <CODE> decompress
        224     LOAD_CONST                      26: 'decompress'
        226     MAKE_FUNCTION                   0
        228     STORE_NAME                      30: decompress
        230     LOAD_CONST                      27: <CODE> main
        232     LOAD_CONST                      28: 'main'
        234     MAKE_FUNCTION                   0
        236     STORE_NAME                      31: main
        238     LOAD_NAME                       32: __name__
        240     LOAD_CONST                      29: '__main__'
        242     COMPARE_OP                      2 (==)
        244     POP_JUMP_IF_FALSE               128 (to 256)
        246     LOAD_NAME                       31: main
        248     CALL_FUNCTION                   0
        250     POP_TOP                         
        252     LOAD_CONST                      2: None
        254     RETURN_VALUE                    
        256     LOAD_CONST                      2: None
        258     RETURN_VALUE                    
