webbrowser.pyc (Python 3.10)
[Code]
    File Name: webbrowser.py
    Object Name: <module>
    Arg Count: 0
    Pos Only Arg Count: 0
    KW Only Arg Count: 0
    Locals: 0
    Stack Size: 4
    Flags: 0x00000040 (CO_NOFREE)
    [Names]
        '__doc__'
        'os'
        'shlex'
        'shutil'
        'sys'
        'subprocess'
        'threading'
        '__all__'
        'Exception'
        'Error'
        'RLock'
        '_lock'
        '_browsers'
        '_tryorder'
        '_os_preferred_browser'
        'register'
        'get'
        'open'
        'open_new'
        'open_new_tab'
        '_synthesize'
        'object'
        'BaseBrowser'
        'GenericBrowser'
        'BackgroundBrowser'
        'UnixBrowser'
        'Mozilla'
        'Netscape'
        'Galeon'
        'Chrome'
        'Chromium'
        'Opera'
        'Elinks'
        'Konqueror'
        'Grail'
        'register_X_browsers'
        'register_standard_browsers'
        'platform'
        'WindowsDefault'
        'MacOSX'
        'MacOSXOSAScript'
        'main'
        '__name__'
    [Var Names]
    [Free Vars]
    [Cell Vars]
    [Constants]
        'Interfaces for launching and remotely controlling web browsers.'
        0
        None
        (
            'Error'
            'open'
            'open_new'
            'open_new_tab'
            'get'
            'register'
        )
        [Code]
            File Name: webbrowser.py
            Object Name: Error
            Arg Count: 0
            Pos Only Arg Count: 0
            KW Only Arg Count: 0
            Locals: 0
            Stack Size: 1
            Flags: 0x00000040 (CO_NOFREE)
            [Names]
                '__name__'
                '__module__'
                '__qualname__'
            [Var Names]
            [Free Vars]
            [Cell Vars]
            [Constants]
                'Error'
                None
            [Disassembly]
                0       LOAD_NAME                       0: __name__
                2       STORE_NAME                      1: __module__
                4       LOAD_CONST                      0: 'Error'
                6       STORE_NAME                      2: __qualname__
                8       LOAD_CONST                      1: None
                10      RETURN_VALUE                    
        'Error'
        False
        (
            'preferred'
        )
        [Code]
            File Name: webbrowser.py
            Object Name: register
            Arg Count: 3
            Pos Only Arg Count: 0
            KW Only Arg Count: 1
            Locals: 4
            Stack Size: 8
            Flags: 0x00000043 (CO_OPTIMIZED | CO_NEWLOCALS | CO_NOFREE)
            [Names]
                '_lock'
                '_tryorder'
                'register_standard_browsers'
                '_browsers'
                'lower'
                '_os_preferred_browser'
                'insert'
                'append'
            [Var Names]
                'name'
                'klass'
                'instance'
                'preferred'
            [Free Vars]
            [Cell Vars]
            [Constants]
                'Register a browser connector.'
                None
                0
            [Disassembly]
                0       LOAD_GLOBAL                     0: _lock
                2       SETUP_WITH                      52 (to 108)
                4       POP_TOP                         
                6       LOAD_GLOBAL                     1: _tryorder
                8       LOAD_CONST                      1: None
                10      IS_OP                           0 (is)
                12      POP_JUMP_IF_FALSE               10 (to 20)
                14      LOAD_GLOBAL                     2: register_standard_browsers
                16      CALL_FUNCTION                   0
                18      POP_TOP                         
                20      LOAD_FAST                       1: klass
                22      LOAD_FAST                       2: instance
                24      BUILD_LIST                      2
                26      LOAD_GLOBAL                     3: _browsers
                28      LOAD_FAST                       0: name
                30      LOAD_METHOD                     4: lower
                32      CALL_METHOD                     0
                34      STORE_SUBSCR                    
                36      LOAD_FAST                       3: preferred
                38      POP_JUMP_IF_TRUE                26 (to 52)
                40      LOAD_GLOBAL                     5: _os_preferred_browser
                42      POP_JUMP_IF_FALSE               33 (to 66)
                44      LOAD_FAST                       0: name
                46      LOAD_GLOBAL                     5: _os_preferred_browser
                48      CONTAINS_OP                     0 (in)
                50      POP_JUMP_IF_FALSE               33 (to 66)
                52      LOAD_GLOBAL                     1: _tryorder
                54      LOAD_METHOD                     6: insert
                56      LOAD_CONST                      2: 0
                58      LOAD_FAST                       0: name
                60      CALL_METHOD                     2
                62      POP_TOP                         
                64      JUMP_FORWARD                    13 (to 92)
                66      LOAD_GLOBAL                     1: _tryorder
                68      LOAD_METHOD                     7: append
                70      LOAD_FAST                       0: name
                72      CALL_METHOD                     1
                74      POP_TOP                         
                76      POP_BLOCK                       
                78      LOAD_CONST                      1: None
                80      DUP_TOP                         
                82      DUP_TOP                         
                84      CALL_FUNCTION                   3
                86      POP_TOP                         
                88      LOAD_CONST                      1: None
                90      RETURN_VALUE                    
                92      POP_BLOCK                       
                94      LOAD_CONST                      1: None
                96      DUP_TOP                         
                98      DUP_TOP                         
                100     CALL_FUNCTION                   3
                102     POP_TOP                         
                104     LOAD_CONST                      1: None
                106     RETURN_VALUE                    
                108     WITH_EXCEPT_START               
                110     POP_JUMP_IF_TRUE                57 (to 114)
                112     RERAISE                         1
                114     POP_TOP                         
                116     POP_TOP                         
                118     POP_TOP                         
                120     POP_EXCEPT                      
                122     POP_TOP                         
                124     LOAD_CONST                      1: None
                126     RETURN_VALUE                    
        'register'
        [Code]
            File Name: webbrowser.py
            Object Name: get
            Arg Count: 1
            Pos Only Arg Count: 0
            KW Only Arg Count: 0
            Locals: 4
            Stack Size: 9
            Flags: 0x00000043 (CO_OPTIMIZED | CO_NEWLOCALS | CO_NOFREE)
            [Names]
                '_tryorder'
                '_lock'
                'register_standard_browsers'
                'shlex'
                'split'
                'BackgroundBrowser'
                'GenericBrowser'
                '_browsers'
                'lower'
                'KeyError'
                '_synthesize'
                'Error'
            [Var Names]
                'using'
                'alternatives'
                'browser'
                'command'
            [Free Vars]
            [Cell Vars]
            [Constants]
                'Return a browser launcher instance appropriate for the environment.'
                None
                '%s'
                -1
                '&'
                1
                0
                'could not locate runnable browser'
            [Disassembly]
                0       LOAD_GLOBAL                     0: _tryorder
                2       LOAD_CONST                      1: None
                4       IS_OP                           0 (is)
                6       POP_JUMP_IF_FALSE               29 (to 58)
                8       LOAD_GLOBAL                     1: _lock
                10      SETUP_WITH                      15 (to 42)
                12      POP_TOP                         
                14      LOAD_GLOBAL                     0: _tryorder
                16      LOAD_CONST                      1: None
                18      IS_OP                           0 (is)
                20      POP_JUMP_IF_FALSE               14 (to 28)
                22      LOAD_GLOBAL                     2: register_standard_browsers
                24      CALL_FUNCTION                   0
                26      POP_TOP                         
                28      POP_BLOCK                       
                30      LOAD_CONST                      1: None
                32      DUP_TOP                         
                34      DUP_TOP                         
                36      CALL_FUNCTION                   3
                38      POP_TOP                         
                40      JUMP_FORWARD                    8 (to 58)
                42      WITH_EXCEPT_START               
                44      POP_JUMP_IF_TRUE                24 (to 48)
                46      RERAISE                         1
                48      POP_TOP                         
                50      POP_TOP                         
                52      POP_TOP                         
                54      POP_EXCEPT                      
                56      POP_TOP                         
                58      LOAD_FAST                       0: using
                60      LOAD_CONST                      1: None
                62      IS_OP                           1 (is not)
                64      POP_JUMP_IF_FALSE               37 (to 74)
                66      LOAD_FAST                       0: using
                68      BUILD_LIST                      1
                70      STORE_FAST                      1: alternatives
                72      JUMP_FORWARD                    2 (to 78)
                74      LOAD_GLOBAL                     0: _tryorder
                76      STORE_FAST                      1: alternatives
                78      LOAD_FAST                       1: alternatives
                80      GET_ITER                        
                82      FOR_ITER                        80 (to 244)
                84      STORE_FAST                      2: browser
                86      LOAD_CONST                      2: '%s'
                88      LOAD_FAST                       2: browser
                90      CONTAINS_OP                     0 (in)
                92      POP_JUMP_IF_FALSE               74 (to 148)
                94      LOAD_GLOBAL                     3: shlex
                96      LOAD_METHOD                     4: split
                98      LOAD_FAST                       2: browser
                100     CALL_METHOD                     1
                102     STORE_FAST                      2: browser
                104     LOAD_FAST                       2: browser
                106     LOAD_CONST                      3: -1
                108     BINARY_SUBSCR                   
                110     LOAD_CONST                      4: '&'
                112     COMPARE_OP                      2 (==)
                114     POP_JUMP_IF_FALSE               68 (to 136)
                116     LOAD_GLOBAL                     5: BackgroundBrowser
                118     LOAD_FAST                       2: browser
                120     LOAD_CONST                      1: None
                122     LOAD_CONST                      3: -1
                124     BUILD_SLICE                     2
                126     BINARY_SUBSCR                   
                128     CALL_FUNCTION                   1
                130     ROT_TWO                         
                132     POP_TOP                         
                134     RETURN_VALUE                    
                136     LOAD_GLOBAL                     6: GenericBrowser
                138     LOAD_FAST                       2: browser
                140     CALL_FUNCTION                   1
                142     ROT_TWO                         
                144     POP_TOP                         
                146     RETURN_VALUE                    
                148     SETUP_FINALLY                   8 (to 166)
                150     LOAD_GLOBAL                     7: _browsers
                152     LOAD_FAST                       2: browser
                154     LOAD_METHOD                     8: lower
                156     CALL_METHOD                     0
                158     BINARY_SUBSCR                   
                160     STORE_FAST                      3: command
                162     POP_BLOCK                       
                164     JUMP_FORWARD                    13 (to 192)
                166     DUP_TOP                         
                168     LOAD_GLOBAL                     9: KeyError
                170     JUMP_IF_NOT_EXC_MATCH           95 (to 190)
                172     POP_TOP                         
                174     POP_TOP                         
                176     POP_TOP                         
                178     LOAD_GLOBAL                     10: _synthesize
                180     LOAD_FAST                       2: browser
                182     CALL_FUNCTION                   1
                184     STORE_FAST                      3: command
                186     POP_EXCEPT                      
                188     JUMP_FORWARD                    1 (to 192)
                190     RERAISE                         0
                192     LOAD_FAST                       3: command
                194     LOAD_CONST                      5: 1
                196     BINARY_SUBSCR                   
                198     LOAD_CONST                      1: None
                200     IS_OP                           1 (is not)
                202     POP_JUMP_IF_FALSE               108 (to 216)
                204     LOAD_FAST                       3: command
                206     LOAD_CONST                      5: 1
                208     BINARY_SUBSCR                   
                210     ROT_TWO                         
                212     POP_TOP                         
                214     RETURN_VALUE                    
                216     LOAD_FAST                       3: command
                218     LOAD_CONST                      6: 0
                220     BINARY_SUBSCR                   
                222     LOAD_CONST                      1: None
                224     IS_OP                           1 (is not)
                226     POP_JUMP_IF_FALSE               121 (to 242)
                228     LOAD_FAST                       3: command
                230     LOAD_CONST                      6: 0
                232     BINARY_SUBSCR                   
                234     CALL_FUNCTION                   0
                236     ROT_TWO                         
                238     POP_TOP                         
                240     RETURN_VALUE                    
                242     JUMP_ABSOLUTE                   41 (to 82)
                244     LOAD_GLOBAL                     11: Error
                246     LOAD_CONST                      7: 'could not locate runnable browser'
                248     CALL_FUNCTION                   1
                250     RAISE_VARARGS                   1
        'get'
        True
        [Code]
            File Name: webbrowser.py
            Object Name: open
            Arg Count: 3
            Pos Only Arg Count: 0
            KW Only Arg Count: 0
            Locals: 5
            Stack Size: 8
            Flags: 0x00000043 (CO_OPTIMIZED | CO_NEWLOCALS | CO_NOFREE)
            [Names]
                '_tryorder'
                '_lock'
                'register_standard_browsers'
                'get'
                'open'
            [Var Names]
                'url'
                'new'
                'autoraise'
                'name'
                'browser'
            [Free Vars]
            [Cell Vars]
            [Constants]
                'Display url using the default browser.\n\n    If possible, open url in a location determined by new.\n    - 0: the same browser window (the default).\n    - 1: a new browser window.\n    - 2: a new browser page ("tab").\n    If possible, autoraise raises the window (the default) or not.\n    '
                None
                True
                False
            [Disassembly]
                0       LOAD_GLOBAL                     0: _tryorder
                2       LOAD_CONST                      1: None
                4       IS_OP                           0 (is)
                6       POP_JUMP_IF_FALSE               29 (to 58)
                8       LOAD_GLOBAL                     1: _lock
                10      SETUP_WITH                      15 (to 42)
                12      POP_TOP                         
                14      LOAD_GLOBAL                     0: _tryorder
                16      LOAD_CONST                      1: None
                18      IS_OP                           0 (is)
                20      POP_JUMP_IF_FALSE               14 (to 28)
                22      LOAD_GLOBAL                     2: register_standard_browsers
                24      CALL_FUNCTION                   0
                26      POP_TOP                         
                28      POP_BLOCK                       
                30      LOAD_CONST                      1: None
                32      DUP_TOP                         
                34      DUP_TOP                         
                36      CALL_FUNCTION                   3
                38      POP_TOP                         
                40      JUMP_FORWARD                    8 (to 58)
                42      WITH_EXCEPT_START               
                44      POP_JUMP_IF_TRUE                24 (to 48)
                46      RERAISE                         1
                48      POP_TOP                         
                50      POP_TOP                         
                52      POP_TOP                         
                54      POP_EXCEPT                      
                56      POP_TOP                         
                58      LOAD_GLOBAL                     0: _tryorder
                60      GET_ITER                        
                62      FOR_ITER                        16 (to 96)
                64      STORE_FAST                      3: name
                66      LOAD_GLOBAL                     3: get
                68      LOAD_FAST                       3: name
                70      CALL_FUNCTION                   1
                72      STORE_FAST                      4: browser
                74      LOAD_FAST                       4: browser
                76      LOAD_METHOD                     4: open
                78      LOAD_FAST                       0: url
                80      LOAD_FAST                       1: new
                82      LOAD_FAST                       2: autoraise
                84      CALL_METHOD                     3
                86      POP_JUMP_IF_FALSE               47 (to 94)
                88      POP_TOP                         
                90      LOAD_CONST                      2: True
                92      RETURN_VALUE                    
                94      JUMP_ABSOLUTE                   31 (to 62)
                96      LOAD_CONST                      3: False
                98      RETURN_VALUE                    
        'open'
        [Code]
            File Name: webbrowser.py
            Object Name: open_new
            Arg Count: 1
            Pos Only Arg Count: 0
            KW Only Arg Count: 0
            Locals: 1
            Stack Size: 3
            Flags: 0x00000043 (CO_OPTIMIZED | CO_NEWLOCALS | CO_NOFREE)
            [Names]
                'open'
            [Var Names]
                'url'
            [Free Vars]
            [Cell Vars]
            [Constants]
                'Open url in a new window of the default browser.\n\n    If not possible, then open url in the only browser window.\n    '
                1
            [Disassembly]
                0       LOAD_GLOBAL                     0: open
                2       LOAD_FAST                       0: url
                4       LOAD_CONST                      1: 1
                6       CALL_FUNCTION                   2
                8       RETURN_VALUE                    
        'open_new'
        [Code]
            File Name: webbrowser.py
            Object Name: open_new_tab
            Arg Count: 1
            Pos Only Arg Count: 0
            KW Only Arg Count: 0
            Locals: 1
            Stack Size: 3
            Flags: 0x00000043 (CO_OPTIMIZED | CO_NEWLOCALS | CO_NOFREE)
            [Names]
                'open'
            [Var Names]
                'url'
            [Free Vars]
            [Cell Vars]
            [Constants]
                'Open url in a new page ("tab") of the default browser.\n\n    If not possible, then the behavior becomes equivalent to open_new().\n    '
                2
            [Disassembly]
                0       LOAD_GLOBAL                     0: open
                2       LOAD_FAST                       0: url
                4       LOAD_CONST                      1: 2
                6       CALL_FUNCTION                   2
                8       RETURN_VALUE                    
        'open_new_tab'
        [Code]
            File Name: webbrowser.py
            Object Name: _synthesize
            Arg Count: 1
            Pos Only Arg Count: 0
            KW Only Arg Count: 1
            Locals: 7
            Stack Size: 8
            Flags: 0x00000043 (CO_OPTIMIZED | CO_NEWLOCALS | CO_NOFREE)
            [Names]
                'split'
                'shutil'
                'which'
                'os'
                'path'
                'basename'
                '_browsers'
                'lower'
                'KeyError'
                'copy'
                'name'
                'register'
            [Var Names]
                'browser'
                'preferred'
                'cmd'
                'name'
                'command'
                'controller'
                'copy'
            [Free Vars]
            [Cell Vars]
            [Constants]
                "Attempt to synthesize a controller based on existing controllers.\n\n    This is useful to create a controller when a user specifies a path to\n    an entry in the BROWSER environment variable -- we can copy a general\n    controller to operate using a specific installation of the desired\n    browser in this way.\n\n    If we can't create a controller in this way, or if there is no\n    executable for the requested browser, return [None, None].\n\n    "
                0
                None
                1
                (
                    'instance'
                    'preferred'
                )
            [Disassembly]
                0       LOAD_FAST                       0: browser
                2       LOAD_METHOD                     0: split
                4       CALL_METHOD                     0
                6       LOAD_CONST                      1: 0
                8       BINARY_SUBSCR                   
                10      STORE_FAST                      2: cmd
                12      LOAD_GLOBAL                     1: shutil
                14      LOAD_METHOD                     2: which
                16      LOAD_FAST                       2: cmd
                18      CALL_METHOD                     1
                20      POP_JUMP_IF_TRUE                15 (to 30)
                22      LOAD_CONST                      2: None
                24      LOAD_CONST                      2: None
                26      BUILD_LIST                      2
                28      RETURN_VALUE                    
                30      LOAD_GLOBAL                     3: os
                32      LOAD_ATTR                       4: path
                34      LOAD_METHOD                     5: basename
                36      LOAD_FAST                       2: cmd
                38      CALL_METHOD                     1
                40      STORE_FAST                      3: name
                42      SETUP_FINALLY                   8 (to 60)
                44      LOAD_GLOBAL                     6: _browsers
                46      LOAD_FAST                       3: name
                48      LOAD_METHOD                     7: lower
                50      CALL_METHOD                     0
                52      BINARY_SUBSCR                   
                54      STORE_FAST                      4: command
                56      POP_BLOCK                       
                58      JUMP_FORWARD                    13 (to 86)
                60      DUP_TOP                         
                62      LOAD_GLOBAL                     8: KeyError
                64      JUMP_IF_NOT_EXC_MATCH           42 (to 84)
                66      POP_TOP                         
                68      POP_TOP                         
                70      POP_TOP                         
                72      LOAD_CONST                      2: None
                74      LOAD_CONST                      2: None
                76      BUILD_LIST                      2
                78      ROT_FOUR                        
                80      POP_EXCEPT                      
                82      RETURN_VALUE                    
                84      RERAISE                         0
                86      LOAD_FAST                       4: command
                88      LOAD_CONST                      3: 1
                90      BINARY_SUBSCR                   
                92      STORE_FAST                      5: controller
                94      LOAD_FAST                       5: controller
                96      POP_JUMP_IF_FALSE               87 (to 174)
                98      LOAD_FAST                       3: name
                100     LOAD_METHOD                     7: lower
                102     CALL_METHOD                     0
                104     LOAD_FAST                       5: controller
                106     LOAD_ATTR                       5: basename
                108     COMPARE_OP                      2 (==)
                110     POP_JUMP_IF_FALSE               87 (to 174)
                112     LOAD_CONST                      1: 0
                114     LOAD_CONST                      2: None
                116     IMPORT_NAME                     9: copy
                118     STORE_FAST                      6: copy
                120     LOAD_FAST                       6: copy
                122     LOAD_METHOD                     9: copy
                124     LOAD_FAST                       5: controller
                126     CALL_METHOD                     1
                128     STORE_FAST                      5: controller
                130     LOAD_FAST                       0: browser
                132     LOAD_FAST                       5: controller
                134     STORE_ATTR                      10: name
                136     LOAD_GLOBAL                     3: os
                138     LOAD_ATTR                       4: path
                140     LOAD_METHOD                     5: basename
                142     LOAD_FAST                       0: browser
                144     CALL_METHOD                     1
                146     LOAD_FAST                       5: controller
                148     STORE_ATTR                      5: basename
                150     LOAD_GLOBAL                     11: register
                152     LOAD_FAST                       0: browser
                154     LOAD_CONST                      2: None
                156     LOAD_FAST                       5: controller
                158     LOAD_FAST                       1: preferred
                160     LOAD_CONST                      4: ('instance', 'preferred')
                162     CALL_FUNCTION_KW                4
                164     POP_TOP                         
                166     LOAD_CONST                      2: None
                168     LOAD_FAST                       5: controller
                170     BUILD_LIST                      2
                172     RETURN_VALUE                    
                174     LOAD_CONST                      2: None
                176     LOAD_CONST                      2: None
                178     BUILD_LIST                      2
                180     RETURN_VALUE                    
        '_synthesize'
        [Code]
            File Name: webbrowser.py
            Object Name: BaseBrowser
            Arg Count: 0
            Pos Only Arg Count: 0
            KW Only Arg Count: 0
            Locals: 0
            Stack Size: 3
            Flags: 0x00000040 (CO_NOFREE)
            [Names]
                '__name__'
                '__module__'
                '__qualname__'
                '__doc__'
                'args'
                '__init__'
                'open'
                'open_new'
                'open_new_tab'
            [Var Names]
            [Free Vars]
            [Cell Vars]
            [Constants]
                'BaseBrowser'
                'Parent class for all browsers. Do not use directly.'
                '%s'
                ''
                [Code]
                    File Name: webbrowser.py
                    Object Name: __init__
                    Arg Count: 2
                    Pos Only Arg Count: 0
                    KW Only Arg Count: 0
                    Locals: 2
                    Stack Size: 2
                    Flags: 0x00000043 (CO_OPTIMIZED | CO_NEWLOCALS | CO_NOFREE)
                    [Names]
                        'name'
                        'basename'
                    [Var Names]
                        'self'
                        'name'
                    [Free Vars]
                    [Cell Vars]
                    [Constants]
                        None
                    [Disassembly]
                        0       LOAD_FAST                       1: name
                        2       LOAD_FAST                       0: self
                        4       STORE_ATTR                      0: name
                        6       LOAD_FAST                       1: name
                        8       LOAD_FAST                       0: self
                        10      STORE_ATTR                      1: basename
                        12      LOAD_CONST                      0: None
                        14      RETURN_VALUE                    
                'BaseBrowser.__init__'
                0
                True
                [Code]
                    File Name: webbrowser.py
                    Object Name: open
                    Arg Count: 4
                    Pos Only Arg Count: 0
                    KW Only Arg Count: 0
                    Locals: 4
                    Stack Size: 1
                    Flags: 0x00000043 (CO_OPTIMIZED | CO_NEWLOCALS | CO_NOFREE)
                    [Names]
                        'NotImplementedError'
                    [Var Names]
                        'self'
                        'url'
                        'new'
                        'autoraise'
                    [Free Vars]
                    [Cell Vars]
                    [Constants]
                        None
                    [Disassembly]
                        0       LOAD_GLOBAL                     0: NotImplementedError
                        2       RAISE_VARARGS                   1
                'BaseBrowser.open'
                [Code]
                    File Name: webbrowser.py
                    Object Name: open_new
                    Arg Count: 2
                    Pos Only Arg Count: 0
                    KW Only Arg Count: 0
                    Locals: 2
                    Stack Size: 4
                    Flags: 0x00000043 (CO_OPTIMIZED | CO_NEWLOCALS | CO_NOFREE)
                    [Names]
                        'open'
                    [Var Names]
                        'self'
                        'url'
                    [Free Vars]
                    [Cell Vars]
                    [Constants]
                        None
                        1
                    [Disassembly]
                        0       LOAD_FAST                       0: self
                        2       LOAD_METHOD                     0: open
                        4       LOAD_FAST                       1: url
                        6       LOAD_CONST                      1: 1
                        8       CALL_METHOD                     2
                        10      RETURN_VALUE                    
                'BaseBrowser.open_new'
                [Code]
                    File Name: webbrowser.py
                    Object Name: open_new_tab
                    Arg Count: 2
                    Pos Only Arg Count: 0
                    KW Only Arg Count: 0
                    Locals: 2
                    Stack Size: 4
                    Flags: 0x00000043 (CO_OPTIMIZED | CO_NEWLOCALS | CO_NOFREE)
                    [Names]
                        'open'
                    [Var Names]
                        'self'
                        'url'
                    [Free Vars]
                    [Cell Vars]
                    [Constants]
                        None
                        2
                    [Disassembly]
                        0       LOAD_FAST                       0: self
                        2       LOAD_METHOD                     0: open
                        4       LOAD_FAST                       1: url
                        6       LOAD_CONST                      1: 2
                        8       CALL_METHOD                     2
                        10      RETURN_VALUE                    
                'BaseBrowser.open_new_tab'
                None
                (
                    ''
                )
                (
                    0
                    True
                )
            [Disassembly]
                0       LOAD_NAME                       0: __name__
                2       STORE_NAME                      1: __module__
                4       LOAD_CONST                      0: 'BaseBrowser'
                6       STORE_NAME                      2: __qualname__
                8       LOAD_CONST                      1: 'Parent class for all browsers. Do not use directly.'
                10      STORE_NAME                      3: __doc__
                12      LOAD_CONST                      2: '%s'
                14      BUILD_LIST                      1
                16      STORE_NAME                      4: args
                18      LOAD_CONST                      15: ('',)
                20      LOAD_CONST                      4: <CODE> __init__
                22      LOAD_CONST                      5: 'BaseBrowser.__init__'
                24      MAKE_FUNCTION                   1
                26      STORE_NAME                      5: __init__
                28      LOAD_CONST                      16: (0, True)
                30      LOAD_CONST                      8: <CODE> open
                32      LOAD_CONST                      9: 'BaseBrowser.open'
                34      MAKE_FUNCTION                   1
                36      STORE_NAME                      6: open
                38      LOAD_CONST                      10: <CODE> open_new
                40      LOAD_CONST                      11: 'BaseBrowser.open_new'
                42      MAKE_FUNCTION                   0
                44      STORE_NAME                      7: open_new
                46      LOAD_CONST                      12: <CODE> open_new_tab
                48      LOAD_CONST                      13: 'BaseBrowser.open_new_tab'
                50      MAKE_FUNCTION                   0
                52      STORE_NAME                      8: open_new_tab
                54      LOAD_CONST                      14: None
                56      RETURN_VALUE                    
        'BaseBrowser'
        [Code]
            File Name: webbrowser.py
            Object Name: GenericBrowser
            Arg Count: 0
            Pos Only Arg Count: 0
            KW Only Arg Count: 0
            Locals: 0
            Stack Size: 3
            Flags: 0x00000040 (CO_NOFREE)
            [Names]
                '__name__'
                '__module__'
                '__qualname__'
                '__doc__'
                '__init__'
                'open'
            [Var Names]
            [Free Vars]
            [Cell Vars]
            [Constants]
                'GenericBrowser'
                'Class for all browsers started with a command\n       and without remote functionality.'
                [Code]
                    File Name: webbrowser.py
                    Object Name: __init__
                    Arg Count: 2
                    Pos Only Arg Count: 0
                    KW Only Arg Count: 0
                    Locals: 2
                    Stack Size: 3
                    Flags: 0x00000043 (CO_OPTIMIZED | CO_NEWLOCALS | CO_NOFREE)
                    [Names]
                        'isinstance'
                        'str'
                        'name'
                        'args'
                        'os'
                        'path'
                        'basename'
                    [Var Names]
                        'self'
                        'name'
                    [Free Vars]
                    [Cell Vars]
                    [Constants]
                        None
                        '%s'
                        0
                        1
                    [Disassembly]
                        0       LOAD_GLOBAL                     0: isinstance
                        2       LOAD_FAST                       1: name
                        4       LOAD_GLOBAL                     1: str
                        6       CALL_FUNCTION                   2
                        8       POP_JUMP_IF_FALSE               13 (to 26)
                        10      LOAD_FAST                       1: name
                        12      LOAD_FAST                       0: self
                        14      STORE_ATTR                      2: name
                        16      LOAD_CONST                      1: '%s'
                        18      BUILD_LIST                      1
                        20      LOAD_FAST                       0: self
                        22      STORE_ATTR                      3: args
                        24      JUMP_FORWARD                    12 (to 50)
                        26      LOAD_FAST                       1: name
                        28      LOAD_CONST                      2: 0
                        30      BINARY_SUBSCR                   
                        32      LOAD_FAST                       0: self
                        34      STORE_ATTR                      2: name
                        36      LOAD_FAST                       1: name
                        38      LOAD_CONST                      3: 1
                        40      LOAD_CONST                      0: None
                        42      BUILD_SLICE                     2
                        44      BINARY_SUBSCR                   
                        46      LOAD_FAST                       0: self
                        48      STORE_ATTR                      3: args
                        50      LOAD_GLOBAL                     4: os
                        52      LOAD_ATTR                       5: path
                        54      LOAD_METHOD                     6: basename
                        56      LOAD_FAST                       0: self
                        58      LOAD_ATTR                       2: name
                        60      CALL_METHOD                     1
                        62      LOAD_FAST                       0: self
                        64      STORE_ATTR                      6: basename
                        66      LOAD_CONST                      0: None
                        68      RETURN_VALUE                    
                'GenericBrowser.__init__'
                0
                True
                [Code]
                    File Name: webbrowser.py
                    Object Name: open
                    Arg Count: 4
                    Pos Only Arg Count: 0
                    KW Only Arg Count: 0
                    Locals: 6
                    Stack Size: 8
                    Flags: 0x00000003 (CO_OPTIMIZED | CO_NEWLOCALS)
                    [Names]
                        'sys'
                        'audit'
                        'name'
                        'args'
                        'platform'
                        'subprocess'
                        'Popen'
                        'wait'
                        'OSError'
                    [Var Names]
                        'self'
                        'url'
                        'new'
                        'autoraise'
                        'cmdline'
                        'p'
                    [Free Vars]
                    [Cell Vars]
                        'url'
                    [Constants]
                        None
                        'webbrowser.open'
                        [Code]
                            File Name: webbrowser.py
                            Object Name: <listcomp>
                            Arg Count: 1
                            Pos Only Arg Count: 0
                            KW Only Arg Count: 0
                            Locals: 2
                            Stack Size: 6
                            Flags: 0x00000013 (CO_OPTIMIZED | CO_NEWLOCALS | CO_NESTED)
                            [Names]
                                'replace'
                            [Var Names]
                                '.0'
                                'arg'
                            [Free Vars]
                                'url'
                            [Cell Vars]
                            [Constants]
                                '%s'
                            [Disassembly]
                                0       BUILD_LIST                      0
                                2       LOAD_FAST                       0: .0
                                4       FOR_ITER                        8 (to 22)
                                6       STORE_FAST                      1: arg
                                8       LOAD_FAST                       1: arg
                                10      LOAD_METHOD                     0: replace
                                12      LOAD_CONST                      0: '%s'
                                14      LOAD_DEREF                      0: url
                                16      CALL_METHOD                     2
                                18      LIST_APPEND                     2
                                20      JUMP_ABSOLUTE                   2 (to 4)
                                22      RETURN_VALUE                    
                        'GenericBrowser.open.<locals>.<listcomp>'
                        3
                        'win'
                        True
                        (
                            'close_fds'
                        )
                        False
                    [Disassembly]
                        0       LOAD_GLOBAL                     0: sys
                        2       LOAD_METHOD                     1: audit
                        4       LOAD_CONST                      1: 'webbrowser.open'
                        6       LOAD_DEREF                      0: url
                        8       CALL_METHOD                     2
                        10      POP_TOP                         
                        12      LOAD_FAST                       0: self
                        14      LOAD_ATTR                       2: name
                        16      BUILD_LIST                      1
                        18      LOAD_CLOSURE                    0: url
                        20      BUILD_TUPLE                     1
                        22      LOAD_CONST                      2: <CODE> <listcomp>
                        24      LOAD_CONST                      3: 'GenericBrowser.open.<locals>.<listcomp>'
                        26      MAKE_FUNCTION                   8
                        28      LOAD_FAST                       0: self
                        30      LOAD_ATTR                       3: args
                        32      GET_ITER                        
                        34      CALL_FUNCTION                   1
                        36      BINARY_ADD                      
                        38      STORE_FAST                      4: cmdline
                        40      SETUP_FINALLY                   28 (to 98)
                        42      LOAD_GLOBAL                     0: sys
                        44      LOAD_ATTR                       4: platform
                        46      LOAD_CONST                      0: None
                        48      LOAD_CONST                      4: 3
                        50      BUILD_SLICE                     2
                        52      BINARY_SUBSCR                   
                        54      LOAD_CONST                      5: 'win'
                        56      COMPARE_OP                      2 (==)
                        58      POP_JUMP_IF_FALSE               36 (to 72)
                        60      LOAD_GLOBAL                     5: subprocess
                        62      LOAD_METHOD                     6: Popen
                        64      LOAD_FAST                       4: cmdline
                        66      CALL_METHOD                     1
                        68      STORE_FAST                      5: p
                        70      JUMP_FORWARD                    7 (to 86)
                        72      LOAD_GLOBAL                     5: subprocess
                        74      LOAD_ATTR                       6: Popen
                        76      LOAD_FAST                       4: cmdline
                        78      LOAD_CONST                      6: True
                        80      LOAD_CONST                      7: ('close_fds',)
                        82      CALL_FUNCTION_KW                2
                        84      STORE_FAST                      5: p
                        86      LOAD_FAST                       5: p
                        88      LOAD_METHOD                     7: wait
                        90      CALL_METHOD                     0
                        92      UNARY_NOT                       
                        94      POP_BLOCK                       
                        96      RETURN_VALUE                    
                        98      DUP_TOP                         
                        100     LOAD_GLOBAL                     8: OSError
                        102     JUMP_IF_NOT_EXC_MATCH           58 (to 116)
                        104     POP_TOP                         
                        106     POP_TOP                         
                        108     POP_TOP                         
                        110     POP_EXCEPT                      
                        112     LOAD_CONST                      8: False
                        114     RETURN_VALUE                    
                        116     RERAISE                         0
                'GenericBrowser.open'
                None
                (
                    0
                    True
                )
            [Disassembly]
                0       LOAD_NAME                       0: __name__
                2       STORE_NAME                      1: __module__
                4       LOAD_CONST                      0: 'GenericBrowser'
                6       STORE_NAME                      2: __qualname__
                8       LOAD_CONST                      1: 'Class for all browsers started with a command\n       and without remote functionality.'
                10      STORE_NAME                      3: __doc__
                12      LOAD_CONST                      2: <CODE> __init__
                14      LOAD_CONST                      3: 'GenericBrowser.__init__'
                16      MAKE_FUNCTION                   0
                18      STORE_NAME                      4: __init__
                20      LOAD_CONST                      9: (0, True)
                22      LOAD_CONST                      6: <CODE> open
                24      LOAD_CONST                      7: 'GenericBrowser.open'
                26      MAKE_FUNCTION                   1
                28      STORE_NAME                      5: open
                30      LOAD_CONST                      8: None
                32      RETURN_VALUE                    
        'GenericBrowser'
        [Code]
            File Name: webbrowser.py
            Object Name: BackgroundBrowser
            Arg Count: 0
            Pos Only Arg Count: 0
            KW Only Arg Count: 0
            Locals: 0
            Stack Size: 3
            Flags: 0x00000040 (CO_NOFREE)
            [Names]
                '__name__'
                '__module__'
                '__qualname__'
                '__doc__'
                'open'
            [Var Names]
            [Free Vars]
            [Cell Vars]
            [Constants]
                'BackgroundBrowser'
                'Class for all browsers which are to be started in the\n       background.'
                0
                True
                [Code]
                    File Name: webbrowser.py
                    Object Name: open
                    Arg Count: 4
                    Pos Only Arg Count: 0
                    KW Only Arg Count: 0
                    Locals: 6
                    Stack Size: 8
                    Flags: 0x00000003 (CO_OPTIMIZED | CO_NEWLOCALS)
                    [Names]
                        'name'
                        'args'
                        'sys'
                        'audit'
                        'platform'
                        'subprocess'
                        'Popen'
                        'poll'
                        'OSError'
                    [Var Names]
                        'self'
                        'url'
                        'new'
                        'autoraise'
                        'cmdline'
                        'p'
                    [Free Vars]
                    [Cell Vars]
                        'url'
                    [Constants]
                        None
                        [Code]
                            File Name: webbrowser.py
                            Object Name: <listcomp>
                            Arg Count: 1
                            Pos Only Arg Count: 0
                            KW Only Arg Count: 0
                            Locals: 2
                            Stack Size: 6
                            Flags: 0x00000013 (CO_OPTIMIZED | CO_NEWLOCALS | CO_NESTED)
                            [Names]
                                'replace'
                            [Var Names]
                                '.0'
                                'arg'
                            [Free Vars]
                                'url'
                            [Cell Vars]
                            [Constants]
                                '%s'
                            [Disassembly]
                                0       BUILD_LIST                      0
                                2       LOAD_FAST                       0: .0
                                4       FOR_ITER                        8 (to 22)
                                6       STORE_FAST                      1: arg
                                8       LOAD_FAST                       1: arg
                                10      LOAD_METHOD                     0: replace
                                12      LOAD_CONST                      0: '%s'
                                14      LOAD_DEREF                      0: url
                                16      CALL_METHOD                     2
                                18      LIST_APPEND                     2
                                20      JUMP_ABSOLUTE                   2 (to 4)
                                22      RETURN_VALUE                    
                        'BackgroundBrowser.open.<locals>.<listcomp>'
                        'webbrowser.open'
                        3
                        'win'
                        True
                        (
                            'close_fds'
                            'start_new_session'
                        )
                        False
                    [Disassembly]
                        0       LOAD_FAST                       0: self
                        2       LOAD_ATTR                       0: name
                        4       BUILD_LIST                      1
                        6       LOAD_CLOSURE                    0: url
                        8       BUILD_TUPLE                     1
                        10      LOAD_CONST                      1: <CODE> <listcomp>
                        12      LOAD_CONST                      2: 'BackgroundBrowser.open.<locals>.<listcomp>'
                        14      MAKE_FUNCTION                   8
                        16      LOAD_FAST                       0: self
                        18      LOAD_ATTR                       1: args
                        20      GET_ITER                        
                        22      CALL_FUNCTION                   1
                        24      BINARY_ADD                      
                        26      STORE_FAST                      4: cmdline
                        28      LOAD_GLOBAL                     2: sys
                        30      LOAD_METHOD                     3: audit
                        32      LOAD_CONST                      3: 'webbrowser.open'
                        34      LOAD_DEREF                      0: url
                        36      CALL_METHOD                     2
                        38      POP_TOP                         
                        40      SETUP_FINALLY                   30 (to 102)
                        42      LOAD_GLOBAL                     2: sys
                        44      LOAD_ATTR                       4: platform
                        46      LOAD_CONST                      0: None
                        48      LOAD_CONST                      4: 3
                        50      BUILD_SLICE                     2
                        52      BINARY_SUBSCR                   
                        54      LOAD_CONST                      5: 'win'
                        56      COMPARE_OP                      2 (==)
                        58      POP_JUMP_IF_FALSE               36 (to 72)
                        60      LOAD_GLOBAL                     5: subprocess
                        62      LOAD_METHOD                     6: Popen
                        64      LOAD_FAST                       4: cmdline
                        66      CALL_METHOD                     1
                        68      STORE_FAST                      5: p
                        70      JUMP_FORWARD                    8 (to 88)
                        72      LOAD_GLOBAL                     5: subprocess
                        74      LOAD_ATTR                       6: Popen
                        76      LOAD_FAST                       4: cmdline
                        78      LOAD_CONST                      6: True
                        80      LOAD_CONST                      6: True
                        82      LOAD_CONST                      7: ('close_fds', 'start_new_session')
                        84      CALL_FUNCTION_KW                3
                        86      STORE_FAST                      5: p
                        88      LOAD_FAST                       5: p
                        90      LOAD_METHOD                     7: poll
                        92      CALL_METHOD                     0
                        94      LOAD_CONST                      0: None
                        96      IS_OP                           0 (is)
                        98      POP_BLOCK                       
                        100     RETURN_VALUE                    
                        102     DUP_TOP                         
                        104     LOAD_GLOBAL                     8: OSError
                        106     JUMP_IF_NOT_EXC_MATCH           60 (to 120)
                        108     POP_TOP                         
                        110     POP_TOP                         
                        112     POP_TOP                         
                        114     POP_EXCEPT                      
                        116     LOAD_CONST                      8: False
                        118     RETURN_VALUE                    
                        120     RERAISE                         0
                'BackgroundBrowser.open'
                None
                (
                    0
                    True
                )
            [Disassembly]
                0       LOAD_NAME                       0: __name__
                2       STORE_NAME                      1: __module__
                4       LOAD_CONST                      0: 'BackgroundBrowser'
                6       STORE_NAME                      2: __qualname__
                8       LOAD_CONST                      1: 'Class for all browsers which are to be started in the\n       background.'
                10      STORE_NAME                      3: __doc__
                12      LOAD_CONST                      7: (0, True)
                14      LOAD_CONST                      4: <CODE> open
                16      LOAD_CONST                      5: 'BackgroundBrowser.open'
                18      MAKE_FUNCTION                   1
                20      STORE_NAME                      4: open
                22      LOAD_CONST                      6: None
                24      RETURN_VALUE                    
        'BackgroundBrowser'
        [Code]
            File Name: webbrowser.py
            Object Name: UnixBrowser
            Arg Count: 0
            Pos Only Arg Count: 0
            KW Only Arg Count: 0
            Locals: 0
            Stack Size: 3
            Flags: 0x00000040 (CO_NOFREE)
            [Names]
                '__name__'
                '__module__'
                '__qualname__'
                '__doc__'
                'raise_opts'
                'background'
                'redirect_stdout'
                'remote_args'
                'remote_action'
                'remote_action_newwin'
                'remote_action_newtab'
                '_invoke'
                'open'
            [Var Names]
            [Free Vars]
            [Cell Vars]
            [Constants]
                'UnixBrowser'
                'Parent class for all Unix browsers with remote functionality.'
                None
                False
                True
                '%action'
                '%s'
                [Code]
                    File Name: webbrowser.py
                    Object Name: _invoke
                    Arg Count: 5
                    Pos Only Arg Count: 0
                    KW Only Arg Count: 0
                    Locals: 11
                    Stack Size: 8
                    Flags: 0x00000043 (CO_OPTIMIZED | CO_NEWLOCALS | CO_NOFREE)
                    [Names]
                        'raise_opts'
                        'int'
                        'name'
                        'background'
                        'subprocess'
                        'DEVNULL'
                        'Popen'
                        'redirect_stdout'
                        'wait'
                        'TimeoutExpired'
                        'poll'
                    [Var Names]
                        'self'
                        'args'
                        'remote'
                        'autoraise'
                        'url'
                        'raise_opt'
                        'opt'
                        'cmdline'
                        'inout'
                        'p'
                        'rc'
                    [Free Vars]
                    [Cell Vars]
                    [Constants]
                        None
                        True
                        (
                            'close_fds'
                            'stdin'
                            'stdout'
                            'stderr'
                            'start_new_session'
                        )
                        5
                        False
                    [Disassembly]
                        0       BUILD_LIST                      0
                        2       STORE_FAST                      5: raise_opt
                        4       LOAD_FAST                       2: remote
                        6       POP_JUMP_IF_FALSE               21 (to 42)
                        8       LOAD_FAST                       0: self
                        10      LOAD_ATTR                       0: raise_opts
                        12      POP_JUMP_IF_FALSE               21 (to 42)
                        14      LOAD_GLOBAL                     1: int
                        16      LOAD_FAST                       3: autoraise
                        18      CALL_FUNCTION                   1
                        20      STORE_FAST                      3: autoraise
                        22      LOAD_FAST                       0: self
                        24      LOAD_ATTR                       0: raise_opts
                        26      LOAD_FAST                       3: autoraise
                        28      BINARY_SUBSCR                   
                        30      STORE_FAST                      6: opt
                        32      LOAD_FAST                       6: opt
                        34      POP_JUMP_IF_FALSE               21 (to 42)
                        36      LOAD_FAST                       6: opt
                        38      BUILD_LIST                      1
                        40      STORE_FAST                      5: raise_opt
                        42      LOAD_FAST                       0: self
                        44      LOAD_ATTR                       2: name
                        46      BUILD_LIST                      1
                        48      LOAD_FAST                       5: raise_opt
                        50      BINARY_ADD                      
                        52      LOAD_FAST                       1: args
                        54      BINARY_ADD                      
                        56      STORE_FAST                      7: cmdline
                        58      LOAD_FAST                       2: remote
                        60      POP_JUMP_IF_TRUE                34 (to 68)
                        62      LOAD_FAST                       0: self
                        64      LOAD_ATTR                       3: background
                        66      POP_JUMP_IF_FALSE               38 (to 76)
                        68      LOAD_GLOBAL                     4: subprocess
                        70      LOAD_ATTR                       5: DEVNULL
                        72      STORE_FAST                      8: inout
                        74      JUMP_FORWARD                    2 (to 80)
                        76      LOAD_CONST                      0: None
                        78      STORE_FAST                      8: inout
                        80      LOAD_GLOBAL                     4: subprocess
                        82      LOAD_ATTR                       6: Popen
                        84      LOAD_FAST                       7: cmdline
                        86      LOAD_CONST                      1: True
                        88      LOAD_FAST                       8: inout
                        90      LOAD_FAST                       0: self
                        92      LOAD_ATTR                       7: redirect_stdout
                        94      POP_JUMP_IF_FALSE               50 (to 100)
                        96      LOAD_FAST                       8: inout
                        98      JUMP_IF_TRUE_OR_POP             51 (to 102)
                        100     LOAD_CONST                      0: None
                        102     LOAD_FAST                       8: inout
                        104     LOAD_CONST                      1: True
                        106     LOAD_CONST                      2: ('close_fds', 'stdin', 'stdout', 'stderr', 'start_new_session')
                        108     CALL_FUNCTION_KW                6
                        110     STORE_FAST                      9: p
                        112     LOAD_FAST                       2: remote
                        114     POP_JUMP_IF_FALSE               79 (to 158)
                        116     SETUP_FINALLY                   9 (to 136)
                        118     LOAD_FAST                       9: p
                        120     LOAD_METHOD                     8: wait
                        122     LOAD_CONST                      3: 5
                        124     CALL_METHOD                     1
                        126     STORE_FAST                      10: rc
                        128     LOAD_FAST                       10: rc
                        130     UNARY_NOT                       
                        132     POP_BLOCK                       
                        134     RETURN_VALUE                    
                        136     DUP_TOP                         
                        138     LOAD_GLOBAL                     4: subprocess
                        140     LOAD_ATTR                       9: TimeoutExpired
                        142     JUMP_IF_NOT_EXC_MATCH           78 (to 156)
                        144     POP_TOP                         
                        146     POP_TOP                         
                        148     POP_TOP                         
                        150     POP_EXCEPT                      
                        152     LOAD_CONST                      1: True
                        154     RETURN_VALUE                    
                        156     RERAISE                         0
                        158     LOAD_FAST                       0: self
                        160     LOAD_ATTR                       3: background
                        162     POP_JUMP_IF_FALSE               92 (to 184)
                        164     LOAD_FAST                       9: p
                        166     LOAD_METHOD                     10: poll
                        168     CALL_METHOD                     0
                        170     LOAD_CONST                      0: None
                        172     IS_OP                           0 (is)
                        174     POP_JUMP_IF_FALSE               90 (to 180)
                        176     LOAD_CONST                      1: True
                        178     RETURN_VALUE                    
                        180     LOAD_CONST                      4: False
                        182     RETURN_VALUE                    
                        184     LOAD_FAST                       9: p
                        186     LOAD_METHOD                     8: wait
                        188     CALL_METHOD                     0
                        190     UNARY_NOT                       
                        192     RETURN_VALUE                    
                'UnixBrowser._invoke'
                0
                [Code]
                    File Name: webbrowser.py
                    Object Name: open
                    Arg Count: 4
                    Pos Only Arg Count: 0
                    KW Only Arg Count: 0
                    Locals: 6
                    Stack Size: 6
                    Flags: 0x00000003 (CO_OPTIMIZED | CO_NEWLOCALS)
                    [Names]
                        'sys'
                        'audit'
                        'remote_action'
                        'remote_action_newwin'
                        'remote_action_newtab'
                        'Error'
                        'remote_args'
                        '_invoke'
                        'args'
                    [Var Names]
                        'self'
                        'url'
                        'new'
                        'autoraise'
                        'args'
                        'success'
                    [Free Vars]
                    [Cell Vars]
                        'action'
                        'url'
                    [Constants]
                        None
                        'webbrowser.open'
                        0
                        1
                        2
                        "Bad 'new' parameter to open(); "
                        'expected 0, 1, or 2, got %s'
                        [Code]
                            File Name: webbrowser.py
                            Object Name: <listcomp>
                            Arg Count: 1
                            Pos Only Arg Count: 0
                            KW Only Arg Count: 0
                            Locals: 2
                            Stack Size: 6
                            Flags: 0x00000013 (CO_OPTIMIZED | CO_NEWLOCALS | CO_NESTED)
                            [Names]
                                'replace'
                            [Var Names]
                                '.0'
                                'arg'
                            [Free Vars]
                                'action'
                                'url'
                            [Cell Vars]
                            [Constants]
                                '%s'
                                '%action'
                            [Disassembly]
                                0       BUILD_LIST                      0
                                2       LOAD_FAST                       0: .0
                                4       FOR_ITER                        12 (to 30)
                                6       STORE_FAST                      1: arg
                                8       LOAD_FAST                       1: arg
                                10      LOAD_METHOD                     0: replace
                                12      LOAD_CONST                      0: '%s'
                                14      LOAD_DEREF                      1: url
                                16      CALL_METHOD                     2
                                18      LOAD_METHOD                     0: replace
                                20      LOAD_CONST                      1: '%action'
                                22      LOAD_DEREF                      0: action
                                24      CALL_METHOD                     2
                                26      LIST_APPEND                     2
                                28      JUMP_ABSOLUTE                   2 (to 4)
                                30      RETURN_VALUE                    
                        'UnixBrowser.open.<locals>.<listcomp>'
                        [Code]
                            File Name: webbrowser.py
                            Object Name: <listcomp>
                            Arg Count: 1
                            Pos Only Arg Count: 0
                            KW Only Arg Count: 0
                            Locals: 2
                            Stack Size: 3
                            Flags: 0x00000053 (CO_OPTIMIZED | CO_NEWLOCALS | CO_NESTED | CO_NOFREE)
                            [Names]
                            [Var Names]
                                '.0'
                                'arg'
                            [Free Vars]
                            [Cell Vars]
                            [Constants]
                            [Disassembly]
                                0       BUILD_LIST                      0
                                2       LOAD_FAST                       0: .0
                                4       FOR_ITER                        6 (to 18)
                                6       STORE_FAST                      1: arg
                                8       LOAD_FAST                       1: arg
                                10      POP_JUMP_IF_FALSE               2 (to 4)
                                12      LOAD_FAST                       1: arg
                                14      LIST_APPEND                     2
                                16      JUMP_ABSOLUTE                   2 (to 4)
                                18      RETURN_VALUE                    
                        True
                        [Code]
                            File Name: webbrowser.py
                            Object Name: <listcomp>
                            Arg Count: 1
                            Pos Only Arg Count: 0
                            KW Only Arg Count: 0
                            Locals: 2
                            Stack Size: 6
                            Flags: 0x00000013 (CO_OPTIMIZED | CO_NEWLOCALS | CO_NESTED)
                            [Names]
                                'replace'
                            [Var Names]
                                '.0'
                                'arg'
                            [Free Vars]
                                'url'
                            [Cell Vars]
                            [Constants]
                                '%s'
                            [Disassembly]
                                0       BUILD_LIST                      0
                                2       LOAD_FAST                       0: .0
                                4       FOR_ITER                        8 (to 22)
                                6       STORE_FAST                      1: arg
                                8       LOAD_FAST                       1: arg
                                10      LOAD_METHOD                     0: replace
                                12      LOAD_CONST                      0: '%s'
                                14      LOAD_DEREF                      0: url
                                16      CALL_METHOD                     2
                                18      LIST_APPEND                     2
                                20      JUMP_ABSOLUTE                   2 (to 4)
                                22      RETURN_VALUE                    
                        False
                    [Disassembly]
                        0       LOAD_GLOBAL                     0: sys
                        2       LOAD_METHOD                     1: audit
                        4       LOAD_CONST                      1: 'webbrowser.open'
                        6       LOAD_DEREF                      1: url
                        8       CALL_METHOD                     2
                        10      POP_TOP                         
                        12      LOAD_FAST                       2: new
                        14      LOAD_CONST                      2: 0
                        16      COMPARE_OP                      2 (==)
                        18      POP_JUMP_IF_FALSE               14 (to 28)
                        20      LOAD_FAST                       0: self
                        22      LOAD_ATTR                       2: remote_action
                        24      STORE_DEREF                     0: action
                        26      JUMP_FORWARD                    33 (to 94)
                        28      LOAD_FAST                       2: new
                        30      LOAD_CONST                      3: 1
                        32      COMPARE_OP                      2 (==)
                        34      POP_JUMP_IF_FALSE               22 (to 44)
                        36      LOAD_FAST                       0: self
                        38      LOAD_ATTR                       3: remote_action_newwin
                        40      STORE_DEREF                     0: action
                        42      JUMP_FORWARD                    25 (to 94)
                        44      LOAD_FAST                       2: new
                        46      LOAD_CONST                      4: 2
                        48      COMPARE_OP                      2 (==)
                        50      POP_JUMP_IF_FALSE               39 (to 78)
                        52      LOAD_FAST                       0: self
                        54      LOAD_ATTR                       4: remote_action_newtab
                        56      LOAD_CONST                      0: None
                        58      IS_OP                           0 (is)
                        60      POP_JUMP_IF_FALSE               35 (to 70)
                        62      LOAD_FAST                       0: self
                        64      LOAD_ATTR                       3: remote_action_newwin
                        66      STORE_DEREF                     0: action
                        68      JUMP_FORWARD                    12 (to 94)
                        70      LOAD_FAST                       0: self
                        72      LOAD_ATTR                       4: remote_action_newtab
                        74      STORE_DEREF                     0: action
                        76      JUMP_FORWARD                    8 (to 94)
                        78      LOAD_GLOBAL                     5: Error
                        80      LOAD_CONST                      5: "Bad 'new' parameter to open(); "
                        82      LOAD_CONST                      6: 'expected 0, 1, or 2, got %s'
                        84      LOAD_FAST                       2: new
                        86      BINARY_MODULO                   
                        88      BINARY_ADD                      
                        90      CALL_FUNCTION                   1
                        92      RAISE_VARARGS                   1
                        94      LOAD_CLOSURE                    0: action
                        96      LOAD_CLOSURE                    1: url
                        98      BUILD_TUPLE                     2
                        100     LOAD_CONST                      7: <CODE> <listcomp>
                        102     LOAD_CONST                      8: 'UnixBrowser.open.<locals>.<listcomp>'
                        104     MAKE_FUNCTION                   8
                        106     LOAD_FAST                       0: self
                        108     LOAD_ATTR                       6: remote_args
                        110     GET_ITER                        
                        112     CALL_FUNCTION                   1
                        114     STORE_FAST                      4: args
                        116     LOAD_CONST                      9: <CODE> <listcomp>
                        118     LOAD_CONST                      8: 'UnixBrowser.open.<locals>.<listcomp>'
                        120     MAKE_FUNCTION                   0
                        122     LOAD_FAST                       4: args
                        124     GET_ITER                        
                        126     CALL_FUNCTION                   1
                        128     STORE_FAST                      4: args
                        130     LOAD_FAST                       0: self
                        132     LOAD_METHOD                     7: _invoke
                        134     LOAD_FAST                       4: args
                        136     LOAD_CONST                      10: True
                        138     LOAD_FAST                       3: autoraise
                        140     LOAD_DEREF                      1: url
                        142     CALL_METHOD                     4
                        144     STORE_FAST                      5: success
                        146     LOAD_FAST                       5: success
                        148     POP_JUMP_IF_TRUE                92 (to 184)
                        150     LOAD_CLOSURE                    1: url
                        152     BUILD_TUPLE                     1
                        154     LOAD_CONST                      11: <CODE> <listcomp>
                        156     LOAD_CONST                      8: 'UnixBrowser.open.<locals>.<listcomp>'
                        158     MAKE_FUNCTION                   8
                        160     LOAD_FAST                       0: self
                        162     LOAD_ATTR                       8: args
                        164     GET_ITER                        
                        166     CALL_FUNCTION                   1
                        168     STORE_FAST                      4: args
                        170     LOAD_FAST                       0: self
                        172     LOAD_METHOD                     7: _invoke
                        174     LOAD_FAST                       4: args
                        176     LOAD_CONST                      12: False
                        178     LOAD_CONST                      12: False
                        180     CALL_METHOD                     3
                        182     RETURN_VALUE                    
                        184     LOAD_CONST                      10: True
                        186     RETURN_VALUE                    
                'UnixBrowser.open'
                (
                    None
                )
                (
                    0
                    True
                )
            [Disassembly]
                0       LOAD_NAME                       0: __name__
                2       STORE_NAME                      1: __module__
                4       LOAD_CONST                      0: 'UnixBrowser'
                6       STORE_NAME                      2: __qualname__
                8       LOAD_CONST                      1: 'Parent class for all Unix browsers with remote functionality.'
                10      STORE_NAME                      3: __doc__
                12      LOAD_CONST                      2: None
                14      STORE_NAME                      4: raise_opts
                16      LOAD_CONST                      3: False
                18      STORE_NAME                      5: background
                20      LOAD_CONST                      4: True
                22      STORE_NAME                      6: redirect_stdout
                24      LOAD_CONST                      5: '%action'
                26      LOAD_CONST                      6: '%s'
                28      BUILD_LIST                      2
                30      STORE_NAME                      7: remote_args
                32      LOAD_CONST                      2: None
                34      STORE_NAME                      8: remote_action
                36      LOAD_CONST                      2: None
                38      STORE_NAME                      9: remote_action_newwin
                40      LOAD_CONST                      2: None
                42      STORE_NAME                      10: remote_action_newtab
                44      LOAD_CONST                      12: (None,)
                46      LOAD_CONST                      7: <CODE> _invoke
                48      LOAD_CONST                      8: 'UnixBrowser._invoke'
                50      MAKE_FUNCTION                   1
                52      STORE_NAME                      11: _invoke
                54      LOAD_CONST                      13: (0, True)
                56      LOAD_CONST                      10: <CODE> open
                58      LOAD_CONST                      11: 'UnixBrowser.open'
                60      MAKE_FUNCTION                   1
                62      STORE_NAME                      12: open
                64      LOAD_CONST                      2: None
                66      RETURN_VALUE                    
        'UnixBrowser'
        [Code]
            File Name: webbrowser.py
            Object Name: Mozilla
            Arg Count: 0
            Pos Only Arg Count: 0
            KW Only Arg Count: 0
            Locals: 0
            Stack Size: 2
            Flags: 0x00000040 (CO_NOFREE)
            [Names]
                '__name__'
                '__module__'
                '__qualname__'
                '__doc__'
                'remote_args'
                'remote_action'
                'remote_action_newwin'
                'remote_action_newtab'
                'background'
            [Var Names]
            [Free Vars]
            [Cell Vars]
            [Constants]
                'Mozilla'
                'Launcher class for Mozilla browsers.'
                '%action'
                '%s'
                ''
                '-new-window'
                '-new-tab'
                True
                None
            [Disassembly]
                0       LOAD_NAME                       0: __name__
                2       STORE_NAME                      1: __module__
                4       LOAD_CONST                      0: 'Mozilla'
                6       STORE_NAME                      2: __qualname__
                8       LOAD_CONST                      1: 'Launcher class for Mozilla browsers.'
                10      STORE_NAME                      3: __doc__
                12      LOAD_CONST                      2: '%action'
                14      LOAD_CONST                      3: '%s'
                16      BUILD_LIST                      2
                18      STORE_NAME                      4: remote_args
                20      LOAD_CONST                      4: ''
                22      STORE_NAME                      5: remote_action
                24      LOAD_CONST                      5: '-new-window'
                26      STORE_NAME                      6: remote_action_newwin
                28      LOAD_CONST                      6: '-new-tab'
                30      STORE_NAME                      7: remote_action_newtab
                32      LOAD_CONST                      7: True
                34      STORE_NAME                      8: background
                36      LOAD_CONST                      8: None
                38      RETURN_VALUE                    
        'Mozilla'
        [Code]
            File Name: webbrowser.py
            Object Name: Netscape
            Arg Count: 0
            Pos Only Arg Count: 0
            KW Only Arg Count: 0
            Locals: 0
            Stack Size: 2
            Flags: 0x00000040 (CO_NOFREE)
            [Names]
                '__name__'
                '__module__'
                '__qualname__'
                '__doc__'
                'raise_opts'
                'remote_args'
                'remote_action'
                'remote_action_newwin'
                'remote_action_newtab'
                'background'
            [Var Names]
            [Free Vars]
            [Cell Vars]
            [Constants]
                'Netscape'
                'Launcher class for Netscape browser.'
                '-noraise'
                '-raise'
                '-remote'
                'openURL(%s%action)'
                ''
                ',new-window'
                ',new-tab'
                True
                None
            [Disassembly]
                0       LOAD_NAME                       0: __name__
                2       STORE_NAME                      1: __module__
                4       LOAD_CONST                      0: 'Netscape'
                6       STORE_NAME                      2: __qualname__
                8       LOAD_CONST                      1: 'Launcher class for Netscape browser.'
                10      STORE_NAME                      3: __doc__
                12      LOAD_CONST                      2: '-noraise'
                14      LOAD_CONST                      3: '-raise'
                16      BUILD_LIST                      2
                18      STORE_NAME                      4: raise_opts
                20      LOAD_CONST                      4: '-remote'
                22      LOAD_CONST                      5: 'openURL(%s%action)'
                24      BUILD_LIST                      2
                26      STORE_NAME                      5: remote_args
                28      LOAD_CONST                      6: ''
                30      STORE_NAME                      6: remote_action
                32      LOAD_CONST                      7: ',new-window'
                34      STORE_NAME                      7: remote_action_newwin
                36      LOAD_CONST                      8: ',new-tab'
                38      STORE_NAME                      8: remote_action_newtab
                40      LOAD_CONST                      9: True
                42      STORE_NAME                      9: background
                44      LOAD_CONST                      10: None
                46      RETURN_VALUE                    
        'Netscape'
        [Code]
            File Name: webbrowser.py
            Object Name: Galeon
            Arg Count: 0
            Pos Only Arg Count: 0
            KW Only Arg Count: 0
            Locals: 0
            Stack Size: 2
            Flags: 0x00000040 (CO_NOFREE)
            [Names]
                '__name__'
                '__module__'
                '__qualname__'
                '__doc__'
                'raise_opts'
                'remote_args'
                'remote_action'
                'remote_action_newwin'
                'background'
            [Var Names]
            [Free Vars]
            [Cell Vars]
            [Constants]
                'Galeon'
                'Launcher class for Galeon/Epiphany browsers.'
                '-noraise'
                ''
                '%action'
                '%s'
                '-n'
                '-w'
                True
                None
            [Disassembly]
                0       LOAD_NAME                       0: __name__
                2       STORE_NAME                      1: __module__
                4       LOAD_CONST                      0: 'Galeon'
                6       STORE_NAME                      2: __qualname__
                8       LOAD_CONST                      1: 'Launcher class for Galeon/Epiphany browsers.'
                10      STORE_NAME                      3: __doc__
                12      LOAD_CONST                      2: '-noraise'
                14      LOAD_CONST                      3: ''
                16      BUILD_LIST                      2
                18      STORE_NAME                      4: raise_opts
                20      LOAD_CONST                      4: '%action'
                22      LOAD_CONST                      5: '%s'
                24      BUILD_LIST                      2
                26      STORE_NAME                      5: remote_args
                28      LOAD_CONST                      6: '-n'
                30      STORE_NAME                      6: remote_action
                32      LOAD_CONST                      7: '-w'
                34      STORE_NAME                      7: remote_action_newwin
                36      LOAD_CONST                      8: True
                38      STORE_NAME                      8: background
                40      LOAD_CONST                      9: None
                42      RETURN_VALUE                    
        'Galeon'
        [Code]
            File Name: webbrowser.py
            Object Name: Chrome
            Arg Count: 0
            Pos Only Arg Count: 0
            KW Only Arg Count: 0
            Locals: 0
            Stack Size: 2
            Flags: 0x00000040 (CO_NOFREE)
            [Names]
                '__name__'
                '__module__'
                '__qualname__'
                '__doc__'
                'remote_args'
                'remote_action'
                'remote_action_newwin'
                'remote_action_newtab'
                'background'
            [Var Names]
            [Free Vars]
            [Cell Vars]
            [Constants]
                'Chrome'
                'Launcher class for Google Chrome browser.'
                '%action'
                '%s'
                ''
                '--new-window'
                True
                None
            [Disassembly]
                0       LOAD_NAME                       0: __name__
                2       STORE_NAME                      1: __module__
                4       LOAD_CONST                      0: 'Chrome'
                6       STORE_NAME                      2: __qualname__
                8       LOAD_CONST                      1: 'Launcher class for Google Chrome browser.'
                10      STORE_NAME                      3: __doc__
                12      LOAD_CONST                      2: '%action'
                14      LOAD_CONST                      3: '%s'
                16      BUILD_LIST                      2
                18      STORE_NAME                      4: remote_args
                20      LOAD_CONST                      4: ''
                22      STORE_NAME                      5: remote_action
                24      LOAD_CONST                      5: '--new-window'
                26      STORE_NAME                      6: remote_action_newwin
                28      LOAD_CONST                      4: ''
                30      STORE_NAME                      7: remote_action_newtab
                32      LOAD_CONST                      6: True
                34      STORE_NAME                      8: background
                36      LOAD_CONST                      7: None
                38      RETURN_VALUE                    
        'Chrome'
        [Code]
            File Name: webbrowser.py
            Object Name: Opera
            Arg Count: 0
            Pos Only Arg Count: 0
            KW Only Arg Count: 0
            Locals: 0
            Stack Size: 2
            Flags: 0x00000040 (CO_NOFREE)
            [Names]
                '__name__'
                '__module__'
                '__qualname__'
                '__doc__'
                'remote_args'
                'remote_action'
                'remote_action_newwin'
                'remote_action_newtab'
                'background'
            [Var Names]
            [Free Vars]
            [Cell Vars]
            [Constants]
                'Opera'
                'Launcher class for Opera browser.'
                '%action'
                '%s'
                ''
                '--new-window'
                True
                None
            [Disassembly]
                0       LOAD_NAME                       0: __name__
                2       STORE_NAME                      1: __module__
                4       LOAD_CONST                      0: 'Opera'
                6       STORE_NAME                      2: __qualname__
                8       LOAD_CONST                      1: 'Launcher class for Opera browser.'
                10      STORE_NAME                      3: __doc__
                12      LOAD_CONST                      2: '%action'
                14      LOAD_CONST                      3: '%s'
                16      BUILD_LIST                      2
                18      STORE_NAME                      4: remote_args
                20      LOAD_CONST                      4: ''
                22      STORE_NAME                      5: remote_action
                24      LOAD_CONST                      5: '--new-window'
                26      STORE_NAME                      6: remote_action_newwin
                28      LOAD_CONST                      4: ''
                30      STORE_NAME                      7: remote_action_newtab
                32      LOAD_CONST                      6: True
                34      STORE_NAME                      8: background
                36      LOAD_CONST                      7: None
                38      RETURN_VALUE                    
        'Opera'
        [Code]
            File Name: webbrowser.py
            Object Name: Elinks
            Arg Count: 0
            Pos Only Arg Count: 0
            KW Only Arg Count: 0
            Locals: 0
            Stack Size: 2
            Flags: 0x00000040 (CO_NOFREE)
            [Names]
                '__name__'
                '__module__'
                '__qualname__'
                '__doc__'
                'remote_args'
                'remote_action'
                'remote_action_newwin'
                'remote_action_newtab'
                'background'
                'redirect_stdout'
            [Var Names]
            [Free Vars]
            [Cell Vars]
            [Constants]
                'Elinks'
                'Launcher class for Elinks browsers.'
                '-remote'
                'openURL(%s%action)'
                ''
                ',new-window'
                ',new-tab'
                False
                None
            [Disassembly]
                0       LOAD_NAME                       0: __name__
                2       STORE_NAME                      1: __module__
                4       LOAD_CONST                      0: 'Elinks'
                6       STORE_NAME                      2: __qualname__
                8       LOAD_CONST                      1: 'Launcher class for Elinks browsers.'
                10      STORE_NAME                      3: __doc__
                12      LOAD_CONST                      2: '-remote'
                14      LOAD_CONST                      3: 'openURL(%s%action)'
                16      BUILD_LIST                      2
                18      STORE_NAME                      4: remote_args
                20      LOAD_CONST                      4: ''
                22      STORE_NAME                      5: remote_action
                24      LOAD_CONST                      5: ',new-window'
                26      STORE_NAME                      6: remote_action_newwin
                28      LOAD_CONST                      6: ',new-tab'
                30      STORE_NAME                      7: remote_action_newtab
                32      LOAD_CONST                      7: False
                34      STORE_NAME                      8: background
                36      LOAD_CONST                      7: False
                38      STORE_NAME                      9: redirect_stdout
                40      LOAD_CONST                      8: None
                42      RETURN_VALUE                    
        'Elinks'
        [Code]
            File Name: webbrowser.py
            Object Name: Konqueror
            Arg Count: 0
            Pos Only Arg Count: 0
            KW Only Arg Count: 0
            Locals: 0
            Stack Size: 3
            Flags: 0x00000040 (CO_NOFREE)
            [Names]
                '__name__'
                '__module__'
                '__qualname__'
                '__doc__'
                'open'
            [Var Names]
            [Free Vars]
            [Cell Vars]
            [Constants]
                'Konqueror'
                'Controller for the KDE File Manager (kfm, or Konqueror).\n\n    See the output of ``kfmclient --commands``\n    for more information on the Konqueror remote-control interface.\n    '
                0
                True
                [Code]
                    File Name: webbrowser.py
                    Object Name: open
                    Arg Count: 4
                    Pos Only Arg Count: 0
                    KW Only Arg Count: 0
                    Locals: 7
                    Stack Size: 8
                    Flags: 0x00000043 (CO_OPTIMIZED | CO_NEWLOCALS | CO_NOFREE)
                    [Names]
                        'sys'
                        'audit'
                        'subprocess'
                        'DEVNULL'
                        'Popen'
                        'OSError'
                        'wait'
                        'poll'
                    [Var Names]
                        'self'
                        'url'
                        'new'
                        'autoraise'
                        'action'
                        'devnull'
                        'p'
                    [Free Vars]
                    [Cell Vars]
                    [Constants]
                        None
                        'webbrowser.open'
                        2
                        'newTab'
                        'openURL'
                        'kfmclient'
                        True
                        (
                            'close_fds'
                            'stdin'
                            'stdout'
                            'stderr'
                        )
                        'konqueror'
                        '--silent'
                        (
                            'close_fds'
                            'stdin'
                            'stdout'
                            'stderr'
                            'start_new_session'
                        )
                        'kfm'
                        '-d'
                        False
                    [Disassembly]
                        0       LOAD_GLOBAL                     0: sys
                        2       LOAD_METHOD                     1: audit
                        4       LOAD_CONST                      1: 'webbrowser.open'
                        6       LOAD_FAST                       1: url
                        8       CALL_METHOD                     2
                        10      POP_TOP                         
                        12      LOAD_FAST                       2: new
                        14      LOAD_CONST                      2: 2
                        16      COMPARE_OP                      2 (==)
                        18      POP_JUMP_IF_FALSE               13 (to 26)
                        20      LOAD_CONST                      3: 'newTab'
                        22      STORE_FAST                      4: action
                        24      JUMP_FORWARD                    2 (to 30)
                        26      LOAD_CONST                      4: 'openURL'
                        28      STORE_FAST                      4: action
                        30      LOAD_GLOBAL                     2: subprocess
                        32      LOAD_ATTR                       3: DEVNULL
                        34      STORE_FAST                      5: devnull
                        36      SETUP_FINALLY                   15 (to 68)
                        38      LOAD_GLOBAL                     2: subprocess
                        40      LOAD_ATTR                       4: Popen
                        42      LOAD_CONST                      5: 'kfmclient'
                        44      LOAD_FAST                       4: action
                        46      LOAD_FAST                       1: url
                        48      BUILD_LIST                      3
                        50      LOAD_CONST                      6: True
                        52      LOAD_FAST                       5: devnull
                        54      LOAD_FAST                       5: devnull
                        56      LOAD_FAST                       5: devnull
                        58      LOAD_CONST                      7: ('close_fds', 'stdin', 'stdout', 'stderr')
                        60      CALL_FUNCTION_KW                5
                        62      STORE_FAST                      6: p
                        64      POP_BLOCK                       
                        66      JUMP_FORWARD                    9 (to 86)
                        68      DUP_TOP                         
                        70      LOAD_GLOBAL                     5: OSError
                        72      JUMP_IF_NOT_EXC_MATCH           42 (to 84)
                        74      POP_TOP                         
                        76      POP_TOP                         
                        78      POP_TOP                         
                        80      POP_EXCEPT                      
                        82      JUMP_FORWARD                    7 (to 98)
                        84      RERAISE                         0
                        86      LOAD_FAST                       6: p
                        88      LOAD_METHOD                     6: wait
                        90      CALL_METHOD                     0
                        92      POP_TOP                         
                        94      LOAD_CONST                      6: True
                        96      RETURN_VALUE                    
                        98      SETUP_FINALLY                   16 (to 132)
                        100     LOAD_GLOBAL                     2: subprocess
                        102     LOAD_ATTR                       4: Popen
                        104     LOAD_CONST                      8: 'konqueror'
                        106     LOAD_CONST                      9: '--silent'
                        108     LOAD_FAST                       1: url
                        110     BUILD_LIST                      3
                        112     LOAD_CONST                      6: True
                        114     LOAD_FAST                       5: devnull
                        116     LOAD_FAST                       5: devnull
                        118     LOAD_FAST                       5: devnull
                        120     LOAD_CONST                      6: True
                        122     LOAD_CONST                      10: ('close_fds', 'stdin', 'stdout', 'stderr', 'start_new_session')
                        124     CALL_FUNCTION_KW                6
                        126     STORE_FAST                      6: p
                        128     POP_BLOCK                       
                        130     JUMP_FORWARD                    9 (to 150)
                        132     DUP_TOP                         
                        134     LOAD_GLOBAL                     5: OSError
                        136     JUMP_IF_NOT_EXC_MATCH           74 (to 148)
                        138     POP_TOP                         
                        140     POP_TOP                         
                        142     POP_TOP                         
                        144     POP_EXCEPT                      
                        146     JUMP_FORWARD                    9 (to 166)
                        148     RERAISE                         0
                        150     LOAD_FAST                       6: p
                        152     LOAD_METHOD                     7: poll
                        154     CALL_METHOD                     0
                        156     LOAD_CONST                      0: None
                        158     IS_OP                           0 (is)
                        160     POP_JUMP_IF_FALSE               83 (to 166)
                        162     LOAD_CONST                      6: True
                        164     RETURN_VALUE                    
                        166     SETUP_FINALLY                   16 (to 200)
                        168     LOAD_GLOBAL                     2: subprocess
                        170     LOAD_ATTR                       4: Popen
                        172     LOAD_CONST                      11: 'kfm'
                        174     LOAD_CONST                      12: '-d'
                        176     LOAD_FAST                       1: url
                        178     BUILD_LIST                      3
                        180     LOAD_CONST                      6: True
                        182     LOAD_FAST                       5: devnull
                        184     LOAD_FAST                       5: devnull
                        186     LOAD_FAST                       5: devnull
                        188     LOAD_CONST                      6: True
                        190     LOAD_CONST                      10: ('close_fds', 'stdin', 'stdout', 'stderr', 'start_new_session')
                        192     CALL_FUNCTION_KW                6
                        194     STORE_FAST                      6: p
                        196     POP_BLOCK                       
                        198     JUMP_FORWARD                    10 (to 220)
                        200     DUP_TOP                         
                        202     LOAD_GLOBAL                     5: OSError
                        204     JUMP_IF_NOT_EXC_MATCH           109 (to 218)
                        206     POP_TOP                         
                        208     POP_TOP                         
                        210     POP_TOP                         
                        212     POP_EXCEPT                      
                        214     LOAD_CONST                      13: False
                        216     RETURN_VALUE                    
                        218     RERAISE                         0
                        220     LOAD_FAST                       6: p
                        222     LOAD_METHOD                     7: poll
                        224     CALL_METHOD                     0
                        226     LOAD_CONST                      0: None
                        228     IS_OP                           0 (is)
                        230     RETURN_VALUE                    
                'Konqueror.open'
                None
                (
                    0
                    True
                )
            [Disassembly]
                0       LOAD_NAME                       0: __name__
                2       STORE_NAME                      1: __module__
                4       LOAD_CONST                      0: 'Konqueror'
                6       STORE_NAME                      2: __qualname__
                8       LOAD_CONST                      1: 'Controller for the KDE File Manager (kfm, or Konqueror).\n\n    See the output of ``kfmclient --commands``\n    for more information on the Konqueror remote-control interface.\n    '
                10      STORE_NAME                      3: __doc__
                12      LOAD_CONST                      7: (0, True)
                14      LOAD_CONST                      4: <CODE> open
                16      LOAD_CONST                      5: 'Konqueror.open'
                18      MAKE_FUNCTION                   1
                20      STORE_NAME                      4: open
                22      LOAD_CONST                      6: None
                24      RETURN_VALUE                    
        'Konqueror'
        [Code]
            File Name: webbrowser.py
            Object Name: Grail
            Arg Count: 0
            Pos Only Arg Count: 0
            KW Only Arg Count: 0
            Locals: 0
            Stack Size: 3
            Flags: 0x00000040 (CO_NOFREE)
            [Names]
                '__name__'
                '__module__'
                '__qualname__'
                '_find_grail_rc'
                '_remote'
                'open'
            [Var Names]
            [Free Vars]
            [Cell Vars]
            [Constants]
                'Grail'
                [Code]
                    File Name: webbrowser.py
                    Object Name: _find_grail_rc
                    Arg Count: 1
                    Pos Only Arg Count: 0
                    KW Only Arg Count: 0
                    Locals: 11
                    Stack Size: 12
                    Flags: 0x00000043 (CO_OPTIMIZED | CO_NEWLOCALS | CO_NOFREE)
                    [Names]
                        'glob'
                        'pwd'
                        'socket'
                        'tempfile'
                        'os'
                        'path'
                        'join'
                        'gettempdir'
                        'getpwuid'
                        'getuid'
                        'escape'
                        'AF_UNIX'
                        'SOCK_STREAM'
                        'connect'
                        'OSError'
                        'unlink'
                    [Var Names]
                        'self'
                        'glob'
                        'pwd'
                        'socket'
                        'tempfile'
                        'tempdir'
                        'user'
                        'filename'
                        'maybes'
                        's'
                        'fn'
                    [Free Vars]
                    [Cell Vars]
                    [Constants]
                        None
                        0
                        '.grail-unix'
                        '-*'
                    [Disassembly]
                        0       LOAD_CONST                      1: 0
                        2       LOAD_CONST                      0: None
                        4       IMPORT_NAME                     0: glob
                        6       STORE_FAST                      1: glob
                        8       LOAD_CONST                      1: 0
                        10      LOAD_CONST                      0: None
                        12      IMPORT_NAME                     1: pwd
                        14      STORE_FAST                      2: pwd
                        16      LOAD_CONST                      1: 0
                        18      LOAD_CONST                      0: None
                        20      IMPORT_NAME                     2: socket
                        22      STORE_FAST                      3: socket
                        24      LOAD_CONST                      1: 0
                        26      LOAD_CONST                      0: None
                        28      IMPORT_NAME                     3: tempfile
                        30      STORE_FAST                      4: tempfile
                        32      LOAD_GLOBAL                     4: os
                        34      LOAD_ATTR                       5: path
                        36      LOAD_METHOD                     6: join
                        38      LOAD_FAST                       4: tempfile
                        40      LOAD_METHOD                     7: gettempdir
                        42      CALL_METHOD                     0
                        44      LOAD_CONST                      2: '.grail-unix'
                        46      CALL_METHOD                     2
                        48      STORE_FAST                      5: tempdir
                        50      LOAD_FAST                       2: pwd
                        52      LOAD_METHOD                     8: getpwuid
                        54      LOAD_GLOBAL                     4: os
                        56      LOAD_METHOD                     9: getuid
                        58      CALL_METHOD                     0
                        60      CALL_METHOD                     1
                        62      LOAD_CONST                      1: 0
                        64      BINARY_SUBSCR                   
                        66      STORE_FAST                      6: user
                        68      LOAD_GLOBAL                     4: os
                        70      LOAD_ATTR                       5: path
                        72      LOAD_METHOD                     6: join
                        74      LOAD_FAST                       1: glob
                        76      LOAD_METHOD                     10: escape
                        78      LOAD_FAST                       5: tempdir
                        80      CALL_METHOD                     1
                        82      LOAD_FAST                       1: glob
                        84      LOAD_METHOD                     10: escape
                        86      LOAD_FAST                       6: user
                        88      CALL_METHOD                     1
                        90      LOAD_CONST                      3: '-*'
                        92      BINARY_ADD                      
                        94      CALL_METHOD                     2
                        96      STORE_FAST                      7: filename
                        98      LOAD_FAST                       1: glob
                        100     LOAD_METHOD                     0: glob
                        102     LOAD_FAST                       7: filename
                        104     CALL_METHOD                     1
                        106     STORE_FAST                      8: maybes
                        108     LOAD_FAST                       8: maybes
                        110     POP_JUMP_IF_TRUE                58 (to 116)
                        112     LOAD_CONST                      0: None
                        114     RETURN_VALUE                    
                        116     LOAD_FAST                       3: socket
                        118     LOAD_METHOD                     2: socket
                        120     LOAD_FAST                       3: socket
                        122     LOAD_ATTR                       11: AF_UNIX
                        124     LOAD_FAST                       3: socket
                        126     LOAD_ATTR                       12: SOCK_STREAM
                        128     CALL_METHOD                     2
                        130     STORE_FAST                      9: s
                        132     LOAD_FAST                       8: maybes
                        134     GET_ITER                        
                        136     FOR_ITER                        38 (to 214)
                        138     STORE_FAST                      10: fn
                        140     SETUP_FINALLY                   10 (to 162)
                        142     LOAD_FAST                       9: s
                        144     LOAD_METHOD                     13: connect
                        146     LOAD_FAST                       10: fn
                        148     CALL_METHOD                     1
                        150     POP_TOP                         
                        152     POP_BLOCK                       
                        154     LOAD_FAST                       9: s
                        156     ROT_TWO                         
                        158     POP_TOP                         
                        160     RETURN_VALUE                    
                        162     DUP_TOP                         
                        164     LOAD_GLOBAL                     14: OSError
                        166     JUMP_IF_NOT_EXC_MATCH           106 (to 212)
                        168     POP_TOP                         
                        170     POP_TOP                         
                        172     POP_TOP                         
                        174     SETUP_FINALLY                   7 (to 190)
                        176     LOAD_GLOBAL                     4: os
                        178     LOAD_METHOD                     15: unlink
                        180     LOAD_FAST                       10: fn
                        182     CALL_METHOD                     1
                        184     POP_TOP                         
                        186     POP_BLOCK                       
                        188     JUMP_FORWARD                    9 (to 208)
                        190     DUP_TOP                         
                        192     LOAD_GLOBAL                     14: OSError
                        194     JUMP_IF_NOT_EXC_MATCH           103 (to 206)
                        196     POP_TOP                         
                        198     POP_TOP                         
                        200     POP_TOP                         
                        202     POP_EXCEPT                      
                        204     JUMP_FORWARD                    1 (to 208)
                        206     RERAISE                         0
                        208     POP_EXCEPT                      
                        210     JUMP_ABSOLUTE                   68 (to 136)
                        212     RERAISE                         0
                        214     LOAD_CONST                      0: None
                        216     RETURN_VALUE                    
                'Grail._find_grail_rc'
                [Code]
                    File Name: webbrowser.py
                    Object Name: _remote
                    Arg Count: 2
                    Pos Only Arg Count: 0
                    KW Only Arg Count: 0
                    Locals: 3
                    Stack Size: 3
                    Flags: 0x00000043 (CO_OPTIMIZED | CO_NEWLOCALS | CO_NOFREE)
                    [Names]
                        '_find_grail_rc'
                        'send'
                        'close'
                    [Var Names]
                        'self'
                        'action'
                        's'
                    [Free Vars]
                    [Cell Vars]
                    [Constants]
                        None
                        0
                        1
                    [Disassembly]
                        0       LOAD_FAST                       0: self
                        2       LOAD_METHOD                     0: _find_grail_rc
                        4       CALL_METHOD                     0
                        6       STORE_FAST                      2: s
                        8       LOAD_FAST                       2: s
                        10      POP_JUMP_IF_TRUE                8 (to 16)
                        12      LOAD_CONST                      1: 0
                        14      RETURN_VALUE                    
                        16      LOAD_FAST                       2: s
                        18      LOAD_METHOD                     1: send
                        20      LOAD_FAST                       1: action
                        22      CALL_METHOD                     1
                        24      POP_TOP                         
                        26      LOAD_FAST                       2: s
                        28      LOAD_METHOD                     2: close
                        30      CALL_METHOD                     0
                        32      POP_TOP                         
                        34      LOAD_CONST                      2: 1
                        36      RETURN_VALUE                    
                'Grail._remote'
                0
                True
                [Code]
                    File Name: webbrowser.py
                    Object Name: open
                    Arg Count: 4
                    Pos Only Arg Count: 0
                    KW Only Arg Count: 0
                    Locals: 5
                    Stack Size: 4
                    Flags: 0x00000043 (CO_OPTIMIZED | CO_NEWLOCALS | CO_NOFREE)
                    [Names]
                        'sys'
                        'audit'
                        '_remote'
                    [Var Names]
                        'self'
                        'url'
                        'new'
                        'autoraise'
                        'ok'
                    [Free Vars]
                    [Cell Vars]
                    [Constants]
                        None
                        'webbrowser.open'
                        'LOADNEW '
                        'LOAD '
                    [Disassembly]
                        0       LOAD_GLOBAL                     0: sys
                        2       LOAD_METHOD                     1: audit
                        4       LOAD_CONST                      1: 'webbrowser.open'
                        6       LOAD_FAST                       1: url
                        8       CALL_METHOD                     2
                        10      POP_TOP                         
                        12      LOAD_FAST                       2: new
                        14      POP_JUMP_IF_FALSE               17 (to 34)
                        16      LOAD_FAST                       0: self
                        18      LOAD_METHOD                     2: _remote
                        20      LOAD_CONST                      2: 'LOADNEW '
                        22      LOAD_FAST                       1: url
                        24      BINARY_ADD                      
                        26      CALL_METHOD                     1
                        28      STORE_FAST                      4: ok
                        30      LOAD_FAST                       4: ok
                        32      RETURN_VALUE                    
                        34      LOAD_FAST                       0: self
                        36      LOAD_METHOD                     2: _remote
                        38      LOAD_CONST                      3: 'LOAD '
                        40      LOAD_FAST                       1: url
                        42      BINARY_ADD                      
                        44      CALL_METHOD                     1
                        46      STORE_FAST                      4: ok
                        48      LOAD_FAST                       4: ok
                        50      RETURN_VALUE                    
                'Grail.open'
                None
                (
                    0
                    True
                )
            [Disassembly]
                0       LOAD_NAME                       0: __name__
                2       STORE_NAME                      1: __module__
                4       LOAD_CONST                      0: 'Grail'
                6       STORE_NAME                      2: __qualname__
                8       LOAD_CONST                      1: <CODE> _find_grail_rc
                10      LOAD_CONST                      2: 'Grail._find_grail_rc'
                12      MAKE_FUNCTION                   0
                14      STORE_NAME                      3: _find_grail_rc
                16      LOAD_CONST                      3: <CODE> _remote
                18      LOAD_CONST                      4: 'Grail._remote'
                20      MAKE_FUNCTION                   0
                22      STORE_NAME                      4: _remote
                24      LOAD_CONST                      10: (0, True)
                26      LOAD_CONST                      7: <CODE> open
                28      LOAD_CONST                      8: 'Grail.open'
                30      MAKE_FUNCTION                   1
                32      STORE_NAME                      5: open
                34      LOAD_CONST                      9: None
                36      RETURN_VALUE                    
        'Grail'
        [Code]
            File Name: webbrowser.py
            Object Name: register_X_browsers
            Arg Count: 0
            Pos Only Arg Count: 0
            KW Only Arg Count: 0
            Locals: 1
            Stack Size: 6
            Flags: 0x00000043 (CO_OPTIMIZED | CO_NEWLOCALS | CO_NOFREE)
            [Names]
                'shutil'
                'which'
                'register'
                'BackgroundBrowser'
                'os'
                'environ'
                'Konqueror'
                'Mozilla'
                'Netscape'
                'Galeon'
                'Chrome'
                'Opera'
                'Grail'
            [Var Names]
                'browser'
            [Free Vars]
            [Cell Vars]
            [Constants]
                None
                'xdg-open'
                'GNOME_DESKTOP_SESSION_ID'
                'gvfs-open'
                'gnome-open'
                'KDE_FULL_SESSION'
                'kfmclient'
                'x-www-browser'
                (
                    'firefox'
                    'iceweasel'
                    'iceape'
                    'seamonkey'
                )
                (
                    'mozilla-firefox'
                    'mozilla-firebird'
                    'firebird'
                    'mozilla'
                    'netscape'
                )
                'kfm'
                'konqueror'
                (
                    'galeon'
                    'epiphany'
                )
                'skipstone'
                (
                    'google-chrome'
                    'chrome'
                    'chromium'
                    'chromium-browser'
                )
                'opera'
                'mosaic'
                'grail'
            [Disassembly]
                0       LOAD_GLOBAL                     0: shutil
                2       LOAD_METHOD                     1: which
                4       LOAD_CONST                      1: 'xdg-open'
                6       CALL_METHOD                     1
                8       POP_JUMP_IF_FALSE               13 (to 26)
                10      LOAD_GLOBAL                     2: register
                12      LOAD_CONST                      1: 'xdg-open'
                14      LOAD_CONST                      0: None
                16      LOAD_GLOBAL                     3: BackgroundBrowser
                18      LOAD_CONST                      1: 'xdg-open'
                20      CALL_FUNCTION                   1
                22      CALL_FUNCTION                   3
                24      POP_TOP                         
                26      LOAD_CONST                      2: 'GNOME_DESKTOP_SESSION_ID'
                28      LOAD_GLOBAL                     4: os
                30      LOAD_ATTR                       5: environ
                32      CONTAINS_OP                     0 (in)
                34      POP_JUMP_IF_FALSE               31 (to 62)
                36      LOAD_GLOBAL                     0: shutil
                38      LOAD_METHOD                     1: which
                40      LOAD_CONST                      3: 'gvfs-open'
                42      CALL_METHOD                     1
                44      POP_JUMP_IF_FALSE               31 (to 62)
                46      LOAD_GLOBAL                     2: register
                48      LOAD_CONST                      3: 'gvfs-open'
                50      LOAD_CONST                      0: None
                52      LOAD_GLOBAL                     3: BackgroundBrowser
                54      LOAD_CONST                      3: 'gvfs-open'
                56      CALL_FUNCTION                   1
                58      CALL_FUNCTION                   3
                60      POP_TOP                         
                62      LOAD_CONST                      2: 'GNOME_DESKTOP_SESSION_ID'
                64      LOAD_GLOBAL                     4: os
                66      LOAD_ATTR                       5: environ
                68      CONTAINS_OP                     0 (in)
                70      POP_JUMP_IF_FALSE               49 (to 98)
                72      LOAD_GLOBAL                     0: shutil
                74      LOAD_METHOD                     1: which
                76      LOAD_CONST                      4: 'gnome-open'
                78      CALL_METHOD                     1
                80      POP_JUMP_IF_FALSE               49 (to 98)
                82      LOAD_GLOBAL                     2: register
                84      LOAD_CONST                      4: 'gnome-open'
                86      LOAD_CONST                      0: None
                88      LOAD_GLOBAL                     3: BackgroundBrowser
                90      LOAD_CONST                      4: 'gnome-open'
                92      CALL_FUNCTION                   1
                94      CALL_FUNCTION                   3
                96      POP_TOP                         
                98      LOAD_CONST                      5: 'KDE_FULL_SESSION'
                100     LOAD_GLOBAL                     4: os
                102     LOAD_ATTR                       5: environ
                104     CONTAINS_OP                     0 (in)
                106     POP_JUMP_IF_FALSE               67 (to 134)
                108     LOAD_GLOBAL                     0: shutil
                110     LOAD_METHOD                     1: which
                112     LOAD_CONST                      6: 'kfmclient'
                114     CALL_METHOD                     1
                116     POP_JUMP_IF_FALSE               67 (to 134)
                118     LOAD_GLOBAL                     2: register
                120     LOAD_CONST                      6: 'kfmclient'
                122     LOAD_GLOBAL                     6: Konqueror
                124     LOAD_GLOBAL                     6: Konqueror
                126     LOAD_CONST                      6: 'kfmclient'
                128     CALL_FUNCTION                   1
                130     CALL_FUNCTION                   3
                132     POP_TOP                         
                134     LOAD_GLOBAL                     0: shutil
                136     LOAD_METHOD                     1: which
                138     LOAD_CONST                      7: 'x-www-browser'
                140     CALL_METHOD                     1
                142     POP_JUMP_IF_FALSE               80 (to 160)
                144     LOAD_GLOBAL                     2: register
                146     LOAD_CONST                      7: 'x-www-browser'
                148     LOAD_CONST                      0: None
                150     LOAD_GLOBAL                     3: BackgroundBrowser
                152     LOAD_CONST                      7: 'x-www-browser'
                154     CALL_FUNCTION                   1
                156     CALL_FUNCTION                   3
                158     POP_TOP                         
                160     LOAD_CONST                      8: ('firefox', 'iceweasel', 'iceape', 'seamonkey')
                162     GET_ITER                        
                164     FOR_ITER                        15 (to 196)
                166     STORE_FAST                      0: browser
                168     LOAD_GLOBAL                     0: shutil
                170     LOAD_METHOD                     1: which
                172     LOAD_FAST                       0: browser
                174     CALL_METHOD                     1
                176     POP_JUMP_IF_FALSE               97 (to 194)
                178     LOAD_GLOBAL                     2: register
                180     LOAD_FAST                       0: browser
                182     LOAD_CONST                      0: None
                184     LOAD_GLOBAL                     7: Mozilla
                186     LOAD_FAST                       0: browser
                188     CALL_FUNCTION                   1
                190     CALL_FUNCTION                   3
                192     POP_TOP                         
                194     JUMP_ABSOLUTE                   82 (to 164)
                196     LOAD_CONST                      9: ('mozilla-firefox', 'mozilla-firebird', 'firebird', 'mozilla', 'netscape')
                198     GET_ITER                        
                200     FOR_ITER                        15 (to 232)
                202     STORE_FAST                      0: browser
                204     LOAD_GLOBAL                     0: shutil
                206     LOAD_METHOD                     1: which
                208     LOAD_FAST                       0: browser
                210     CALL_METHOD                     1
                212     POP_JUMP_IF_FALSE               115 (to 230)
                214     LOAD_GLOBAL                     2: register
                216     LOAD_FAST                       0: browser
                218     LOAD_CONST                      0: None
                220     LOAD_GLOBAL                     8: Netscape
                222     LOAD_FAST                       0: browser
                224     CALL_FUNCTION                   1
                226     CALL_FUNCTION                   3
                228     POP_TOP                         
                230     JUMP_ABSOLUTE                   100 (to 200)
                232     LOAD_GLOBAL                     0: shutil
                234     LOAD_METHOD                     1: which
                236     LOAD_CONST                      10: 'kfm'
                238     CALL_METHOD                     1
                240     POP_JUMP_IF_FALSE               130 (to 260)
                242     LOAD_GLOBAL                     2: register
                244     LOAD_CONST                      10: 'kfm'
                246     LOAD_GLOBAL                     6: Konqueror
                248     LOAD_GLOBAL                     6: Konqueror
                250     LOAD_CONST                      10: 'kfm'
                252     CALL_FUNCTION                   1
                254     CALL_FUNCTION                   3
                256     POP_TOP                         
                258     JUMP_FORWARD                    13 (to 286)
                260     LOAD_GLOBAL                     0: shutil
                262     LOAD_METHOD                     1: which
                264     LOAD_CONST                      11: 'konqueror'
                266     CALL_METHOD                     1
                268     POP_JUMP_IF_FALSE               143 (to 286)
                270     LOAD_GLOBAL                     2: register
                272     LOAD_CONST                      11: 'konqueror'
                274     LOAD_GLOBAL                     6: Konqueror
                276     LOAD_GLOBAL                     6: Konqueror
                278     LOAD_CONST                      11: 'konqueror'
                280     CALL_FUNCTION                   1
                282     CALL_FUNCTION                   3
                284     POP_TOP                         
                286     LOAD_CONST                      12: ('galeon', 'epiphany')
                288     GET_ITER                        
                290     FOR_ITER                        15 (to 322)
                292     STORE_FAST                      0: browser
                294     LOAD_GLOBAL                     0: shutil
                296     LOAD_METHOD                     1: which
                298     LOAD_FAST                       0: browser
                300     CALL_METHOD                     1
                302     POP_JUMP_IF_FALSE               160 (to 320)
                304     LOAD_GLOBAL                     2: register
                306     LOAD_FAST                       0: browser
                308     LOAD_CONST                      0: None
                310     LOAD_GLOBAL                     9: Galeon
                312     LOAD_FAST                       0: browser
                314     CALL_FUNCTION                   1
                316     CALL_FUNCTION                   3
                318     POP_TOP                         
                320     JUMP_ABSOLUTE                   145 (to 290)
                322     LOAD_GLOBAL                     0: shutil
                324     LOAD_METHOD                     1: which
                326     LOAD_CONST                      13: 'skipstone'
                328     CALL_METHOD                     1
                330     POP_JUMP_IF_FALSE               174 (to 348)
                332     LOAD_GLOBAL                     2: register
                334     LOAD_CONST                      13: 'skipstone'
                336     LOAD_CONST                      0: None
                338     LOAD_GLOBAL                     3: BackgroundBrowser
                340     LOAD_CONST                      13: 'skipstone'
                342     CALL_FUNCTION                   1
                344     CALL_FUNCTION                   3
                346     POP_TOP                         
                348     LOAD_CONST                      14: ('google-chrome', 'chrome', 'chromium', 'chromium-browser')
                350     GET_ITER                        
                352     FOR_ITER                        15 (to 384)
                354     STORE_FAST                      0: browser
                356     LOAD_GLOBAL                     0: shutil
                358     LOAD_METHOD                     1: which
                360     LOAD_FAST                       0: browser
                362     CALL_METHOD                     1
                364     POP_JUMP_IF_FALSE               191 (to 382)
                366     LOAD_GLOBAL                     2: register
                368     LOAD_FAST                       0: browser
                370     LOAD_CONST                      0: None
                372     LOAD_GLOBAL                     10: Chrome
                374     LOAD_FAST                       0: browser
                376     CALL_FUNCTION                   1
                378     CALL_FUNCTION                   3
                380     POP_TOP                         
                382     JUMP_ABSOLUTE                   176 (to 352)
                384     LOAD_GLOBAL                     0: shutil
                386     LOAD_METHOD                     1: which
                388     LOAD_CONST                      15: 'opera'
                390     CALL_METHOD                     1
                392     POP_JUMP_IF_FALSE               205 (to 410)
                394     LOAD_GLOBAL                     2: register
                396     LOAD_CONST                      15: 'opera'
                398     LOAD_CONST                      0: None
                400     LOAD_GLOBAL                     11: Opera
                402     LOAD_CONST                      15: 'opera'
                404     CALL_FUNCTION                   1
                406     CALL_FUNCTION                   3
                408     POP_TOP                         
                410     LOAD_GLOBAL                     0: shutil
                412     LOAD_METHOD                     1: which
                414     LOAD_CONST                      16: 'mosaic'
                416     CALL_METHOD                     1
                418     POP_JUMP_IF_FALSE               218 (to 436)
                420     LOAD_GLOBAL                     2: register
                422     LOAD_CONST                      16: 'mosaic'
                424     LOAD_CONST                      0: None
                426     LOAD_GLOBAL                     3: BackgroundBrowser
                428     LOAD_CONST                      16: 'mosaic'
                430     CALL_FUNCTION                   1
                432     CALL_FUNCTION                   3
                434     POP_TOP                         
                436     LOAD_GLOBAL                     0: shutil
                438     LOAD_METHOD                     1: which
                440     LOAD_CONST                      17: 'grail'
                442     CALL_METHOD                     1
                444     POP_JUMP_IF_FALSE               231 (to 462)
                446     LOAD_GLOBAL                     2: register
                448     LOAD_CONST                      17: 'grail'
                450     LOAD_GLOBAL                     12: Grail
                452     LOAD_CONST                      0: None
                454     CALL_FUNCTION                   3
                456     POP_TOP                         
                458     LOAD_CONST                      0: None
                460     RETURN_VALUE                    
                462     LOAD_CONST                      0: None
                464     RETURN_VALUE                    
        'register_X_browsers'
        [Code]
            File Name: webbrowser.py
            Object Name: register_standard_browsers
            Arg Count: 0
            Pos Only Arg Count: 0
            KW Only Arg Count: 0
            Locals: 7
            Stack Size: 11
            Flags: 0x00000043 (CO_OPTIMIZED | CO_NEWLOCALS | CO_NOFREE)
            [Names]
                '_tryorder'
                'sys'
                'platform'
                'register'
                'MacOSXOSAScript'
                'BackgroundBrowser'
                'WindowsDefault'
                'os'
                'path'
                'join'
                'environ'
                'get'
                'shutil'
                'which'
                'split'
                'subprocess'
                'check_output'
                'DEVNULL'
                'decode'
                'strip'
                'FileNotFoundError'
                'CalledProcessError'
                'PermissionError'
                'NotADirectoryError'
                '_os_preferred_browser'
                'register_X_browsers'
                'GenericBrowser'
                'Elinks'
                'pathsep'
                'reverse'
                '_synthesize'
            [Var Names]
                'iexplore'
                'browser'
                'cmd'
                'raw_result'
                'result'
                'userchoices'
                'cmdline'
            [Free Vars]
            [Cell Vars]
            [Constants]
                None
                'darwin'
                'MacOSX'
                'default'
                'chrome'
                'firefox'
                'safari'
                'serenityos'
                'Browser'
                3
                'win'
                'windows-default'
                'PROGRAMFILES'
                'C:\\Program Files'
                'Internet Explorer\\IEXPLORE.EXE'
                'firebird'
                'seamonkey'
                'mozilla'
                'netscape'
                'opera'
                'DISPLAY'
                'WAYLAND_DISPLAY'
                'xdg-settings get default-web-browser'
                (
                    'stderr'
                )
                'TERM'
                'www-browser'
                'links'
                'elinks'
                'lynx'
                'w3m'
                'BROWSER'
                ''
                True
                (
                    'preferred'
                )
                1
            [Disassembly]
                0       BUILD_LIST                      0
                2       STORE_GLOBAL                    0: _tryorder
                4       LOAD_GLOBAL                     1: sys
                6       LOAD_ATTR                       2: platform
                8       LOAD_CONST                      1: 'darwin'
                10      COMPARE_OP                      2 (==)
                12      POP_JUMP_IF_FALSE               39 (to 78)
                14      LOAD_GLOBAL                     3: register
                16      LOAD_CONST                      2: 'MacOSX'
                18      LOAD_CONST                      0: None
                20      LOAD_GLOBAL                     4: MacOSXOSAScript
                22      LOAD_CONST                      3: 'default'
                24      CALL_FUNCTION                   1
                26      CALL_FUNCTION                   3
                28      POP_TOP                         
                30      LOAD_GLOBAL                     3: register
                32      LOAD_CONST                      4: 'chrome'
                34      LOAD_CONST                      0: None
                36      LOAD_GLOBAL                     4: MacOSXOSAScript
                38      LOAD_CONST                      4: 'chrome'
                40      CALL_FUNCTION                   1
                42      CALL_FUNCTION                   3
                44      POP_TOP                         
                46      LOAD_GLOBAL                     3: register
                48      LOAD_CONST                      5: 'firefox'
                50      LOAD_CONST                      0: None
                52      LOAD_GLOBAL                     4: MacOSXOSAScript
                54      LOAD_CONST                      5: 'firefox'
                56      CALL_FUNCTION                   1
                58      CALL_FUNCTION                   3
                60      POP_TOP                         
                62      LOAD_GLOBAL                     3: register
                64      LOAD_CONST                      6: 'safari'
                66      LOAD_CONST                      0: None
                68      LOAD_GLOBAL                     4: MacOSXOSAScript
                70      LOAD_CONST                      6: 'safari'
                72      CALL_FUNCTION                   1
                74      CALL_FUNCTION                   3
                76      POP_TOP                         
                78      LOAD_GLOBAL                     1: sys
                80      LOAD_ATTR                       2: platform
                82      LOAD_CONST                      7: 'serenityos'
                84      COMPARE_OP                      2 (==)
                86      POP_JUMP_IF_FALSE               52 (to 104)
                88      LOAD_GLOBAL                     3: register
                90      LOAD_CONST                      8: 'Browser'
                92      LOAD_CONST                      0: None
                94      LOAD_GLOBAL                     5: BackgroundBrowser
                96      LOAD_CONST                      8: 'Browser'
                98      CALL_FUNCTION                   1
                100     CALL_FUNCTION                   3
                102     POP_TOP                         
                104     LOAD_GLOBAL                     1: sys
                106     LOAD_ATTR                       2: platform
                108     LOAD_CONST                      0: None
                110     LOAD_CONST                      9: 3
                112     BUILD_SLICE                     2
                114     BINARY_SUBSCR                   
                116     LOAD_CONST                      10: 'win'
                118     COMPARE_OP                      2 (==)
                120     POP_JUMP_IF_FALSE               104 (to 208)
                122     LOAD_GLOBAL                     3: register
                124     LOAD_CONST                      11: 'windows-default'
                126     LOAD_GLOBAL                     6: WindowsDefault
                128     CALL_FUNCTION                   2
                130     POP_TOP                         
                132     LOAD_GLOBAL                     7: os
                134     LOAD_ATTR                       8: path
                136     LOAD_METHOD                     9: join
                138     LOAD_GLOBAL                     7: os
                140     LOAD_ATTR                       10: environ
                142     LOAD_METHOD                     11: get
                144     LOAD_CONST                      12: 'PROGRAMFILES'
                146     LOAD_CONST                      13: 'C:\\Program Files'
                148     CALL_METHOD                     2
                150     LOAD_CONST                      14: 'Internet Explorer\\IEXPLORE.EXE'
                152     CALL_METHOD                     2
                154     STORE_FAST                      0: iexplore
                156     LOAD_CONST                      5: 'firefox'
                158     LOAD_CONST                      15: 'firebird'
                160     LOAD_CONST                      16: 'seamonkey'
                162     LOAD_CONST                      17: 'mozilla'
                164     LOAD_CONST                      18: 'netscape'
                166     LOAD_CONST                      19: 'opera'
                168     LOAD_FAST                       0: iexplore
                170     BUILD_TUPLE                     7
                172     GET_ITER                        
                174     FOR_ITER                        15 (to 206)
                176     STORE_FAST                      1: browser
                178     LOAD_GLOBAL                     12: shutil
                180     LOAD_METHOD                     13: which
                182     LOAD_FAST                       1: browser
                184     CALL_METHOD                     1
                186     POP_JUMP_IF_FALSE               102 (to 204)
                188     LOAD_GLOBAL                     3: register
                190     LOAD_FAST                       1: browser
                192     LOAD_CONST                      0: None
                194     LOAD_GLOBAL                     5: BackgroundBrowser
                196     LOAD_FAST                       1: browser
                198     CALL_FUNCTION                   1
                200     CALL_FUNCTION                   3
                202     POP_TOP                         
                204     JUMP_ABSOLUTE                   87 (to 174)
                206     JUMP_FORWARD                    123 (to 454)
                208     LOAD_GLOBAL                     7: os
                210     LOAD_ATTR                       10: environ
                212     LOAD_METHOD                     11: get
                214     LOAD_CONST                      20: 'DISPLAY'
                216     CALL_METHOD                     1
                218     POP_JUMP_IF_TRUE                116 (to 232)
                220     LOAD_GLOBAL                     7: os
                222     LOAD_ATTR                       10: environ
                224     LOAD_METHOD                     11: get
                226     LOAD_CONST                      21: 'WAYLAND_DISPLAY'
                228     CALL_METHOD                     1
                230     POP_JUMP_IF_FALSE               156 (to 312)
                232     SETUP_FINALLY                   20 (to 274)
                234     LOAD_CONST                      22: 'xdg-settings get default-web-browser'
                236     LOAD_METHOD                     14: split
                238     CALL_METHOD                     0
                240     STORE_FAST                      2: cmd
                242     LOAD_GLOBAL                     15: subprocess
                244     LOAD_ATTR                       16: check_output
                246     LOAD_FAST                       2: cmd
                248     LOAD_GLOBAL                     15: subprocess
                250     LOAD_ATTR                       17: DEVNULL
                252     LOAD_CONST                      23: ('stderr',)
                254     CALL_FUNCTION_KW                2
                256     STORE_FAST                      3: raw_result
                258     LOAD_FAST                       3: raw_result
                260     LOAD_METHOD                     18: decode
                262     CALL_METHOD                     0
                264     LOAD_METHOD                     19: strip
                266     CALL_METHOD                     0
                268     STORE_FAST                      4: result
                270     POP_BLOCK                       
                272     JUMP_FORWARD                    14 (to 302)
                274     DUP_TOP                         
                276     LOAD_GLOBAL                     20: FileNotFoundError
                278     LOAD_GLOBAL                     15: subprocess
                280     LOAD_ATTR                       21: CalledProcessError
                282     LOAD_GLOBAL                     22: PermissionError
                284     LOAD_GLOBAL                     23: NotADirectoryError
                286     BUILD_TUPLE                     4
                288     JUMP_IF_NOT_EXC_MATCH           150 (to 300)
                290     POP_TOP                         
                292     POP_TOP                         
                294     POP_TOP                         
                296     POP_EXCEPT                      
                298     JUMP_FORWARD                    3 (to 306)
                300     RERAISE                         0
                302     LOAD_FAST                       4: result
                304     STORE_GLOBAL                    24: _os_preferred_browser
                306     LOAD_GLOBAL                     25: register_X_browsers
                308     CALL_FUNCTION                   0
                310     POP_TOP                         
                312     LOAD_GLOBAL                     7: os
                314     LOAD_ATTR                       10: environ
                316     LOAD_METHOD                     11: get
                318     LOAD_CONST                      24: 'TERM'
                320     CALL_METHOD                     1
                322     POP_JUMP_IF_FALSE               227 (to 454)
                324     LOAD_GLOBAL                     12: shutil
                326     LOAD_METHOD                     13: which
                328     LOAD_CONST                      25: 'www-browser'
                330     CALL_METHOD                     1
                332     POP_JUMP_IF_FALSE               175 (to 350)
                334     LOAD_GLOBAL                     3: register
                336     LOAD_CONST                      25: 'www-browser'
                338     LOAD_CONST                      0: None
                340     LOAD_GLOBAL                     26: GenericBrowser
                342     LOAD_CONST                      25: 'www-browser'
                344     CALL_FUNCTION                   1
                346     CALL_FUNCTION                   3
                348     POP_TOP                         
                350     LOAD_GLOBAL                     12: shutil
                352     LOAD_METHOD                     13: which
                354     LOAD_CONST                      26: 'links'
                356     CALL_METHOD                     1
                358     POP_JUMP_IF_FALSE               188 (to 376)
                360     LOAD_GLOBAL                     3: register
                362     LOAD_CONST                      26: 'links'
                364     LOAD_CONST                      0: None
                366     LOAD_GLOBAL                     26: GenericBrowser
                368     LOAD_CONST                      26: 'links'
                370     CALL_FUNCTION                   1
                372     CALL_FUNCTION                   3
                374     POP_TOP                         
                376     LOAD_GLOBAL                     12: shutil
                378     LOAD_METHOD                     13: which
                380     LOAD_CONST                      27: 'elinks'
                382     CALL_METHOD                     1
                384     POP_JUMP_IF_FALSE               201 (to 402)
                386     LOAD_GLOBAL                     3: register
                388     LOAD_CONST                      27: 'elinks'
                390     LOAD_CONST                      0: None
                392     LOAD_GLOBAL                     27: Elinks
                394     LOAD_CONST                      27: 'elinks'
                396     CALL_FUNCTION                   1
                398     CALL_FUNCTION                   3
                400     POP_TOP                         
                402     LOAD_GLOBAL                     12: shutil
                404     LOAD_METHOD                     13: which
                406     LOAD_CONST                      28: 'lynx'
                408     CALL_METHOD                     1
                410     POP_JUMP_IF_FALSE               214 (to 428)
                412     LOAD_GLOBAL                     3: register
                414     LOAD_CONST                      28: 'lynx'
                416     LOAD_CONST                      0: None
                418     LOAD_GLOBAL                     26: GenericBrowser
                420     LOAD_CONST                      28: 'lynx'
                422     CALL_FUNCTION                   1
                424     CALL_FUNCTION                   3
                426     POP_TOP                         
                428     LOAD_GLOBAL                     12: shutil
                430     LOAD_METHOD                     13: which
                432     LOAD_CONST                      29: 'w3m'
                434     CALL_METHOD                     1
                436     POP_JUMP_IF_FALSE               227 (to 454)
                438     LOAD_GLOBAL                     3: register
                440     LOAD_CONST                      29: 'w3m'
                442     LOAD_CONST                      0: None
                444     LOAD_GLOBAL                     26: GenericBrowser
                446     LOAD_CONST                      29: 'w3m'
                448     CALL_FUNCTION                   1
                450     CALL_FUNCTION                   3
                452     POP_TOP                         
                454     LOAD_CONST                      30: 'BROWSER'
                456     LOAD_GLOBAL                     7: os
                458     LOAD_ATTR                       10: environ
                460     CONTAINS_OP                     0 (in)
                462     POP_JUMP_IF_FALSE               279 (to 558)
                466     LOAD_GLOBAL                     7: os
                468     LOAD_ATTR                       10: environ
                470     LOAD_CONST                      30: 'BROWSER'
                472     BINARY_SUBSCR                   
                474     LOAD_METHOD                     14: split
                476     LOAD_GLOBAL                     7: os
                478     LOAD_ATTR                       28: pathsep
                480     CALL_METHOD                     1
                482     STORE_FAST                      5: userchoices
                484     LOAD_FAST                       5: userchoices
                486     LOAD_METHOD                     29: reverse
                488     CALL_METHOD                     0
                490     POP_TOP                         
                492     LOAD_FAST                       5: userchoices
                494     GET_ITER                        
                496     FOR_ITER                        32 (to 562)
                498     STORE_FAST                      6: cmdline
                500     LOAD_FAST                       6: cmdline
                502     LOAD_CONST                      31: ''
                504     COMPARE_OP                      3 (!=)
                506     POP_JUMP_IF_FALSE               278 (to 556)
                510     LOAD_GLOBAL                     30: _synthesize
                512     LOAD_FAST                       6: cmdline
                514     LOAD_CONST                      32: True
                516     LOAD_CONST                      33: ('preferred',)
                518     CALL_FUNCTION_KW                2
                520     STORE_FAST                      2: cmd
                522     LOAD_FAST                       2: cmd
                524     LOAD_CONST                      34: 1
                526     BINARY_SUBSCR                   
                528     LOAD_CONST                      0: None
                530     IS_OP                           0 (is)
                532     POP_JUMP_IF_FALSE               278 (to 556)
                536     LOAD_GLOBAL                     3: register
                538     LOAD_FAST                       6: cmdline
                540     LOAD_CONST                      0: None
                542     LOAD_GLOBAL                     26: GenericBrowser
                544     LOAD_FAST                       6: cmdline
                546     CALL_FUNCTION                   1
                548     LOAD_CONST                      32: True
                550     LOAD_CONST                      33: ('preferred',)
                552     CALL_FUNCTION_KW                4
                554     POP_TOP                         
                556     JUMP_ABSOLUTE                   248 (to 496)
                558     LOAD_CONST                      0: None
                560     RETURN_VALUE                    
                562     LOAD_CONST                      0: None
                564     RETURN_VALUE                    
        'register_standard_browsers'
        3
        'win'
        [Code]
            File Name: webbrowser.py
            Object Name: WindowsDefault
            Arg Count: 0
            Pos Only Arg Count: 0
            KW Only Arg Count: 0
            Locals: 0
            Stack Size: 3
            Flags: 0x00000040 (CO_NOFREE)
            [Names]
                '__name__'
                '__module__'
                '__qualname__'
                'open'
            [Var Names]
            [Free Vars]
            [Cell Vars]
            [Constants]
                'WindowsDefault'
                0
                True
                [Code]
                    File Name: webbrowser.py
                    Object Name: open
                    Arg Count: 4
                    Pos Only Arg Count: 0
                    KW Only Arg Count: 0
                    Locals: 4
                    Stack Size: 8
                    Flags: 0x00000043 (CO_OPTIMIZED | CO_NEWLOCALS | CO_NOFREE)
                    [Names]
                        'sys'
                        'audit'
                        'os'
                        'startfile'
                        'OSError'
                    [Var Names]
                        'self'
                        'url'
                        'new'
                        'autoraise'
                    [Free Vars]
                    [Cell Vars]
                    [Constants]
                        None
                        'webbrowser.open'
                        False
                        True
                    [Disassembly]
                        0       LOAD_GLOBAL                     0: sys
                        2       LOAD_METHOD                     1: audit
                        4       LOAD_CONST                      1: 'webbrowser.open'
                        6       LOAD_FAST                       1: url
                        8       CALL_METHOD                     2
                        10      POP_TOP                         
                        12      SETUP_FINALLY                   8 (to 30)
                        14      LOAD_GLOBAL                     2: os
                        16      LOAD_METHOD                     3: startfile
                        18      LOAD_FAST                       1: url
                        20      CALL_METHOD                     1
                        22      POP_TOP                         
                        24      POP_BLOCK                       
                        26      LOAD_CONST                      3: True
                        28      RETURN_VALUE                    
                        30      DUP_TOP                         
                        32      LOAD_GLOBAL                     4: OSError
                        34      JUMP_IF_NOT_EXC_MATCH           24 (to 48)
                        36      POP_TOP                         
                        38      POP_TOP                         
                        40      POP_TOP                         
                        42      POP_EXCEPT                      
                        44      LOAD_CONST                      2: False
                        46      RETURN_VALUE                    
                        48      RERAISE                         0
                'WindowsDefault.open'
                None
                (
                    0
                    True
                )
            [Disassembly]
                0       LOAD_NAME                       0: __name__
                2       STORE_NAME                      1: __module__
                4       LOAD_CONST                      0: 'WindowsDefault'
                6       STORE_NAME                      2: __qualname__
                8       LOAD_CONST                      6: (0, True)
                10      LOAD_CONST                      3: <CODE> open
                12      LOAD_CONST                      4: 'WindowsDefault.open'
                14      MAKE_FUNCTION                   1
                16      STORE_NAME                      3: open
                18      LOAD_CONST                      5: None
                20      RETURN_VALUE                    
        'WindowsDefault'
        'darwin'
        [Code]
            File Name: webbrowser.py
            Object Name: MacOSX
            Arg Count: 0
            Pos Only Arg Count: 0
            KW Only Arg Count: 0
            Locals: 0
            Stack Size: 3
            Flags: 0x00000040 (CO_NOFREE)
            [Names]
                '__name__'
                '__module__'
                '__qualname__'
                '__doc__'
                '__init__'
                'open'
            [Var Names]
            [Free Vars]
            [Cell Vars]
            [Constants]
                'MacOSX'
                'Launcher class for Aqua browsers on Mac OS X\n\n        Optionally specify a browser name on instantiation.  Note that this\n        will not work for Aqua browsers if the user has moved the application\n        package after installation.\n\n        If no browser is specified, the default browser, as specified in the\n        Internet System Preferences panel, will be used.\n        '
                [Code]
                    File Name: webbrowser.py
                    Object Name: __init__
                    Arg Count: 2
                    Pos Only Arg Count: 0
                    KW Only Arg Count: 0
                    Locals: 2
                    Stack Size: 2
                    Flags: 0x00000043 (CO_OPTIMIZED | CO_NEWLOCALS | CO_NOFREE)
                    [Names]
                        'name'
                    [Var Names]
                        'self'
                        'name'
                    [Free Vars]
                    [Cell Vars]
                    [Constants]
                        None
                    [Disassembly]
                        0       LOAD_FAST                       1: name
                        2       LOAD_FAST                       0: self
                        4       STORE_ATTR                      0: name
                        6       LOAD_CONST                      0: None
                        8       RETURN_VALUE                    
                'MacOSX.__init__'
                0
                True
                [Code]
                    File Name: webbrowser.py
                    Object Name: open
                    Arg Count: 4
                    Pos Only Arg Count: 0
                    KW Only Arg Count: 0
                    Locals: 9
                    Stack Size: 5
                    Flags: 0x00000043 (CO_OPTIMIZED | CO_NEWLOCALS | CO_NOFREE)
                    [Names]
                        'sys'
                        'audit'
                        'int'
                        'bool'
                        'name'
                        'replace'
                        'os'
                        'popen'
                        'write'
                        'close'
                    [Var Names]
                        'self'
                        'url'
                        'new'
                        'autoraise'
                        'script'
                        'toWindow'
                        'cmd'
                        'osapipe'
                        'rc'
                    [Free Vars]
                    [Cell Vars]
                    [Constants]
                        None
                        'webbrowser.open'
                        "'"
                        ':'
                        'file:'
                        'default'
                        'open location "%s"'
                        '"'
                        '%22'
                        'OmniWeb'
                        ''
                        'toWindow %d'
                        1
                        'OpenURL "%s"'
                        'tell application "%s"\n                                activate\n                                %s %s\n                            end tell'
                        'osascript'
                        'w'
                        False
                    [Disassembly]
                        0       LOAD_GLOBAL                     0: sys
                        2       LOAD_METHOD                     1: audit
                        4       LOAD_CONST                      1: 'webbrowser.open'
                        6       LOAD_FAST                       1: url
                        8       CALL_METHOD                     2
                        10      POP_TOP                         
                        12      LOAD_CONST                      2: "'"
                        14      LOAD_FAST                       1: url
                        16      CONTAINS_OP                     1 (not in)
                        18      POP_JUMP_IF_TRUE                12 (to 24)
                        20      LOAD_ASSERTION_ERROR            
                        22      RAISE_VARARGS                   1
                        24      LOAD_CONST                      3: ':'
                        26      LOAD_FAST                       1: url
                        28      CONTAINS_OP                     1 (not in)
                        30      POP_JUMP_IF_FALSE               20 (to 40)
                        32      LOAD_CONST                      4: 'file:'
                        34      LOAD_FAST                       1: url
                        36      BINARY_ADD                      
                        38      STORE_FAST                      1: url
                        40      LOAD_GLOBAL                     2: int
                        42      LOAD_GLOBAL                     3: bool
                        44      LOAD_FAST                       2: new
                        46      CALL_FUNCTION                   1
                        48      CALL_FUNCTION                   1
                        50      STORE_FAST                      2: new
                        52      LOAD_FAST                       0: self
                        54      LOAD_ATTR                       4: name
                        56      LOAD_CONST                      5: 'default'
                        58      COMPARE_OP                      2 (==)
                        60      POP_JUMP_IF_FALSE               40 (to 80)
                        62      LOAD_CONST                      6: 'open location "%s"'
                        64      LOAD_FAST                       1: url
                        66      LOAD_METHOD                     5: replace
                        68      LOAD_CONST                      7: '"'
                        70      LOAD_CONST                      8: '%22'
                        72      CALL_METHOD                     2
                        74      BINARY_MODULO                   
                        76      STORE_FAST                      4: script
                        78      JUMP_FORWARD                    30 (to 140)
                        80      LOAD_FAST                       0: self
                        82      LOAD_ATTR                       4: name
                        84      LOAD_CONST                      9: 'OmniWeb'
                        86      COMPARE_OP                      2 (==)
                        88      POP_JUMP_IF_FALSE               48 (to 96)
                        90      LOAD_CONST                      10: ''
                        92      STORE_FAST                      5: toWindow
                        94      JUMP_FORWARD                    6 (to 108)
                        96      LOAD_CONST                      11: 'toWindow %d'
                        98      LOAD_FAST                       2: new
                        100     LOAD_CONST                      12: 1
                        102     BINARY_SUBTRACT                 
                        104     BINARY_MODULO                   
                        106     STORE_FAST                      5: toWindow
                        108     LOAD_CONST                      13: 'OpenURL "%s"'
                        110     LOAD_FAST                       1: url
                        112     LOAD_METHOD                     5: replace
                        114     LOAD_CONST                      7: '"'
                        116     LOAD_CONST                      8: '%22'
                        118     CALL_METHOD                     2
                        120     BINARY_MODULO                   
                        122     STORE_FAST                      6: cmd
                        124     LOAD_CONST                      14: 'tell application "%s"\n                                activate\n                                %s %s\n                            end tell'
                        126     LOAD_FAST                       0: self
                        128     LOAD_ATTR                       4: name
                        130     LOAD_FAST                       6: cmd
                        132     LOAD_FAST                       5: toWindow
                        134     BUILD_TUPLE                     3
                        136     BINARY_MODULO                   
                        138     STORE_FAST                      4: script
                        140     LOAD_GLOBAL                     6: os
                        142     LOAD_METHOD                     7: popen
                        144     LOAD_CONST                      15: 'osascript'
                        146     LOAD_CONST                      16: 'w'
                        148     CALL_METHOD                     2
                        150     STORE_FAST                      7: osapipe
                        152     LOAD_FAST                       7: osapipe
                        154     LOAD_CONST                      0: None
                        156     IS_OP                           0 (is)
                        158     POP_JUMP_IF_FALSE               82 (to 164)
                        160     LOAD_CONST                      17: False
                        162     RETURN_VALUE                    
                        164     LOAD_FAST                       7: osapipe
                        166     LOAD_METHOD                     8: write
                        168     LOAD_FAST                       4: script
                        170     CALL_METHOD                     1
                        172     POP_TOP                         
                        174     LOAD_FAST                       7: osapipe
                        176     LOAD_METHOD                     9: close
                        178     CALL_METHOD                     0
                        180     STORE_FAST                      8: rc
                        182     LOAD_FAST                       8: rc
                        184     UNARY_NOT                       
                        186     RETURN_VALUE                    
                'MacOSX.open'
                None
                (
                    0
                    True
                )
            [Disassembly]
                0       LOAD_NAME                       0: __name__
                2       STORE_NAME                      1: __module__
                4       LOAD_CONST                      0: 'MacOSX'
                6       STORE_NAME                      2: __qualname__
                8       LOAD_CONST                      1: 'Launcher class for Aqua browsers on Mac OS X\n\n        Optionally specify a browser name on instantiation.  Note that this\n        will not work for Aqua browsers if the user has moved the application\n        package after installation.\n\n        If no browser is specified, the default browser, as specified in the\n        Internet System Preferences panel, will be used.\n        '
                10      STORE_NAME                      3: __doc__
                12      LOAD_CONST                      2: <CODE> __init__
                14      LOAD_CONST                      3: 'MacOSX.__init__'
                16      MAKE_FUNCTION                   0
                18      STORE_NAME                      4: __init__
                20      LOAD_CONST                      9: (0, True)
                22      LOAD_CONST                      6: <CODE> open
                24      LOAD_CONST                      7: 'MacOSX.open'
                26      MAKE_FUNCTION                   1
                28      STORE_NAME                      5: open
                30      LOAD_CONST                      8: None
                32      RETURN_VALUE                    
        'MacOSX'
        [Code]
            File Name: webbrowser.py
            Object Name: MacOSXOSAScript
            Arg Count: 0
            Pos Only Arg Count: 0
            KW Only Arg Count: 0
            Locals: 0
            Stack Size: 3
            Flags: 0x00000040 (CO_NOFREE)
            [Names]
                '__name__'
                '__module__'
                '__qualname__'
                '__init__'
                'open'
            [Var Names]
            [Free Vars]
            [Cell Vars]
            [Constants]
                'MacOSXOSAScript'
                [Code]
                    File Name: webbrowser.py
                    Object Name: __init__
                    Arg Count: 2
                    Pos Only Arg Count: 0
                    KW Only Arg Count: 0
                    Locals: 2
                    Stack Size: 2
                    Flags: 0x00000043 (CO_OPTIMIZED | CO_NEWLOCALS | CO_NOFREE)
                    [Names]
                        '_name'
                    [Var Names]
                        'self'
                        'name'
                    [Free Vars]
                    [Cell Vars]
                    [Constants]
                        None
                    [Disassembly]
                        0       LOAD_FAST                       1: name
                        2       LOAD_FAST                       0: self
                        4       STORE_ATTR                      0: _name
                        6       LOAD_CONST                      0: None
                        8       RETURN_VALUE                    
                'MacOSXOSAScript.__init__'
                0
                True
                [Code]
                    File Name: webbrowser.py
                    Object Name: open
                    Arg Count: 4
                    Pos Only Arg Count: 0
                    KW Only Arg Count: 0
                    Locals: 7
                    Stack Size: 6
                    Flags: 0x00000043 (CO_OPTIMIZED | CO_NEWLOCALS | CO_NOFREE)
                    [Names]
                        '_name'
                        'replace'
                        'os'
                        'popen'
                        'write'
                        'close'
                    [Var Names]
                        'self'
                        'url'
                        'new'
                        'autoraise'
                        'script'
                        'osapipe'
                        'rc'
                    [Free Vars]
                    [Cell Vars]
                    [Constants]
                        None
                        'default'
                        'open location "%s"'
                        '"'
                        '%22'
                        '\n                   tell application "%s"\n                       activate\n                       open location "%s"\n                   end\n                   '
                        'osascript'
                        'w'
                        False
                    [Disassembly]
                        0       LOAD_FAST                       0: self
                        2       LOAD_ATTR                       0: _name
                        4       LOAD_CONST                      1: 'default'
                        6       COMPARE_OP                      2 (==)
                        8       POP_JUMP_IF_FALSE               14 (to 28)
                        10      LOAD_CONST                      2: 'open location "%s"'
                        12      LOAD_FAST                       1: url
                        14      LOAD_METHOD                     1: replace
                        16      LOAD_CONST                      3: '"'
                        18      LOAD_CONST                      4: '%22'
                        20      CALL_METHOD                     2
                        22      BINARY_MODULO                   
                        24      STORE_FAST                      4: script
                        26      JUMP_FORWARD                    11 (to 50)
                        28      LOAD_CONST                      5: '\n                   tell application "%s"\n                       activate\n                       open location "%s"\n                   end\n                   '
                        30      LOAD_FAST                       0: self
                        32      LOAD_ATTR                       0: _name
                        34      LOAD_FAST                       1: url
                        36      LOAD_METHOD                     1: replace
                        38      LOAD_CONST                      3: '"'
                        40      LOAD_CONST                      4: '%22'
                        42      CALL_METHOD                     2
                        44      BUILD_TUPLE                     2
                        46      BINARY_MODULO                   
                        48      STORE_FAST                      4: script
                        50      LOAD_GLOBAL                     2: os
                        52      LOAD_METHOD                     3: popen
                        54      LOAD_CONST                      6: 'osascript'
                        56      LOAD_CONST                      7: 'w'
                        58      CALL_METHOD                     2
                        60      STORE_FAST                      5: osapipe
                        62      LOAD_FAST                       5: osapipe
                        64      LOAD_CONST                      0: None
                        66      IS_OP                           0 (is)
                        68      POP_JUMP_IF_FALSE               37 (to 74)
                        70      LOAD_CONST                      8: False
                        72      RETURN_VALUE                    
                        74      LOAD_FAST                       5: osapipe
                        76      LOAD_METHOD                     4: write
                        78      LOAD_FAST                       4: script
                        80      CALL_METHOD                     1
                        82      POP_TOP                         
                        84      LOAD_FAST                       5: osapipe
                        86      LOAD_METHOD                     5: close
                        88      CALL_METHOD                     0
                        90      STORE_FAST                      6: rc
                        92      LOAD_FAST                       6: rc
                        94      UNARY_NOT                       
                        96      RETURN_VALUE                    
                'MacOSXOSAScript.open'
                None
                (
                    0
                    True
                )
            [Disassembly]
                0       LOAD_NAME                       0: __name__
                2       STORE_NAME                      1: __module__
                4       LOAD_CONST                      0: 'MacOSXOSAScript'
                6       STORE_NAME                      2: __qualname__
                8       LOAD_CONST                      1: <CODE> __init__
                10      LOAD_CONST                      2: 'MacOSXOSAScript.__init__'
                12      MAKE_FUNCTION                   0
                14      STORE_NAME                      3: __init__
                16      LOAD_CONST                      8: (0, True)
                18      LOAD_CONST                      5: <CODE> open
                20      LOAD_CONST                      6: 'MacOSXOSAScript.open'
                22      MAKE_FUNCTION                   1
                24      STORE_NAME                      4: open
                26      LOAD_CONST                      7: None
                28      RETURN_VALUE                    
        'MacOSXOSAScript'
        [Code]
            File Name: webbrowser.py
            Object Name: main
            Arg Count: 0
            Pos Only Arg Count: 0
            KW Only Arg Count: 0
            Locals: 9
            Stack Size: 10
            Flags: 0x00000043 (CO_OPTIMIZED | CO_NEWLOCALS | CO_NOFREE)
            [Names]
                'getopt'
                'sys'
                'argv'
                'error'
                'print'
                'stderr'
                'exit'
                'len'
                'open'
            [Var Names]
                'getopt'
                'usage'
                'opts'
                'args'
                'msg'
                'new_win'
                'o'
                'a'
                'url'
            [Free Vars]
            [Cell Vars]
            [Constants]
                None
                0
                'Usage: %s [-n | -t] url\n    -n: open new window\n    -t: open new tab'
                1
                'ntd'
                (
                    'file'
                )
                '-n'
                '-t'
                2
                '\x07'
            [Disassembly]
                0       LOAD_CONST                      1: 0
                2       LOAD_CONST                      0: None
                4       IMPORT_NAME                     0: getopt
                6       STORE_FAST                      0: getopt
                8       LOAD_CONST                      2: 'Usage: %s [-n | -t] url\n    -n: open new window\n    -t: open new tab'
                10      LOAD_GLOBAL                     1: sys
                12      LOAD_ATTR                       2: argv
                14      LOAD_CONST                      1: 0
                16      BINARY_SUBSCR                   
                18      BINARY_MODULO                   
                20      STORE_FAST                      1: usage
                22      SETUP_FINALLY                   15 (to 54)
                24      LOAD_FAST                       0: getopt
                26      LOAD_METHOD                     0: getopt
                28      LOAD_GLOBAL                     1: sys
                30      LOAD_ATTR                       2: argv
                32      LOAD_CONST                      3: 1
                34      LOAD_CONST                      0: None
                36      BUILD_SLICE                     2
                38      BINARY_SUBSCR                   
                40      LOAD_CONST                      4: 'ntd'
                42      CALL_METHOD                     2
                44      UNPACK_SEQUENCE                 2
                46      STORE_FAST                      2: opts
                48      STORE_FAST                      3: args
                50      POP_BLOCK                       
                52      JUMP_FORWARD                    38 (to 130)
                54      DUP_TOP                         
                56      LOAD_FAST                       0: getopt
                58      LOAD_ATTR                       3: error
                60      JUMP_IF_NOT_EXC_MATCH           64 (to 128)
                62      POP_TOP                         
                64      STORE_FAST                      4: msg
                66      POP_TOP                         
                68      SETUP_FINALLY                   25 (to 120)
                70      LOAD_GLOBAL                     4: print
                72      LOAD_FAST                       4: msg
                74      LOAD_GLOBAL                     1: sys
                76      LOAD_ATTR                       5: stderr
                78      LOAD_CONST                      5: ('file',)
                80      CALL_FUNCTION_KW                2
                82      POP_TOP                         
                84      LOAD_GLOBAL                     4: print
                86      LOAD_FAST                       1: usage
                88      LOAD_GLOBAL                     1: sys
                90      LOAD_ATTR                       5: stderr
                92      LOAD_CONST                      5: ('file',)
                94      CALL_FUNCTION_KW                2
                96      POP_TOP                         
                98      LOAD_GLOBAL                     1: sys
                100     LOAD_METHOD                     6: exit
                102     LOAD_CONST                      3: 1
                104     CALL_METHOD                     1
                106     POP_TOP                         
                108     POP_BLOCK                       
                110     POP_EXCEPT                      
                112     LOAD_CONST                      0: None
                114     STORE_FAST                      4: msg
                116     DELETE_FAST                     4: msg
                118     JUMP_FORWARD                    5 (to 130)
                120     LOAD_CONST                      0: None
                122     STORE_FAST                      4: msg
                124     DELETE_FAST                     4: msg
                126     RERAISE                         1
                128     RERAISE                         0
                130     LOAD_CONST                      1: 0
                132     STORE_FAST                      5: new_win
                134     LOAD_FAST                       2: opts
                136     GET_ITER                        
                138     FOR_ITER                        17 (to 174)
                140     UNPACK_SEQUENCE                 2
                142     STORE_FAST                      6: o
                144     STORE_FAST                      7: a
                146     LOAD_FAST                       6: o
                148     LOAD_CONST                      6: '-n'
                150     COMPARE_OP                      2 (==)
                152     POP_JUMP_IF_FALSE               80 (to 160)
                154     LOAD_CONST                      3: 1
                156     STORE_FAST                      5: new_win
                158     JUMP_ABSOLUTE                   69 (to 138)
                160     LOAD_FAST                       6: o
                162     LOAD_CONST                      7: '-t'
                164     COMPARE_OP                      2 (==)
                166     POP_JUMP_IF_FALSE               86 (to 172)
                168     LOAD_CONST                      8: 2
                170     STORE_FAST                      5: new_win
                172     JUMP_ABSOLUTE                   69 (to 138)
                174     LOAD_GLOBAL                     7: len
                176     LOAD_FAST                       3: args
                178     CALL_FUNCTION                   1
                180     LOAD_CONST                      3: 1
                182     COMPARE_OP                      3 (!=)
                184     POP_JUMP_IF_FALSE               105 (to 210)
                186     LOAD_GLOBAL                     4: print
                188     LOAD_FAST                       1: usage
                190     LOAD_GLOBAL                     1: sys
                192     LOAD_ATTR                       5: stderr
                194     LOAD_CONST                      5: ('file',)
                196     CALL_FUNCTION_KW                2
                198     POP_TOP                         
                200     LOAD_GLOBAL                     1: sys
                202     LOAD_METHOD                     6: exit
                204     LOAD_CONST                      3: 1
                206     CALL_METHOD                     1
                208     POP_TOP                         
                210     LOAD_FAST                       3: args
                212     LOAD_CONST                      1: 0
                214     BINARY_SUBSCR                   
                216     STORE_FAST                      8: url
                218     LOAD_GLOBAL                     8: open
                220     LOAD_FAST                       8: url
                222     LOAD_FAST                       5: new_win
                224     CALL_FUNCTION                   2
                226     POP_TOP                         
                228     LOAD_GLOBAL                     4: print
                230     LOAD_CONST                      9: '\x07'
                232     CALL_FUNCTION                   1
                234     POP_TOP                         
                236     LOAD_CONST                      0: None
                238     RETURN_VALUE                    
        'main'
        '__main__'
        (
            None
        )
        (
            0
            True
        )
    [Disassembly]
        0       LOAD_CONST                      0: 'Interfaces for launching and remotely controlling web browsers.'
        2       STORE_NAME                      0: __doc__
        4       LOAD_CONST                      1: 0
        6       LOAD_CONST                      2: None
        8       IMPORT_NAME                     1: os
        10      STORE_NAME                      1: os
        12      LOAD_CONST                      1: 0
        14      LOAD_CONST                      2: None
        16      IMPORT_NAME                     2: shlex
        18      STORE_NAME                      2: shlex
        20      LOAD_CONST                      1: 0
        22      LOAD_CONST                      2: None
        24      IMPORT_NAME                     3: shutil
        26      STORE_NAME                      3: shutil
        28      LOAD_CONST                      1: 0
        30      LOAD_CONST                      2: None
        32      IMPORT_NAME                     4: sys
        34      STORE_NAME                      4: sys
        36      LOAD_CONST                      1: 0
        38      LOAD_CONST                      2: None
        40      IMPORT_NAME                     5: subprocess
        42      STORE_NAME                      5: subprocess
        44      LOAD_CONST                      1: 0
        46      LOAD_CONST                      2: None
        48      IMPORT_NAME                     6: threading
        50      STORE_NAME                      6: threading
        52      BUILD_LIST                      0
        54      LOAD_CONST                      3: ('Error', 'open', 'open_new', 'open_new_tab', 'get', 'register')
        56      LIST_EXTEND                     1
        58      STORE_NAME                      7: __all__
        60      LOAD_BUILD_CLASS                
        62      LOAD_CONST                      4: <CODE> Error
        64      LOAD_CONST                      5: 'Error'
        66      MAKE_FUNCTION                   0
        68      LOAD_CONST                      5: 'Error'
        70      LOAD_NAME                       8: Exception
        72      CALL_FUNCTION                   3
        74      STORE_NAME                      9: Error
        76      LOAD_NAME                       6: threading
        78      LOAD_METHOD                     10: RLock
        80      CALL_METHOD                     0
        82      STORE_NAME                      11: _lock
        84      BUILD_MAP                       0
        86      STORE_NAME                      12: _browsers
        88      LOAD_CONST                      2: None
        90      STORE_GLOBAL                    13: _tryorder
        92      LOAD_CONST                      2: None
        94      STORE_GLOBAL                    14: _os_preferred_browser
        96      LOAD_CONST                      61: (None,)
        98      LOAD_CONST                      6: False
        100     LOAD_CONST                      7: ('preferred',)
        102     BUILD_CONST_KEY_MAP             1
        104     LOAD_CONST                      8: <CODE> register
        106     LOAD_CONST                      9: 'register'
        108     MAKE_FUNCTION                   3
        110     STORE_NAME                      15: register
        112     LOAD_CONST                      61: (None,)
        114     LOAD_CONST                      10: <CODE> get
        116     LOAD_CONST                      11: 'get'
        118     MAKE_FUNCTION                   1
        120     STORE_NAME                      16: get
        122     LOAD_CONST                      62: (0, True)
        124     LOAD_CONST                      13: <CODE> open
        126     LOAD_CONST                      14: 'open'
        128     MAKE_FUNCTION                   1
        130     STORE_NAME                      17: open
        132     LOAD_CONST                      15: <CODE> open_new
        134     LOAD_CONST                      16: 'open_new'
        136     MAKE_FUNCTION                   0
        138     STORE_NAME                      18: open_new
        140     LOAD_CONST                      17: <CODE> open_new_tab
        142     LOAD_CONST                      18: 'open_new_tab'
        144     MAKE_FUNCTION                   0
        146     STORE_NAME                      19: open_new_tab
        148     LOAD_CONST                      6: False
        150     LOAD_CONST                      7: ('preferred',)
        152     BUILD_CONST_KEY_MAP             1
        154     LOAD_CONST                      19: <CODE> _synthesize
        156     LOAD_CONST                      20: '_synthesize'
        158     MAKE_FUNCTION                   2
        160     STORE_NAME                      20: _synthesize
        162     LOAD_BUILD_CLASS                
        164     LOAD_CONST                      21: <CODE> BaseBrowser
        166     LOAD_CONST                      22: 'BaseBrowser'
        168     MAKE_FUNCTION                   0
        170     LOAD_CONST                      22: 'BaseBrowser'
        172     LOAD_NAME                       21: object
        174     CALL_FUNCTION                   3
        176     STORE_NAME                      22: BaseBrowser
        178     LOAD_BUILD_CLASS                
        180     LOAD_CONST                      23: <CODE> GenericBrowser
        182     LOAD_CONST                      24: 'GenericBrowser'
        184     MAKE_FUNCTION                   0
        186     LOAD_CONST                      24: 'GenericBrowser'
        188     LOAD_NAME                       22: BaseBrowser
        190     CALL_FUNCTION                   3
        192     STORE_NAME                      23: GenericBrowser
        194     LOAD_BUILD_CLASS                
        196     LOAD_CONST                      25: <CODE> BackgroundBrowser
        198     LOAD_CONST                      26: 'BackgroundBrowser'
        200     MAKE_FUNCTION                   0
        202     LOAD_CONST                      26: 'BackgroundBrowser'
        204     LOAD_NAME                       23: GenericBrowser
        206     CALL_FUNCTION                   3
        208     STORE_NAME                      24: BackgroundBrowser
        210     LOAD_BUILD_CLASS                
        212     LOAD_CONST                      27: <CODE> UnixBrowser
        214     LOAD_CONST                      28: 'UnixBrowser'
        216     MAKE_FUNCTION                   0
        218     LOAD_CONST                      28: 'UnixBrowser'
        220     LOAD_NAME                       22: BaseBrowser
        222     CALL_FUNCTION                   3
        224     STORE_NAME                      25: UnixBrowser
        226     LOAD_BUILD_CLASS                
        228     LOAD_CONST                      29: <CODE> Mozilla
        230     LOAD_CONST                      30: 'Mozilla'
        232     MAKE_FUNCTION                   0
        234     LOAD_CONST                      30: 'Mozilla'
        236     LOAD_NAME                       25: UnixBrowser
        238     CALL_FUNCTION                   3
        240     STORE_NAME                      26: Mozilla
        242     LOAD_BUILD_CLASS                
        244     LOAD_CONST                      31: <CODE> Netscape
        246     LOAD_CONST                      32: 'Netscape'
        248     MAKE_FUNCTION                   0
        250     LOAD_CONST                      32: 'Netscape'
        252     LOAD_NAME                       25: UnixBrowser
        254     CALL_FUNCTION                   3
        256     STORE_NAME                      27: Netscape
        258     LOAD_BUILD_CLASS                
        260     LOAD_CONST                      33: <CODE> Galeon
        262     LOAD_CONST                      34: 'Galeon'
        264     MAKE_FUNCTION                   0
        266     LOAD_CONST                      34: 'Galeon'
        268     LOAD_NAME                       25: UnixBrowser
        270     CALL_FUNCTION                   3
        272     STORE_NAME                      28: Galeon
        274     LOAD_BUILD_CLASS                
        276     LOAD_CONST                      35: <CODE> Chrome
        278     LOAD_CONST                      36: 'Chrome'
        280     MAKE_FUNCTION                   0
        282     LOAD_CONST                      36: 'Chrome'
        284     LOAD_NAME                       25: UnixBrowser
        286     CALL_FUNCTION                   3
        288     STORE_NAME                      29: Chrome
        290     LOAD_NAME                       29: Chrome
        292     STORE_NAME                      30: Chromium
        294     LOAD_BUILD_CLASS                
        296     LOAD_CONST                      37: <CODE> Opera
        298     LOAD_CONST                      38: 'Opera'
        300     MAKE_FUNCTION                   0
        302     LOAD_CONST                      38: 'Opera'
        304     LOAD_NAME                       25: UnixBrowser
        306     CALL_FUNCTION                   3
        308     STORE_NAME                      31: Opera
        310     LOAD_BUILD_CLASS                
        312     LOAD_CONST                      39: <CODE> Elinks
        314     LOAD_CONST                      40: 'Elinks'
        316     MAKE_FUNCTION                   0
        318     LOAD_CONST                      40: 'Elinks'
        320     LOAD_NAME                       25: UnixBrowser
        322     CALL_FUNCTION                   3
        324     STORE_NAME                      32: Elinks
        326     LOAD_BUILD_CLASS                
        328     LOAD_CONST                      41: <CODE> Konqueror
        330     LOAD_CONST                      42: 'Konqueror'
        332     MAKE_FUNCTION                   0
        334     LOAD_CONST                      42: 'Konqueror'
        336     LOAD_NAME                       22: BaseBrowser
        338     CALL_FUNCTION                   3
        340     STORE_NAME                      33: Konqueror
        342     LOAD_BUILD_CLASS                
        344     LOAD_CONST                      43: <CODE> Grail
        346     LOAD_CONST                      44: 'Grail'
        348     MAKE_FUNCTION                   0
        350     LOAD_CONST                      44: 'Grail'
        352     LOAD_NAME                       22: BaseBrowser
        354     CALL_FUNCTION                   3
        356     STORE_NAME                      34: Grail
        358     LOAD_CONST                      45: <CODE> register_X_browsers
        360     LOAD_CONST                      46: 'register_X_browsers'
        362     MAKE_FUNCTION                   0
        364     STORE_NAME                      35: register_X_browsers
        366     LOAD_CONST                      47: <CODE> register_standard_browsers
        368     LOAD_CONST                      48: 'register_standard_browsers'
        370     MAKE_FUNCTION                   0
        372     STORE_NAME                      36: register_standard_browsers
        374     LOAD_NAME                       4: sys
        376     LOAD_ATTR                       37: platform
        378     LOAD_CONST                      2: None
        380     LOAD_CONST                      49: 3
        382     BUILD_SLICE                     2
        384     BINARY_SUBSCR                   
        386     LOAD_CONST                      50: 'win'
        388     COMPARE_OP                      2 (==)
        390     POP_JUMP_IF_FALSE               204 (to 408)
        392     LOAD_BUILD_CLASS                
        394     LOAD_CONST                      51: <CODE> WindowsDefault
        396     LOAD_CONST                      52: 'WindowsDefault'
        398     MAKE_FUNCTION                   0
        400     LOAD_CONST                      52: 'WindowsDefault'
        402     LOAD_NAME                       22: BaseBrowser
        404     CALL_FUNCTION                   3
        406     STORE_NAME                      38: WindowsDefault
        408     LOAD_NAME                       4: sys
        410     LOAD_ATTR                       37: platform
        412     LOAD_CONST                      53: 'darwin'
        414     COMPARE_OP                      2 (==)
        416     POP_JUMP_IF_FALSE               225 (to 450)
        418     LOAD_BUILD_CLASS                
        420     LOAD_CONST                      54: <CODE> MacOSX
        422     LOAD_CONST                      55: 'MacOSX'
        424     MAKE_FUNCTION                   0
        426     LOAD_CONST                      55: 'MacOSX'
        428     LOAD_NAME                       22: BaseBrowser
        430     CALL_FUNCTION                   3
        432     STORE_NAME                      39: MacOSX
        434     LOAD_BUILD_CLASS                
        436     LOAD_CONST                      56: <CODE> MacOSXOSAScript
        438     LOAD_CONST                      57: 'MacOSXOSAScript'
        440     MAKE_FUNCTION                   0
        442     LOAD_CONST                      57: 'MacOSXOSAScript'
        444     LOAD_NAME                       22: BaseBrowser
        446     CALL_FUNCTION                   3
        448     STORE_NAME                      40: MacOSXOSAScript
        450     LOAD_CONST                      58: <CODE> main
        452     LOAD_CONST                      59: 'main'
        454     MAKE_FUNCTION                   0
        456     STORE_NAME                      41: main
        458     LOAD_NAME                       42: __name__
        460     LOAD_CONST                      60: '__main__'
        462     COMPARE_OP                      2 (==)
        464     POP_JUMP_IF_FALSE               238 (to 476)
        466     LOAD_NAME                       41: main
        468     CALL_FUNCTION                   0
        470     POP_TOP                         
        472     LOAD_CONST                      2: None
        474     RETURN_VALUE                    
        476     LOAD_CONST                      2: None
        478     RETURN_VALUE                    
