gettext.pyc (Python 3.10)
[Code]
    File Name: gettext.py
    Object Name: <module>
    Arg Count: 0
    Pos Only Arg Count: 0
    KW Only Arg Count: 0
    Locals: 0
    Stack Size: 5
    Flags: 0x00000040 (CO_NOFREE)
    [Names]
        '__doc__'
        'os'
        're'
        'sys'
        '__all__'
        'path'
        'join'
        'base_prefix'
        '_default_localedir'
        'compile'
        'VERBOSE'
        'DOTALL'
        '_token_pattern'
        '_tokenize'
        '_error'
        '_binary_ops'
        'enumerate'
        '_c2py_ops'
        '_parse'
        '_as_int'
        'c2py'
        '_expand_lang'
        'NullTranslations'
        'GNUTranslations'
        'find'
        '_translations'
        '_unspecified'
        'translation'
        'install'
        '_localedirs'
        '_localecodesets'
        '_current_domain'
        'textdomain'
        'bindtextdomain'
        'bind_textdomain_codeset'
        'dgettext'
        'ldgettext'
        'dngettext'
        'ldngettext'
        'dpgettext'
        'dnpgettext'
        'gettext'
        'lgettext'
        'ngettext'
        'lngettext'
        'pgettext'
        'npgettext'
        'Catalog'
    [Var Names]
    [Free Vars]
    [Cell Vars]
    [Constants]
        'Internationalization and localization support.\n\nThis module provides internationalization (I18N) and localization (L10N)\nsupport for your Python programs by providing an interface to the GNU gettext\nmessage catalog library.\n\nI18N refers to the operation by which a program is made aware of multiple\nlanguages.  L10N refers to the adaptation of your program, once\ninternationalized, to the local language and cultural habits.\n\n'
        0
        None
        (
            'NullTranslations'
            'GNUTranslations'
            'Catalog'
            'find'
            'translation'
            'install'
            'textdomain'
            'bindtextdomain'
            'bind_textdomain_codeset'
            'dgettext'
            'dngettext'
            'gettext'
            'lgettext'
            'ldgettext'
            'ldngettext'
            'lngettext'
            'ngettext'
            'pgettext'
            'dpgettext'
            'npgettext'
            'dnpgettext'
        )
        'share'
        'locale'
        '\n        (?P<WHITESPACES>[ \\t]+)                    | # spaces and horizontal tabs\n        (?P<NUMBER>[0-9]+\\b)                       | # decimal integer\n        (?P<NAME>n\\b)                              | # only n is allowed\n        (?P<PARENTHESIS>[()])                      |\n        (?P<OPERATOR>[-*/%+?:]|[><!]=?|==|&&|\\|\\|) | # !, *, /, %, +, -, <, >,\n                                                     # <=, >=, ==, !=, &&, ||,\n                                                     # ? :\n                                                     # unary and bitwise ops\n                                                     # not allowed\n        (?P<INVALID>\\w+|.)                           # invalid token\n    '
        [Code]
            File Name: gettext.py
            Object Name: _tokenize
            Arg Count: 1
            Pos Only Arg Count: 0
            KW Only Arg Count: 0
            Locals: 4
            Stack Size: 4
            Flags: 0x00000063 (CO_OPTIMIZED | CO_NEWLOCALS | CO_GENERATOR | CO_NOFREE)
            [Names]
                're'
                'finditer'
                '_token_pattern'
                'lastgroup'
                'group'
                'ValueError'
            [Var Names]
                'plural'
                'mo'
                'kind'
                'value'
            [Free Vars]
            [Cell Vars]
            [Constants]
                None
                'WHITESPACES'
                'INVALID'
                'invalid token in plural form: %s'
                ''
            [Disassembly]
                0       GEN_START                       0
                2       LOAD_GLOBAL                     0: re
                4       LOAD_METHOD                     1: finditer
                6       LOAD_GLOBAL                     2: _token_pattern
                8       LOAD_FAST                       0: plural
                10      CALL_METHOD                     2
                12      GET_ITER                        
                14      FOR_ITER                        28 (to 72)
                16      STORE_FAST                      1: mo
                18      LOAD_FAST                       1: mo
                20      LOAD_ATTR                       3: lastgroup
                22      STORE_FAST                      2: kind
                24      LOAD_FAST                       2: kind
                26      LOAD_CONST                      1: 'WHITESPACES'
                28      COMPARE_OP                      2 (==)
                30      POP_JUMP_IF_FALSE               17 (to 34)
                32      JUMP_ABSOLUTE                   7 (to 14)
                34      LOAD_FAST                       1: mo
                36      LOAD_METHOD                     4: group
                38      LOAD_FAST                       2: kind
                40      CALL_METHOD                     1
                42      STORE_FAST                      3: value
                44      LOAD_FAST                       2: kind
                46      LOAD_CONST                      2: 'INVALID'
                48      COMPARE_OP                      2 (==)
                50      POP_JUMP_IF_FALSE               32 (to 64)
                52      LOAD_GLOBAL                     5: ValueError
                54      LOAD_CONST                      3: 'invalid token in plural form: %s'
                56      LOAD_FAST                       3: value
                58      BINARY_MODULO                   
                60      CALL_FUNCTION                   1
                62      RAISE_VARARGS                   1
                64      LOAD_FAST                       3: value
                66      YIELD_VALUE                     
                68      POP_TOP                         
                70      JUMP_ABSOLUTE                   7 (to 14)
                72      LOAD_CONST                      4: ''
                74      YIELD_VALUE                     
                76      POP_TOP                         
                78      LOAD_CONST                      0: None
                80      RETURN_VALUE                    
        '_tokenize'
        [Code]
            File Name: gettext.py
            Object Name: _error
            Arg Count: 1
            Pos Only Arg Count: 0
            KW Only Arg Count: 0
            Locals: 1
            Stack Size: 3
            Flags: 0x00000043 (CO_OPTIMIZED | CO_NEWLOCALS | CO_NOFREE)
            [Names]
                'ValueError'
            [Var Names]
                'value'
            [Free Vars]
            [Cell Vars]
            [Constants]
                None
                'unexpected token in plural form: %s'
                'unexpected end of plural form'
            [Disassembly]
                0       LOAD_FAST                       0: value
                2       POP_JUMP_IF_FALSE               8 (to 16)
                4       LOAD_GLOBAL                     0: ValueError
                6       LOAD_CONST                      1: 'unexpected token in plural form: %s'
                8       LOAD_FAST                       0: value
                10      BINARY_MODULO                   
                12      CALL_FUNCTION                   1
                14      RETURN_VALUE                    
                16      LOAD_GLOBAL                     0: ValueError
                18      LOAD_CONST                      2: 'unexpected end of plural form'
                20      CALL_FUNCTION                   1
                22      RETURN_VALUE                    
        '_error'
        (
            (
                '||'
            )
            (
                '&&'
            )
            (
                '=='
                '!='
            )
            (
                '<'
                '>'
                '<='
                '>='
            )
            (
                '+'
                '-'
            )
            (
                '*'
                '/'
                '%'
            )
        )
        [Code]
            File Name: gettext.py
            Object Name: <dictcomp>
            Arg Count: 1
            Pos Only Arg Count: 0
            KW Only Arg Count: 0
            Locals: 4
            Stack Size: 5
            Flags: 0x00000043 (CO_OPTIMIZED | CO_NEWLOCALS | CO_NOFREE)
            [Names]
            [Var Names]
                '.0'
                'i'
                'ops'
                'op'
            [Free Vars]
            [Cell Vars]
            [Constants]
            [Disassembly]
                0       BUILD_MAP                       0
                2       LOAD_FAST                       0: .0
                4       FOR_ITER                        12 (to 30)
                6       UNPACK_SEQUENCE                 2
                8       STORE_FAST                      1: i
                10      STORE_FAST                      2: ops
                12      LOAD_FAST                       2: ops
                14      GET_ITER                        
                16      FOR_ITER                        5 (to 28)
                18      STORE_FAST                      3: op
                20      LOAD_FAST                       3: op
                22      LOAD_FAST                       1: i
                24      MAP_ADD                         3
                26      JUMP_ABSOLUTE                   8 (to 16)
                28      JUMP_ABSOLUTE                   2 (to 4)
                30      RETURN_VALUE                    
        '<dictcomp>'
        1
        'or'
        'and'
        '//'
        (
            '||'
            '&&'
            '/'
        )
        -1
        [Code]
            File Name: gettext.py
            Object Name: _parse
            Arg Count: 2
            Pos Only Arg Count: 0
            KW Only Arg Count: 0
            Locals: 12
            Stack Size: 8
            Flags: 0x00000043 (CO_OPTIMIZED | CO_NEWLOCALS | CO_NOFREE)
            [Names]
                'next'
                '_parse'
                'ValueError'
                'int'
                '_error'
                '_binary_ops'
                '_c2py_ops'
                'get'
            [Var Names]
                'tokens'
                'priority'
                'result'
                'nexttok'
                'sub'
                'value'
                'j'
                'i'
                'op'
                'right'
                'if_true'
                'if_false'
            [Free Vars]
            [Cell Vars]
            [Constants]
                None
                ''
                '!'
                'not '
                '('
                '%s(%s)'
                ')'
                'unbalanced parenthesis in plural form'
                'n'
                '%s%s'
                10
                '%s%d'
                100
                (
                    3
                    4
                )
                '(%s)'
                1
                '%s %s %s'
                4
                '?'
                0
                ':'
                '%s if %s else %s'
            [Disassembly]
                0       LOAD_CONST                      1: ''
                2       STORE_FAST                      2: result
                4       LOAD_GLOBAL                     0: next
                6       LOAD_FAST                       0: tokens
                8       CALL_FUNCTION                   1
                10      STORE_FAST                      3: nexttok
                12      LOAD_FAST                       3: nexttok
                14      LOAD_CONST                      2: '!'
                16      COMPARE_OP                      2 (==)
                18      POP_JUMP_IF_FALSE               22 (to 44)
                20      LOAD_FAST                       2: result
                22      LOAD_CONST                      3: 'not '
                24      INPLACE_ADD                     
                26      STORE_FAST                      2: result
                28      LOAD_GLOBAL                     0: next
                30      LOAD_FAST                       0: tokens
                32      CALL_FUNCTION                   1
                34      STORE_FAST                      3: nexttok
                36      LOAD_FAST                       3: nexttok
                38      LOAD_CONST                      2: '!'
                40      COMPARE_OP                      2 (==)
                42      POP_JUMP_IF_TRUE                10 (to 20)
                44      LOAD_FAST                       3: nexttok
                46      LOAD_CONST                      4: '('
                48      COMPARE_OP                      2 (==)
                50      POP_JUMP_IF_FALSE               47 (to 94)
                52      LOAD_GLOBAL                     1: _parse
                54      LOAD_FAST                       0: tokens
                56      CALL_FUNCTION                   1
                58      UNPACK_SEQUENCE                 2
                60      STORE_FAST                      4: sub
                62      STORE_FAST                      3: nexttok
                64      LOAD_CONST                      5: '%s(%s)'
                66      LOAD_FAST                       2: result
                68      LOAD_FAST                       4: sub
                70      BUILD_TUPLE                     2
                72      BINARY_MODULO                   
                74      STORE_FAST                      2: result
                76      LOAD_FAST                       3: nexttok
                78      LOAD_CONST                      6: ')'
                80      COMPARE_OP                      3 (!=)
                82      POP_JUMP_IF_FALSE               46 (to 92)
                84      LOAD_GLOBAL                     2: ValueError
                86      LOAD_CONST                      7: 'unbalanced parenthesis in plural form'
                88      CALL_FUNCTION                   1
                90      RAISE_VARARGS                   1
                92      JUMP_FORWARD                    37 (to 168)
                94      LOAD_FAST                       3: nexttok
                96      LOAD_CONST                      8: 'n'
                98      COMPARE_OP                      2 (==)
                100     POP_JUMP_IF_FALSE               58 (to 116)
                102     LOAD_CONST                      9: '%s%s'
                104     LOAD_FAST                       2: result
                106     LOAD_FAST                       3: nexttok
                108     BUILD_TUPLE                     2
                110     BINARY_MODULO                   
                112     STORE_FAST                      2: result
                114     JUMP_FORWARD                    26 (to 168)
                116     SETUP_FINALLY                   7 (to 132)
                118     LOAD_GLOBAL                     3: int
                120     LOAD_FAST                       3: nexttok
                122     LOAD_CONST                      10: 10
                124     CALL_FUNCTION                   2
                126     STORE_FAST                      5: value
                128     POP_BLOCK                       
                130     JUMP_FORWARD                    12 (to 156)
                132     DUP_TOP                         
                134     LOAD_GLOBAL                     2: ValueError
                136     JUMP_IF_NOT_EXC_MATCH           77 (to 154)
                138     POP_TOP                         
                140     POP_TOP                         
                142     POP_TOP                         
                144     LOAD_GLOBAL                     4: _error
                146     LOAD_FAST                       3: nexttok
                148     CALL_FUNCTION                   1
                150     LOAD_CONST                      0: None
                152     RAISE_VARARGS                   2
                154     RERAISE                         0
                156     LOAD_CONST                      11: '%s%d'
                158     LOAD_FAST                       2: result
                160     LOAD_FAST                       5: value
                162     BUILD_TUPLE                     2
                164     BINARY_MODULO                   
                166     STORE_FAST                      2: result
                168     LOAD_GLOBAL                     0: next
                170     LOAD_FAST                       0: tokens
                172     CALL_FUNCTION                   1
                174     STORE_FAST                      3: nexttok
                176     LOAD_CONST                      12: 100
                178     STORE_FAST                      6: j
                180     LOAD_FAST                       3: nexttok
                182     LOAD_GLOBAL                     5: _binary_ops
                184     CONTAINS_OP                     0 (in)
                186     POP_JUMP_IF_FALSE               143 (to 286)
                188     LOAD_GLOBAL                     5: _binary_ops
                190     LOAD_FAST                       3: nexttok
                192     BINARY_SUBSCR                   
                194     STORE_FAST                      7: i
                196     LOAD_FAST                       7: i
                198     LOAD_FAST                       1: priority
                200     COMPARE_OP                      0 (<)
                202     POP_JUMP_IF_FALSE               103 (to 206)
                204     JUMP_FORWARD                    40 (to 286)
                206     LOAD_FAST                       7: i
                208     LOAD_CONST                      13: (3, 4)
                210     CONTAINS_OP                     0 (in)
                212     POP_JUMP_IF_FALSE               115 (to 230)
                214     LOAD_FAST                       6: j
                216     LOAD_CONST                      13: (3, 4)
                218     CONTAINS_OP                     0 (in)
                220     POP_JUMP_IF_FALSE               115 (to 230)
                222     LOAD_CONST                      14: '(%s)'
                224     LOAD_FAST                       2: result
                226     BINARY_MODULO                   
                228     STORE_FAST                      2: result
                230     LOAD_GLOBAL                     6: _c2py_ops
                232     LOAD_METHOD                     7: get
                234     LOAD_FAST                       3: nexttok
                236     LOAD_FAST                       3: nexttok
                238     CALL_METHOD                     2
                240     STORE_FAST                      8: op
                242     LOAD_GLOBAL                     1: _parse
                244     LOAD_FAST                       0: tokens
                246     LOAD_FAST                       7: i
                248     LOAD_CONST                      15: 1
                250     BINARY_ADD                      
                252     CALL_FUNCTION                   2
                254     UNPACK_SEQUENCE                 2
                256     STORE_FAST                      9: right
                258     STORE_FAST                      3: nexttok
                260     LOAD_CONST                      16: '%s %s %s'
                262     LOAD_FAST                       2: result
                264     LOAD_FAST                       8: op
                266     LOAD_FAST                       9: right
                268     BUILD_TUPLE                     3
                270     BINARY_MODULO                   
                272     STORE_FAST                      2: result
                274     LOAD_FAST                       7: i
                276     STORE_FAST                      6: j
                278     LOAD_FAST                       3: nexttok
                280     LOAD_GLOBAL                     5: _binary_ops
                282     CONTAINS_OP                     0 (in)
                284     POP_JUMP_IF_TRUE                94 (to 188)
                286     LOAD_FAST                       6: j
                288     LOAD_FAST                       1: priority
                290     DUP_TOP                         
                292     ROT_THREE                       
                294     COMPARE_OP                      2 (==)
                296     POP_JUMP_IF_FALSE               153 (to 306)
                298     LOAD_CONST                      17: 4
                300     COMPARE_OP                      2 (==)
                302     POP_JUMP_IF_FALSE               159 (to 318)
                304     JUMP_FORWARD                    2 (to 310)
                306     POP_TOP                         
                308     JUMP_FORWARD                    4 (to 318)
                310     LOAD_CONST                      14: '(%s)'
                312     LOAD_FAST                       2: result
                314     BINARY_MODULO                   
                316     STORE_FAST                      2: result
                318     LOAD_FAST                       3: nexttok
                320     LOAD_CONST                      18: '?'
                322     COMPARE_OP                      2 (==)
                324     POP_JUMP_IF_FALSE               203 (to 406)
                326     LOAD_FAST                       1: priority
                328     LOAD_CONST                      19: 0
                330     COMPARE_OP                      1 (<=)
                332     POP_JUMP_IF_FALSE               203 (to 406)
                334     LOAD_GLOBAL                     1: _parse
                336     LOAD_FAST                       0: tokens
                338     LOAD_CONST                      19: 0
                340     CALL_FUNCTION                   2
                342     UNPACK_SEQUENCE                 2
                344     STORE_FAST                      10: if_true
                346     STORE_FAST                      3: nexttok
                348     LOAD_FAST                       3: nexttok
                350     LOAD_CONST                      20: ':'
                352     COMPARE_OP                      3 (!=)
                354     POP_JUMP_IF_FALSE               182 (to 364)
                356     LOAD_GLOBAL                     4: _error
                358     LOAD_FAST                       3: nexttok
                360     CALL_FUNCTION                   1
                362     RAISE_VARARGS                   1
                364     LOAD_GLOBAL                     1: _parse
                366     LOAD_FAST                       0: tokens
                368     CALL_FUNCTION                   1
                370     UNPACK_SEQUENCE                 2
                372     STORE_FAST                      11: if_false
                374     STORE_FAST                      3: nexttok
                376     LOAD_CONST                      21: '%s if %s else %s'
                378     LOAD_FAST                       10: if_true
                380     LOAD_FAST                       2: result
                382     LOAD_FAST                       11: if_false
                384     BUILD_TUPLE                     3
                386     BINARY_MODULO                   
                388     STORE_FAST                      2: result
                390     LOAD_FAST                       1: priority
                392     LOAD_CONST                      19: 0
                394     COMPARE_OP                      2 (==)
                396     POP_JUMP_IF_FALSE               203 (to 406)
                398     LOAD_CONST                      14: '(%s)'
                400     LOAD_FAST                       2: result
                402     BINARY_MODULO                   
                404     STORE_FAST                      2: result
                406     LOAD_FAST                       2: result
                408     LOAD_FAST                       3: nexttok
                410     BUILD_TUPLE                     2
                412     RETURN_VALUE                    
        '_parse'
        [Code]
            File Name: gettext.py
            Object Name: _as_int
            Arg Count: 1
            Pos Only Arg Count: 0
            KW Only Arg Count: 0
            Locals: 3
            Stack Size: 8
            Flags: 0x00000043 (CO_OPTIMIZED | CO_NEWLOCALS | CO_NOFREE)
            [Names]
                'round'
                'TypeError'
                '__class__'
                '__name__'
                'warnings'
                'warn'
                'DeprecationWarning'
            [Var Names]
                'n'
                'i'
                'warnings'
            [Free Vars]
            [Cell Vars]
            [Constants]
                None
                'Plural value must be an integer, got %s'
                0
                4
            [Disassembly]
                0       SETUP_FINALLY                   6 (to 14)
                2       LOAD_GLOBAL                     0: round
                4       LOAD_FAST                       0: n
                6       CALL_FUNCTION                   1
                8       STORE_FAST                      1: i
                10      POP_BLOCK                       
                12      JUMP_FORWARD                    17 (to 48)
                14      DUP_TOP                         
                16      LOAD_GLOBAL                     1: TypeError
                18      JUMP_IF_NOT_EXC_MATCH           23 (to 46)
                20      POP_TOP                         
                22      POP_TOP                         
                24      POP_TOP                         
                26      LOAD_GLOBAL                     1: TypeError
                28      LOAD_CONST                      1: 'Plural value must be an integer, got %s'
                30      LOAD_FAST                       0: n
                32      LOAD_ATTR                       2: __class__
                34      LOAD_ATTR                       3: __name__
                36      BUILD_TUPLE                     1
                38      BINARY_MODULO                   
                40      CALL_FUNCTION                   1
                42      LOAD_CONST                      0: None
                44      RAISE_VARARGS                   2
                46      RERAISE                         0
                48      LOAD_CONST                      2: 0
                50      LOAD_CONST                      0: None
                52      IMPORT_NAME                     4: warnings
                54      STORE_FAST                      2: warnings
                56      LOAD_FAST                       2: warnings
                58      LOAD_METHOD                     5: warn
                60      LOAD_CONST                      1: 'Plural value must be an integer, got %s'
                62      LOAD_FAST                       0: n
                64      LOAD_ATTR                       2: __class__
                66      LOAD_ATTR                       3: __name__
                68      BUILD_TUPLE                     1
                70      BINARY_MODULO                   
                72      LOAD_GLOBAL                     6: DeprecationWarning
                74      LOAD_CONST                      3: 4
                76      CALL_METHOD                     3
                78      POP_TOP                         
                80      LOAD_FAST                       0: n
                82      RETURN_VALUE                    
        '_as_int'
        [Code]
            File Name: gettext.py
            Object Name: c2py
            Arg Count: 1
            Pos Only Arg Count: 0
            KW Only Arg Count: 0
            Locals: 6
            Stack Size: 8
            Flags: 0x00000043 (CO_OPTIMIZED | CO_NEWLOCALS | CO_NOFREE)
            [Names]
                'len'
                'ValueError'
                '_parse'
                '_tokenize'
                '_error'
                '_as_int'
                'exec'
                'RecursionError'
            [Var Names]
                'plural'
                'result'
                'nexttok'
                'depth'
                'c'
                'ns'
            [Free Vars]
            [Cell Vars]
            [Constants]
                'Gets a C expression as used in PO files for plural forms and returns a\n    Python function that implements an equivalent expression.\n    '
                1000
                'plural form expression is too long'
                0
                '('
                1
                20
                'plural form expression is too complex'
                ')'
                '_as_int'
                'if True:\n            def func(n):\n                if not isinstance(n, int):\n                    n = _as_int(n)\n                return int(%s)\n            '
                'func'
            [Disassembly]
                0       LOAD_GLOBAL                     0: len
                2       LOAD_FAST                       0: plural
                4       CALL_FUNCTION                   1
                6       LOAD_CONST                      1: 1000
                8       COMPARE_OP                      4 (>)
                10      POP_JUMP_IF_FALSE               10 (to 20)
                12      LOAD_GLOBAL                     1: ValueError
                14      LOAD_CONST                      2: 'plural form expression is too long'
                16      CALL_FUNCTION                   1
                18      RAISE_VARARGS                   1
                20      SETUP_FINALLY                   62 (to 146)
                22      LOAD_GLOBAL                     2: _parse
                24      LOAD_GLOBAL                     3: _tokenize
                26      LOAD_FAST                       0: plural
                28      CALL_FUNCTION                   1
                30      CALL_FUNCTION                   1
                32      UNPACK_SEQUENCE                 2
                34      STORE_FAST                      1: result
                36      STORE_FAST                      2: nexttok
                38      LOAD_FAST                       2: nexttok
                40      POP_JUMP_IF_FALSE               25 (to 50)
                42      LOAD_GLOBAL                     4: _error
                44      LOAD_FAST                       2: nexttok
                46      CALL_FUNCTION                   1
                48      RAISE_VARARGS                   1
                50      LOAD_CONST                      3: 0
                52      STORE_FAST                      3: depth
                54      LOAD_FAST                       1: result
                56      GET_ITER                        
                58      FOR_ITER                        27 (to 114)
                60      STORE_FAST                      4: c
                62      LOAD_FAST                       4: c
                64      LOAD_CONST                      4: '('
                66      COMPARE_OP                      2 (==)
                68      POP_JUMP_IF_FALSE               48 (to 96)
                70      LOAD_FAST                       3: depth
                72      LOAD_CONST                      5: 1
                74      INPLACE_ADD                     
                76      STORE_FAST                      3: depth
                78      LOAD_FAST                       3: depth
                80      LOAD_CONST                      6: 20
                82      COMPARE_OP                      4 (>)
                84      POP_JUMP_IF_FALSE               47 (to 94)
                86      LOAD_GLOBAL                     1: ValueError
                88      LOAD_CONST                      7: 'plural form expression is too complex'
                90      CALL_FUNCTION                   1
                92      RAISE_VARARGS                   1
                94      JUMP_ABSOLUTE                   29 (to 58)
                96      LOAD_FAST                       4: c
                98      LOAD_CONST                      8: ')'
                100     COMPARE_OP                      2 (==)
                102     POP_JUMP_IF_FALSE               56 (to 112)
                104     LOAD_FAST                       3: depth
                106     LOAD_CONST                      5: 1
                108     INPLACE_SUBTRACT                
                110     STORE_FAST                      3: depth
                112     JUMP_ABSOLUTE                   29 (to 58)
                114     LOAD_CONST                      9: '_as_int'
                116     LOAD_GLOBAL                     5: _as_int
                118     BUILD_MAP                       1
                120     STORE_FAST                      5: ns
                122     LOAD_GLOBAL                     6: exec
                124     LOAD_CONST                      10: 'if True:\n            def func(n):\n                if not isinstance(n, int):\n                    n = _as_int(n)\n                return int(%s)\n            '
                126     LOAD_FAST                       1: result
                128     BINARY_MODULO                   
                130     LOAD_FAST                       5: ns
                132     CALL_FUNCTION                   2
                134     POP_TOP                         
                136     LOAD_FAST                       5: ns
                138     LOAD_CONST                      11: 'func'
                140     BINARY_SUBSCR                   
                142     POP_BLOCK                       
                144     RETURN_VALUE                    
                146     DUP_TOP                         
                148     LOAD_GLOBAL                     7: RecursionError
                150     JUMP_IF_NOT_EXC_MATCH           83 (to 166)
                152     POP_TOP                         
                154     POP_TOP                         
                156     POP_TOP                         
                158     LOAD_GLOBAL                     1: ValueError
                160     LOAD_CONST                      7: 'plural form expression is too complex'
                162     CALL_FUNCTION                   1
                164     RAISE_VARARGS                   1
                166     RERAISE                         0
        'c2py'
        [Code]
            File Name: gettext.py
            Object Name: _expand_lang
            Arg Count: 1
            Pos Only Arg Count: 0
            KW Only Arg Count: 0
            Locals: 14
            Stack Size: 4
            Flags: 0x00000043 (CO_OPTIMIZED | CO_NEWLOCALS | CO_NOFREE)
            [Names]
                'locale'
                'normalize'
                'find'
                'range'
                'append'
                'reverse'
            [Var Names]
                'loc'
                'locale'
                'COMPONENT_CODESET'
                'COMPONENT_TERRITORY'
                'COMPONENT_MODIFIER'
                'mask'
                'pos'
                'modifier'
                'codeset'
                'territory'
                'language'
                'ret'
                'i'
                'val'
            [Free Vars]
            [Cell Vars]
            [Constants]
                None
                0
                1
                2
                4
                '@'
                ''
                '.'
                '_'
            [Disassembly]
                0       LOAD_CONST                      1: 0
                2       LOAD_CONST                      0: None
                4       IMPORT_NAME                     0: locale
                6       STORE_FAST                      1: locale
                8       LOAD_FAST                       1: locale
                10      LOAD_METHOD                     1: normalize
                12      LOAD_FAST                       0: loc
                14      CALL_METHOD                     1
                16      STORE_FAST                      0: loc
                18      LOAD_CONST                      2: 1
                20      STORE_FAST                      2: COMPONENT_CODESET
                22      LOAD_CONST                      3: 2
                24      STORE_FAST                      3: COMPONENT_TERRITORY
                26      LOAD_CONST                      4: 4
                28      STORE_FAST                      4: COMPONENT_MODIFIER
                30      LOAD_CONST                      1: 0
                32      STORE_FAST                      5: mask
                34      LOAD_FAST                       0: loc
                36      LOAD_METHOD                     2: find
                38      LOAD_CONST                      5: '@'
                40      CALL_METHOD                     1
                42      STORE_FAST                      6: pos
                44      LOAD_FAST                       6: pos
                46      LOAD_CONST                      1: 0
                48      COMPARE_OP                      5 (>=)
                50      POP_JUMP_IF_FALSE               43 (to 86)
                52      LOAD_FAST                       0: loc
                54      LOAD_FAST                       6: pos
                56      LOAD_CONST                      0: None
                58      BUILD_SLICE                     2
                60      BINARY_SUBSCR                   
                62      STORE_FAST                      7: modifier
                64      LOAD_FAST                       0: loc
                66      LOAD_CONST                      0: None
                68      LOAD_FAST                       6: pos
                70      BUILD_SLICE                     2
                72      BINARY_SUBSCR                   
                74      STORE_FAST                      0: loc
                76      LOAD_FAST                       5: mask
                78      LOAD_FAST                       4: COMPONENT_MODIFIER
                80      INPLACE_OR                      
                82      STORE_FAST                      5: mask
                84      JUMP_FORWARD                    2 (to 90)
                86      LOAD_CONST                      6: ''
                88      STORE_FAST                      7: modifier
                90      LOAD_FAST                       0: loc
                92      LOAD_METHOD                     2: find
                94      LOAD_CONST                      7: '.'
                96      CALL_METHOD                     1
                98      STORE_FAST                      6: pos
                100     LOAD_FAST                       6: pos
                102     LOAD_CONST                      1: 0
                104     COMPARE_OP                      5 (>=)
                106     POP_JUMP_IF_FALSE               71 (to 142)
                108     LOAD_FAST                       0: loc
                110     LOAD_FAST                       6: pos
                112     LOAD_CONST                      0: None
                114     BUILD_SLICE                     2
                116     BINARY_SUBSCR                   
                118     STORE_FAST                      8: codeset
                120     LOAD_FAST                       0: loc
                122     LOAD_CONST                      0: None
                124     LOAD_FAST                       6: pos
                126     BUILD_SLICE                     2
                128     BINARY_SUBSCR                   
                130     STORE_FAST                      0: loc
                132     LOAD_FAST                       5: mask
                134     LOAD_FAST                       2: COMPONENT_CODESET
                136     INPLACE_OR                      
                138     STORE_FAST                      5: mask
                140     JUMP_FORWARD                    2 (to 146)
                142     LOAD_CONST                      6: ''
                144     STORE_FAST                      8: codeset
                146     LOAD_FAST                       0: loc
                148     LOAD_METHOD                     2: find
                150     LOAD_CONST                      8: '_'
                152     CALL_METHOD                     1
                154     STORE_FAST                      6: pos
                156     LOAD_FAST                       6: pos
                158     LOAD_CONST                      1: 0
                160     COMPARE_OP                      5 (>=)
                162     POP_JUMP_IF_FALSE               99 (to 198)
                164     LOAD_FAST                       0: loc
                166     LOAD_FAST                       6: pos
                168     LOAD_CONST                      0: None
                170     BUILD_SLICE                     2
                172     BINARY_SUBSCR                   
                174     STORE_FAST                      9: territory
                176     LOAD_FAST                       0: loc
                178     LOAD_CONST                      0: None
                180     LOAD_FAST                       6: pos
                182     BUILD_SLICE                     2
                184     BINARY_SUBSCR                   
                186     STORE_FAST                      0: loc
                188     LOAD_FAST                       5: mask
                190     LOAD_FAST                       3: COMPONENT_TERRITORY
                192     INPLACE_OR                      
                194     STORE_FAST                      5: mask
                196     JUMP_FORWARD                    2 (to 202)
                198     LOAD_CONST                      6: ''
                200     STORE_FAST                      9: territory
                202     LOAD_FAST                       0: loc
                204     STORE_FAST                      10: language
                206     BUILD_LIST                      0
                208     STORE_FAST                      11: ret
                210     LOAD_GLOBAL                     3: range
                212     LOAD_FAST                       5: mask
                214     LOAD_CONST                      2: 1
                216     BINARY_ADD                      
                218     CALL_FUNCTION                   1
                220     GET_ITER                        
                222     FOR_ITER                        38 (to 300)
                224     STORE_FAST                      12: i
                226     LOAD_FAST                       12: i
                228     LOAD_FAST                       5: mask
                230     UNARY_INVERT                    
                232     BINARY_AND                      
                234     POP_JUMP_IF_TRUE                149 (to 298)
                236     LOAD_FAST                       10: language
                238     STORE_FAST                      13: val
                240     LOAD_FAST                       12: i
                242     LOAD_FAST                       3: COMPONENT_TERRITORY
                244     BINARY_AND                      
                246     POP_JUMP_IF_FALSE               128 (to 256)
                248     LOAD_FAST                       13: val
                250     LOAD_FAST                       9: territory
                252     INPLACE_ADD                     
                254     STORE_FAST                      13: val
                256     LOAD_FAST                       12: i
                258     LOAD_FAST                       2: COMPONENT_CODESET
                260     BINARY_AND                      
                262     POP_JUMP_IF_FALSE               136 (to 272)
                264     LOAD_FAST                       13: val
                266     LOAD_FAST                       8: codeset
                268     INPLACE_ADD                     
                270     STORE_FAST                      13: val
                272     LOAD_FAST                       12: i
                274     LOAD_FAST                       4: COMPONENT_MODIFIER
                276     BINARY_AND                      
                278     POP_JUMP_IF_FALSE               144 (to 288)
                280     LOAD_FAST                       13: val
                282     LOAD_FAST                       7: modifier
                284     INPLACE_ADD                     
                286     STORE_FAST                      13: val
                288     LOAD_FAST                       11: ret
                290     LOAD_METHOD                     4: append
                292     LOAD_FAST                       13: val
                294     CALL_METHOD                     1
                296     POP_TOP                         
                298     JUMP_ABSOLUTE                   111 (to 222)
                300     LOAD_FAST                       11: ret
                302     LOAD_METHOD                     5: reverse
                304     CALL_METHOD                     0
                306     POP_TOP                         
                308     LOAD_FAST                       11: ret
                310     RETURN_VALUE                    
        '_expand_lang'
        [Code]
            File Name: gettext.py
            Object Name: NullTranslations
            Arg Count: 0
            Pos Only Arg Count: 0
            KW Only Arg Count: 0
            Locals: 0
            Stack Size: 3
            Flags: 0x00000040 (CO_NOFREE)
            [Names]
                '__name__'
                '__module__'
                '__qualname__'
                '__init__'
                '_parse'
                'add_fallback'
                'gettext'
                'lgettext'
                'ngettext'
                'lngettext'
                'pgettext'
                'npgettext'
                'info'
                'charset'
                'output_charset'
                'set_output_charset'
                'install'
            [Var Names]
            [Free Vars]
            [Cell Vars]
            [Constants]
                'NullTranslations'
                None
                [Code]
                    File Name: gettext.py
                    Object Name: __init__
                    Arg Count: 2
                    Pos Only Arg Count: 0
                    KW Only Arg Count: 0
                    Locals: 2
                    Stack Size: 3
                    Flags: 0x00000043 (CO_OPTIMIZED | CO_NEWLOCALS | CO_NOFREE)
                    [Names]
                        '_info'
                        '_charset'
                        '_output_charset'
                        '_fallback'
                        '_parse'
                    [Var Names]
                        'self'
                        'fp'
                    [Free Vars]
                    [Cell Vars]
                    [Constants]
                        None
                    [Disassembly]
                        0       BUILD_MAP                       0
                        2       LOAD_FAST                       0: self
                        4       STORE_ATTR                      0: _info
                        6       LOAD_CONST                      0: None
                        8       LOAD_FAST                       0: self
                        10      STORE_ATTR                      1: _charset
                        12      LOAD_CONST                      0: None
                        14      LOAD_FAST                       0: self
                        16      STORE_ATTR                      2: _output_charset
                        18      LOAD_CONST                      0: None
                        20      LOAD_FAST                       0: self
                        22      STORE_ATTR                      3: _fallback
                        24      LOAD_FAST                       1: fp
                        26      LOAD_CONST                      0: None
                        28      IS_OP                           1 (is not)
                        30      POP_JUMP_IF_FALSE               23 (to 46)
                        32      LOAD_FAST                       0: self
                        34      LOAD_METHOD                     4: _parse
                        36      LOAD_FAST                       1: fp
                        38      CALL_METHOD                     1
                        40      POP_TOP                         
                        42      LOAD_CONST                      0: None
                        44      RETURN_VALUE                    
                        46      LOAD_CONST                      0: None
                        48      RETURN_VALUE                    
                'NullTranslations.__init__'
                [Code]
                    File Name: gettext.py
                    Object Name: _parse
                    Arg Count: 2
                    Pos Only Arg Count: 0
                    KW Only Arg Count: 0
                    Locals: 2
                    Stack Size: 1
                    Flags: 0x00000043 (CO_OPTIMIZED | CO_NEWLOCALS | CO_NOFREE)
                    [Names]
                    [Var Names]
                        'self'
                        'fp'
                    [Free Vars]
                    [Cell Vars]
                    [Constants]
                        None
                    [Disassembly]
                        0       LOAD_CONST                      0: None
                        2       RETURN_VALUE                    
                'NullTranslations._parse'
                [Code]
                    File Name: gettext.py
                    Object Name: add_fallback
                    Arg Count: 2
                    Pos Only Arg Count: 0
                    KW Only Arg Count: 0
                    Locals: 2
                    Stack Size: 3
                    Flags: 0x00000043 (CO_OPTIMIZED | CO_NEWLOCALS | CO_NOFREE)
                    [Names]
                        '_fallback'
                        'add_fallback'
                    [Var Names]
                        'self'
                        'fallback'
                    [Free Vars]
                    [Cell Vars]
                    [Constants]
                        None
                    [Disassembly]
                        0       LOAD_FAST                       0: self
                        2       LOAD_ATTR                       0: _fallback
                        4       POP_JUMP_IF_FALSE               11 (to 22)
                        6       LOAD_FAST                       0: self
                        8       LOAD_ATTR                       0: _fallback
                        10      LOAD_METHOD                     1: add_fallback
                        12      LOAD_FAST                       1: fallback
                        14      CALL_METHOD                     1
                        16      POP_TOP                         
                        18      LOAD_CONST                      0: None
                        20      RETURN_VALUE                    
                        22      LOAD_FAST                       1: fallback
                        24      LOAD_FAST                       0: self
                        26      STORE_ATTR                      0: _fallback
                        28      LOAD_CONST                      0: None
                        30      RETURN_VALUE                    
                'NullTranslations.add_fallback'
                [Code]
                    File Name: gettext.py
                    Object Name: gettext
                    Arg Count: 2
                    Pos Only Arg Count: 0
                    KW Only Arg Count: 0
                    Locals: 2
                    Stack Size: 3
                    Flags: 0x00000043 (CO_OPTIMIZED | CO_NEWLOCALS | CO_NOFREE)
                    [Names]
                        '_fallback'
                        'gettext'
                    [Var Names]
                        'self'
                        'message'
                    [Free Vars]
                    [Cell Vars]
                    [Constants]
                        None
                    [Disassembly]
                        0       LOAD_FAST                       0: self
                        2       LOAD_ATTR                       0: _fallback
                        4       POP_JUMP_IF_FALSE               9 (to 18)
                        6       LOAD_FAST                       0: self
                        8       LOAD_ATTR                       0: _fallback
                        10      LOAD_METHOD                     1: gettext
                        12      LOAD_FAST                       1: message
                        14      CALL_METHOD                     1
                        16      RETURN_VALUE                    
                        18      LOAD_FAST                       1: message
                        20      RETURN_VALUE                    
                'NullTranslations.gettext'
                [Code]
                    File Name: gettext.py
                    Object Name: lgettext
                    Arg Count: 2
                    Pos Only Arg Count: 0
                    KW Only Arg Count: 0
                    Locals: 4
                    Stack Size: 8
                    Flags: 0x00000043 (CO_OPTIMIZED | CO_NEWLOCALS | CO_NOFREE)
                    [Names]
                        'warnings'
                        'warn'
                        'DeprecationWarning'
                        'locale'
                        '_fallback'
                        'catch_warnings'
                        'filterwarnings'
                        'lgettext'
                        '_output_charset'
                        'encode'
                        'getpreferredencoding'
                    [Var Names]
                        'self'
                        'message'
                        'warnings'
                        'locale'
                    [Free Vars]
                    [Cell Vars]
                    [Constants]
                        None
                        0
                        'lgettext() is deprecated, use gettext() instead'
                        2
                        'ignore'
                        '.*\\blgettext\\b.*'
                    [Disassembly]
                        0       LOAD_CONST                      1: 0
                        2       LOAD_CONST                      0: None
                        4       IMPORT_NAME                     0: warnings
                        6       STORE_FAST                      2: warnings
                        8       LOAD_FAST                       2: warnings
                        10      LOAD_METHOD                     1: warn
                        12      LOAD_CONST                      2: 'lgettext() is deprecated, use gettext() instead'
                        14      LOAD_GLOBAL                     2: DeprecationWarning
                        16      LOAD_CONST                      3: 2
                        18      CALL_METHOD                     3
                        20      POP_TOP                         
                        22      LOAD_CONST                      1: 0
                        24      LOAD_CONST                      0: None
                        26      IMPORT_NAME                     3: locale
                        28      STORE_FAST                      3: locale
                        30      LOAD_FAST                       0: self
                        32      LOAD_ATTR                       4: _fallback
                        34      POP_JUMP_IF_FALSE               51 (to 102)
                        36      LOAD_FAST                       2: warnings
                        38      LOAD_METHOD                     5: catch_warnings
                        40      CALL_METHOD                     0
                        42      SETUP_WITH                      21 (to 86)
                        44      POP_TOP                         
                        46      LOAD_FAST                       2: warnings
                        48      LOAD_METHOD                     6: filterwarnings
                        50      LOAD_CONST                      4: 'ignore'
                        52      LOAD_CONST                      5: '.*\\blgettext\\b.*'
                        54      LOAD_GLOBAL                     2: DeprecationWarning
                        56      CALL_METHOD                     3
                        58      POP_TOP                         
                        60      LOAD_FAST                       0: self
                        62      LOAD_ATTR                       4: _fallback
                        64      LOAD_METHOD                     7: lgettext
                        66      LOAD_FAST                       1: message
                        68      CALL_METHOD                     1
                        70      POP_BLOCK                       
                        72      ROT_TWO                         
                        74      LOAD_CONST                      0: None
                        76      DUP_TOP                         
                        78      DUP_TOP                         
                        80      CALL_FUNCTION                   3
                        82      POP_TOP                         
                        84      RETURN_VALUE                    
                        86      WITH_EXCEPT_START               
                        88      POP_JUMP_IF_TRUE                46 (to 92)
                        90      RERAISE                         1
                        92      POP_TOP                         
                        94      POP_TOP                         
                        96      POP_TOP                         
                        98      POP_EXCEPT                      
                        100     POP_TOP                         
                        102     LOAD_FAST                       0: self
                        104     LOAD_ATTR                       8: _output_charset
                        106     POP_JUMP_IF_FALSE               60 (to 120)
                        108     LOAD_FAST                       1: message
                        110     LOAD_METHOD                     9: encode
                        112     LOAD_FAST                       0: self
                        114     LOAD_ATTR                       8: _output_charset
                        116     CALL_METHOD                     1
                        118     RETURN_VALUE                    
                        120     LOAD_FAST                       1: message
                        122     LOAD_METHOD                     9: encode
                        124     LOAD_FAST                       3: locale
                        126     LOAD_METHOD                     10: getpreferredencoding
                        128     CALL_METHOD                     0
                        130     CALL_METHOD                     1
                        132     RETURN_VALUE                    
                'NullTranslations.lgettext'
                [Code]
                    File Name: gettext.py
                    Object Name: ngettext
                    Arg Count: 4
                    Pos Only Arg Count: 0
                    KW Only Arg Count: 0
                    Locals: 4
                    Stack Size: 5
                    Flags: 0x00000043 (CO_OPTIMIZED | CO_NEWLOCALS | CO_NOFREE)
                    [Names]
                        '_fallback'
                        'ngettext'
                    [Var Names]
                        'self'
                        'msgid1'
                        'msgid2'
                        'n'
                    [Free Vars]
                    [Cell Vars]
                    [Constants]
                        None
                        1
                    [Disassembly]
                        0       LOAD_FAST                       0: self
                        2       LOAD_ATTR                       0: _fallback
                        4       POP_JUMP_IF_FALSE               11 (to 22)
                        6       LOAD_FAST                       0: self
                        8       LOAD_ATTR                       0: _fallback
                        10      LOAD_METHOD                     1: ngettext
                        12      LOAD_FAST                       1: msgid1
                        14      LOAD_FAST                       2: msgid2
                        16      LOAD_FAST                       3: n
                        18      CALL_METHOD                     3
                        20      RETURN_VALUE                    
                        22      LOAD_FAST                       3: n
                        24      LOAD_CONST                      1: 1
                        26      COMPARE_OP                      2 (==)
                        28      POP_JUMP_IF_FALSE               17 (to 34)
                        30      LOAD_FAST                       1: msgid1
                        32      RETURN_VALUE                    
                        34      LOAD_FAST                       2: msgid2
                        36      RETURN_VALUE                    
                'NullTranslations.ngettext'
                [Code]
                    File Name: gettext.py
                    Object Name: lngettext
                    Arg Count: 4
                    Pos Only Arg Count: 0
                    KW Only Arg Count: 0
                    Locals: 7
                    Stack Size: 8
                    Flags: 0x00000043 (CO_OPTIMIZED | CO_NEWLOCALS | CO_NOFREE)
                    [Names]
                        'warnings'
                        'warn'
                        'DeprecationWarning'
                        'locale'
                        '_fallback'
                        'catch_warnings'
                        'filterwarnings'
                        'lngettext'
                        '_output_charset'
                        'encode'
                        'getpreferredencoding'
                    [Var Names]
                        'self'
                        'msgid1'
                        'msgid2'
                        'n'
                        'warnings'
                        'locale'
                        'tmsg'
                    [Free Vars]
                    [Cell Vars]
                    [Constants]
                        None
                        0
                        'lngettext() is deprecated, use ngettext() instead'
                        2
                        'ignore'
                        '.*\\blngettext\\b.*'
                        1
                    [Disassembly]
                        0       LOAD_CONST                      1: 0
                        2       LOAD_CONST                      0: None
                        4       IMPORT_NAME                     0: warnings
                        6       STORE_FAST                      4: warnings
                        8       LOAD_FAST                       4: warnings
                        10      LOAD_METHOD                     1: warn
                        12      LOAD_CONST                      2: 'lngettext() is deprecated, use ngettext() instead'
                        14      LOAD_GLOBAL                     2: DeprecationWarning
                        16      LOAD_CONST                      3: 2
                        18      CALL_METHOD                     3
                        20      POP_TOP                         
                        22      LOAD_CONST                      1: 0
                        24      LOAD_CONST                      0: None
                        26      IMPORT_NAME                     3: locale
                        28      STORE_FAST                      5: locale
                        30      LOAD_FAST                       0: self
                        32      LOAD_ATTR                       4: _fallback
                        34      POP_JUMP_IF_FALSE               53 (to 106)
                        36      LOAD_FAST                       4: warnings
                        38      LOAD_METHOD                     5: catch_warnings
                        40      CALL_METHOD                     0
                        42      SETUP_WITH                      23 (to 90)
                        44      POP_TOP                         
                        46      LOAD_FAST                       4: warnings
                        48      LOAD_METHOD                     6: filterwarnings
                        50      LOAD_CONST                      4: 'ignore'
                        52      LOAD_CONST                      5: '.*\\blngettext\\b.*'
                        54      LOAD_GLOBAL                     2: DeprecationWarning
                        56      CALL_METHOD                     3
                        58      POP_TOP                         
                        60      LOAD_FAST                       0: self
                        62      LOAD_ATTR                       4: _fallback
                        64      LOAD_METHOD                     7: lngettext
                        66      LOAD_FAST                       1: msgid1
                        68      LOAD_FAST                       2: msgid2
                        70      LOAD_FAST                       3: n
                        72      CALL_METHOD                     3
                        74      POP_BLOCK                       
                        76      ROT_TWO                         
                        78      LOAD_CONST                      0: None
                        80      DUP_TOP                         
                        82      DUP_TOP                         
                        84      CALL_FUNCTION                   3
                        86      POP_TOP                         
                        88      RETURN_VALUE                    
                        90      WITH_EXCEPT_START               
                        92      POP_JUMP_IF_TRUE                48 (to 96)
                        94      RERAISE                         1
                        96      POP_TOP                         
                        98      POP_TOP                         
                        100     POP_TOP                         
                        102     POP_EXCEPT                      
                        104     POP_TOP                         
                        106     LOAD_FAST                       3: n
                        108     LOAD_CONST                      6: 1
                        110     COMPARE_OP                      2 (==)
                        112     POP_JUMP_IF_FALSE               60 (to 120)
                        114     LOAD_FAST                       1: msgid1
                        116     STORE_FAST                      6: tmsg
                        118     JUMP_FORWARD                    2 (to 124)
                        120     LOAD_FAST                       2: msgid2
                        122     STORE_FAST                      6: tmsg
                        124     LOAD_FAST                       0: self
                        126     LOAD_ATTR                       8: _output_charset
                        128     POP_JUMP_IF_FALSE               71 (to 142)
                        130     LOAD_FAST                       6: tmsg
                        132     LOAD_METHOD                     9: encode
                        134     LOAD_FAST                       0: self
                        136     LOAD_ATTR                       8: _output_charset
                        138     CALL_METHOD                     1
                        140     RETURN_VALUE                    
                        142     LOAD_FAST                       6: tmsg
                        144     LOAD_METHOD                     9: encode
                        146     LOAD_FAST                       5: locale
                        148     LOAD_METHOD                     10: getpreferredencoding
                        150     CALL_METHOD                     0
                        152     CALL_METHOD                     1
                        154     RETURN_VALUE                    
                'NullTranslations.lngettext'
                [Code]
                    File Name: gettext.py
                    Object Name: pgettext
                    Arg Count: 3
                    Pos Only Arg Count: 0
                    KW Only Arg Count: 0
                    Locals: 3
                    Stack Size: 4
                    Flags: 0x00000043 (CO_OPTIMIZED | CO_NEWLOCALS | CO_NOFREE)
                    [Names]
                        '_fallback'
                        'pgettext'
                    [Var Names]
                        'self'
                        'context'
                        'message'
                    [Free Vars]
                    [Cell Vars]
                    [Constants]
                        None
                    [Disassembly]
                        0       LOAD_FAST                       0: self
                        2       LOAD_ATTR                       0: _fallback
                        4       POP_JUMP_IF_FALSE               10 (to 20)
                        6       LOAD_FAST                       0: self
                        8       LOAD_ATTR                       0: _fallback
                        10      LOAD_METHOD                     1: pgettext
                        12      LOAD_FAST                       1: context
                        14      LOAD_FAST                       2: message
                        16      CALL_METHOD                     2
                        18      RETURN_VALUE                    
                        20      LOAD_FAST                       2: message
                        22      RETURN_VALUE                    
                'NullTranslations.pgettext'
                [Code]
                    File Name: gettext.py
                    Object Name: npgettext
                    Arg Count: 5
                    Pos Only Arg Count: 0
                    KW Only Arg Count: 0
                    Locals: 5
                    Stack Size: 6
                    Flags: 0x00000043 (CO_OPTIMIZED | CO_NEWLOCALS | CO_NOFREE)
                    [Names]
                        '_fallback'
                        'npgettext'
                    [Var Names]
                        'self'
                        'context'
                        'msgid1'
                        'msgid2'
                        'n'
                    [Free Vars]
                    [Cell Vars]
                    [Constants]
                        None
                        1
                    [Disassembly]
                        0       LOAD_FAST                       0: self
                        2       LOAD_ATTR                       0: _fallback
                        4       POP_JUMP_IF_FALSE               12 (to 24)
                        6       LOAD_FAST                       0: self
                        8       LOAD_ATTR                       0: _fallback
                        10      LOAD_METHOD                     1: npgettext
                        12      LOAD_FAST                       1: context
                        14      LOAD_FAST                       2: msgid1
                        16      LOAD_FAST                       3: msgid2
                        18      LOAD_FAST                       4: n
                        20      CALL_METHOD                     4
                        22      RETURN_VALUE                    
                        24      LOAD_FAST                       4: n
                        26      LOAD_CONST                      1: 1
                        28      COMPARE_OP                      2 (==)
                        30      POP_JUMP_IF_FALSE               18 (to 36)
                        32      LOAD_FAST                       2: msgid1
                        34      RETURN_VALUE                    
                        36      LOAD_FAST                       3: msgid2
                        38      RETURN_VALUE                    
                'NullTranslations.npgettext'
                [Code]
                    File Name: gettext.py
                    Object Name: info
                    Arg Count: 1
                    Pos Only Arg Count: 0
                    KW Only Arg Count: 0
                    Locals: 1
                    Stack Size: 1
                    Flags: 0x00000043 (CO_OPTIMIZED | CO_NEWLOCALS | CO_NOFREE)
                    [Names]
                        '_info'
                    [Var Names]
                        'self'
                    [Free Vars]
                    [Cell Vars]
                    [Constants]
                        None
                    [Disassembly]
                        0       LOAD_FAST                       0: self
                        2       LOAD_ATTR                       0: _info
                        4       RETURN_VALUE                    
                'NullTranslations.info'
                [Code]
                    File Name: gettext.py
                    Object Name: charset
                    Arg Count: 1
                    Pos Only Arg Count: 0
                    KW Only Arg Count: 0
                    Locals: 1
                    Stack Size: 1
                    Flags: 0x00000043 (CO_OPTIMIZED | CO_NEWLOCALS | CO_NOFREE)
                    [Names]
                        '_charset'
                    [Var Names]
                        'self'
                    [Free Vars]
                    [Cell Vars]
                    [Constants]
                        None
                    [Disassembly]
                        0       LOAD_FAST                       0: self
                        2       LOAD_ATTR                       0: _charset
                        4       RETURN_VALUE                    
                'NullTranslations.charset'
                [Code]
                    File Name: gettext.py
                    Object Name: output_charset
                    Arg Count: 1
                    Pos Only Arg Count: 0
                    KW Only Arg Count: 0
                    Locals: 2
                    Stack Size: 5
                    Flags: 0x00000043 (CO_OPTIMIZED | CO_NEWLOCALS | CO_NOFREE)
                    [Names]
                        'warnings'
                        'warn'
                        'DeprecationWarning'
                        '_output_charset'
                    [Var Names]
                        'self'
                        'warnings'
                    [Free Vars]
                    [Cell Vars]
                    [Constants]
                        None
                        0
                        'output_charset() is deprecated'
                        2
                    [Disassembly]
                        0       LOAD_CONST                      1: 0
                        2       LOAD_CONST                      0: None
                        4       IMPORT_NAME                     0: warnings
                        6       STORE_FAST                      1: warnings
                        8       LOAD_FAST                       1: warnings
                        10      LOAD_METHOD                     1: warn
                        12      LOAD_CONST                      2: 'output_charset() is deprecated'
                        14      LOAD_GLOBAL                     2: DeprecationWarning
                        16      LOAD_CONST                      3: 2
                        18      CALL_METHOD                     3
                        20      POP_TOP                         
                        22      LOAD_FAST                       0: self
                        24      LOAD_ATTR                       3: _output_charset
                        26      RETURN_VALUE                    
                'NullTranslations.output_charset'
                [Code]
                    File Name: gettext.py
                    Object Name: set_output_charset
                    Arg Count: 2
                    Pos Only Arg Count: 0
                    KW Only Arg Count: 0
                    Locals: 3
                    Stack Size: 5
                    Flags: 0x00000043 (CO_OPTIMIZED | CO_NEWLOCALS | CO_NOFREE)
                    [Names]
                        'warnings'
                        'warn'
                        'DeprecationWarning'
                        '_output_charset'
                    [Var Names]
                        'self'
                        'charset'
                        'warnings'
                    [Free Vars]
                    [Cell Vars]
                    [Constants]
                        None
                        0
                        'set_output_charset() is deprecated'
                        2
                    [Disassembly]
                        0       LOAD_CONST                      1: 0
                        2       LOAD_CONST                      0: None
                        4       IMPORT_NAME                     0: warnings
                        6       STORE_FAST                      2: warnings
                        8       LOAD_FAST                       2: warnings
                        10      LOAD_METHOD                     1: warn
                        12      LOAD_CONST                      2: 'set_output_charset() is deprecated'
                        14      LOAD_GLOBAL                     2: DeprecationWarning
                        16      LOAD_CONST                      3: 2
                        18      CALL_METHOD                     3
                        20      POP_TOP                         
                        22      LOAD_FAST                       1: charset
                        24      LOAD_FAST                       0: self
                        26      STORE_ATTR                      3: _output_charset
                        28      LOAD_CONST                      0: None
                        30      RETURN_VALUE                    
                'NullTranslations.set_output_charset'
                [Code]
                    File Name: gettext.py
                    Object Name: install
                    Arg Count: 2
                    Pos Only Arg Count: 0
                    KW Only Arg Count: 0
                    Locals: 5
                    Stack Size: 4
                    Flags: 0x00000043 (CO_OPTIMIZED | CO_NEWLOCALS | CO_NOFREE)
                    [Names]
                        'builtins'
                        'gettext'
                        '__dict__'
                        'set'
                        'getattr'
                    [Var Names]
                        'self'
                        'names'
                        'builtins'
                        'allowed'
                        'name'
                    [Free Vars]
                    [Cell Vars]
                    [Constants]
                        None
                        0
                        '_'
                        frozenset({
                            'gettext'
                            'lgettext'
                            'ngettext'
                            'pgettext'
                            'lngettext'
                            'npgettext'
                        })
                    [Disassembly]
                        0       LOAD_CONST                      1: 0
                        2       LOAD_CONST                      0: None
                        4       IMPORT_NAME                     0: builtins
                        6       STORE_FAST                      2: builtins
                        8       LOAD_FAST                       0: self
                        10      LOAD_ATTR                       1: gettext
                        12      LOAD_FAST                       2: builtins
                        14      LOAD_ATTR                       2: __dict__
                        16      LOAD_CONST                      2: '_'
                        18      STORE_SUBSCR                    
                        20      LOAD_FAST                       1: names
                        22      LOAD_CONST                      0: None
                        24      IS_OP                           1 (is not)
                        26      POP_JUMP_IF_FALSE               35 (to 70)
                        28      BUILD_SET                       0
                        30      LOAD_CONST                      3: frozenset({'gettext', 'lgettext', 'ngettext', 'pgettext', 'lngettext', 'npgettext'})
                        32      SET_UPDATE                      1
                        34      STORE_FAST                      3: allowed
                        36      LOAD_FAST                       3: allowed
                        38      LOAD_GLOBAL                     3: set
                        40      LOAD_FAST                       1: names
                        42      CALL_FUNCTION                   1
                        44      BINARY_AND                      
                        46      GET_ITER                        
                        48      FOR_ITER                        12 (to 74)
                        50      STORE_FAST                      4: name
                        52      LOAD_GLOBAL                     4: getattr
                        54      LOAD_FAST                       0: self
                        56      LOAD_FAST                       4: name
                        58      CALL_FUNCTION                   2
                        60      LOAD_FAST                       2: builtins
                        62      LOAD_ATTR                       2: __dict__
                        64      LOAD_FAST                       4: name
                        66      STORE_SUBSCR                    
                        68      JUMP_ABSOLUTE                   24 (to 48)
                        70      LOAD_CONST                      0: None
                        72      RETURN_VALUE                    
                        74      LOAD_CONST                      0: None
                        76      RETURN_VALUE                    
                'NullTranslations.install'
                (
                    None
                )
            [Disassembly]
                0       LOAD_NAME                       0: __name__
                2       STORE_NAME                      1: __module__
                4       LOAD_CONST                      0: 'NullTranslations'
                6       STORE_NAME                      2: __qualname__
                8       LOAD_CONST                      30: (None,)
                10      LOAD_CONST                      2: <CODE> __init__
                12      LOAD_CONST                      3: 'NullTranslations.__init__'
                14      MAKE_FUNCTION                   1
                16      STORE_NAME                      3: __init__
                18      LOAD_CONST                      4: <CODE> _parse
                20      LOAD_CONST                      5: 'NullTranslations._parse'
                22      MAKE_FUNCTION                   0
                24      STORE_NAME                      4: _parse
                26      LOAD_CONST                      6: <CODE> add_fallback
                28      LOAD_CONST                      7: 'NullTranslations.add_fallback'
                30      MAKE_FUNCTION                   0
                32      STORE_NAME                      5: add_fallback
                34      LOAD_CONST                      8: <CODE> gettext
                36      LOAD_CONST                      9: 'NullTranslations.gettext'
                38      MAKE_FUNCTION                   0
                40      STORE_NAME                      6: gettext
                42      LOAD_CONST                      10: <CODE> lgettext
                44      LOAD_CONST                      11: 'NullTranslations.lgettext'
                46      MAKE_FUNCTION                   0
                48      STORE_NAME                      7: lgettext
                50      LOAD_CONST                      12: <CODE> ngettext
                52      LOAD_CONST                      13: 'NullTranslations.ngettext'
                54      MAKE_FUNCTION                   0
                56      STORE_NAME                      8: ngettext
                58      LOAD_CONST                      14: <CODE> lngettext
                60      LOAD_CONST                      15: 'NullTranslations.lngettext'
                62      MAKE_FUNCTION                   0
                64      STORE_NAME                      9: lngettext
                66      LOAD_CONST                      16: <CODE> pgettext
                68      LOAD_CONST                      17: 'NullTranslations.pgettext'
                70      MAKE_FUNCTION                   0
                72      STORE_NAME                      10: pgettext
                74      LOAD_CONST                      18: <CODE> npgettext
                76      LOAD_CONST                      19: 'NullTranslations.npgettext'
                78      MAKE_FUNCTION                   0
                80      STORE_NAME                      11: npgettext
                82      LOAD_CONST                      20: <CODE> info
                84      LOAD_CONST                      21: 'NullTranslations.info'
                86      MAKE_FUNCTION                   0
                88      STORE_NAME                      12: info
                90      LOAD_CONST                      22: <CODE> charset
                92      LOAD_CONST                      23: 'NullTranslations.charset'
                94      MAKE_FUNCTION                   0
                96      STORE_NAME                      13: charset
                98      LOAD_CONST                      24: <CODE> output_charset
                100     LOAD_CONST                      25: 'NullTranslations.output_charset'
                102     MAKE_FUNCTION                   0
                104     STORE_NAME                      14: output_charset
                106     LOAD_CONST                      26: <CODE> set_output_charset
                108     LOAD_CONST                      27: 'NullTranslations.set_output_charset'
                110     MAKE_FUNCTION                   0
                112     STORE_NAME                      15: set_output_charset
                114     LOAD_CONST                      30: (None,)
                116     LOAD_CONST                      28: <CODE> install
                118     LOAD_CONST                      29: 'NullTranslations.install'
                120     MAKE_FUNCTION                   1
                122     STORE_NAME                      16: install
                124     LOAD_CONST                      1: None
                126     RETURN_VALUE                    
        'NullTranslations'
        [Code]
            File Name: gettext.py
            Object Name: GNUTranslations
            Arg Count: 0
            Pos Only Arg Count: 0
            KW Only Arg Count: 0
            Locals: 0
            Stack Size: 2
            Flags: 0x00000040 (CO_NOFREE)
            [Names]
                '__name__'
                '__module__'
                '__qualname__'
                'LE_MAGIC'
                'BE_MAGIC'
                'CONTEXT'
                'VERSIONS'
                '_get_versions'
                '_parse'
                'lgettext'
                'lngettext'
                'gettext'
                'ngettext'
                'pgettext'
                'npgettext'
            [Var Names]
            [Free Vars]
            [Cell Vars]
            [Constants]
                'GNUTranslations'
                0x950412DE
                0xDE120495
                '%s\x04%s'
                (
                    0
                    1
                )
                [Code]
                    File Name: gettext.py
                    Object Name: _get_versions
                    Arg Count: 2
                    Pos Only Arg Count: 0
                    KW Only Arg Count: 0
                    Locals: 2
                    Stack Size: 3
                    Flags: 0x00000043 (CO_OPTIMIZED | CO_NEWLOCALS | CO_NOFREE)
                    [Names]
                    [Var Names]
                        'self'
                        'version'
                    [Free Vars]
                    [Cell Vars]
                    [Constants]
                        'Returns a tuple of major version, minor version'
                        16
                        65535
                    [Disassembly]
                        0       LOAD_FAST                       1: version
                        2       LOAD_CONST                      1: 16
                        4       BINARY_RSHIFT                   
                        6       LOAD_FAST                       1: version
                        8       LOAD_CONST                      2: 65535
                        10      BINARY_AND                      
                        12      BUILD_TUPLE                     2
                        14      RETURN_VALUE                    
                'GNUTranslations._get_versions'
                [Code]
                    File Name: gettext.py
                    Object Name: _parse
                    Arg Count: 2
                    Pos Only Arg Count: 0
                    KW Only Arg Count: 0
                    Locals: 34
                    Stack Size: 7
                    Flags: 0x00000043 (CO_OPTIMIZED | CO_NEWLOCALS | CO_NOFREE)
                    [Names]
                        'struct'
                        'unpack'
                        'getattr'
                        '_catalog'
                        'plural'
                        'read'
                        'len'
                        'LE_MAGIC'
                        'BE_MAGIC'
                        'OSError'
                        '_get_versions'
                        'VERSIONS'
                        'str'
                        'range'
                        'split'
                        'decode'
                        'strip'
                        'startswith'
                        'endswith'
                        'lower'
                        '_info'
                        '_charset'
                        'c2py'
                        'enumerate'
                    [Var Names]
                        'self'
                        'fp'
                        'unpack'
                        'filename'
                        'catalog'
                        'buf'
                        'buflen'
                        'magic'
                        'version'
                        'msgcount'
                        'masteridx'
                        'transidx'
                        'ii'
                        'major_version'
                        'minor_version'
                        'i'
                        'mlen'
                        'moff'
                        'mend'
                        'tlen'
                        'toff'
                        'tend'
                        'msg'
                        'tmsg'
                        'lastk'
                        'b_item'
                        'item'
                        'k'
                        'v'
                        'plural'
                        'charset'
                        'msgid1'
                        'msgid2'
                        'x'
                    [Free Vars]
                    [Cell Vars]
                    [Constants]
                        'Override this method to support alternative .mo formats.'
                        0
                        (
                            'unpack'
                        )
                        'name'
                        ''
                        [Code]
                            File Name: gettext.py
                            Object Name: <lambda>
                            Arg Count: 1
                            Pos Only Arg Count: 0
                            KW Only Arg Count: 0
                            Locals: 1
                            Stack Size: 3
                            Flags: 0x00000053 (CO_OPTIMIZED | CO_NEWLOCALS | CO_NESTED | CO_NOFREE)
                            [Names]
                                'int'
                            [Var Names]
                                'n'
                            [Free Vars]
                            [Cell Vars]
                            [Constants]
                                None
                                1
                            [Disassembly]
                                0       LOAD_GLOBAL                     0: int
                                2       LOAD_FAST                       0: n
                                4       LOAD_CONST                      1: 1
                                6       COMPARE_OP                      3 (!=)
                                8       CALL_FUNCTION                   1
                                10      RETURN_VALUE                    
                        'GNUTranslations._parse.<locals>.<lambda>'
                        '<I'
                        None
                        4
                        '<4I'
                        20
                        '<II'
                        '>4I'
                        '>II'
                        'Bad magic number'
                        'Bad version number '
                        8
                        'File is corrupt'
                        b'\n'
                        '#-#-#-#-#'
                        ':'
                        1
                        '\n'
                        'content-type'
                        'charset='
                        'plural-forms'
                        ';'
                        'plural='
                        'ascii'
                        b'\x00'
                    [Disassembly]
                        0       LOAD_CONST                      1: 0
                        2       LOAD_CONST                      2: ('unpack',)
                        4       IMPORT_NAME                     0: struct
                        6       IMPORT_FROM                     1: unpack
                        8       STORE_FAST                      2: unpack
                        10      POP_TOP                         
                        12      LOAD_GLOBAL                     2: getattr
                        14      LOAD_FAST                       1: fp
                        16      LOAD_CONST                      3: 'name'
                        18      LOAD_CONST                      4: ''
                        20      CALL_FUNCTION                   3
                        22      STORE_FAST                      3: filename
                        24      BUILD_MAP                       0
                        26      DUP_TOP                         
                        28      LOAD_FAST                       0: self
                        30      STORE_ATTR                      3: _catalog
                        32      STORE_FAST                      4: catalog
                        34      LOAD_CONST                      5: <CODE> <lambda>
                        36      LOAD_CONST                      6: 'GNUTranslations._parse.<locals>.<lambda>'
                        38      MAKE_FUNCTION                   0
                        40      LOAD_FAST                       0: self
                        42      STORE_ATTR                      4: plural
                        44      LOAD_FAST                       1: fp
                        46      LOAD_METHOD                     5: read
                        48      CALL_METHOD                     0
                        50      STORE_FAST                      5: buf
                        52      LOAD_GLOBAL                     6: len
                        54      LOAD_FAST                       5: buf
                        56      CALL_FUNCTION                   1
                        58      STORE_FAST                      6: buflen
                        60      LOAD_FAST                       2: unpack
                        62      LOAD_CONST                      7: '<I'
                        64      LOAD_FAST                       5: buf
                        66      LOAD_CONST                      8: None
                        68      LOAD_CONST                      9: 4
                        70      BUILD_SLICE                     2
                        72      BINARY_SUBSCR                   
                        74      CALL_FUNCTION                   2
                        76      LOAD_CONST                      1: 0
                        78      BINARY_SUBSCR                   
                        80      STORE_FAST                      7: magic
                        82      LOAD_FAST                       7: magic
                        84      LOAD_FAST                       0: self
                        86      LOAD_ATTR                       7: LE_MAGIC
                        88      COMPARE_OP                      2 (==)
                        90      POP_JUMP_IF_FALSE               62 (to 124)
                        92      LOAD_FAST                       2: unpack
                        94      LOAD_CONST                      10: '<4I'
                        96      LOAD_FAST                       5: buf
                        98      LOAD_CONST                      9: 4
                        100     LOAD_CONST                      11: 20
                        102     BUILD_SLICE                     2
                        104     BINARY_SUBSCR                   
                        106     CALL_FUNCTION                   2
                        108     UNPACK_SEQUENCE                 4
                        110     STORE_FAST                      8: version
                        112     STORE_FAST                      9: msgcount
                        114     STORE_FAST                      10: masteridx
                        116     STORE_FAST                      11: transidx
                        118     LOAD_CONST                      12: '<II'
                        120     STORE_FAST                      12: ii
                        122     JUMP_FORWARD                    27 (to 178)
                        124     LOAD_FAST                       7: magic
                        126     LOAD_FAST                       0: self
                        128     LOAD_ATTR                       8: BE_MAGIC
                        130     COMPARE_OP                      2 (==)
                        132     POP_JUMP_IF_FALSE               83 (to 166)
                        134     LOAD_FAST                       2: unpack
                        136     LOAD_CONST                      13: '>4I'
                        138     LOAD_FAST                       5: buf
                        140     LOAD_CONST                      9: 4
                        142     LOAD_CONST                      11: 20
                        144     BUILD_SLICE                     2
                        146     BINARY_SUBSCR                   
                        148     CALL_FUNCTION                   2
                        150     UNPACK_SEQUENCE                 4
                        152     STORE_FAST                      8: version
                        154     STORE_FAST                      9: msgcount
                        156     STORE_FAST                      10: masteridx
                        158     STORE_FAST                      11: transidx
                        160     LOAD_CONST                      14: '>II'
                        162     STORE_FAST                      12: ii
                        164     JUMP_FORWARD                    6 (to 178)
                        166     LOAD_GLOBAL                     9: OSError
                        168     LOAD_CONST                      1: 0
                        170     LOAD_CONST                      15: 'Bad magic number'
                        172     LOAD_FAST                       3: filename
                        174     CALL_FUNCTION                   3
                        176     RAISE_VARARGS                   1
                        178     LOAD_FAST                       0: self
                        180     LOAD_METHOD                     10: _get_versions
                        182     LOAD_FAST                       8: version
                        184     CALL_METHOD                     1
                        186     UNPACK_SEQUENCE                 2
                        188     STORE_FAST                      13: major_version
                        190     STORE_FAST                      14: minor_version
                        192     LOAD_FAST                       13: major_version
                        194     LOAD_FAST                       0: self
                        196     LOAD_ATTR                       11: VERSIONS
                        198     CONTAINS_OP                     1 (not in)
                        200     POP_JUMP_IF_FALSE               111 (to 222)
                        202     LOAD_GLOBAL                     9: OSError
                        204     LOAD_CONST                      1: 0
                        206     LOAD_CONST                      16: 'Bad version number '
                        208     LOAD_GLOBAL                     12: str
                        210     LOAD_FAST                       13: major_version
                        212     CALL_FUNCTION                   1
                        214     BINARY_ADD                      
                        216     LOAD_FAST                       3: filename
                        218     CALL_FUNCTION                   3
                        220     RAISE_VARARGS                   1
                        222     LOAD_GLOBAL                     13: range
                        224     LOAD_CONST                      1: 0
                        226     LOAD_FAST                       9: msgcount
                        228     CALL_FUNCTION                   2
                        230     GET_ITER                        
                        232     FOR_ITER                        250 (to 734)
                        234     STORE_FAST                      15: i
                        236     LOAD_FAST                       2: unpack
                        238     LOAD_FAST                       12: ii
                        240     LOAD_FAST                       5: buf
                        242     LOAD_FAST                       10: masteridx
                        244     LOAD_FAST                       10: masteridx
                        246     LOAD_CONST                      17: 8
                        248     BINARY_ADD                      
                        250     BUILD_SLICE                     2
                        252     BINARY_SUBSCR                   
                        254     CALL_FUNCTION                   2
                        256     UNPACK_SEQUENCE                 2
                        258     STORE_FAST                      16: mlen
                        260     STORE_FAST                      17: moff
                        262     LOAD_FAST                       17: moff
                        264     LOAD_FAST                       16: mlen
                        266     BINARY_ADD                      
                        268     STORE_FAST                      18: mend
                        270     LOAD_FAST                       2: unpack
                        272     LOAD_FAST                       12: ii
                        274     LOAD_FAST                       5: buf
                        276     LOAD_FAST                       11: transidx
                        278     LOAD_FAST                       11: transidx
                        280     LOAD_CONST                      17: 8
                        282     BINARY_ADD                      
                        284     BUILD_SLICE                     2
                        286     BINARY_SUBSCR                   
                        288     CALL_FUNCTION                   2
                        290     UNPACK_SEQUENCE                 2
                        292     STORE_FAST                      19: tlen
                        294     STORE_FAST                      20: toff
                        296     LOAD_FAST                       20: toff
                        298     LOAD_FAST                       19: tlen
                        300     BINARY_ADD                      
                        302     STORE_FAST                      21: tend
                        304     LOAD_FAST                       18: mend
                        306     LOAD_FAST                       6: buflen
                        308     COMPARE_OP                      0 (<)
                        310     POP_JUMP_IF_FALSE               173 (to 346)
                        312     LOAD_FAST                       21: tend
                        314     LOAD_FAST                       6: buflen
                        316     COMPARE_OP                      0 (<)
                        318     POP_JUMP_IF_FALSE               173 (to 346)
                        320     LOAD_FAST                       5: buf
                        322     LOAD_FAST                       17: moff
                        324     LOAD_FAST                       18: mend
                        326     BUILD_SLICE                     2
                        328     BINARY_SUBSCR                   
                        330     STORE_FAST                      22: msg
                        332     LOAD_FAST                       5: buf
                        334     LOAD_FAST                       20: toff
                        336     LOAD_FAST                       21: tend
                        338     BUILD_SLICE                     2
                        340     BINARY_SUBSCR                   
                        342     STORE_FAST                      23: tmsg
                        344     JUMP_FORWARD                    6 (to 358)
                        346     LOAD_GLOBAL                     9: OSError
                        348     LOAD_CONST                      1: 0
                        350     LOAD_CONST                      18: 'File is corrupt'
                        352     LOAD_FAST                       3: filename
                        354     CALL_FUNCTION                   3
                        356     RAISE_VARARGS                   1
                        358     LOAD_FAST                       16: mlen
                        360     LOAD_CONST                      1: 0
                        362     COMPARE_OP                      2 (==)
                        364     POP_JUMP_IF_FALSE               300 (to 600)
                        368     LOAD_CONST                      8: None
                        370     STORE_FAST                      24: lastk
                        372     LOAD_FAST                       23: tmsg
                        374     LOAD_METHOD                     14: split
                        376     LOAD_CONST                      19: b'\n'
                        378     CALL_METHOD                     1
                        380     GET_ITER                        
                        382     FOR_ITER                        108 (to 600)
                        384     STORE_FAST                      25: b_item
                        386     LOAD_FAST                       25: b_item
                        388     LOAD_METHOD                     15: decode
                        390     CALL_METHOD                     0
                        392     LOAD_METHOD                     16: strip
                        394     CALL_METHOD                     0
                        396     STORE_FAST                      26: item
                        398     LOAD_FAST                       26: item
                        400     POP_JUMP_IF_TRUE                202 (to 404)
                        402     JUMP_ABSOLUTE                   191 (to 382)
                        404     LOAD_FAST                       26: item
                        406     LOAD_METHOD                     17: startswith
                        408     LOAD_CONST                      20: '#-#-#-#-#'
                        410     CALL_METHOD                     1
                        412     POP_JUMP_IF_FALSE               213 (to 426)
                        414     LOAD_FAST                       26: item
                        416     LOAD_METHOD                     18: endswith
                        418     LOAD_CONST                      20: '#-#-#-#-#'
                        420     CALL_METHOD                     1
                        422     POP_JUMP_IF_FALSE               213 (to 426)
                        424     JUMP_ABSOLUTE                   191 (to 382)
                        426     LOAD_CONST                      8: None
                        428     DUP_TOP                         
                        430     STORE_FAST                      27: k
                        432     STORE_FAST                      28: v
                        434     LOAD_CONST                      21: ':'
                        436     LOAD_FAST                       26: item
                        438     CONTAINS_OP                     0 (in)
                        440     POP_JUMP_IF_FALSE               247 (to 494)
                        442     LOAD_FAST                       26: item
                        444     LOAD_METHOD                     14: split
                        446     LOAD_CONST                      21: ':'
                        448     LOAD_CONST                      22: 1
                        450     CALL_METHOD                     2
                        452     UNPACK_SEQUENCE                 2
                        454     STORE_FAST                      27: k
                        456     STORE_FAST                      28: v
                        458     LOAD_FAST                       27: k
                        460     LOAD_METHOD                     16: strip
                        462     CALL_METHOD                     0
                        464     LOAD_METHOD                     19: lower
                        466     CALL_METHOD                     0
                        468     STORE_FAST                      27: k
                        470     LOAD_FAST                       28: v
                        472     LOAD_METHOD                     16: strip
                        474     CALL_METHOD                     0
                        476     STORE_FAST                      28: v
                        478     LOAD_FAST                       28: v
                        480     LOAD_FAST                       0: self
                        482     LOAD_ATTR                       20: _info
                        484     LOAD_FAST                       27: k
                        486     STORE_SUBSCR                    
                        488     LOAD_FAST                       27: k
                        490     STORE_FAST                      24: lastk
                        492     JUMP_FORWARD                    14 (to 522)
                        494     LOAD_FAST                       24: lastk
                        496     POP_JUMP_IF_FALSE               261 (to 522)
                        500     LOAD_FAST                       0: self
                        502     LOAD_ATTR                       20: _info
                        504     LOAD_FAST                       24: lastk
                        506     DUP_TOP_TWO                     
                        508     BINARY_SUBSCR                   
                        510     LOAD_CONST                      23: '\n'
                        512     LOAD_FAST                       26: item
                        514     BINARY_ADD                      
                        516     INPLACE_ADD                     
                        518     ROT_THREE                       
                        520     STORE_SUBSCR                    
                        522     LOAD_FAST                       27: k
                        524     LOAD_CONST                      24: 'content-type'
                        526     COMPARE_OP                      2 (==)
                        528     POP_JUMP_IF_FALSE               275 (to 550)
                        532     LOAD_FAST                       28: v
                        534     LOAD_METHOD                     14: split
                        536     LOAD_CONST                      25: 'charset='
                        538     CALL_METHOD                     1
                        540     LOAD_CONST                      22: 1
                        542     BINARY_SUBSCR                   
                        544     LOAD_FAST                       0: self
                        546     STORE_ATTR                      21: _charset
                        548     JUMP_ABSOLUTE                   191 (to 382)
                        550     LOAD_FAST                       27: k
                        552     LOAD_CONST                      26: 'plural-forms'
                        554     COMPARE_OP                      2 (==)
                        556     POP_JUMP_IF_FALSE               299 (to 598)
                        560     LOAD_FAST                       28: v
                        562     LOAD_METHOD                     14: split
                        564     LOAD_CONST                      27: ';'
                        566     CALL_METHOD                     1
                        568     STORE_FAST                      28: v
                        570     LOAD_FAST                       28: v
                        572     LOAD_CONST                      22: 1
                        574     BINARY_SUBSCR                   
                        576     LOAD_METHOD                     14: split
                        578     LOAD_CONST                      28: 'plural='
                        580     CALL_METHOD                     1
                        582     LOAD_CONST                      22: 1
                        584     BINARY_SUBSCR                   
                        586     STORE_FAST                      29: plural
                        588     LOAD_GLOBAL                     22: c2py
                        590     LOAD_FAST                       29: plural
                        592     CALL_FUNCTION                   1
                        594     LOAD_FAST                       0: self
                        596     STORE_ATTR                      4: plural
                        598     JUMP_ABSOLUTE                   191 (to 382)
                        600     LOAD_FAST                       0: self
                        602     LOAD_ATTR                       21: _charset
                        604     JUMP_IF_TRUE_OR_POP             305 (to 610)
                        608     LOAD_CONST                      29: 'ascii'
                        610     STORE_FAST                      30: charset
                        612     LOAD_CONST                      30: b'\x00'
                        614     LOAD_FAST                       22: msg
                        616     CONTAINS_OP                     0 (in)
                        618     POP_JUMP_IF_FALSE               348 (to 696)
                        622     LOAD_FAST                       22: msg
                        624     LOAD_METHOD                     14: split
                        626     LOAD_CONST                      30: b'\x00'
                        628     CALL_METHOD                     1
                        630     UNPACK_SEQUENCE                 2
                        632     STORE_FAST                      31: msgid1
                        634     STORE_FAST                      32: msgid2
                        636     LOAD_FAST                       23: tmsg
                        638     LOAD_METHOD                     14: split
                        640     LOAD_CONST                      30: b'\x00'
                        642     CALL_METHOD                     1
                        644     STORE_FAST                      23: tmsg
                        646     LOAD_GLOBAL                     12: str
                        648     LOAD_FAST                       31: msgid1
                        650     LOAD_FAST                       30: charset
                        652     CALL_FUNCTION                   2
                        654     STORE_FAST                      31: msgid1
                        656     LOAD_GLOBAL                     23: enumerate
                        658     LOAD_FAST                       23: tmsg
                        660     CALL_FUNCTION                   1
                        662     GET_ITER                        
                        664     FOR_ITER                        14 (to 694)
                        666     UNPACK_SEQUENCE                 2
                        668     STORE_FAST                      15: i
                        670     STORE_FAST                      33: x
                        672     LOAD_GLOBAL                     12: str
                        674     LOAD_FAST                       33: x
                        676     LOAD_FAST                       30: charset
                        678     CALL_FUNCTION                   2
                        680     LOAD_FAST                       4: catalog
                        682     LOAD_FAST                       31: msgid1
                        684     LOAD_FAST                       15: i
                        686     BUILD_TUPLE                     2
                        688     STORE_SUBSCR                    
                        690     JUMP_ABSOLUTE                   332 (to 664)
                        694     JUMP_FORWARD                    10 (to 716)
                        696     LOAD_GLOBAL                     12: str
                        698     LOAD_FAST                       23: tmsg
                        700     LOAD_FAST                       30: charset
                        702     CALL_FUNCTION                   2
                        704     LOAD_FAST                       4: catalog
                        706     LOAD_GLOBAL                     12: str
                        708     LOAD_FAST                       22: msg
                        710     LOAD_FAST                       30: charset
                        712     CALL_FUNCTION                   2
                        714     STORE_SUBSCR                    
                        716     LOAD_FAST                       10: masteridx
                        718     LOAD_CONST                      17: 8
                        720     INPLACE_ADD                     
                        722     STORE_FAST                      10: masteridx
                        724     LOAD_FAST                       11: transidx
                        726     LOAD_CONST                      17: 8
                        728     INPLACE_ADD                     
                        730     STORE_FAST                      11: transidx
                        732     JUMP_ABSOLUTE                   116 (to 232)
                        734     LOAD_CONST                      8: None
                        736     RETURN_VALUE                    
                'GNUTranslations._parse'
                [Code]
                    File Name: gettext.py
                    Object Name: lgettext
                    Arg Count: 2
                    Pos Only Arg Count: 0
                    KW Only Arg Count: 0
                    Locals: 6
                    Stack Size: 5
                    Flags: 0x00000043 (CO_OPTIMIZED | CO_NEWLOCALS | CO_NOFREE)
                    [Names]
                        'warnings'
                        'warn'
                        'DeprecationWarning'
                        'locale'
                        'object'
                        '_catalog'
                        'get'
                        '_fallback'
                        'lgettext'
                        '_output_charset'
                        'encode'
                        'getpreferredencoding'
                    [Var Names]
                        'self'
                        'message'
                        'warnings'
                        'locale'
                        'missing'
                        'tmsg'
                    [Free Vars]
                    [Cell Vars]
                    [Constants]
                        None
                        0
                        'lgettext() is deprecated, use gettext() instead'
                        2
                    [Disassembly]
                        0       LOAD_CONST                      1: 0
                        2       LOAD_CONST                      0: None
                        4       IMPORT_NAME                     0: warnings
                        6       STORE_FAST                      2: warnings
                        8       LOAD_FAST                       2: warnings
                        10      LOAD_METHOD                     1: warn
                        12      LOAD_CONST                      2: 'lgettext() is deprecated, use gettext() instead'
                        14      LOAD_GLOBAL                     2: DeprecationWarning
                        16      LOAD_CONST                      3: 2
                        18      CALL_METHOD                     3
                        20      POP_TOP                         
                        22      LOAD_CONST                      1: 0
                        24      LOAD_CONST                      0: None
                        26      IMPORT_NAME                     3: locale
                        28      STORE_FAST                      3: locale
                        30      LOAD_GLOBAL                     4: object
                        32      CALL_FUNCTION                   0
                        34      STORE_FAST                      4: missing
                        36      LOAD_FAST                       0: self
                        38      LOAD_ATTR                       5: _catalog
                        40      LOAD_METHOD                     6: get
                        42      LOAD_FAST                       1: message
                        44      LOAD_FAST                       4: missing
                        46      CALL_METHOD                     2
                        48      STORE_FAST                      5: tmsg
                        50      LOAD_FAST                       5: tmsg
                        52      LOAD_FAST                       4: missing
                        54      IS_OP                           0 (is)
                        56      POP_JUMP_IF_FALSE               40 (to 80)
                        58      LOAD_FAST                       0: self
                        60      LOAD_ATTR                       7: _fallback
                        62      POP_JUMP_IF_FALSE               38 (to 76)
                        64      LOAD_FAST                       0: self
                        66      LOAD_ATTR                       7: _fallback
                        68      LOAD_METHOD                     8: lgettext
                        70      LOAD_FAST                       1: message
                        72      CALL_METHOD                     1
                        74      RETURN_VALUE                    
                        76      LOAD_FAST                       1: message
                        78      STORE_FAST                      5: tmsg
                        80      LOAD_FAST                       0: self
                        82      LOAD_ATTR                       9: _output_charset
                        84      POP_JUMP_IF_FALSE               49 (to 98)
                        86      LOAD_FAST                       5: tmsg
                        88      LOAD_METHOD                     10: encode
                        90      LOAD_FAST                       0: self
                        92      LOAD_ATTR                       9: _output_charset
                        94      CALL_METHOD                     1
                        96      RETURN_VALUE                    
                        98      LOAD_FAST                       5: tmsg
                        100     LOAD_METHOD                     10: encode
                        102     LOAD_FAST                       3: locale
                        104     LOAD_METHOD                     11: getpreferredencoding
                        106     CALL_METHOD                     0
                        108     CALL_METHOD                     1
                        110     RETURN_VALUE                    
                'GNUTranslations.lgettext'
                [Code]
                    File Name: gettext.py
                    Object Name: lngettext
                    Arg Count: 4
                    Pos Only Arg Count: 0
                    KW Only Arg Count: 0
                    Locals: 7
                    Stack Size: 8
                    Flags: 0x00000043 (CO_OPTIMIZED | CO_NEWLOCALS | CO_NOFREE)
                    [Names]
                        'warnings'
                        'warn'
                        'DeprecationWarning'
                        'locale'
                        '_catalog'
                        'plural'
                        'KeyError'
                        '_fallback'
                        'lngettext'
                        '_output_charset'
                        'encode'
                        'getpreferredencoding'
                    [Var Names]
                        'self'
                        'msgid1'
                        'msgid2'
                        'n'
                        'warnings'
                        'locale'
                        'tmsg'
                    [Free Vars]
                    [Cell Vars]
                    [Constants]
                        None
                        0
                        'lngettext() is deprecated, use ngettext() instead'
                        2
                        1
                    [Disassembly]
                        0       LOAD_CONST                      1: 0
                        2       LOAD_CONST                      0: None
                        4       IMPORT_NAME                     0: warnings
                        6       STORE_FAST                      4: warnings
                        8       LOAD_FAST                       4: warnings
                        10      LOAD_METHOD                     1: warn
                        12      LOAD_CONST                      2: 'lngettext() is deprecated, use ngettext() instead'
                        14      LOAD_GLOBAL                     2: DeprecationWarning
                        16      LOAD_CONST                      3: 2
                        18      CALL_METHOD                     3
                        20      POP_TOP                         
                        22      LOAD_CONST                      1: 0
                        24      LOAD_CONST                      0: None
                        26      IMPORT_NAME                     3: locale
                        28      STORE_FAST                      5: locale
                        30      SETUP_FINALLY                   12 (to 56)
                        32      LOAD_FAST                       0: self
                        34      LOAD_ATTR                       4: _catalog
                        36      LOAD_FAST                       1: msgid1
                        38      LOAD_FAST                       0: self
                        40      LOAD_METHOD                     5: plural
                        42      LOAD_FAST                       3: n
                        44      CALL_METHOD                     1
                        46      BUILD_TUPLE                     2
                        48      BINARY_SUBSCR                   
                        50      STORE_FAST                      6: tmsg
                        52      POP_BLOCK                       
                        54      JUMP_FORWARD                    31 (to 118)
                        56      DUP_TOP                         
                        58      LOAD_GLOBAL                     6: KeyError
                        60      JUMP_IF_NOT_EXC_MATCH           58 (to 116)
                        62      POP_TOP                         
                        64      POP_TOP                         
                        66      POP_TOP                         
                        68      LOAD_FAST                       0: self
                        70      LOAD_ATTR                       7: _fallback
                        72      POP_JUMP_IF_FALSE               47 (to 94)
                        74      LOAD_FAST                       0: self
                        76      LOAD_ATTR                       7: _fallback
                        78      LOAD_METHOD                     8: lngettext
                        80      LOAD_FAST                       1: msgid1
                        82      LOAD_FAST                       2: msgid2
                        84      LOAD_FAST                       3: n
                        86      CALL_METHOD                     3
                        88      ROT_FOUR                        
                        90      POP_EXCEPT                      
                        92      RETURN_VALUE                    
                        94      LOAD_FAST                       3: n
                        96      LOAD_CONST                      4: 1
                        98      COMPARE_OP                      2 (==)
                        100     POP_JUMP_IF_FALSE               54 (to 108)
                        102     LOAD_FAST                       1: msgid1
                        104     STORE_FAST                      6: tmsg
                        106     JUMP_FORWARD                    2 (to 112)
                        108     LOAD_FAST                       2: msgid2
                        110     STORE_FAST                      6: tmsg
                        112     POP_EXCEPT                      
                        114     JUMP_FORWARD                    1 (to 118)
                        116     RERAISE                         0
                        118     LOAD_FAST                       0: self
                        120     LOAD_ATTR                       9: _output_charset
                        122     POP_JUMP_IF_FALSE               68 (to 136)
                        124     LOAD_FAST                       6: tmsg
                        126     LOAD_METHOD                     10: encode
                        128     LOAD_FAST                       0: self
                        130     LOAD_ATTR                       9: _output_charset
                        132     CALL_METHOD                     1
                        134     RETURN_VALUE                    
                        136     LOAD_FAST                       6: tmsg
                        138     LOAD_METHOD                     10: encode
                        140     LOAD_FAST                       5: locale
                        142     LOAD_METHOD                     11: getpreferredencoding
                        144     CALL_METHOD                     0
                        146     CALL_METHOD                     1
                        148     RETURN_VALUE                    
                'GNUTranslations.lngettext'
                [Code]
                    File Name: gettext.py
                    Object Name: gettext
                    Arg Count: 2
                    Pos Only Arg Count: 0
                    KW Only Arg Count: 0
                    Locals: 4
                    Stack Size: 4
                    Flags: 0x00000043 (CO_OPTIMIZED | CO_NEWLOCALS | CO_NOFREE)
                    [Names]
                        'object'
                        '_catalog'
                        'get'
                        '_fallback'
                        'gettext'
                    [Var Names]
                        'self'
                        'message'
                        'missing'
                        'tmsg'
                    [Free Vars]
                    [Cell Vars]
                    [Constants]
                        None
                    [Disassembly]
                        0       LOAD_GLOBAL                     0: object
                        2       CALL_FUNCTION                   0
                        4       STORE_FAST                      2: missing
                        6       LOAD_FAST                       0: self
                        8       LOAD_ATTR                       1: _catalog
                        10      LOAD_METHOD                     2: get
                        12      LOAD_FAST                       1: message
                        14      LOAD_FAST                       2: missing
                        16      CALL_METHOD                     2
                        18      STORE_FAST                      3: tmsg
                        20      LOAD_FAST                       3: tmsg
                        22      LOAD_FAST                       2: missing
                        24      IS_OP                           0 (is)
                        26      POP_JUMP_IF_FALSE               25 (to 50)
                        28      LOAD_FAST                       0: self
                        30      LOAD_ATTR                       3: _fallback
                        32      POP_JUMP_IF_FALSE               23 (to 46)
                        34      LOAD_FAST                       0: self
                        36      LOAD_ATTR                       3: _fallback
                        38      LOAD_METHOD                     4: gettext
                        40      LOAD_FAST                       1: message
                        42      CALL_METHOD                     1
                        44      RETURN_VALUE                    
                        46      LOAD_FAST                       1: message
                        48      RETURN_VALUE                    
                        50      LOAD_FAST                       3: tmsg
                        52      RETURN_VALUE                    
                'GNUTranslations.gettext'
                [Code]
                    File Name: gettext.py
                    Object Name: ngettext
                    Arg Count: 4
                    Pos Only Arg Count: 0
                    KW Only Arg Count: 0
                    Locals: 5
                    Stack Size: 8
                    Flags: 0x00000043 (CO_OPTIMIZED | CO_NEWLOCALS | CO_NOFREE)
                    [Names]
                        '_catalog'
                        'plural'
                        'KeyError'
                        '_fallback'
                        'ngettext'
                    [Var Names]
                        'self'
                        'msgid1'
                        'msgid2'
                        'n'
                        'tmsg'
                    [Free Vars]
                    [Cell Vars]
                    [Constants]
                        None
                        1
                    [Disassembly]
                        0       SETUP_FINALLY                   13 (to 28)
                        2       LOAD_FAST                       0: self
                        4       LOAD_ATTR                       0: _catalog
                        6       LOAD_FAST                       1: msgid1
                        8       LOAD_FAST                       0: self
                        10      LOAD_METHOD                     1: plural
                        12      LOAD_FAST                       3: n
                        14      CALL_METHOD                     1
                        16      BUILD_TUPLE                     2
                        18      BINARY_SUBSCR                   
                        20      STORE_FAST                      4: tmsg
                        22      POP_BLOCK                       
                        24      LOAD_FAST                       4: tmsg
                        26      RETURN_VALUE                    
                        28      DUP_TOP                         
                        30      LOAD_GLOBAL                     2: KeyError
                        32      JUMP_IF_NOT_EXC_MATCH           47 (to 94)
                        34      POP_TOP                         
                        36      POP_TOP                         
                        38      POP_TOP                         
                        40      LOAD_FAST                       0: self
                        42      LOAD_ATTR                       3: _fallback
                        44      POP_JUMP_IF_FALSE               33 (to 66)
                        46      LOAD_FAST                       0: self
                        48      LOAD_ATTR                       3: _fallback
                        50      LOAD_METHOD                     4: ngettext
                        52      LOAD_FAST                       1: msgid1
                        54      LOAD_FAST                       2: msgid2
                        56      LOAD_FAST                       3: n
                        58      CALL_METHOD                     3
                        60      ROT_FOUR                        
                        62      POP_EXCEPT                      
                        64      RETURN_VALUE                    
                        66      LOAD_FAST                       3: n
                        68      LOAD_CONST                      1: 1
                        70      COMPARE_OP                      2 (==)
                        72      POP_JUMP_IF_FALSE               42 (to 84)
                        74      LOAD_FAST                       1: msgid1
                        76      STORE_FAST                      4: tmsg
                        78      POP_EXCEPT                      
                        80      LOAD_FAST                       4: tmsg
                        82      RETURN_VALUE                    
                        84      LOAD_FAST                       2: msgid2
                        86      STORE_FAST                      4: tmsg
                        88      POP_EXCEPT                      
                        90      LOAD_FAST                       4: tmsg
                        92      RETURN_VALUE                    
                        94      RERAISE                         0
                'GNUTranslations.ngettext'
                [Code]
                    File Name: gettext.py
                    Object Name: pgettext
                    Arg Count: 3
                    Pos Only Arg Count: 0
                    KW Only Arg Count: 0
                    Locals: 6
                    Stack Size: 4
                    Flags: 0x00000043 (CO_OPTIMIZED | CO_NEWLOCALS | CO_NOFREE)
                    [Names]
                        'CONTEXT'
                        'object'
                        '_catalog'
                        'get'
                        '_fallback'
                        'pgettext'
                    [Var Names]
                        'self'
                        'context'
                        'message'
                        'ctxt_msg_id'
                        'missing'
                        'tmsg'
                    [Free Vars]
                    [Cell Vars]
                    [Constants]
                        None
                    [Disassembly]
                        0       LOAD_FAST                       0: self
                        2       LOAD_ATTR                       0: CONTEXT
                        4       LOAD_FAST                       1: context
                        6       LOAD_FAST                       2: message
                        8       BUILD_TUPLE                     2
                        10      BINARY_MODULO                   
                        12      STORE_FAST                      3: ctxt_msg_id
                        14      LOAD_GLOBAL                     1: object
                        16      CALL_FUNCTION                   0
                        18      STORE_FAST                      4: missing
                        20      LOAD_FAST                       0: self
                        22      LOAD_ATTR                       2: _catalog
                        24      LOAD_METHOD                     3: get
                        26      LOAD_FAST                       3: ctxt_msg_id
                        28      LOAD_FAST                       4: missing
                        30      CALL_METHOD                     2
                        32      STORE_FAST                      5: tmsg
                        34      LOAD_FAST                       5: tmsg
                        36      LOAD_FAST                       4: missing
                        38      IS_OP                           0 (is)
                        40      POP_JUMP_IF_FALSE               33 (to 66)
                        42      LOAD_FAST                       0: self
                        44      LOAD_ATTR                       4: _fallback
                        46      POP_JUMP_IF_FALSE               31 (to 62)
                        48      LOAD_FAST                       0: self
                        50      LOAD_ATTR                       4: _fallback
                        52      LOAD_METHOD                     5: pgettext
                        54      LOAD_FAST                       1: context
                        56      LOAD_FAST                       2: message
                        58      CALL_METHOD                     2
                        60      RETURN_VALUE                    
                        62      LOAD_FAST                       2: message
                        64      RETURN_VALUE                    
                        66      LOAD_FAST                       5: tmsg
                        68      RETURN_VALUE                    
                'GNUTranslations.pgettext'
                [Code]
                    File Name: gettext.py
                    Object Name: npgettext
                    Arg Count: 5
                    Pos Only Arg Count: 0
                    KW Only Arg Count: 0
                    Locals: 7
                    Stack Size: 9
                    Flags: 0x00000043 (CO_OPTIMIZED | CO_NEWLOCALS | CO_NOFREE)
                    [Names]
                        'CONTEXT'
                        '_catalog'
                        'plural'
                        'KeyError'
                        '_fallback'
                        'npgettext'
                    [Var Names]
                        'self'
                        'context'
                        'msgid1'
                        'msgid2'
                        'n'
                        'ctxt_msg_id'
                        'tmsg'
                    [Free Vars]
                    [Cell Vars]
                    [Constants]
                        None
                        1
                    [Disassembly]
                        0       LOAD_FAST                       0: self
                        2       LOAD_ATTR                       0: CONTEXT
                        4       LOAD_FAST                       1: context
                        6       LOAD_FAST                       2: msgid1
                        8       BUILD_TUPLE                     2
                        10      BINARY_MODULO                   
                        12      STORE_FAST                      5: ctxt_msg_id
                        14      SETUP_FINALLY                   13 (to 42)
                        16      LOAD_FAST                       0: self
                        18      LOAD_ATTR                       1: _catalog
                        20      LOAD_FAST                       5: ctxt_msg_id
                        22      LOAD_FAST                       0: self
                        24      LOAD_METHOD                     2: plural
                        26      LOAD_FAST                       4: n
                        28      CALL_METHOD                     1
                        30      BUILD_TUPLE                     2
                        32      BINARY_SUBSCR                   
                        34      STORE_FAST                      6: tmsg
                        36      POP_BLOCK                       
                        38      LOAD_FAST                       6: tmsg
                        40      RETURN_VALUE                    
                        42      DUP_TOP                         
                        44      LOAD_GLOBAL                     3: KeyError
                        46      JUMP_IF_NOT_EXC_MATCH           55 (to 110)
                        48      POP_TOP                         
                        50      POP_TOP                         
                        52      POP_TOP                         
                        54      LOAD_FAST                       0: self
                        56      LOAD_ATTR                       4: _fallback
                        58      POP_JUMP_IF_FALSE               41 (to 82)
                        60      LOAD_FAST                       0: self
                        62      LOAD_ATTR                       4: _fallback
                        64      LOAD_METHOD                     5: npgettext
                        66      LOAD_FAST                       1: context
                        68      LOAD_FAST                       2: msgid1
                        70      LOAD_FAST                       3: msgid2
                        72      LOAD_FAST                       4: n
                        74      CALL_METHOD                     4
                        76      ROT_FOUR                        
                        78      POP_EXCEPT                      
                        80      RETURN_VALUE                    
                        82      LOAD_FAST                       4: n
                        84      LOAD_CONST                      1: 1
                        86      COMPARE_OP                      2 (==)
                        88      POP_JUMP_IF_FALSE               50 (to 100)
                        90      LOAD_FAST                       2: msgid1
                        92      STORE_FAST                      6: tmsg
                        94      POP_EXCEPT                      
                        96      LOAD_FAST                       6: tmsg
                        98      RETURN_VALUE                    
                        100     LOAD_FAST                       3: msgid2
                        102     STORE_FAST                      6: tmsg
                        104     POP_EXCEPT                      
                        106     LOAD_FAST                       6: tmsg
                        108     RETURN_VALUE                    
                        110     RERAISE                         0
                'GNUTranslations.npgettext'
                None
            [Disassembly]
                0       LOAD_NAME                       0: __name__
                2       STORE_NAME                      1: __module__
                4       LOAD_CONST                      0: 'GNUTranslations'
                6       STORE_NAME                      2: __qualname__
                8       LOAD_CONST                      1: 0x950412DE
                10      STORE_NAME                      3: LE_MAGIC
                12      LOAD_CONST                      2: 0xDE120495
                14      STORE_NAME                      4: BE_MAGIC
                16      LOAD_CONST                      3: '%s\x04%s'
                18      STORE_NAME                      5: CONTEXT
                20      LOAD_CONST                      4: (0, 1)
                22      STORE_NAME                      6: VERSIONS
                24      LOAD_CONST                      5: <CODE> _get_versions
                26      LOAD_CONST                      6: 'GNUTranslations._get_versions'
                28      MAKE_FUNCTION                   0
                30      STORE_NAME                      7: _get_versions
                32      LOAD_CONST                      7: <CODE> _parse
                34      LOAD_CONST                      8: 'GNUTranslations._parse'
                36      MAKE_FUNCTION                   0
                38      STORE_NAME                      8: _parse
                40      LOAD_CONST                      9: <CODE> lgettext
                42      LOAD_CONST                      10: 'GNUTranslations.lgettext'
                44      MAKE_FUNCTION                   0
                46      STORE_NAME                      9: lgettext
                48      LOAD_CONST                      11: <CODE> lngettext
                50      LOAD_CONST                      12: 'GNUTranslations.lngettext'
                52      MAKE_FUNCTION                   0
                54      STORE_NAME                      10: lngettext
                56      LOAD_CONST                      13: <CODE> gettext
                58      LOAD_CONST                      14: 'GNUTranslations.gettext'
                60      MAKE_FUNCTION                   0
                62      STORE_NAME                      11: gettext
                64      LOAD_CONST                      15: <CODE> ngettext
                66      LOAD_CONST                      16: 'GNUTranslations.ngettext'
                68      MAKE_FUNCTION                   0
                70      STORE_NAME                      12: ngettext
                72      LOAD_CONST                      17: <CODE> pgettext
                74      LOAD_CONST                      18: 'GNUTranslations.pgettext'
                76      MAKE_FUNCTION                   0
                78      STORE_NAME                      13: pgettext
                80      LOAD_CONST                      19: <CODE> npgettext
                82      LOAD_CONST                      20: 'GNUTranslations.npgettext'
                84      MAKE_FUNCTION                   0
                86      STORE_NAME                      14: npgettext
                88      LOAD_CONST                      21: None
                90      RETURN_VALUE                    
        'GNUTranslations'
        False
        [Code]
            File Name: gettext.py
            Object Name: find
            Arg Count: 4
            Pos Only Arg Count: 0
            KW Only Arg Count: 0
            Locals: 12
            Stack Size: 8
            Flags: 0x00000043 (CO_OPTIMIZED | CO_NEWLOCALS | CO_NOFREE)
            [Names]
                '_default_localedir'
                'os'
                'environ'
                'get'
                'split'
                'append'
                '_expand_lang'
                'path'
                'join'
                'exists'
            [Var Names]
                'domain'
                'localedir'
                'languages'
                'all'
                'envar'
                'val'
                'nelangs'
                'lang'
                'nelang'
                'result'
                'mofile'
                'mofile_lp'
            [Free Vars]
            [Cell Vars]
            [Constants]
                None
                (
                    'LANGUAGE'
                    'LC_ALL'
                    'LC_MESSAGES'
                    'LANG'
                )
                ':'
                'C'
                'LC_MESSAGES'
                '%s.mo'
                '/usr/share/locale-langpack'
            [Disassembly]
                0       LOAD_FAST                       1: localedir
                2       LOAD_CONST                      0: None
                4       IS_OP                           0 (is)
                6       POP_JUMP_IF_FALSE               6 (to 12)
                8       LOAD_GLOBAL                     0: _default_localedir
                10      STORE_FAST                      1: localedir
                12      LOAD_FAST                       2: languages
                14      LOAD_CONST                      0: None
                16      IS_OP                           0 (is)
                18      POP_JUMP_IF_FALSE               41 (to 82)
                20      BUILD_LIST                      0
                22      STORE_FAST                      2: languages
                24      LOAD_CONST                      1: ('LANGUAGE', 'LC_ALL', 'LC_MESSAGES', 'LANG')
                26      GET_ITER                        
                28      FOR_ITER                        17 (to 64)
                30      STORE_FAST                      4: envar
                32      LOAD_GLOBAL                     1: os
                34      LOAD_ATTR                       2: environ
                36      LOAD_METHOD                     3: get
                38      LOAD_FAST                       4: envar
                40      CALL_METHOD                     1
                42      STORE_FAST                      5: val
                44      LOAD_FAST                       5: val
                46      POP_JUMP_IF_FALSE               31 (to 62)
                48      LOAD_FAST                       5: val
                50      LOAD_METHOD                     4: split
                52      LOAD_CONST                      2: ':'
                54      CALL_METHOD                     1
                56      STORE_FAST                      2: languages
                58      POP_TOP                         
                60      JUMP_FORWARD                    1 (to 64)
                62      JUMP_ABSOLUTE                   14 (to 28)
                64      LOAD_CONST                      3: 'C'
                66      LOAD_FAST                       2: languages
                68      CONTAINS_OP                     1 (not in)
                70      POP_JUMP_IF_FALSE               41 (to 82)
                72      LOAD_FAST                       2: languages
                74      LOAD_METHOD                     5: append
                76      LOAD_CONST                      3: 'C'
                78      CALL_METHOD                     1
                80      POP_TOP                         
                82      BUILD_LIST                      0
                84      STORE_FAST                      6: nelangs
                86      LOAD_FAST                       2: languages
                88      GET_ITER                        
                90      FOR_ITER                        18 (to 128)
                92      STORE_FAST                      7: lang
                94      LOAD_GLOBAL                     6: _expand_lang
                96      LOAD_FAST                       7: lang
                98      CALL_FUNCTION                   1
                100     GET_ITER                        
                102     FOR_ITER                        11 (to 126)
                104     STORE_FAST                      8: nelang
                106     LOAD_FAST                       8: nelang
                108     LOAD_FAST                       6: nelangs
                110     CONTAINS_OP                     1 (not in)
                112     POP_JUMP_IF_FALSE               62 (to 124)
                114     LOAD_FAST                       6: nelangs
                116     LOAD_METHOD                     5: append
                118     LOAD_FAST                       8: nelang
                120     CALL_METHOD                     1
                122     POP_TOP                         
                124     JUMP_ABSOLUTE                   51 (to 102)
                126     JUMP_ABSOLUTE                   45 (to 90)
                128     LOAD_FAST                       3: all
                130     POP_JUMP_IF_FALSE               69 (to 138)
                132     BUILD_LIST                      0
                134     STORE_FAST                      9: result
                136     JUMP_FORWARD                    2 (to 142)
                138     LOAD_CONST                      0: None
                140     STORE_FAST                      9: result
                142     LOAD_FAST                       6: nelangs
                144     GET_ITER                        
                146     FOR_ITER                        67 (to 282)
                148     STORE_FAST                      7: lang
                150     LOAD_FAST                       7: lang
                152     LOAD_CONST                      3: 'C'
                154     COMPARE_OP                      2 (==)
                156     POP_JUMP_IF_FALSE               82 (to 164)
                158     POP_TOP                         
                160     LOAD_FAST                       9: result
                162     RETURN_VALUE                    
                164     LOAD_GLOBAL                     1: os
                166     LOAD_ATTR                       7: path
                168     LOAD_METHOD                     8: join
                170     LOAD_FAST                       1: localedir
                172     LOAD_FAST                       7: lang
                174     LOAD_CONST                      4: 'LC_MESSAGES'
                176     LOAD_CONST                      5: '%s.mo'
                178     LOAD_FAST                       0: domain
                180     BINARY_MODULO                   
                182     CALL_METHOD                     4
                184     STORE_FAST                      10: mofile
                186     LOAD_GLOBAL                     1: os
                188     LOAD_ATTR                       7: path
                190     LOAD_METHOD                     8: join
                192     LOAD_CONST                      6: '/usr/share/locale-langpack'
                194     LOAD_FAST                       7: lang
                196     LOAD_CONST                      4: 'LC_MESSAGES'
                198     LOAD_CONST                      5: '%s.mo'
                200     LOAD_FAST                       0: domain
                202     BINARY_MODULO                   
                204     CALL_METHOD                     4
                206     STORE_FAST                      11: mofile_lp
                208     LOAD_GLOBAL                     1: os
                210     LOAD_ATTR                       7: path
                212     LOAD_METHOD                     9: exists
                214     LOAD_FAST                       10: mofile
                216     CALL_METHOD                     1
                218     POP_JUMP_IF_FALSE               122 (to 244)
                220     LOAD_FAST                       3: all
                222     POP_JUMP_IF_FALSE               118 (to 236)
                224     LOAD_FAST                       9: result
                226     LOAD_METHOD                     5: append
                228     LOAD_FAST                       10: mofile
                230     CALL_METHOD                     1
                232     POP_TOP                         
                234     JUMP_FORWARD                    4 (to 244)
                236     LOAD_FAST                       10: mofile
                238     ROT_TWO                         
                240     POP_TOP                         
                242     RETURN_VALUE                    
                244     LOAD_GLOBAL                     1: os
                246     LOAD_ATTR                       7: path
                248     LOAD_METHOD                     9: exists
                250     LOAD_FAST                       11: mofile_lp
                252     CALL_METHOD                     1
                254     POP_JUMP_IF_FALSE               140 (to 280)
                256     LOAD_FAST                       3: all
                258     POP_JUMP_IF_FALSE               136 (to 272)
                260     LOAD_FAST                       9: result
                262     LOAD_METHOD                     5: append
                264     LOAD_FAST                       11: mofile_lp
                266     CALL_METHOD                     1
                268     POP_TOP                         
                270     JUMP_ABSOLUTE                   73 (to 146)
                272     LOAD_FAST                       11: mofile_lp
                274     ROT_TWO                         
                276     POP_TOP                         
                278     RETURN_VALUE                    
                280     JUMP_ABSOLUTE                   73 (to 146)
                282     LOAD_FAST                       9: result
                284     RETURN_VALUE                    
        'find'
        'unspecified'
        [Code]
            File Name: gettext.py
            Object Name: translation
            Arg Count: 6
            Pos Only Arg Count: 0
            KW Only Arg Count: 0
            Locals: 15
            Stack Size: 9
            Flags: 0x00000043 (CO_OPTIMIZED | CO_NEWLOCALS | CO_NOFREE)
            [Names]
                'GNUTranslations'
                'find'
                'NullTranslations'
                'errno'
                'ENOENT'
                'FileNotFoundError'
                'os'
                'path'
                'abspath'
                '_translations'
                'get'
                'open'
                'setdefault'
                'copy'
                '_unspecified'
                'warnings'
                'warn'
                'DeprecationWarning'
                'catch_warnings'
                'filterwarnings'
                'set_output_charset'
                'add_fallback'
            [Var Names]
                'domain'
                'localedir'
                'languages'
                'class_'
                'fallback'
                'codeset'
                'mofiles'
                'ENOENT'
                'result'
                'mofile'
                'key'
                't'
                'fp'
                'copy'
                'warnings'
            [Free Vars]
            [Cell Vars]
            [Constants]
                None
                True
                (
                    'all'
                )
                0
                (
                    'ENOENT'
                )
                'No translation file found for domain'
                'rb'
                'parameter codeset is deprecated'
                2
                'ignore'
                '.*\\bset_output_charset\\b.*'
            [Disassembly]
                0       LOAD_FAST                       3: class_
                2       LOAD_CONST                      0: None
                4       IS_OP                           0 (is)
                6       POP_JUMP_IF_FALSE               6 (to 12)
                8       LOAD_GLOBAL                     0: GNUTranslations
                10      STORE_FAST                      3: class_
                12      LOAD_GLOBAL                     1: find
                14      LOAD_FAST                       0: domain
                16      LOAD_FAST                       1: localedir
                18      LOAD_FAST                       2: languages
                20      LOAD_CONST                      1: True
                22      LOAD_CONST                      2: ('all',)
                24      CALL_FUNCTION_KW                4
                26      STORE_FAST                      6: mofiles
                28      LOAD_FAST                       6: mofiles
                30      POP_JUMP_IF_TRUE                33 (to 66)
                32      LOAD_FAST                       4: fallback
                34      POP_JUMP_IF_FALSE               21 (to 42)
                36      LOAD_GLOBAL                     2: NullTranslations
                38      CALL_FUNCTION                   0
                40      RETURN_VALUE                    
                42      LOAD_CONST                      3: 0
                44      LOAD_CONST                      4: ('ENOENT',)
                46      IMPORT_NAME                     3: errno
                48      IMPORT_FROM                     4: ENOENT
                50      STORE_FAST                      7: ENOENT
                52      POP_TOP                         
                54      LOAD_GLOBAL                     5: FileNotFoundError
                56      LOAD_FAST                       7: ENOENT
                58      LOAD_CONST                      5: 'No translation file found for domain'
                60      LOAD_FAST                       0: domain
                62      CALL_FUNCTION                   3
                64      RAISE_VARARGS                   1
                66      LOAD_CONST                      0: None
                68      STORE_FAST                      8: result
                70      LOAD_FAST                       6: mofiles
                72      GET_ITER                        
                74      FOR_ITER                        118 (to 312)
                76      STORE_FAST                      9: mofile
                78      LOAD_FAST                       3: class_
                80      LOAD_GLOBAL                     6: os
                82      LOAD_ATTR                       7: path
                84      LOAD_METHOD                     8: abspath
                86      LOAD_FAST                       9: mofile
                88      CALL_METHOD                     1
                90      BUILD_TUPLE                     2
                92      STORE_FAST                      10: key
                94      LOAD_GLOBAL                     9: _translations
                96      LOAD_METHOD                     10: get
                98      LOAD_FAST                       10: key
                100     CALL_METHOD                     1
                102     STORE_FAST                      11: t
                104     LOAD_FAST                       11: t
                106     LOAD_CONST                      0: None
                108     IS_OP                           0 (is)
                110     POP_JUMP_IF_FALSE               85 (to 170)
                112     LOAD_GLOBAL                     11: open
                114     LOAD_FAST                       9: mofile
                116     LOAD_CONST                      6: 'rb'
                118     CALL_FUNCTION                   2
                120     SETUP_WITH                      16 (to 154)
                122     STORE_FAST                      12: fp
                124     LOAD_GLOBAL                     9: _translations
                126     LOAD_METHOD                     12: setdefault
                128     LOAD_FAST                       10: key
                130     LOAD_FAST                       3: class_
                132     LOAD_FAST                       12: fp
                134     CALL_FUNCTION                   1
                136     CALL_METHOD                     2
                138     STORE_FAST                      11: t
                140     POP_BLOCK                       
                142     LOAD_CONST                      0: None
                144     DUP_TOP                         
                146     DUP_TOP                         
                148     CALL_FUNCTION                   3
                150     POP_TOP                         
                152     JUMP_FORWARD                    8 (to 170)
                154     WITH_EXCEPT_START               
                156     POP_JUMP_IF_TRUE                80 (to 160)
                158     RERAISE                         1
                160     POP_TOP                         
                162     POP_TOP                         
                164     POP_TOP                         
                166     POP_EXCEPT                      
                168     POP_TOP                         
                170     LOAD_CONST                      3: 0
                172     LOAD_CONST                      0: None
                174     IMPORT_NAME                     13: copy
                176     STORE_FAST                      13: copy
                178     LOAD_FAST                       13: copy
                180     LOAD_METHOD                     13: copy
                182     LOAD_FAST                       11: t
                184     CALL_METHOD                     1
                186     STORE_FAST                      11: t
                188     LOAD_FAST                       5: codeset
                190     LOAD_GLOBAL                     14: _unspecified
                192     IS_OP                           1 (is not)
                194     POP_JUMP_IF_FALSE               143 (to 286)
                196     LOAD_CONST                      3: 0
                198     LOAD_CONST                      0: None
                200     IMPORT_NAME                     15: warnings
                202     STORE_FAST                      14: warnings
                204     LOAD_FAST                       14: warnings
                206     LOAD_METHOD                     16: warn
                208     LOAD_CONST                      7: 'parameter codeset is deprecated'
                210     LOAD_GLOBAL                     17: DeprecationWarning
                212     LOAD_CONST                      8: 2
                214     CALL_METHOD                     3
                216     POP_TOP                         
                218     LOAD_FAST                       5: codeset
                220     POP_JUMP_IF_FALSE               143 (to 286)
                222     LOAD_FAST                       14: warnings
                224     LOAD_METHOD                     18: catch_warnings
                226     CALL_METHOD                     0
                228     SETUP_WITH                      20 (to 270)
                230     POP_TOP                         
                232     LOAD_FAST                       14: warnings
                234     LOAD_METHOD                     19: filterwarnings
                236     LOAD_CONST                      9: 'ignore'
                238     LOAD_CONST                      10: '.*\\bset_output_charset\\b.*'
                240     LOAD_GLOBAL                     17: DeprecationWarning
                242     CALL_METHOD                     3
                244     POP_TOP                         
                246     LOAD_FAST                       11: t
                248     LOAD_METHOD                     20: set_output_charset
                250     LOAD_FAST                       5: codeset
                252     CALL_METHOD                     1
                254     POP_TOP                         
                256     POP_BLOCK                       
                258     LOAD_CONST                      0: None
                260     DUP_TOP                         
                262     DUP_TOP                         
                264     CALL_FUNCTION                   3
                266     POP_TOP                         
                268     JUMP_FORWARD                    8 (to 286)
                270     WITH_EXCEPT_START               
                272     POP_JUMP_IF_TRUE                138 (to 276)
                274     RERAISE                         1
                276     POP_TOP                         
                278     POP_TOP                         
                280     POP_TOP                         
                282     POP_EXCEPT                      
                284     POP_TOP                         
                286     LOAD_FAST                       8: result
                288     LOAD_CONST                      0: None
                290     IS_OP                           0 (is)
                292     POP_JUMP_IF_FALSE               150 (to 300)
                294     LOAD_FAST                       11: t
                296     STORE_FAST                      8: result
                298     JUMP_ABSOLUTE                   37 (to 74)
                300     LOAD_FAST                       8: result
                302     LOAD_METHOD                     21: add_fallback
                304     LOAD_FAST                       11: t
                306     CALL_METHOD                     1
                308     POP_TOP                         
                310     JUMP_ABSOLUTE                   37 (to 74)
                312     LOAD_FAST                       8: result
                314     RETURN_VALUE                    
        'translation'
        [Code]
            File Name: gettext.py
            Object Name: install
            Arg Count: 4
            Pos Only Arg Count: 0
            KW Only Arg Count: 0
            Locals: 5
            Stack Size: 6
            Flags: 0x00000043 (CO_OPTIMIZED | CO_NEWLOCALS | CO_NOFREE)
            [Names]
                'translation'
                'install'
            [Var Names]
                'domain'
                'localedir'
                'codeset'
                'names'
                't'
            [Free Vars]
            [Cell Vars]
            [Constants]
                None
                True
                (
                    'fallback'
                    'codeset'
                )
            [Disassembly]
                0       LOAD_GLOBAL                     0: translation
                2       LOAD_FAST                       0: domain
                4       LOAD_FAST                       1: localedir
                6       LOAD_CONST                      1: True
                8       LOAD_FAST                       2: codeset
                10      LOAD_CONST                      2: ('fallback', 'codeset')
                12      CALL_FUNCTION_KW                4
                14      STORE_FAST                      4: t
                16      LOAD_FAST                       4: t
                18      LOAD_METHOD                     1: install
                20      LOAD_FAST                       3: names
                22      CALL_METHOD                     1
                24      POP_TOP                         
                26      LOAD_CONST                      0: None
                28      RETURN_VALUE                    
        'install'
        'messages'
        [Code]
            File Name: gettext.py
            Object Name: textdomain
            Arg Count: 1
            Pos Only Arg Count: 0
            KW Only Arg Count: 0
            Locals: 1
            Stack Size: 2
            Flags: 0x00000043 (CO_OPTIMIZED | CO_NEWLOCALS | CO_NOFREE)
            [Names]
                '_current_domain'
            [Var Names]
                'domain'
            [Free Vars]
            [Cell Vars]
            [Constants]
                None
            [Disassembly]
                0       LOAD_FAST                       0: domain
                2       LOAD_CONST                      0: None
                4       IS_OP                           1 (is not)
                6       POP_JUMP_IF_FALSE               6 (to 12)
                8       LOAD_FAST                       0: domain
                10      STORE_GLOBAL                    0: _current_domain
                12      LOAD_GLOBAL                     0: _current_domain
                14      RETURN_VALUE                    
        'textdomain'
        [Code]
            File Name: gettext.py
            Object Name: bindtextdomain
            Arg Count: 2
            Pos Only Arg Count: 0
            KW Only Arg Count: 0
            Locals: 2
            Stack Size: 4
            Flags: 0x00000043 (CO_OPTIMIZED | CO_NEWLOCALS | CO_NOFREE)
            [Names]
                '_localedirs'
                'get'
                '_default_localedir'
            [Var Names]
                'domain'
                'localedir'
            [Free Vars]
            [Cell Vars]
            [Constants]
                None
            [Disassembly]
                0       LOAD_FAST                       1: localedir
                2       LOAD_CONST                      0: None
                4       IS_OP                           1 (is not)
                6       POP_JUMP_IF_FALSE               8 (to 16)
                8       LOAD_FAST                       1: localedir
                10      LOAD_GLOBAL                     0: _localedirs
                12      LOAD_FAST                       0: domain
                14      STORE_SUBSCR                    
                16      LOAD_GLOBAL                     0: _localedirs
                18      LOAD_METHOD                     1: get
                20      LOAD_FAST                       0: domain
                22      LOAD_GLOBAL                     2: _default_localedir
                24      CALL_METHOD                     2
                26      RETURN_VALUE                    
        'bindtextdomain'
        [Code]
            File Name: gettext.py
            Object Name: bind_textdomain_codeset
            Arg Count: 2
            Pos Only Arg Count: 0
            KW Only Arg Count: 0
            Locals: 3
            Stack Size: 5
            Flags: 0x00000043 (CO_OPTIMIZED | CO_NEWLOCALS | CO_NOFREE)
            [Names]
                'warnings'
                'warn'
                'DeprecationWarning'
                '_localecodesets'
                'get'
            [Var Names]
                'domain'
                'codeset'
                'warnings'
            [Free Vars]
            [Cell Vars]
            [Constants]
                None
                0
                'bind_textdomain_codeset() is deprecated'
                2
            [Disassembly]
                0       LOAD_CONST                      1: 0
                2       LOAD_CONST                      0: None
                4       IMPORT_NAME                     0: warnings
                6       STORE_FAST                      2: warnings
                8       LOAD_FAST                       2: warnings
                10      LOAD_METHOD                     1: warn
                12      LOAD_CONST                      2: 'bind_textdomain_codeset() is deprecated'
                14      LOAD_GLOBAL                     2: DeprecationWarning
                16      LOAD_CONST                      3: 2
                18      CALL_METHOD                     3
                20      POP_TOP                         
                22      LOAD_FAST                       1: codeset
                24      LOAD_CONST                      0: None
                26      IS_OP                           1 (is not)
                28      POP_JUMP_IF_FALSE               19 (to 38)
                30      LOAD_FAST                       1: codeset
                32      LOAD_GLOBAL                     3: _localecodesets
                34      LOAD_FAST                       0: domain
                36      STORE_SUBSCR                    
                38      LOAD_GLOBAL                     3: _localecodesets
                40      LOAD_METHOD                     4: get
                42      LOAD_FAST                       0: domain
                44      CALL_METHOD                     1
                46      RETURN_VALUE                    
        'bind_textdomain_codeset'
        [Code]
            File Name: gettext.py
            Object Name: dgettext
            Arg Count: 2
            Pos Only Arg Count: 0
            KW Only Arg Count: 0
            Locals: 3
            Stack Size: 8
            Flags: 0x00000043 (CO_OPTIMIZED | CO_NEWLOCALS | CO_NOFREE)
            [Names]
                'translation'
                '_localedirs'
                'get'
                'OSError'
                'gettext'
            [Var Names]
                'domain'
                'message'
                't'
            [Free Vars]
            [Cell Vars]
            [Constants]
                None
            [Disassembly]
                0       SETUP_FINALLY                   11 (to 24)
                2       LOAD_GLOBAL                     0: translation
                4       LOAD_FAST                       0: domain
                6       LOAD_GLOBAL                     1: _localedirs
                8       LOAD_METHOD                     2: get
                10      LOAD_FAST                       0: domain
                12      LOAD_CONST                      0: None
                14      CALL_METHOD                     2
                16      CALL_FUNCTION                   2
                18      STORE_FAST                      2: t
                20      POP_BLOCK                       
                22      JUMP_FORWARD                    11 (to 46)
                24      DUP_TOP                         
                26      LOAD_GLOBAL                     3: OSError
                28      JUMP_IF_NOT_EXC_MATCH           22 (to 44)
                30      POP_TOP                         
                32      POP_TOP                         
                34      POP_TOP                         
                36      LOAD_FAST                       1: message
                38      ROT_FOUR                        
                40      POP_EXCEPT                      
                42      RETURN_VALUE                    
                44      RERAISE                         0
                46      LOAD_FAST                       2: t
                48      LOAD_METHOD                     4: gettext
                50      LOAD_FAST                       1: message
                52      CALL_METHOD                     1
                54      RETURN_VALUE                    
        'dgettext'
        [Code]
            File Name: gettext.py
            Object Name: ldgettext
            Arg Count: 2
            Pos Only Arg Count: 0
            KW Only Arg Count: 0
            Locals: 6
            Stack Size: 8
            Flags: 0x00000043 (CO_OPTIMIZED | CO_NEWLOCALS | CO_NOFREE)
            [Names]
                'warnings'
                'warn'
                'DeprecationWarning'
                'locale'
                '_localecodesets'
                'get'
                'catch_warnings'
                'filterwarnings'
                'translation'
                '_localedirs'
                'OSError'
                'encode'
                'getpreferredencoding'
                'lgettext'
            [Var Names]
                'domain'
                'message'
                'warnings'
                'locale'
                'codeset'
                't'
            [Free Vars]
            [Cell Vars]
            [Constants]
                None
                0
                'ldgettext() is deprecated, use dgettext() instead'
                2
                'ignore'
                '.*\\bparameter codeset\\b.*'
                (
                    'codeset'
                )
                '.*\\blgettext\\b.*'
            [Disassembly]
                0       LOAD_CONST                      1: 0
                2       LOAD_CONST                      0: None
                4       IMPORT_NAME                     0: warnings
                6       STORE_FAST                      2: warnings
                8       LOAD_FAST                       2: warnings
                10      LOAD_METHOD                     1: warn
                12      LOAD_CONST                      2: 'ldgettext() is deprecated, use dgettext() instead'
                14      LOAD_GLOBAL                     2: DeprecationWarning
                16      LOAD_CONST                      3: 2
                18      CALL_METHOD                     3
                20      POP_TOP                         
                22      LOAD_CONST                      1: 0
                24      LOAD_CONST                      0: None
                26      IMPORT_NAME                     3: locale
                28      STORE_FAST                      3: locale
                30      LOAD_GLOBAL                     4: _localecodesets
                32      LOAD_METHOD                     5: get
                34      LOAD_FAST                       0: domain
                36      CALL_METHOD                     1
                38      STORE_FAST                      4: codeset
                40      SETUP_FINALLY                   40 (to 122)
                42      LOAD_FAST                       2: warnings
                44      LOAD_METHOD                     6: catch_warnings
                46      CALL_METHOD                     0
                48      SETUP_WITH                      26 (to 102)
                50      POP_TOP                         
                52      LOAD_FAST                       2: warnings
                54      LOAD_METHOD                     7: filterwarnings
                56      LOAD_CONST                      4: 'ignore'
                58      LOAD_CONST                      5: '.*\\bparameter codeset\\b.*'
                60      LOAD_GLOBAL                     2: DeprecationWarning
                62      CALL_METHOD                     3
                64      POP_TOP                         
                66      LOAD_GLOBAL                     8: translation
                68      LOAD_FAST                       0: domain
                70      LOAD_GLOBAL                     9: _localedirs
                72      LOAD_METHOD                     5: get
                74      LOAD_FAST                       0: domain
                76      LOAD_CONST                      0: None
                78      CALL_METHOD                     2
                80      LOAD_FAST                       4: codeset
                82      LOAD_CONST                      6: ('codeset',)
                84      CALL_FUNCTION_KW                3
                86      STORE_FAST                      5: t
                88      POP_BLOCK                       
                90      LOAD_CONST                      0: None
                92      DUP_TOP                         
                94      DUP_TOP                         
                96      CALL_FUNCTION                   3
                98      POP_TOP                         
                100     JUMP_FORWARD                    8 (to 118)
                102     WITH_EXCEPT_START               
                104     POP_JUMP_IF_TRUE                54 (to 108)
                106     RERAISE                         1
                108     POP_TOP                         
                110     POP_TOP                         
                112     POP_TOP                         
                114     POP_EXCEPT                      
                116     POP_TOP                         
                118     POP_BLOCK                       
                120     JUMP_FORWARD                    18 (to 158)
                122     DUP_TOP                         
                124     LOAD_GLOBAL                     10: OSError
                126     JUMP_IF_NOT_EXC_MATCH           78 (to 156)
                128     POP_TOP                         
                130     POP_TOP                         
                132     POP_TOP                         
                134     LOAD_FAST                       1: message
                136     LOAD_METHOD                     11: encode
                138     LOAD_FAST                       4: codeset
                140     JUMP_IF_TRUE_OR_POP             74 (to 148)
                142     LOAD_FAST                       3: locale
                144     LOAD_METHOD                     12: getpreferredencoding
                146     CALL_METHOD                     0
                148     CALL_METHOD                     1
                150     ROT_FOUR                        
                152     POP_EXCEPT                      
                154     RETURN_VALUE                    
                156     RERAISE                         0
                158     LOAD_FAST                       2: warnings
                160     LOAD_METHOD                     6: catch_warnings
                162     CALL_METHOD                     0
                164     SETUP_WITH                      20 (to 206)
                166     POP_TOP                         
                168     LOAD_FAST                       2: warnings
                170     LOAD_METHOD                     7: filterwarnings
                172     LOAD_CONST                      4: 'ignore'
                174     LOAD_CONST                      7: '.*\\blgettext\\b.*'
                176     LOAD_GLOBAL                     2: DeprecationWarning
                178     CALL_METHOD                     3
                180     POP_TOP                         
                182     LOAD_FAST                       5: t
                184     LOAD_METHOD                     13: lgettext
                186     LOAD_FAST                       1: message
                188     CALL_METHOD                     1
                190     POP_BLOCK                       
                192     ROT_TWO                         
                194     LOAD_CONST                      0: None
                196     DUP_TOP                         
                198     DUP_TOP                         
                200     CALL_FUNCTION                   3
                202     POP_TOP                         
                204     RETURN_VALUE                    
                206     WITH_EXCEPT_START               
                208     POP_JUMP_IF_TRUE                106 (to 212)
                210     RERAISE                         1
                212     POP_TOP                         
                214     POP_TOP                         
                216     POP_TOP                         
                218     POP_EXCEPT                      
                220     POP_TOP                         
                222     LOAD_CONST                      0: None
                224     RETURN_VALUE                    
        'ldgettext'
        [Code]
            File Name: gettext.py
            Object Name: dngettext
            Arg Count: 4
            Pos Only Arg Count: 0
            KW Only Arg Count: 0
            Locals: 5
            Stack Size: 8
            Flags: 0x00000043 (CO_OPTIMIZED | CO_NEWLOCALS | CO_NOFREE)
            [Names]
                'translation'
                '_localedirs'
                'get'
                'OSError'
                'ngettext'
            [Var Names]
                'domain'
                'msgid1'
                'msgid2'
                'n'
                't'
            [Free Vars]
            [Cell Vars]
            [Constants]
                None
                1
            [Disassembly]
                0       SETUP_FINALLY                   11 (to 24)
                2       LOAD_GLOBAL                     0: translation
                4       LOAD_FAST                       0: domain
                6       LOAD_GLOBAL                     1: _localedirs
                8       LOAD_METHOD                     2: get
                10      LOAD_FAST                       0: domain
                12      LOAD_CONST                      0: None
                14      CALL_METHOD                     2
                16      CALL_FUNCTION                   2
                18      STORE_FAST                      4: t
                20      POP_BLOCK                       
                22      JUMP_FORWARD                    19 (to 62)
                24      DUP_TOP                         
                26      LOAD_GLOBAL                     3: OSError
                28      JUMP_IF_NOT_EXC_MATCH           30 (to 60)
                30      POP_TOP                         
                32      POP_TOP                         
                34      POP_TOP                         
                36      LOAD_FAST                       3: n
                38      LOAD_CONST                      1: 1
                40      COMPARE_OP                      2 (==)
                42      POP_JUMP_IF_FALSE               26 (to 52)
                44      LOAD_FAST                       1: msgid1
                46      ROT_FOUR                        
                48      POP_EXCEPT                      
                50      RETURN_VALUE                    
                52      LOAD_FAST                       2: msgid2
                54      ROT_FOUR                        
                56      POP_EXCEPT                      
                58      RETURN_VALUE                    
                60      RERAISE                         0
                62      LOAD_FAST                       4: t
                64      LOAD_METHOD                     4: ngettext
                66      LOAD_FAST                       1: msgid1
                68      LOAD_FAST                       2: msgid2
                70      LOAD_FAST                       3: n
                72      CALL_METHOD                     3
                74      RETURN_VALUE                    
        'dngettext'
        [Code]
            File Name: gettext.py
            Object Name: ldngettext
            Arg Count: 4
            Pos Only Arg Count: 0
            KW Only Arg Count: 0
            Locals: 9
            Stack Size: 8
            Flags: 0x00000043 (CO_OPTIMIZED | CO_NEWLOCALS | CO_NOFREE)
            [Names]
                'warnings'
                'warn'
                'DeprecationWarning'
                'locale'
                '_localecodesets'
                'get'
                'catch_warnings'
                'filterwarnings'
                'translation'
                '_localedirs'
                'OSError'
                'encode'
                'getpreferredencoding'
                'lngettext'
            [Var Names]
                'domain'
                'msgid1'
                'msgid2'
                'n'
                'warnings'
                'locale'
                'codeset'
                't'
                'tmsg'
            [Free Vars]
            [Cell Vars]
            [Constants]
                None
                0
                'ldngettext() is deprecated, use dngettext() instead'
                2
                'ignore'
                '.*\\bparameter codeset\\b.*'
                (
                    'codeset'
                )
                1
                '.*\\blngettext\\b.*'
            [Disassembly]
                0       LOAD_CONST                      1: 0
                2       LOAD_CONST                      0: None
                4       IMPORT_NAME                     0: warnings
                6       STORE_FAST                      4: warnings
                8       LOAD_FAST                       4: warnings
                10      LOAD_METHOD                     1: warn
                12      LOAD_CONST                      2: 'ldngettext() is deprecated, use dngettext() instead'
                14      LOAD_GLOBAL                     2: DeprecationWarning
                16      LOAD_CONST                      3: 2
                18      CALL_METHOD                     3
                20      POP_TOP                         
                22      LOAD_CONST                      1: 0
                24      LOAD_CONST                      0: None
                26      IMPORT_NAME                     3: locale
                28      STORE_FAST                      5: locale
                30      LOAD_GLOBAL                     4: _localecodesets
                32      LOAD_METHOD                     5: get
                34      LOAD_FAST                       0: domain
                36      CALL_METHOD                     1
                38      STORE_FAST                      6: codeset
                40      SETUP_FINALLY                   40 (to 122)
                42      LOAD_FAST                       4: warnings
                44      LOAD_METHOD                     6: catch_warnings
                46      CALL_METHOD                     0
                48      SETUP_WITH                      26 (to 102)
                50      POP_TOP                         
                52      LOAD_FAST                       4: warnings
                54      LOAD_METHOD                     7: filterwarnings
                56      LOAD_CONST                      4: 'ignore'
                58      LOAD_CONST                      5: '.*\\bparameter codeset\\b.*'
                60      LOAD_GLOBAL                     2: DeprecationWarning
                62      CALL_METHOD                     3
                64      POP_TOP                         
                66      LOAD_GLOBAL                     8: translation
                68      LOAD_FAST                       0: domain
                70      LOAD_GLOBAL                     9: _localedirs
                72      LOAD_METHOD                     5: get
                74      LOAD_FAST                       0: domain
                76      LOAD_CONST                      0: None
                78      CALL_METHOD                     2
                80      LOAD_FAST                       6: codeset
                82      LOAD_CONST                      6: ('codeset',)
                84      CALL_FUNCTION_KW                3
                86      STORE_FAST                      7: t
                88      POP_BLOCK                       
                90      LOAD_CONST                      0: None
                92      DUP_TOP                         
                94      DUP_TOP                         
                96      CALL_FUNCTION                   3
                98      POP_TOP                         
                100     JUMP_FORWARD                    8 (to 118)
                102     WITH_EXCEPT_START               
                104     POP_JUMP_IF_TRUE                54 (to 108)
                106     RERAISE                         1
                108     POP_TOP                         
                110     POP_TOP                         
                112     POP_TOP                         
                114     POP_EXCEPT                      
                116     POP_TOP                         
                118     POP_BLOCK                       
                120     JUMP_FORWARD                    27 (to 176)
                122     DUP_TOP                         
                124     LOAD_GLOBAL                     10: OSError
                126     JUMP_IF_NOT_EXC_MATCH           87 (to 174)
                128     POP_TOP                         
                130     POP_TOP                         
                132     POP_TOP                         
                134     LOAD_FAST                       3: n
                136     LOAD_CONST                      7: 1
                138     COMPARE_OP                      2 (==)
                140     POP_JUMP_IF_FALSE               74 (to 148)
                142     LOAD_FAST                       1: msgid1
                144     STORE_FAST                      8: tmsg
                146     JUMP_FORWARD                    2 (to 152)
                148     LOAD_FAST                       2: msgid2
                150     STORE_FAST                      8: tmsg
                152     LOAD_FAST                       8: tmsg
                154     LOAD_METHOD                     11: encode
                156     LOAD_FAST                       6: codeset
                158     JUMP_IF_TRUE_OR_POP             83 (to 166)
                160     LOAD_FAST                       5: locale
                162     LOAD_METHOD                     12: getpreferredencoding
                164     CALL_METHOD                     0
                166     CALL_METHOD                     1
                168     ROT_FOUR                        
                170     POP_EXCEPT                      
                172     RETURN_VALUE                    
                174     RERAISE                         0
                176     LOAD_FAST                       4: warnings
                178     LOAD_METHOD                     6: catch_warnings
                180     CALL_METHOD                     0
                182     SETUP_WITH                      22 (to 228)
                184     POP_TOP                         
                186     LOAD_FAST                       4: warnings
                188     LOAD_METHOD                     7: filterwarnings
                190     LOAD_CONST                      4: 'ignore'
                192     LOAD_CONST                      8: '.*\\blngettext\\b.*'
                194     LOAD_GLOBAL                     2: DeprecationWarning
                196     CALL_METHOD                     3
                198     POP_TOP                         
                200     LOAD_FAST                       7: t
                202     LOAD_METHOD                     13: lngettext
                204     LOAD_FAST                       1: msgid1
                206     LOAD_FAST                       2: msgid2
                208     LOAD_FAST                       3: n
                210     CALL_METHOD                     3
                212     POP_BLOCK                       
                214     ROT_TWO                         
                216     LOAD_CONST                      0: None
                218     DUP_TOP                         
                220     DUP_TOP                         
                222     CALL_FUNCTION                   3
                224     POP_TOP                         
                226     RETURN_VALUE                    
                228     WITH_EXCEPT_START               
                230     POP_JUMP_IF_TRUE                117 (to 234)
                232     RERAISE                         1
                234     POP_TOP                         
                236     POP_TOP                         
                238     POP_TOP                         
                240     POP_EXCEPT                      
                242     POP_TOP                         
                244     LOAD_CONST                      0: None
                246     RETURN_VALUE                    
        'ldngettext'
        [Code]
            File Name: gettext.py
            Object Name: dpgettext
            Arg Count: 3
            Pos Only Arg Count: 0
            KW Only Arg Count: 0
            Locals: 4
            Stack Size: 8
            Flags: 0x00000043 (CO_OPTIMIZED | CO_NEWLOCALS | CO_NOFREE)
            [Names]
                'translation'
                '_localedirs'
                'get'
                'OSError'
                'pgettext'
            [Var Names]
                'domain'
                'context'
                'message'
                't'
            [Free Vars]
            [Cell Vars]
            [Constants]
                None
            [Disassembly]
                0       SETUP_FINALLY                   11 (to 24)
                2       LOAD_GLOBAL                     0: translation
                4       LOAD_FAST                       0: domain
                6       LOAD_GLOBAL                     1: _localedirs
                8       LOAD_METHOD                     2: get
                10      LOAD_FAST                       0: domain
                12      LOAD_CONST                      0: None
                14      CALL_METHOD                     2
                16      CALL_FUNCTION                   2
                18      STORE_FAST                      3: t
                20      POP_BLOCK                       
                22      JUMP_FORWARD                    11 (to 46)
                24      DUP_TOP                         
                26      LOAD_GLOBAL                     3: OSError
                28      JUMP_IF_NOT_EXC_MATCH           22 (to 44)
                30      POP_TOP                         
                32      POP_TOP                         
                34      POP_TOP                         
                36      LOAD_FAST                       2: message
                38      ROT_FOUR                        
                40      POP_EXCEPT                      
                42      RETURN_VALUE                    
                44      RERAISE                         0
                46      LOAD_FAST                       3: t
                48      LOAD_METHOD                     4: pgettext
                50      LOAD_FAST                       1: context
                52      LOAD_FAST                       2: message
                54      CALL_METHOD                     2
                56      RETURN_VALUE                    
        'dpgettext'
        [Code]
            File Name: gettext.py
            Object Name: dnpgettext
            Arg Count: 5
            Pos Only Arg Count: 0
            KW Only Arg Count: 0
            Locals: 6
            Stack Size: 8
            Flags: 0x00000043 (CO_OPTIMIZED | CO_NEWLOCALS | CO_NOFREE)
            [Names]
                'translation'
                '_localedirs'
                'get'
                'OSError'
                'npgettext'
            [Var Names]
                'domain'
                'context'
                'msgid1'
                'msgid2'
                'n'
                't'
            [Free Vars]
            [Cell Vars]
            [Constants]
                None
                1
            [Disassembly]
                0       SETUP_FINALLY                   11 (to 24)
                2       LOAD_GLOBAL                     0: translation
                4       LOAD_FAST                       0: domain
                6       LOAD_GLOBAL                     1: _localedirs
                8       LOAD_METHOD                     2: get
                10      LOAD_FAST                       0: domain
                12      LOAD_CONST                      0: None
                14      CALL_METHOD                     2
                16      CALL_FUNCTION                   2
                18      STORE_FAST                      5: t
                20      POP_BLOCK                       
                22      JUMP_FORWARD                    19 (to 62)
                24      DUP_TOP                         
                26      LOAD_GLOBAL                     3: OSError
                28      JUMP_IF_NOT_EXC_MATCH           30 (to 60)
                30      POP_TOP                         
                32      POP_TOP                         
                34      POP_TOP                         
                36      LOAD_FAST                       4: n
                38      LOAD_CONST                      1: 1
                40      COMPARE_OP                      2 (==)
                42      POP_JUMP_IF_FALSE               26 (to 52)
                44      LOAD_FAST                       2: msgid1
                46      ROT_FOUR                        
                48      POP_EXCEPT                      
                50      RETURN_VALUE                    
                52      LOAD_FAST                       3: msgid2
                54      ROT_FOUR                        
                56      POP_EXCEPT                      
                58      RETURN_VALUE                    
                60      RERAISE                         0
                62      LOAD_FAST                       5: t
                64      LOAD_METHOD                     4: npgettext
                66      LOAD_FAST                       1: context
                68      LOAD_FAST                       2: msgid1
                70      LOAD_FAST                       3: msgid2
                72      LOAD_FAST                       4: n
                74      CALL_METHOD                     4
                76      RETURN_VALUE                    
        'dnpgettext'
        [Code]
            File Name: gettext.py
            Object Name: gettext
            Arg Count: 1
            Pos Only Arg Count: 0
            KW Only Arg Count: 0
            Locals: 1
            Stack Size: 3
            Flags: 0x00000043 (CO_OPTIMIZED | CO_NEWLOCALS | CO_NOFREE)
            [Names]
                'dgettext'
                '_current_domain'
            [Var Names]
                'message'
            [Free Vars]
            [Cell Vars]
            [Constants]
                None
            [Disassembly]
                0       LOAD_GLOBAL                     0: dgettext
                2       LOAD_GLOBAL                     1: _current_domain
                4       LOAD_FAST                       0: message
                6       CALL_FUNCTION                   2
                8       RETURN_VALUE                    
        'gettext'
        [Code]
            File Name: gettext.py
            Object Name: lgettext
            Arg Count: 1
            Pos Only Arg Count: 0
            KW Only Arg Count: 0
            Locals: 2
            Stack Size: 8
            Flags: 0x00000043 (CO_OPTIMIZED | CO_NEWLOCALS | CO_NOFREE)
            [Names]
                'warnings'
                'warn'
                'DeprecationWarning'
                'catch_warnings'
                'filterwarnings'
                'ldgettext'
                '_current_domain'
            [Var Names]
                'message'
                'warnings'
            [Free Vars]
            [Cell Vars]
            [Constants]
                None
                0
                'lgettext() is deprecated, use gettext() instead'
                2
                'ignore'
                '.*\\bldgettext\\b.*'
            [Disassembly]
                0       LOAD_CONST                      1: 0
                2       LOAD_CONST                      0: None
                4       IMPORT_NAME                     0: warnings
                6       STORE_FAST                      1: warnings
                8       LOAD_FAST                       1: warnings
                10      LOAD_METHOD                     1: warn
                12      LOAD_CONST                      2: 'lgettext() is deprecated, use gettext() instead'
                14      LOAD_GLOBAL                     2: DeprecationWarning
                16      LOAD_CONST                      3: 2
                18      CALL_METHOD                     3
                20      POP_TOP                         
                22      LOAD_FAST                       1: warnings
                24      LOAD_METHOD                     3: catch_warnings
                26      CALL_METHOD                     0
                28      SETUP_WITH                      20 (to 70)
                30      POP_TOP                         
                32      LOAD_FAST                       1: warnings
                34      LOAD_METHOD                     4: filterwarnings
                36      LOAD_CONST                      4: 'ignore'
                38      LOAD_CONST                      5: '.*\\bldgettext\\b.*'
                40      LOAD_GLOBAL                     2: DeprecationWarning
                42      CALL_METHOD                     3
                44      POP_TOP                         
                46      LOAD_GLOBAL                     5: ldgettext
                48      LOAD_GLOBAL                     6: _current_domain
                50      LOAD_FAST                       0: message
                52      CALL_FUNCTION                   2
                54      POP_BLOCK                       
                56      ROT_TWO                         
                58      LOAD_CONST                      0: None
                60      DUP_TOP                         
                62      DUP_TOP                         
                64      CALL_FUNCTION                   3
                66      POP_TOP                         
                68      RETURN_VALUE                    
                70      WITH_EXCEPT_START               
                72      POP_JUMP_IF_TRUE                38 (to 76)
                74      RERAISE                         1
                76      POP_TOP                         
                78      POP_TOP                         
                80      POP_TOP                         
                82      POP_EXCEPT                      
                84      POP_TOP                         
                86      LOAD_CONST                      0: None
                88      RETURN_VALUE                    
        'lgettext'
        [Code]
            File Name: gettext.py
            Object Name: ngettext
            Arg Count: 3
            Pos Only Arg Count: 0
            KW Only Arg Count: 0
            Locals: 3
            Stack Size: 5
            Flags: 0x00000043 (CO_OPTIMIZED | CO_NEWLOCALS | CO_NOFREE)
            [Names]
                'dngettext'
                '_current_domain'
            [Var Names]
                'msgid1'
                'msgid2'
                'n'
            [Free Vars]
            [Cell Vars]
            [Constants]
                None
            [Disassembly]
                0       LOAD_GLOBAL                     0: dngettext
                2       LOAD_GLOBAL                     1: _current_domain
                4       LOAD_FAST                       0: msgid1
                6       LOAD_FAST                       1: msgid2
                8       LOAD_FAST                       2: n
                10      CALL_FUNCTION                   4
                12      RETURN_VALUE                    
        'ngettext'
        [Code]
            File Name: gettext.py
            Object Name: lngettext
            Arg Count: 3
            Pos Only Arg Count: 0
            KW Only Arg Count: 0
            Locals: 4
            Stack Size: 8
            Flags: 0x00000043 (CO_OPTIMIZED | CO_NEWLOCALS | CO_NOFREE)
            [Names]
                'warnings'
                'warn'
                'DeprecationWarning'
                'catch_warnings'
                'filterwarnings'
                'ldngettext'
                '_current_domain'
            [Var Names]
                'msgid1'
                'msgid2'
                'n'
                'warnings'
            [Free Vars]
            [Cell Vars]
            [Constants]
                None
                0
                'lngettext() is deprecated, use ngettext() instead'
                2
                'ignore'
                '.*\\bldngettext\\b.*'
            [Disassembly]
                0       LOAD_CONST                      1: 0
                2       LOAD_CONST                      0: None
                4       IMPORT_NAME                     0: warnings
                6       STORE_FAST                      3: warnings
                8       LOAD_FAST                       3: warnings
                10      LOAD_METHOD                     1: warn
                12      LOAD_CONST                      2: 'lngettext() is deprecated, use ngettext() instead'
                14      LOAD_GLOBAL                     2: DeprecationWarning
                16      LOAD_CONST                      3: 2
                18      CALL_METHOD                     3
                20      POP_TOP                         
                22      LOAD_FAST                       3: warnings
                24      LOAD_METHOD                     3: catch_warnings
                26      CALL_METHOD                     0
                28      SETUP_WITH                      22 (to 74)
                30      POP_TOP                         
                32      LOAD_FAST                       3: warnings
                34      LOAD_METHOD                     4: filterwarnings
                36      LOAD_CONST                      4: 'ignore'
                38      LOAD_CONST                      5: '.*\\bldngettext\\b.*'
                40      LOAD_GLOBAL                     2: DeprecationWarning
                42      CALL_METHOD                     3
                44      POP_TOP                         
                46      LOAD_GLOBAL                     5: ldngettext
                48      LOAD_GLOBAL                     6: _current_domain
                50      LOAD_FAST                       0: msgid1
                52      LOAD_FAST                       1: msgid2
                54      LOAD_FAST                       2: n
                56      CALL_FUNCTION                   4
                58      POP_BLOCK                       
                60      ROT_TWO                         
                62      LOAD_CONST                      0: None
                64      DUP_TOP                         
                66      DUP_TOP                         
                68      CALL_FUNCTION                   3
                70      POP_TOP                         
                72      RETURN_VALUE                    
                74      WITH_EXCEPT_START               
                76      POP_JUMP_IF_TRUE                40 (to 80)
                78      RERAISE                         1
                80      POP_TOP                         
                82      POP_TOP                         
                84      POP_TOP                         
                86      POP_EXCEPT                      
                88      POP_TOP                         
                90      LOAD_CONST                      0: None
                92      RETURN_VALUE                    
        'lngettext'
        [Code]
            File Name: gettext.py
            Object Name: pgettext
            Arg Count: 2
            Pos Only Arg Count: 0
            KW Only Arg Count: 0
            Locals: 2
            Stack Size: 4
            Flags: 0x00000043 (CO_OPTIMIZED | CO_NEWLOCALS | CO_NOFREE)
            [Names]
                'dpgettext'
                '_current_domain'
            [Var Names]
                'context'
                'message'
            [Free Vars]
            [Cell Vars]
            [Constants]
                None
            [Disassembly]
                0       LOAD_GLOBAL                     0: dpgettext
                2       LOAD_GLOBAL                     1: _current_domain
                4       LOAD_FAST                       0: context
                6       LOAD_FAST                       1: message
                8       CALL_FUNCTION                   3
                10      RETURN_VALUE                    
        'pgettext'
        [Code]
            File Name: gettext.py
            Object Name: npgettext
            Arg Count: 4
            Pos Only Arg Count: 0
            KW Only Arg Count: 0
            Locals: 4
            Stack Size: 6
            Flags: 0x00000043 (CO_OPTIMIZED | CO_NEWLOCALS | CO_NOFREE)
            [Names]
                'dnpgettext'
                '_current_domain'
            [Var Names]
                'context'
                'msgid1'
                'msgid2'
                'n'
            [Free Vars]
            [Cell Vars]
            [Constants]
                None
            [Disassembly]
                0       LOAD_GLOBAL                     0: dnpgettext
                2       LOAD_GLOBAL                     1: _current_domain
                4       LOAD_FAST                       0: context
                6       LOAD_FAST                       1: msgid1
                8       LOAD_FAST                       2: msgid2
                10      LOAD_FAST                       3: n
                12      CALL_FUNCTION                   5
                14      RETURN_VALUE                    
        'npgettext'
        (
            -1
        )
        (
            None
            None
            False
        )
        (
            None
        )
    [Disassembly]
        0       LOAD_CONST                      0: 'Internationalization and localization support.\n\nThis module provides internationalization (I18N) and localization (L10N)\nsupport for your Python programs by providing an interface to the GNU gettext\nmessage catalog library.\n\nI18N refers to the operation by which a program is made aware of multiple\nlanguages.  L10N refers to the adaptation of your program, once\ninternationalized, to the local language and cultural habits.\n\n'
        2       STORE_NAME                      0: __doc__
        4       LOAD_CONST                      1: 0
        6       LOAD_CONST                      2: None
        8       IMPORT_NAME                     1: os
        10      STORE_NAME                      1: os
        12      LOAD_CONST                      1: 0
        14      LOAD_CONST                      2: None
        16      IMPORT_NAME                     2: re
        18      STORE_NAME                      2: re
        20      LOAD_CONST                      1: 0
        22      LOAD_CONST                      2: None
        24      IMPORT_NAME                     3: sys
        26      STORE_NAME                      3: sys
        28      BUILD_LIST                      0
        30      LOAD_CONST                      3: ('NullTranslations', 'GNUTranslations', 'Catalog', 'find', 'translation', 'install', 'textdomain', 'bindtextdomain', 'bind_textdomain_codeset', 'dgettext', 'dngettext', 'gettext', 'lgettext', 'ldgettext', 'ldngettext', 'lngettext', 'ngettext', 'pgettext', 'dpgettext', 'npgettext', 'dnpgettext')
        32      LIST_EXTEND                     1
        34      STORE_NAME                      4: __all__
        36      LOAD_NAME                       1: os
        38      LOAD_ATTR                       5: path
        40      LOAD_METHOD                     6: join
        42      LOAD_NAME                       3: sys
        44      LOAD_ATTR                       7: base_prefix
        46      LOAD_CONST                      4: 'share'
        48      LOAD_CONST                      5: 'locale'
        50      CALL_METHOD                     3
        52      STORE_NAME                      8: _default_localedir
        54      LOAD_NAME                       2: re
        56      LOAD_METHOD                     9: compile
        58      LOAD_CONST                      6: '\n        (?P<WHITESPACES>[ \\t]+)                    | # spaces and horizontal tabs\n        (?P<NUMBER>[0-9]+\\b)                       | # decimal integer\n        (?P<NAME>n\\b)                              | # only n is allowed\n        (?P<PARENTHESIS>[()])                      |\n        (?P<OPERATOR>[-*/%+?:]|[><!]=?|==|&&|\\|\\|) | # !, *, /, %, +, -, <, >,\n                                                     # <=, >=, ==, !=, &&, ||,\n                                                     # ? :\n                                                     # unary and bitwise ops\n                                                     # not allowed\n        (?P<INVALID>\\w+|.)                           # invalid token\n    '
        60      LOAD_NAME                       2: re
        62      LOAD_ATTR                       10: VERBOSE
        64      LOAD_NAME                       2: re
        66      LOAD_ATTR                       11: DOTALL
        68      BINARY_OR                       
        70      CALL_METHOD                     2
        72      STORE_NAME                      12: _token_pattern
        74      LOAD_CONST                      7: <CODE> _tokenize
        76      LOAD_CONST                      8: '_tokenize'
        78      MAKE_FUNCTION                   0
        80      STORE_NAME                      13: _tokenize
        82      LOAD_CONST                      9: <CODE> _error
        84      LOAD_CONST                      10: '_error'
        86      MAKE_FUNCTION                   0
        88      STORE_NAME                      14: _error
        90      LOAD_CONST                      11: (('||',), ('&&',), ('==', '!='), ('<', '>', '<=', '>='), ('+', '-'), ('*', '/', '%'))
        92      STORE_NAME                      15: _binary_ops
        94      LOAD_CONST                      12: <CODE> <dictcomp>
        96      LOAD_CONST                      13: '<dictcomp>'
        98      MAKE_FUNCTION                   0
        100     LOAD_NAME                       16: enumerate
        102     LOAD_NAME                       15: _binary_ops
        104     LOAD_CONST                      14: 1
        106     CALL_FUNCTION                   2
        108     GET_ITER                        
        110     CALL_FUNCTION                   1
        112     STORE_NAME                      15: _binary_ops
        114     LOAD_CONST                      15: 'or'
        116     LOAD_CONST                      16: 'and'
        118     LOAD_CONST                      17: '//'
        120     LOAD_CONST                      18: ('||', '&&', '/')
        122     BUILD_CONST_KEY_MAP             3
        124     STORE_NAME                      17: _c2py_ops
        126     LOAD_CONST                      71: (-1,)
        128     LOAD_CONST                      20: <CODE> _parse
        130     LOAD_CONST                      21: '_parse'
        132     MAKE_FUNCTION                   1
        134     STORE_NAME                      18: _parse
        136     LOAD_CONST                      22: <CODE> _as_int
        138     LOAD_CONST                      23: '_as_int'
        140     MAKE_FUNCTION                   0
        142     STORE_NAME                      19: _as_int
        144     LOAD_CONST                      24: <CODE> c2py
        146     LOAD_CONST                      25: 'c2py'
        148     MAKE_FUNCTION                   0
        150     STORE_NAME                      20: c2py
        152     LOAD_CONST                      26: <CODE> _expand_lang
        154     LOAD_CONST                      27: '_expand_lang'
        156     MAKE_FUNCTION                   0
        158     STORE_NAME                      21: _expand_lang
        160     LOAD_BUILD_CLASS                
        162     LOAD_CONST                      28: <CODE> NullTranslations
        164     LOAD_CONST                      29: 'NullTranslations'
        166     MAKE_FUNCTION                   0
        168     LOAD_CONST                      29: 'NullTranslations'
        170     CALL_FUNCTION                   2
        172     STORE_NAME                      22: NullTranslations
        174     LOAD_BUILD_CLASS                
        176     LOAD_CONST                      30: <CODE> GNUTranslations
        178     LOAD_CONST                      31: 'GNUTranslations'
        180     MAKE_FUNCTION                   0
        182     LOAD_CONST                      31: 'GNUTranslations'
        184     LOAD_NAME                       22: NullTranslations
        186     CALL_FUNCTION                   3
        188     STORE_NAME                      23: GNUTranslations
        190     LOAD_CONST                      72: (None, None, False)
        192     LOAD_CONST                      33: <CODE> find
        194     LOAD_CONST                      34: 'find'
        196     MAKE_FUNCTION                   1
        198     STORE_NAME                      24: find
        200     BUILD_MAP                       0
        202     STORE_NAME                      25: _translations
        204     LOAD_CONST                      35: 'unspecified'
        206     BUILD_LIST                      1
        208     STORE_NAME                      26: _unspecified
        210     LOAD_CONST                      2: None
        212     LOAD_CONST                      2: None
        214     LOAD_CONST                      2: None
        216     LOAD_CONST                      32: False
        218     LOAD_NAME                       26: _unspecified
        220     BUILD_TUPLE                     5
        222     LOAD_CONST                      36: <CODE> translation
        224     LOAD_CONST                      37: 'translation'
        226     MAKE_FUNCTION                   1
        228     STORE_NAME                      27: translation
        230     LOAD_CONST                      2: None
        232     LOAD_NAME                       26: _unspecified
        234     LOAD_CONST                      2: None
        236     BUILD_TUPLE                     3
        238     LOAD_CONST                      38: <CODE> install
        240     LOAD_CONST                      39: 'install'
        242     MAKE_FUNCTION                   1
        244     STORE_NAME                      28: install
        246     BUILD_MAP                       0
        248     STORE_GLOBAL                    29: _localedirs
        250     BUILD_MAP                       0
        252     STORE_GLOBAL                    30: _localecodesets
        254     LOAD_CONST                      40: 'messages'
        256     STORE_GLOBAL                    31: _current_domain
        258     LOAD_CONST                      73: (None,)
        260     LOAD_CONST                      41: <CODE> textdomain
        262     LOAD_CONST                      42: 'textdomain'
        264     MAKE_FUNCTION                   1
        266     STORE_NAME                      32: textdomain
        268     LOAD_CONST                      73: (None,)
        270     LOAD_CONST                      43: <CODE> bindtextdomain
        272     LOAD_CONST                      44: 'bindtextdomain'
        274     MAKE_FUNCTION                   1
        276     STORE_NAME                      33: bindtextdomain
        278     LOAD_CONST                      73: (None,)
        280     LOAD_CONST                      45: <CODE> bind_textdomain_codeset
        282     LOAD_CONST                      46: 'bind_textdomain_codeset'
        284     MAKE_FUNCTION                   1
        286     STORE_NAME                      34: bind_textdomain_codeset
        288     LOAD_CONST                      47: <CODE> dgettext
        290     LOAD_CONST                      48: 'dgettext'
        292     MAKE_FUNCTION                   0
        294     STORE_NAME                      35: dgettext
        296     LOAD_CONST                      49: <CODE> ldgettext
        298     LOAD_CONST                      50: 'ldgettext'
        300     MAKE_FUNCTION                   0
        302     STORE_NAME                      36: ldgettext
        304     LOAD_CONST                      51: <CODE> dngettext
        306     LOAD_CONST                      52: 'dngettext'
        308     MAKE_FUNCTION                   0
        310     STORE_NAME                      37: dngettext
        312     LOAD_CONST                      53: <CODE> ldngettext
        314     LOAD_CONST                      54: 'ldngettext'
        316     MAKE_FUNCTION                   0
        318     STORE_NAME                      38: ldngettext
        320     LOAD_CONST                      55: <CODE> dpgettext
        322     LOAD_CONST                      56: 'dpgettext'
        324     MAKE_FUNCTION                   0
        326     STORE_NAME                      39: dpgettext
        328     LOAD_CONST                      57: <CODE> dnpgettext
        330     LOAD_CONST                      58: 'dnpgettext'
        332     MAKE_FUNCTION                   0
        334     STORE_NAME                      40: dnpgettext
        336     LOAD_CONST                      59: <CODE> gettext
        338     LOAD_CONST                      60: 'gettext'
        340     MAKE_FUNCTION                   0
        342     STORE_NAME                      41: gettext
        344     LOAD_CONST                      61: <CODE> lgettext
        346     LOAD_CONST                      62: 'lgettext'
        348     MAKE_FUNCTION                   0
        350     STORE_NAME                      42: lgettext
        352     LOAD_CONST                      63: <CODE> ngettext
        354     LOAD_CONST                      64: 'ngettext'
        356     MAKE_FUNCTION                   0
        358     STORE_NAME                      43: ngettext
        360     LOAD_CONST                      65: <CODE> lngettext
        362     LOAD_CONST                      66: 'lngettext'
        364     MAKE_FUNCTION                   0
        366     STORE_NAME                      44: lngettext
        368     LOAD_CONST                      67: <CODE> pgettext
        370     LOAD_CONST                      68: 'pgettext'
        372     MAKE_FUNCTION                   0
        374     STORE_NAME                      45: pgettext
        376     LOAD_CONST                      69: <CODE> npgettext
        378     LOAD_CONST                      70: 'npgettext'
        380     MAKE_FUNCTION                   0
        382     STORE_NAME                      46: npgettext
        384     LOAD_NAME                       27: translation
        386     STORE_NAME                      47: Catalog
        388     LOAD_CONST                      2: None
        390     RETURN_VALUE                    
