pprint.pyc (Python 3.10)
[Code]
    File Name: pprint.py
    Object Name: <module>
    Arg Count: 0
    Pos Only Arg Count: 0
    KW Only Arg Count: 0
    Locals: 0
    Stack Size: 9
    Flags: 0x00000040 (CO_NOFREE)
    [Names]
        '__doc__'
        'collections'
        '_collections'
        'dataclasses'
        '_dataclasses'
        're'
        'sys'
        '_sys'
        'types'
        '_types'
        'io'
        'StringIO'
        '_StringIO'
        '__all__'
        'pprint'
        'pformat'
        'pp'
        'saferepr'
        'isreadable'
        'isrecursive'
        '_safe_key'
        '_safe_tuple'
        'PrettyPrinter'
        'frozenset'
        'str'
        'bytes'
        'bytearray'
        'float'
        'complex'
        'bool'
        'type'
        '_builtin_scalars'
        '_recursion'
        '_perfcheck'
        '_wrap_bytes_repr'
        '__name__'
    [Var Names]
    [Free Vars]
    [Cell Vars]
    [Constants]
        "Support to pretty-print lists, tuples, & dictionaries recursively.\n\nVery simple, but useful, especially in debugging data structures.\n\nClasses\n-------\n\nPrettyPrinter()\n    Handle pretty-printing operations onto a stream using a configured\n    set of formatting parameters.\n\nFunctions\n---------\n\npformat()\n    Format a Python object into a pretty-printed representation.\n\npprint()\n    Pretty-print a Python object to a stream [default is sys.stdout].\n\nsaferepr()\n    Generate a 'standard' repr()-like value, but protect against recursive\n    data structures.\n\n"
        0
        None
        (
            'StringIO'
        )
        (
            'pprint'
            'pformat'
            'isreadable'
            'isrecursive'
            'saferepr'
            'PrettyPrinter'
            'pp'
        )
        1
        80
        False
        True
        (
            'compact'
            'sort_dicts'
            'underscore_numbers'
        )
        [Code]
            File Name: pprint.py
            Object Name: pprint
            Arg Count: 5
            Pos Only Arg Count: 0
            KW Only Arg Count: 3
            Locals: 9
            Stack Size: 9
            Flags: 0x00000043 (CO_OPTIMIZED | CO_NEWLOCALS | CO_NOFREE)
            [Names]
                'PrettyPrinter'
                'pprint'
            [Var Names]
                'object'
                'stream'
                'indent'
                'width'
                'depth'
                'compact'
                'sort_dicts'
                'underscore_numbers'
                'printer'
            [Free Vars]
            [Cell Vars]
            [Constants]
                'Pretty-print a Python object to a stream [default is sys.stdout].'
                (
                    'stream'
                    'indent'
                    'width'
                    'depth'
                    'compact'
                    'sort_dicts'
                    'underscore_numbers'
                )
                None
            [Disassembly]
                0       LOAD_GLOBAL                     0: PrettyPrinter
                2       LOAD_FAST                       1: stream
                4       LOAD_FAST                       2: indent
                6       LOAD_FAST                       3: width
                8       LOAD_FAST                       4: depth
                10      LOAD_FAST                       5: compact
                12      LOAD_FAST                       6: sort_dicts
                14      LOAD_FAST                       7: underscore_numbers
                16      LOAD_CONST                      1: ('stream', 'indent', 'width', 'depth', 'compact', 'sort_dicts', 'underscore_numbers')
                18      CALL_FUNCTION_KW                7
                20      STORE_FAST                      8: printer
                22      LOAD_FAST                       8: printer
                24      LOAD_METHOD                     1: pprint
                26      LOAD_FAST                       0: object
                28      CALL_METHOD                     1
                30      POP_TOP                         
                32      LOAD_CONST                      2: None
                34      RETURN_VALUE                    
        'pprint'
        [Code]
            File Name: pprint.py
            Object Name: pformat
            Arg Count: 4
            Pos Only Arg Count: 0
            KW Only Arg Count: 3
            Locals: 7
            Stack Size: 8
            Flags: 0x00000043 (CO_OPTIMIZED | CO_NEWLOCALS | CO_NOFREE)
            [Names]
                'PrettyPrinter'
                'pformat'
            [Var Names]
                'object'
                'indent'
                'width'
                'depth'
                'compact'
                'sort_dicts'
                'underscore_numbers'
            [Free Vars]
            [Cell Vars]
            [Constants]
                'Format a Python object into a pretty-printed representation.'
                (
                    'indent'
                    'width'
                    'depth'
                    'compact'
                    'sort_dicts'
                    'underscore_numbers'
                )
            [Disassembly]
                0       LOAD_GLOBAL                     0: PrettyPrinter
                2       LOAD_FAST                       1: indent
                4       LOAD_FAST                       2: width
                6       LOAD_FAST                       3: depth
                8       LOAD_FAST                       4: compact
                10      LOAD_FAST                       5: sort_dicts
                12      LOAD_FAST                       6: underscore_numbers
                14      LOAD_CONST                      1: ('indent', 'width', 'depth', 'compact', 'sort_dicts', 'underscore_numbers')
                16      CALL_FUNCTION_KW                6
                18      LOAD_METHOD                     1: pformat
                20      LOAD_FAST                       0: object
                22      CALL_METHOD                     1
                24      RETURN_VALUE                    
        'pformat'
        (
            'sort_dicts'
        )
        [Code]
            File Name: pprint.py
            Object Name: pp
            Arg Count: 1
            Pos Only Arg Count: 0
            KW Only Arg Count: 1
            Locals: 4
            Stack Size: 4
            Flags: 0x0000004F (CO_OPTIMIZED | CO_NEWLOCALS | CO_VARARGS | CO_VARKEYWORDS | CO_NOFREE)
            [Names]
                'pprint'
            [Var Names]
                'object'
                'sort_dicts'
                'args'
                'kwargs'
            [Free Vars]
            [Cell Vars]
            [Constants]
                'Pretty-print a Python object'
                'sort_dicts'
                None
            [Disassembly]
                0       LOAD_GLOBAL                     0: pprint
                2       LOAD_FAST                       0: object
                4       BUILD_LIST                      1
                6       LOAD_FAST                       2: args
                8       LIST_EXTEND                     1
                10      LIST_TO_TUPLE                   
                12      LOAD_CONST                      1: 'sort_dicts'
                14      LOAD_FAST                       1: sort_dicts
                16      BUILD_MAP                       1
                18      LOAD_FAST                       3: kwargs
                20      DICT_MERGE                      1
                22      CALL_FUNCTION_EX                1
                24      POP_TOP                         
                26      LOAD_CONST                      2: None
                28      RETURN_VALUE                    
        'pp'
        [Code]
            File Name: pprint.py
            Object Name: saferepr
            Arg Count: 1
            Pos Only Arg Count: 0
            KW Only Arg Count: 0
            Locals: 1
            Stack Size: 6
            Flags: 0x00000043 (CO_OPTIMIZED | CO_NEWLOCALS | CO_NOFREE)
            [Names]
                'PrettyPrinter'
                '_safe_repr'
            [Var Names]
                'object'
            [Free Vars]
            [Cell Vars]
            [Constants]
                'Version of repr() which can handle recursive data structures.'
                None
                0
            [Disassembly]
                0       LOAD_GLOBAL                     0: PrettyPrinter
                2       CALL_FUNCTION                   0
                4       LOAD_METHOD                     1: _safe_repr
                6       LOAD_FAST                       0: object
                8       BUILD_MAP                       0
                10      LOAD_CONST                      1: None
                12      LOAD_CONST                      2: 0
                14      CALL_METHOD                     4
                16      LOAD_CONST                      2: 0
                18      BINARY_SUBSCR                   
                20      RETURN_VALUE                    
        'saferepr'
        [Code]
            File Name: pprint.py
            Object Name: isreadable
            Arg Count: 1
            Pos Only Arg Count: 0
            KW Only Arg Count: 0
            Locals: 1
            Stack Size: 6
            Flags: 0x00000043 (CO_OPTIMIZED | CO_NEWLOCALS | CO_NOFREE)
            [Names]
                'PrettyPrinter'
                '_safe_repr'
            [Var Names]
                'object'
            [Free Vars]
            [Cell Vars]
            [Constants]
                'Determine if saferepr(object) is readable by eval().'
                None
                0
                1
            [Disassembly]
                0       LOAD_GLOBAL                     0: PrettyPrinter
                2       CALL_FUNCTION                   0
                4       LOAD_METHOD                     1: _safe_repr
                6       LOAD_FAST                       0: object
                8       BUILD_MAP                       0
                10      LOAD_CONST                      1: None
                12      LOAD_CONST                      2: 0
                14      CALL_METHOD                     4
                16      LOAD_CONST                      3: 1
                18      BINARY_SUBSCR                   
                20      RETURN_VALUE                    
        'isreadable'
        [Code]
            File Name: pprint.py
            Object Name: isrecursive
            Arg Count: 1
            Pos Only Arg Count: 0
            KW Only Arg Count: 0
            Locals: 1
            Stack Size: 6
            Flags: 0x00000043 (CO_OPTIMIZED | CO_NEWLOCALS | CO_NOFREE)
            [Names]
                'PrettyPrinter'
                '_safe_repr'
            [Var Names]
                'object'
            [Free Vars]
            [Cell Vars]
            [Constants]
                'Determine if object requires a recursive representation.'
                None
                0
                2
            [Disassembly]
                0       LOAD_GLOBAL                     0: PrettyPrinter
                2       CALL_FUNCTION                   0
                4       LOAD_METHOD                     1: _safe_repr
                6       LOAD_FAST                       0: object
                8       BUILD_MAP                       0
                10      LOAD_CONST                      1: None
                12      LOAD_CONST                      2: 0
                14      CALL_METHOD                     4
                16      LOAD_CONST                      3: 2
                18      BINARY_SUBSCR                   
                20      RETURN_VALUE                    
        'isrecursive'
        [Code]
            File Name: pprint.py
            Object Name: _safe_key
            Arg Count: 0
            Pos Only Arg Count: 0
            KW Only Arg Count: 0
            Locals: 0
            Stack Size: 2
            Flags: 0x00000040 (CO_NOFREE)
            [Names]
                '__name__'
                '__module__'
                '__qualname__'
                '__doc__'
                '__slots__'
                '__init__'
                '__lt__'
            [Var Names]
            [Free Vars]
            [Cell Vars]
            [Constants]
                '_safe_key'
                'Helper function for key functions when sorting unorderable objects.\n\n    The wrapped-object will fallback to a Py2.x style comparison for\n    unorderable types (sorting first comparing the type name and then by\n    the obj ids).  Does not work recursively, so dict.items() must have\n    _safe_key applied to both the key and the value.\n\n    '
                'obj'
                [Code]
                    File Name: pprint.py
                    Object Name: __init__
                    Arg Count: 2
                    Pos Only Arg Count: 0
                    KW Only Arg Count: 0
                    Locals: 2
                    Stack Size: 2
                    Flags: 0x00000043 (CO_OPTIMIZED | CO_NEWLOCALS | CO_NOFREE)
                    [Names]
                        'obj'
                    [Var Names]
                        'self'
                        'obj'
                    [Free Vars]
                    [Cell Vars]
                    [Constants]
                        None
                    [Disassembly]
                        0       LOAD_FAST                       1: obj
                        2       LOAD_FAST                       0: self
                        4       STORE_ATTR                      0: obj
                        6       LOAD_CONST                      0: None
                        8       RETURN_VALUE                    
                '_safe_key.__init__'
                [Code]
                    File Name: pprint.py
                    Object Name: __lt__
                    Arg Count: 2
                    Pos Only Arg Count: 0
                    KW Only Arg Count: 0
                    Locals: 2
                    Stack Size: 8
                    Flags: 0x00000043 (CO_OPTIMIZED | CO_NEWLOCALS | CO_NOFREE)
                    [Names]
                        'obj'
                        'TypeError'
                        'str'
                        'type'
                        'id'
                    [Var Names]
                        'self'
                        'other'
                    [Free Vars]
                    [Cell Vars]
                    [Constants]
                        None
                    [Disassembly]
                        0       SETUP_FINALLY                   7 (to 16)
                        2       LOAD_FAST                       0: self
                        4       LOAD_ATTR                       0: obj
                        6       LOAD_FAST                       1: other
                        8       LOAD_ATTR                       0: obj
                        10      COMPARE_OP                      0 (<)
                        12      POP_BLOCK                       
                        14      RETURN_VALUE                    
                        16      DUP_TOP                         
                        18      LOAD_GLOBAL                     1: TypeError
                        20      JUMP_IF_NOT_EXC_MATCH           40 (to 80)
                        22      POP_TOP                         
                        24      POP_TOP                         
                        26      POP_TOP                         
                        28      LOAD_GLOBAL                     2: str
                        30      LOAD_GLOBAL                     3: type
                        32      LOAD_FAST                       0: self
                        34      LOAD_ATTR                       0: obj
                        36      CALL_FUNCTION                   1
                        38      CALL_FUNCTION                   1
                        40      LOAD_GLOBAL                     4: id
                        42      LOAD_FAST                       0: self
                        44      LOAD_ATTR                       0: obj
                        46      CALL_FUNCTION                   1
                        48      BUILD_TUPLE                     2
                        50      LOAD_GLOBAL                     2: str
                        52      LOAD_GLOBAL                     3: type
                        54      LOAD_FAST                       1: other
                        56      LOAD_ATTR                       0: obj
                        58      CALL_FUNCTION                   1
                        60      CALL_FUNCTION                   1
                        62      LOAD_GLOBAL                     4: id
                        64      LOAD_FAST                       1: other
                        66      LOAD_ATTR                       0: obj
                        68      CALL_FUNCTION                   1
                        70      BUILD_TUPLE                     2
                        72      COMPARE_OP                      0 (<)
                        74      ROT_FOUR                        
                        76      POP_EXCEPT                      
                        78      RETURN_VALUE                    
                        80      RERAISE                         0
                '_safe_key.__lt__'
                None
            [Disassembly]
                0       LOAD_NAME                       0: __name__
                2       STORE_NAME                      1: __module__
                4       LOAD_CONST                      0: '_safe_key'
                6       STORE_NAME                      2: __qualname__
                8       LOAD_CONST                      1: 'Helper function for key functions when sorting unorderable objects.\n\n    The wrapped-object will fallback to a Py2.x style comparison for\n    unorderable types (sorting first comparing the type name and then by\n    the obj ids).  Does not work recursively, so dict.items() must have\n    _safe_key applied to both the key and the value.\n\n    '
                10      STORE_NAME                      3: __doc__
                12      LOAD_CONST                      2: 'obj'
                14      BUILD_LIST                      1
                16      STORE_NAME                      4: __slots__
                18      LOAD_CONST                      3: <CODE> __init__
                20      LOAD_CONST                      4: '_safe_key.__init__'
                22      MAKE_FUNCTION                   0
                24      STORE_NAME                      5: __init__
                26      LOAD_CONST                      5: <CODE> __lt__
                28      LOAD_CONST                      6: '_safe_key.__lt__'
                30      MAKE_FUNCTION                   0
                32      STORE_NAME                      6: __lt__
                34      LOAD_CONST                      7: None
                36      RETURN_VALUE                    
        '_safe_key'
        [Code]
            File Name: pprint.py
            Object Name: _safe_tuple
            Arg Count: 1
            Pos Only Arg Count: 0
            KW Only Arg Count: 0
            Locals: 1
            Stack Size: 4
            Flags: 0x00000043 (CO_OPTIMIZED | CO_NEWLOCALS | CO_NOFREE)
            [Names]
                '_safe_key'
            [Var Names]
                't'
            [Free Vars]
            [Cell Vars]
            [Constants]
                'Helper function for comparing 2-tuples'
                0
                1
            [Disassembly]
                0       LOAD_GLOBAL                     0: _safe_key
                2       LOAD_FAST                       0: t
                4       LOAD_CONST                      1: 0
                6       BINARY_SUBSCR                   
                8       CALL_FUNCTION                   1
                10      LOAD_GLOBAL                     0: _safe_key
                12      LOAD_FAST                       0: t
                14      LOAD_CONST                      2: 1
                16      BINARY_SUBSCR                   
                18      CALL_FUNCTION                   1
                20      BUILD_TUPLE                     2
                22      RETURN_VALUE                    
        '_safe_tuple'
        [Code]
            File Name: pprint.py
            Object Name: PrettyPrinter
            Arg Count: 0
            Pos Only Arg Count: 0
            KW Only Arg Count: 0
            Locals: 0
            Stack Size: 5
            Flags: 0x00000040 (CO_NOFREE)
            [Names]
                '__name__'
                '__module__'
                '__qualname__'
                '__init__'
                'pprint'
                'pformat'
                'isrecursive'
                'isreadable'
                '_format'
                '_pprint_dataclass'
                '_dispatch'
                '_pprint_dict'
                'dict'
                '__repr__'
                '_pprint_ordered_dict'
                '_collections'
                'OrderedDict'
                '_pprint_list'
                'list'
                '_pprint_tuple'
                'tuple'
                '_pprint_set'
                'set'
                'frozenset'
                '_pprint_str'
                'str'
                '_pprint_bytes'
                'bytes'
                '_pprint_bytearray'
                'bytearray'
                '_pprint_mappingproxy'
                '_types'
                'MappingProxyType'
                '_pprint_simplenamespace'
                'SimpleNamespace'
                '_format_dict_items'
                '_format_namespace_items'
                '_format_items'
                '_repr'
                'format'
                '_pprint_default_dict'
                'defaultdict'
                '_pprint_counter'
                'Counter'
                '_pprint_chain_map'
                'ChainMap'
                '_pprint_deque'
                'deque'
                '_pprint_user_dict'
                'UserDict'
                '_pprint_user_list'
                'UserList'
                '_pprint_user_string'
                'UserString'
                '_safe_repr'
            [Var Names]
            [Free Vars]
            [Cell Vars]
            [Constants]
                'PrettyPrinter'
                1
                80
                None
                False
                True
                (
                    'compact'
                    'sort_dicts'
                    'underscore_numbers'
                )
                [Code]
                    File Name: pprint.py
                    Object Name: __init__
                    Arg Count: 5
                    Pos Only Arg Count: 0
                    KW Only Arg Count: 3
                    Locals: 8
                    Stack Size: 2
                    Flags: 0x00000043 (CO_OPTIMIZED | CO_NEWLOCALS | CO_NOFREE)
                    [Names]
                        'int'
                        'ValueError'
                        '_depth'
                        '_indent_per_level'
                        '_width'
                        '_stream'
                        '_sys'
                        'stdout'
                        'bool'
                        '_compact'
                        '_sort_dicts'
                        '_underscore_numbers'
                    [Var Names]
                        'self'
                        'indent'
                        'width'
                        'depth'
                        'stream'
                        'compact'
                        'sort_dicts'
                        'underscore_numbers'
                    [Free Vars]
                    [Cell Vars]
                    [Constants]
                        'Handle pretty printing operations onto a stream using a set of\n        configured parameters.\n\n        indent\n            Number of spaces to indent for each level of nesting.\n\n        width\n            Attempted maximum number of columns in the output.\n\n        depth\n            The maximum depth to print out nested structures.\n\n        stream\n            The desired output stream.  If omitted (or false), the standard\n            output stream available at construction will be used.\n\n        compact\n            If true, several items will be combined in one line.\n\n        sort_dicts\n            If true, dict keys are sorted.\n\n        '
                        0
                        'indent must be >= 0'
                        None
                        'depth must be > 0'
                        'width must be != 0'
                    [Disassembly]
                        0       LOAD_GLOBAL                     0: int
                        2       LOAD_FAST                       1: indent
                        4       CALL_FUNCTION                   1
                        6       STORE_FAST                      1: indent
                        8       LOAD_GLOBAL                     0: int
                        10      LOAD_FAST                       2: width
                        12      CALL_FUNCTION                   1
                        14      STORE_FAST                      2: width
                        16      LOAD_FAST                       1: indent
                        18      LOAD_CONST                      1: 0
                        20      COMPARE_OP                      0 (<)
                        22      POP_JUMP_IF_FALSE               16 (to 32)
                        24      LOAD_GLOBAL                     1: ValueError
                        26      LOAD_CONST                      2: 'indent must be >= 0'
                        28      CALL_FUNCTION                   1
                        30      RAISE_VARARGS                   1
                        32      LOAD_FAST                       3: depth
                        34      LOAD_CONST                      3: None
                        36      IS_OP                           1 (is not)
                        38      POP_JUMP_IF_FALSE               28 (to 56)
                        40      LOAD_FAST                       3: depth
                        42      LOAD_CONST                      1: 0
                        44      COMPARE_OP                      1 (<=)
                        46      POP_JUMP_IF_FALSE               28 (to 56)
                        48      LOAD_GLOBAL                     1: ValueError
                        50      LOAD_CONST                      4: 'depth must be > 0'
                        52      CALL_FUNCTION                   1
                        54      RAISE_VARARGS                   1
                        56      LOAD_FAST                       2: width
                        58      POP_JUMP_IF_TRUE                34 (to 68)
                        60      LOAD_GLOBAL                     1: ValueError
                        62      LOAD_CONST                      5: 'width must be != 0'
                        64      CALL_FUNCTION                   1
                        66      RAISE_VARARGS                   1
                        68      LOAD_FAST                       3: depth
                        70      LOAD_FAST                       0: self
                        72      STORE_ATTR                      2: _depth
                        74      LOAD_FAST                       1: indent
                        76      LOAD_FAST                       0: self
                        78      STORE_ATTR                      3: _indent_per_level
                        80      LOAD_FAST                       2: width
                        82      LOAD_FAST                       0: self
                        84      STORE_ATTR                      4: _width
                        86      LOAD_FAST                       4: stream
                        88      LOAD_CONST                      3: None
                        90      IS_OP                           1 (is not)
                        92      POP_JUMP_IF_FALSE               51 (to 102)
                        94      LOAD_FAST                       4: stream
                        96      LOAD_FAST                       0: self
                        98      STORE_ATTR                      5: _stream
                        100     JUMP_FORWARD                    4 (to 110)
                        102     LOAD_GLOBAL                     6: _sys
                        104     LOAD_ATTR                       7: stdout
                        106     LOAD_FAST                       0: self
                        108     STORE_ATTR                      5: _stream
                        110     LOAD_GLOBAL                     8: bool
                        112     LOAD_FAST                       5: compact
                        114     CALL_FUNCTION                   1
                        116     LOAD_FAST                       0: self
                        118     STORE_ATTR                      9: _compact
                        120     LOAD_FAST                       6: sort_dicts
                        122     LOAD_FAST                       0: self
                        124     STORE_ATTR                      10: _sort_dicts
                        126     LOAD_FAST                       7: underscore_numbers
                        128     LOAD_FAST                       0: self
                        130     STORE_ATTR                      11: _underscore_numbers
                        132     LOAD_CONST                      3: None
                        134     RETURN_VALUE                    
                'PrettyPrinter.__init__'
                [Code]
                    File Name: pprint.py
                    Object Name: pprint
                    Arg Count: 2
                    Pos Only Arg Count: 0
                    KW Only Arg Count: 0
                    Locals: 2
                    Stack Size: 8
                    Flags: 0x00000043 (CO_OPTIMIZED | CO_NEWLOCALS | CO_NOFREE)
                    [Names]
                        '_format'
                        '_stream'
                        'write'
                    [Var Names]
                        'self'
                        'object'
                    [Free Vars]
                    [Cell Vars]
                    [Constants]
                        None
                        0
                        '\n'
                    [Disassembly]
                        0       LOAD_FAST                       0: self
                        2       LOAD_METHOD                     0: _format
                        4       LOAD_FAST                       1: object
                        6       LOAD_FAST                       0: self
                        8       LOAD_ATTR                       1: _stream
                        10      LOAD_CONST                      1: 0
                        12      LOAD_CONST                      1: 0
                        14      BUILD_MAP                       0
                        16      LOAD_CONST                      1: 0
                        18      CALL_METHOD                     6
                        20      POP_TOP                         
                        22      LOAD_FAST                       0: self
                        24      LOAD_ATTR                       1: _stream
                        26      LOAD_METHOD                     2: write
                        28      LOAD_CONST                      2: '\n'
                        30      CALL_METHOD                     1
                        32      POP_TOP                         
                        34      LOAD_CONST                      0: None
                        36      RETURN_VALUE                    
                'PrettyPrinter.pprint'
                [Code]
                    File Name: pprint.py
                    Object Name: pformat
                    Arg Count: 2
                    Pos Only Arg Count: 0
                    KW Only Arg Count: 0
                    Locals: 3
                    Stack Size: 8
                    Flags: 0x00000043 (CO_OPTIMIZED | CO_NEWLOCALS | CO_NOFREE)
                    [Names]
                        '_StringIO'
                        '_format'
                        'getvalue'
                    [Var Names]
                        'self'
                        'object'
                        'sio'
                    [Free Vars]
                    [Cell Vars]
                    [Constants]
                        None
                        0
                    [Disassembly]
                        0       LOAD_GLOBAL                     0: _StringIO
                        2       CALL_FUNCTION                   0
                        4       STORE_FAST                      2: sio
                        6       LOAD_FAST                       0: self
                        8       LOAD_METHOD                     1: _format
                        10      LOAD_FAST                       1: object
                        12      LOAD_FAST                       2: sio
                        14      LOAD_CONST                      1: 0
                        16      LOAD_CONST                      1: 0
                        18      BUILD_MAP                       0
                        20      LOAD_CONST                      1: 0
                        22      CALL_METHOD                     6
                        24      POP_TOP                         
                        26      LOAD_FAST                       2: sio
                        28      LOAD_METHOD                     2: getvalue
                        30      CALL_METHOD                     0
                        32      RETURN_VALUE                    
                'PrettyPrinter.pformat'
                [Code]
                    File Name: pprint.py
                    Object Name: isrecursive
                    Arg Count: 2
                    Pos Only Arg Count: 0
                    KW Only Arg Count: 0
                    Locals: 2
                    Stack Size: 6
                    Flags: 0x00000043 (CO_OPTIMIZED | CO_NEWLOCALS | CO_NOFREE)
                    [Names]
                        'format'
                    [Var Names]
                        'self'
                        'object'
                    [Free Vars]
                    [Cell Vars]
                    [Constants]
                        None
                        0
                        2
                    [Disassembly]
                        0       LOAD_FAST                       0: self
                        2       LOAD_METHOD                     0: format
                        4       LOAD_FAST                       1: object
                        6       BUILD_MAP                       0
                        8       LOAD_CONST                      1: 0
                        10      LOAD_CONST                      1: 0
                        12      CALL_METHOD                     4
                        14      LOAD_CONST                      2: 2
                        16      BINARY_SUBSCR                   
                        18      RETURN_VALUE                    
                'PrettyPrinter.isrecursive'
                [Code]
                    File Name: pprint.py
                    Object Name: isreadable
                    Arg Count: 2
                    Pos Only Arg Count: 0
                    KW Only Arg Count: 0
                    Locals: 5
                    Stack Size: 6
                    Flags: 0x00000043 (CO_OPTIMIZED | CO_NEWLOCALS | CO_NOFREE)
                    [Names]
                        'format'
                    [Var Names]
                        'self'
                        'object'
                        's'
                        'readable'
                        'recursive'
                    [Free Vars]
                    [Cell Vars]
                    [Constants]
                        None
                        0
                    [Disassembly]
                        0       LOAD_FAST                       0: self
                        2       LOAD_METHOD                     0: format
                        4       LOAD_FAST                       1: object
                        6       BUILD_MAP                       0
                        8       LOAD_CONST                      1: 0
                        10      LOAD_CONST                      1: 0
                        12      CALL_METHOD                     4
                        14      UNPACK_SEQUENCE                 3
                        16      STORE_FAST                      2: s
                        18      STORE_FAST                      3: readable
                        20      STORE_FAST                      4: recursive
                        22      LOAD_FAST                       3: readable
                        24      JUMP_IF_FALSE_OR_POP            15 (to 30)
                        26      LOAD_FAST                       4: recursive
                        28      UNARY_NOT                       
                        30      RETURN_VALUE                    
                'PrettyPrinter.isreadable'
                [Code]
                    File Name: pprint.py
                    Object Name: _format
                    Arg Count: 7
                    Pos Only Arg Count: 0
                    KW Only Arg Count: 0
                    Locals: 11
                    Stack Size: 9
                    Flags: 0x00000043 (CO_OPTIMIZED | CO_NEWLOCALS | CO_NOFREE)
                    [Names]
                        'id'
                        'write'
                        '_recursion'
                        '_recursive'
                        '_readable'
                        '_repr'
                        '_width'
                        'len'
                        '_dispatch'
                        'get'
                        'type'
                        '__repr__'
                        '_dataclasses'
                        'is_dataclass'
                        'isinstance'
                        '__dataclass_params__'
                        'repr'
                        'hasattr'
                        '__wrapped__'
                        '__qualname__'
                        '_pprint_dataclass'
                    [Var Names]
                        'self'
                        'object'
                        'stream'
                        'indent'
                        'allowance'
                        'context'
                        'level'
                        'objid'
                        'rep'
                        'max_width'
                        'p'
                    [Free Vars]
                    [Cell Vars]
                    [Constants]
                        None
                        True
                        False
                        1
                        '__wrapped__'
                        '__create_fn__'
                    [Disassembly]
                        0       LOAD_GLOBAL                     0: id
                        2       LOAD_FAST                       1: object
                        4       CALL_FUNCTION                   1
                        6       STORE_FAST                      7: objid
                        8       LOAD_FAST                       7: objid
                        10      LOAD_FAST                       5: context
                        12      CONTAINS_OP                     0 (in)
                        14      POP_JUMP_IF_FALSE               23 (to 46)
                        16      LOAD_FAST                       2: stream
                        18      LOAD_METHOD                     1: write
                        20      LOAD_GLOBAL                     2: _recursion
                        22      LOAD_FAST                       1: object
                        24      CALL_FUNCTION                   1
                        26      CALL_METHOD                     1
                        28      POP_TOP                         
                        30      LOAD_CONST                      1: True
                        32      LOAD_FAST                       0: self
                        34      STORE_ATTR                      3: _recursive
                        36      LOAD_CONST                      2: False
                        38      LOAD_FAST                       0: self
                        40      STORE_ATTR                      4: _readable
                        42      LOAD_CONST                      0: None
                        44      RETURN_VALUE                    
                        46      LOAD_FAST                       0: self
                        48      LOAD_METHOD                     5: _repr
                        50      LOAD_FAST                       1: object
                        52      LOAD_FAST                       5: context
                        54      LOAD_FAST                       6: level
                        56      CALL_METHOD                     3
                        58      STORE_FAST                      8: rep
                        60      LOAD_FAST                       0: self
                        62      LOAD_ATTR                       6: _width
                        64      LOAD_FAST                       3: indent
                        66      BINARY_SUBTRACT                 
                        68      LOAD_FAST                       4: allowance
                        70      BINARY_SUBTRACT                 
                        72      STORE_FAST                      9: max_width
                        74      LOAD_GLOBAL                     7: len
                        76      LOAD_FAST                       8: rep
                        78      CALL_FUNCTION                   1
                        80      LOAD_FAST                       9: max_width
                        82      COMPARE_OP                      4 (>)
                        84      POP_JUMP_IF_FALSE               126 (to 252)
                        86      LOAD_FAST                       0: self
                        88      LOAD_ATTR                       8: _dispatch
                        90      LOAD_METHOD                     9: get
                        92      LOAD_GLOBAL                     10: type
                        94      LOAD_FAST                       1: object
                        96      CALL_FUNCTION                   1
                        98      LOAD_ATTR                       11: __repr__
                        100     LOAD_CONST                      0: None
                        102     CALL_METHOD                     2
                        104     STORE_FAST                      10: p
                        106     LOAD_FAST                       10: p
                        108     LOAD_CONST                      0: None
                        110     IS_OP                           1 (is not)
                        112     POP_JUMP_IF_FALSE               78 (to 156)
                        114     LOAD_CONST                      3: 1
                        116     LOAD_FAST                       5: context
                        118     LOAD_FAST                       7: objid
                        120     STORE_SUBSCR                    
                        122     LOAD_FAST                       10: p
                        124     LOAD_FAST                       0: self
                        126     LOAD_FAST                       1: object
                        128     LOAD_FAST                       2: stream
                        130     LOAD_FAST                       3: indent
                        132     LOAD_FAST                       4: allowance
                        134     LOAD_FAST                       5: context
                        136     LOAD_FAST                       6: level
                        138     LOAD_CONST                      3: 1
                        140     BINARY_ADD                      
                        142     CALL_FUNCTION                   7
                        144     POP_TOP                         
                        146     LOAD_FAST                       5: context
                        148     LOAD_FAST                       7: objid
                        150     DELETE_SUBSCR                   
                        152     LOAD_CONST                      0: None
                        154     RETURN_VALUE                    
                        156     LOAD_GLOBAL                     12: _dataclasses
                        158     LOAD_METHOD                     13: is_dataclass
                        160     LOAD_FAST                       1: object
                        162     CALL_METHOD                     1
                        164     POP_JUMP_IF_FALSE               126 (to 252)
                        166     LOAD_GLOBAL                     14: isinstance
                        168     LOAD_FAST                       1: object
                        170     LOAD_GLOBAL                     10: type
                        172     CALL_FUNCTION                   2
                        174     POP_JUMP_IF_TRUE                126 (to 252)
                        176     LOAD_FAST                       1: object
                        178     LOAD_ATTR                       15: __dataclass_params__
                        180     LOAD_ATTR                       16: repr
                        182     POP_JUMP_IF_FALSE               126 (to 252)
                        184     LOAD_GLOBAL                     17: hasattr
                        186     LOAD_FAST                       1: object
                        188     LOAD_ATTR                       11: __repr__
                        190     LOAD_CONST                      4: '__wrapped__'
                        192     CALL_FUNCTION                   2
                        194     POP_JUMP_IF_FALSE               126 (to 252)
                        196     LOAD_CONST                      5: '__create_fn__'
                        198     LOAD_FAST                       1: object
                        200     LOAD_ATTR                       11: __repr__
                        202     LOAD_ATTR                       18: __wrapped__
                        204     LOAD_ATTR                       19: __qualname__
                        206     CONTAINS_OP                     0 (in)
                        208     POP_JUMP_IF_FALSE               126 (to 252)
                        210     LOAD_CONST                      3: 1
                        212     LOAD_FAST                       5: context
                        214     LOAD_FAST                       7: objid
                        216     STORE_SUBSCR                    
                        218     LOAD_FAST                       0: self
                        220     LOAD_METHOD                     20: _pprint_dataclass
                        222     LOAD_FAST                       1: object
                        224     LOAD_FAST                       2: stream
                        226     LOAD_FAST                       3: indent
                        228     LOAD_FAST                       4: allowance
                        230     LOAD_FAST                       5: context
                        232     LOAD_FAST                       6: level
                        234     LOAD_CONST                      3: 1
                        236     BINARY_ADD                      
                        238     CALL_METHOD                     6
                        240     POP_TOP                         
                        242     LOAD_FAST                       5: context
                        244     LOAD_FAST                       7: objid
                        246     DELETE_SUBSCR                   
                        248     LOAD_CONST                      0: None
                        250     RETURN_VALUE                    
                        252     LOAD_FAST                       2: stream
                        254     LOAD_METHOD                     1: write
                        256     LOAD_FAST                       8: rep
                        258     CALL_METHOD                     1
                        260     POP_TOP                         
                        262     LOAD_CONST                      0: None
                        264     RETURN_VALUE                    
                'PrettyPrinter._format'
                [Code]
                    File Name: pprint.py
                    Object Name: _pprint_dataclass
                    Arg Count: 7
                    Pos Only Arg Count: 0
                    KW Only Arg Count: 0
                    Locals: 9
                    Stack Size: 8
                    Flags: 0x00000003 (CO_OPTIMIZED | CO_NEWLOCALS)
                    [Names]
                        '__class__'
                        '__name__'
                        'len'
                        '_dataclasses'
                        'fields'
                        'write'
                        '_format_namespace_items'
                    [Var Names]
                        'self'
                        'object'
                        'stream'
                        'indent'
                        'allowance'
                        'context'
                        'level'
                        'cls_name'
                        'items'
                    [Free Vars]
                    [Cell Vars]
                        'object'
                    [Constants]
                        None
                        1
                        [Code]
                            File Name: pprint.py
                            Object Name: <listcomp>
                            Arg Count: 1
                            Pos Only Arg Count: 0
                            KW Only Arg Count: 0
                            Locals: 2
                            Stack Size: 6
                            Flags: 0x00000013 (CO_OPTIMIZED | CO_NEWLOCALS | CO_NESTED)
                            [Names]
                                'repr'
                                'name'
                                'getattr'
                            [Var Names]
                                '.0'
                                'f'
                            [Free Vars]
                                'object'
                            [Cell Vars]
                            [Constants]
                            [Disassembly]
                                0       BUILD_LIST                      0
                                2       LOAD_FAST                       0: .0
                                4       FOR_ITER                        14 (to 34)
                                6       STORE_FAST                      1: f
                                8       LOAD_FAST                       1: f
                                10      LOAD_ATTR                       0: repr
                                12      POP_JUMP_IF_FALSE               2 (to 4)
                                14      LOAD_FAST                       1: f
                                16      LOAD_ATTR                       1: name
                                18      LOAD_GLOBAL                     2: getattr
                                20      LOAD_DEREF                      0: object
                                22      LOAD_FAST                       1: f
                                24      LOAD_ATTR                       1: name
                                26      CALL_FUNCTION                   2
                                28      BUILD_TUPLE                     2
                                30      LIST_APPEND                     2
                                32      JUMP_ABSOLUTE                   2 (to 4)
                                34      RETURN_VALUE                    
                        'PrettyPrinter._pprint_dataclass.<locals>.<listcomp>'
                        '('
                        ')'
                    [Disassembly]
                        0       LOAD_DEREF                      0: object
                        2       LOAD_ATTR                       0: __class__
                        4       LOAD_ATTR                       1: __name__
                        6       STORE_FAST                      7: cls_name
                        8       LOAD_FAST                       3: indent
                        10      LOAD_GLOBAL                     2: len
                        12      LOAD_FAST                       7: cls_name
                        14      CALL_FUNCTION                   1
                        16      LOAD_CONST                      1: 1
                        18      BINARY_ADD                      
                        20      INPLACE_ADD                     
                        22      STORE_FAST                      3: indent
                        24      LOAD_CLOSURE                    0: object
                        26      BUILD_TUPLE                     1
                        28      LOAD_CONST                      2: <CODE> <listcomp>
                        30      LOAD_CONST                      3: 'PrettyPrinter._pprint_dataclass.<locals>.<listcomp>'
                        32      MAKE_FUNCTION                   8
                        34      LOAD_GLOBAL                     3: _dataclasses
                        36      LOAD_METHOD                     4: fields
                        38      LOAD_DEREF                      0: object
                        40      CALL_METHOD                     1
                        42      GET_ITER                        
                        44      CALL_FUNCTION                   1
                        46      STORE_FAST                      8: items
                        48      LOAD_FAST                       2: stream
                        50      LOAD_METHOD                     5: write
                        52      LOAD_FAST                       7: cls_name
                        54      LOAD_CONST                      4: '('
                        56      BINARY_ADD                      
                        58      CALL_METHOD                     1
                        60      POP_TOP                         
                        62      LOAD_FAST                       0: self
                        64      LOAD_METHOD                     6: _format_namespace_items
                        66      LOAD_FAST                       8: items
                        68      LOAD_FAST                       2: stream
                        70      LOAD_FAST                       3: indent
                        72      LOAD_FAST                       4: allowance
                        74      LOAD_FAST                       5: context
                        76      LOAD_FAST                       6: level
                        78      CALL_METHOD                     6
                        80      POP_TOP                         
                        82      LOAD_FAST                       2: stream
                        84      LOAD_METHOD                     5: write
                        86      LOAD_CONST                      5: ')'
                        88      CALL_METHOD                     1
                        90      POP_TOP                         
                        92      LOAD_CONST                      0: None
                        94      RETURN_VALUE                    
                'PrettyPrinter._pprint_dataclass'
                [Code]
                    File Name: pprint.py
                    Object Name: _pprint_dict
                    Arg Count: 7
                    Pos Only Arg Count: 0
                    KW Only Arg Count: 0
                    Locals: 10
                    Stack Size: 8
                    Flags: 0x00000043 (CO_OPTIMIZED | CO_NEWLOCALS | CO_NOFREE)
                    [Names]
                        'write'
                        '_indent_per_level'
                        'len'
                        '_sort_dicts'
                        'sorted'
                        'items'
                        '_safe_tuple'
                        '_format_dict_items'
                    [Var Names]
                        'self'
                        'object'
                        'stream'
                        'indent'
                        'allowance'
                        'context'
                        'level'
                        'write'
                        'length'
                        'items'
                    [Free Vars]
                    [Cell Vars]
                    [Constants]
                        None
                        '{'
                        1
                        ' '
                        (
                            'key'
                        )
                        '}'
                    [Disassembly]
                        0       LOAD_FAST                       2: stream
                        2       LOAD_ATTR                       0: write
                        4       STORE_FAST                      7: write
                        6       LOAD_FAST                       7: write
                        8       LOAD_CONST                      1: '{'
                        10      CALL_FUNCTION                   1
                        12      POP_TOP                         
                        14      LOAD_FAST                       0: self
                        16      LOAD_ATTR                       1: _indent_per_level
                        18      LOAD_CONST                      2: 1
                        20      COMPARE_OP                      4 (>)
                        22      POP_JUMP_IF_FALSE               21 (to 42)
                        24      LOAD_FAST                       7: write
                        26      LOAD_FAST                       0: self
                        28      LOAD_ATTR                       1: _indent_per_level
                        30      LOAD_CONST                      2: 1
                        32      BINARY_SUBTRACT                 
                        34      LOAD_CONST                      3: ' '
                        36      BINARY_MULTIPLY                 
                        38      CALL_FUNCTION                   1
                        40      POP_TOP                         
                        42      LOAD_GLOBAL                     2: len
                        44      LOAD_FAST                       1: object
                        46      CALL_FUNCTION                   1
                        48      STORE_FAST                      8: length
                        50      LOAD_FAST                       8: length
                        52      POP_JUMP_IF_FALSE               55 (to 110)
                        54      LOAD_FAST                       0: self
                        56      LOAD_ATTR                       3: _sort_dicts
                        58      POP_JUMP_IF_FALSE               39 (to 78)
                        60      LOAD_GLOBAL                     4: sorted
                        62      LOAD_FAST                       1: object
                        64      LOAD_METHOD                     5: items
                        66      CALL_METHOD                     0
                        68      LOAD_GLOBAL                     6: _safe_tuple
                        70      LOAD_CONST                      4: ('key',)
                        72      CALL_FUNCTION_KW                2
                        74      STORE_FAST                      9: items
                        76      JUMP_FORWARD                    4 (to 86)
                        78      LOAD_FAST                       1: object
                        80      LOAD_METHOD                     5: items
                        82      CALL_METHOD                     0
                        84      STORE_FAST                      9: items
                        86      LOAD_FAST                       0: self
                        88      LOAD_METHOD                     7: _format_dict_items
                        90      LOAD_FAST                       9: items
                        92      LOAD_FAST                       2: stream
                        94      LOAD_FAST                       3: indent
                        96      LOAD_FAST                       4: allowance
                        98      LOAD_CONST                      2: 1
                        100     BINARY_ADD                      
                        102     LOAD_FAST                       5: context
                        104     LOAD_FAST                       6: level
                        106     CALL_METHOD                     6
                        108     POP_TOP                         
                        110     LOAD_FAST                       7: write
                        112     LOAD_CONST                      5: '}'
                        114     CALL_FUNCTION                   1
                        116     POP_TOP                         
                        118     LOAD_CONST                      0: None
                        120     RETURN_VALUE                    
                'PrettyPrinter._pprint_dict'
                [Code]
                    File Name: pprint.py
                    Object Name: _pprint_ordered_dict
                    Arg Count: 7
                    Pos Only Arg Count: 0
                    KW Only Arg Count: 0
                    Locals: 8
                    Stack Size: 8
                    Flags: 0x00000043 (CO_OPTIMIZED | CO_NEWLOCALS | CO_NOFREE)
                    [Names]
                        'len'
                        'write'
                        'repr'
                        '__class__'
                        '__name__'
                        '_format'
                        'list'
                        'items'
                    [Var Names]
                        'self'
                        'object'
                        'stream'
                        'indent'
                        'allowance'
                        'context'
                        'level'
                        'cls'
                    [Free Vars]
                    [Cell Vars]
                    [Constants]
                        None
                        '('
                        1
                        ')'
                    [Disassembly]
                        0       LOAD_GLOBAL                     0: len
                        2       LOAD_FAST                       1: object
                        4       CALL_FUNCTION                   1
                        6       POP_JUMP_IF_TRUE                13 (to 26)
                        8       LOAD_FAST                       2: stream
                        10      LOAD_METHOD                     1: write
                        12      LOAD_GLOBAL                     2: repr
                        14      LOAD_FAST                       1: object
                        16      CALL_FUNCTION                   1
                        18      CALL_METHOD                     1
                        20      POP_TOP                         
                        22      LOAD_CONST                      0: None
                        24      RETURN_VALUE                    
                        26      LOAD_FAST                       1: object
                        28      LOAD_ATTR                       3: __class__
                        30      STORE_FAST                      7: cls
                        32      LOAD_FAST                       2: stream
                        34      LOAD_METHOD                     1: write
                        36      LOAD_FAST                       7: cls
                        38      LOAD_ATTR                       4: __name__
                        40      LOAD_CONST                      1: '('
                        42      BINARY_ADD                      
                        44      CALL_METHOD                     1
                        46      POP_TOP                         
                        48      LOAD_FAST                       0: self
                        50      LOAD_METHOD                     5: _format
                        52      LOAD_GLOBAL                     6: list
                        54      LOAD_FAST                       1: object
                        56      LOAD_METHOD                     7: items
                        58      CALL_METHOD                     0
                        60      CALL_FUNCTION                   1
                        62      LOAD_FAST                       2: stream
                        64      LOAD_FAST                       3: indent
                        66      LOAD_GLOBAL                     0: len
                        68      LOAD_FAST                       7: cls
                        70      LOAD_ATTR                       4: __name__
                        72      CALL_FUNCTION                   1
                        74      BINARY_ADD                      
                        76      LOAD_CONST                      2: 1
                        78      BINARY_ADD                      
                        80      LOAD_FAST                       4: allowance
                        82      LOAD_CONST                      2: 1
                        84      BINARY_ADD                      
                        86      LOAD_FAST                       5: context
                        88      LOAD_FAST                       6: level
                        90      CALL_METHOD                     6
                        92      POP_TOP                         
                        94      LOAD_FAST                       2: stream
                        96      LOAD_METHOD                     1: write
                        98      LOAD_CONST                      3: ')'
                        100     CALL_METHOD                     1
                        102     POP_TOP                         
                        104     LOAD_CONST                      0: None
                        106     RETURN_VALUE                    
                'PrettyPrinter._pprint_ordered_dict'
                [Code]
                    File Name: pprint.py
                    Object Name: _pprint_list
                    Arg Count: 7
                    Pos Only Arg Count: 0
                    KW Only Arg Count: 0
                    Locals: 7
                    Stack Size: 8
                    Flags: 0x00000043 (CO_OPTIMIZED | CO_NEWLOCALS | CO_NOFREE)
                    [Names]
                        'write'
                        '_format_items'
                    [Var Names]
                        'self'
                        'object'
                        'stream'
                        'indent'
                        'allowance'
                        'context'
                        'level'
                    [Free Vars]
                    [Cell Vars]
                    [Constants]
                        None
                        '['
                        1
                        ']'
                    [Disassembly]
                        0       LOAD_FAST                       2: stream
                        2       LOAD_METHOD                     0: write
                        4       LOAD_CONST                      1: '['
                        6       CALL_METHOD                     1
                        8       POP_TOP                         
                        10      LOAD_FAST                       0: self
                        12      LOAD_METHOD                     1: _format_items
                        14      LOAD_FAST                       1: object
                        16      LOAD_FAST                       2: stream
                        18      LOAD_FAST                       3: indent
                        20      LOAD_FAST                       4: allowance
                        22      LOAD_CONST                      2: 1
                        24      BINARY_ADD                      
                        26      LOAD_FAST                       5: context
                        28      LOAD_FAST                       6: level
                        30      CALL_METHOD                     6
                        32      POP_TOP                         
                        34      LOAD_FAST                       2: stream
                        36      LOAD_METHOD                     0: write
                        38      LOAD_CONST                      3: ']'
                        40      CALL_METHOD                     1
                        42      POP_TOP                         
                        44      LOAD_CONST                      0: None
                        46      RETURN_VALUE                    
                'PrettyPrinter._pprint_list'
                [Code]
                    File Name: pprint.py
                    Object Name: _pprint_tuple
                    Arg Count: 7
                    Pos Only Arg Count: 0
                    KW Only Arg Count: 0
                    Locals: 8
                    Stack Size: 8
                    Flags: 0x00000043 (CO_OPTIMIZED | CO_NEWLOCALS | CO_NOFREE)
                    [Names]
                        'write'
                        'len'
                        '_format_items'
                    [Var Names]
                        'self'
                        'object'
                        'stream'
                        'indent'
                        'allowance'
                        'context'
                        'level'
                        'endchar'
                    [Free Vars]
                    [Cell Vars]
                    [Constants]
                        None
                        '('
                        1
                        ',)'
                        ')'
                    [Disassembly]
                        0       LOAD_FAST                       2: stream
                        2       LOAD_METHOD                     0: write
                        4       LOAD_CONST                      1: '('
                        6       CALL_METHOD                     1
                        8       POP_TOP                         
                        10      LOAD_GLOBAL                     1: len
                        12      LOAD_FAST                       1: object
                        14      CALL_FUNCTION                   1
                        16      LOAD_CONST                      2: 1
                        18      COMPARE_OP                      2 (==)
                        20      POP_JUMP_IF_FALSE               13 (to 26)
                        22      LOAD_CONST                      3: ',)'
                        24      JUMP_FORWARD                    1 (to 28)
                        26      LOAD_CONST                      4: ')'
                        28      STORE_FAST                      7: endchar
                        30      LOAD_FAST                       0: self
                        32      LOAD_METHOD                     2: _format_items
                        34      LOAD_FAST                       1: object
                        36      LOAD_FAST                       2: stream
                        38      LOAD_FAST                       3: indent
                        40      LOAD_FAST                       4: allowance
                        42      LOAD_GLOBAL                     1: len
                        44      LOAD_FAST                       7: endchar
                        46      CALL_FUNCTION                   1
                        48      BINARY_ADD                      
                        50      LOAD_FAST                       5: context
                        52      LOAD_FAST                       6: level
                        54      CALL_METHOD                     6
                        56      POP_TOP                         
                        58      LOAD_FAST                       2: stream
                        60      LOAD_METHOD                     0: write
                        62      LOAD_FAST                       7: endchar
                        64      CALL_METHOD                     1
                        66      POP_TOP                         
                        68      LOAD_CONST                      0: None
                        70      RETURN_VALUE                    
                'PrettyPrinter._pprint_tuple'
                [Code]
                    File Name: pprint.py
                    Object Name: _pprint_set
                    Arg Count: 7
                    Pos Only Arg Count: 0
                    KW Only Arg Count: 0
                    Locals: 9
                    Stack Size: 8
                    Flags: 0x00000043 (CO_OPTIMIZED | CO_NEWLOCALS | CO_NOFREE)
                    [Names]
                        'len'
                        'write'
                        'repr'
                        '__class__'
                        'set'
                        '__name__'
                        'sorted'
                        '_safe_key'
                        '_format_items'
                    [Var Names]
                        'self'
                        'object'
                        'stream'
                        'indent'
                        'allowance'
                        'context'
                        'level'
                        'typ'
                        'endchar'
                    [Free Vars]
                    [Cell Vars]
                    [Constants]
                        None
                        '{'
                        '}'
                        '({'
                        '})'
                        1
                        (
                            'key'
                        )
                    [Disassembly]
                        0       LOAD_GLOBAL                     0: len
                        2       LOAD_FAST                       1: object
                        4       CALL_FUNCTION                   1
                        6       POP_JUMP_IF_TRUE                13 (to 26)
                        8       LOAD_FAST                       2: stream
                        10      LOAD_METHOD                     1: write
                        12      LOAD_GLOBAL                     2: repr
                        14      LOAD_FAST                       1: object
                        16      CALL_FUNCTION                   1
                        18      CALL_METHOD                     1
                        20      POP_TOP                         
                        22      LOAD_CONST                      0: None
                        24      RETURN_VALUE                    
                        26      LOAD_FAST                       1: object
                        28      LOAD_ATTR                       3: __class__
                        30      STORE_FAST                      7: typ
                        32      LOAD_FAST                       7: typ
                        34      LOAD_GLOBAL                     4: set
                        36      IS_OP                           0 (is)
                        38      POP_JUMP_IF_FALSE               28 (to 56)
                        40      LOAD_FAST                       2: stream
                        42      LOAD_METHOD                     1: write
                        44      LOAD_CONST                      1: '{'
                        46      CALL_METHOD                     1
                        48      POP_TOP                         
                        50      LOAD_CONST                      2: '}'
                        52      STORE_FAST                      8: endchar
                        54      JUMP_FORWARD                    19 (to 94)
                        56      LOAD_FAST                       2: stream
                        58      LOAD_METHOD                     1: write
                        60      LOAD_FAST                       7: typ
                        62      LOAD_ATTR                       5: __name__
                        64      LOAD_CONST                      3: '({'
                        66      BINARY_ADD                      
                        68      CALL_METHOD                     1
                        70      POP_TOP                         
                        72      LOAD_CONST                      4: '})'
                        74      STORE_FAST                      8: endchar
                        76      LOAD_FAST                       3: indent
                        78      LOAD_GLOBAL                     0: len
                        80      LOAD_FAST                       7: typ
                        82      LOAD_ATTR                       5: __name__
                        84      CALL_FUNCTION                   1
                        86      LOAD_CONST                      5: 1
                        88      BINARY_ADD                      
                        90      INPLACE_ADD                     
                        92      STORE_FAST                      3: indent
                        94      LOAD_GLOBAL                     6: sorted
                        96      LOAD_FAST                       1: object
                        98      LOAD_GLOBAL                     7: _safe_key
                        100     LOAD_CONST                      6: ('key',)
                        102     CALL_FUNCTION_KW                2
                        104     STORE_FAST                      1: object
                        106     LOAD_FAST                       0: self
                        108     LOAD_METHOD                     8: _format_items
                        110     LOAD_FAST                       1: object
                        112     LOAD_FAST                       2: stream
                        114     LOAD_FAST                       3: indent
                        116     LOAD_FAST                       4: allowance
                        118     LOAD_GLOBAL                     0: len
                        120     LOAD_FAST                       8: endchar
                        122     CALL_FUNCTION                   1
                        124     BINARY_ADD                      
                        126     LOAD_FAST                       5: context
                        128     LOAD_FAST                       6: level
                        130     CALL_METHOD                     6
                        132     POP_TOP                         
                        134     LOAD_FAST                       2: stream
                        136     LOAD_METHOD                     1: write
                        138     LOAD_FAST                       8: endchar
                        140     CALL_METHOD                     1
                        142     POP_TOP                         
                        144     LOAD_CONST                      0: None
                        146     RETURN_VALUE                    
                'PrettyPrinter._pprint_set'
                [Code]
                    File Name: pprint.py
                    Object Name: _pprint_str
                    Arg Count: 7
                    Pos Only Arg Count: 0
                    KW Only Arg Count: 0
                    Locals: 21
                    Stack Size: 6
                    Flags: 0x00000043 (CO_OPTIMIZED | CO_NEWLOCALS | CO_NOFREE)
                    [Names]
                        'write'
                        'len'
                        'repr'
                        'splitlines'
                        '_width'
                        'enumerate'
                        'append'
                        're'
                        'findall'
                        'pop'
                    [Var Names]
                        'self'
                        'object'
                        'stream'
                        'indent'
                        'allowance'
                        'context'
                        'level'
                        'write'
                        'chunks'
                        'lines'
                        'max_width1'
                        'max_width'
                        'i'
                        'line'
                        'rep'
                        'parts'
                        'max_width2'
                        'current'
                        'j'
                        'part'
                        'candidate'
                    [Free Vars]
                    [Cell Vars]
                    [Constants]
                        None
                        True
                        1
                        '\\S*\\s*'
                        -1
                        ''
                        '('
                        0
                        '\n'
                        ' '
                        ')'
                    [Disassembly]
                        0       LOAD_FAST                       2: stream
                        2       LOAD_ATTR                       0: write
                        4       STORE_FAST                      7: write
                        6       LOAD_GLOBAL                     1: len
                        8       LOAD_FAST                       1: object
                        10      CALL_FUNCTION                   1
                        12      POP_JUMP_IF_TRUE                15 (to 30)
                        14      LOAD_FAST                       7: write
                        16      LOAD_GLOBAL                     2: repr
                        18      LOAD_FAST                       1: object
                        20      CALL_FUNCTION                   1
                        22      CALL_FUNCTION                   1
                        24      POP_TOP                         
                        26      LOAD_CONST                      0: None
                        28      RETURN_VALUE                    
                        30      BUILD_LIST                      0
                        32      STORE_FAST                      8: chunks
                        34      LOAD_FAST                       1: object
                        36      LOAD_METHOD                     3: splitlines
                        38      LOAD_CONST                      1: True
                        40      CALL_METHOD                     1
                        42      STORE_FAST                      9: lines
                        44      LOAD_FAST                       6: level
                        46      LOAD_CONST                      2: 1
                        48      COMPARE_OP                      2 (==)
                        50      POP_JUMP_IF_FALSE               34 (to 68)
                        52      LOAD_FAST                       3: indent
                        54      LOAD_CONST                      2: 1
                        56      INPLACE_ADD                     
                        58      STORE_FAST                      3: indent
                        60      LOAD_FAST                       4: allowance
                        62      LOAD_CONST                      2: 1
                        64      INPLACE_ADD                     
                        66      STORE_FAST                      4: allowance
                        68      LOAD_FAST                       0: self
                        70      LOAD_ATTR                       4: _width
                        72      LOAD_FAST                       3: indent
                        74      BINARY_SUBTRACT                 
                        76      DUP_TOP                         
                        78      STORE_FAST                      10: max_width1
                        80      STORE_FAST                      11: max_width
                        82      LOAD_GLOBAL                     5: enumerate
                        84      LOAD_FAST                       9: lines
                        86      CALL_FUNCTION                   1
                        88      GET_ITER                        
                        90      FOR_ITER                        120 (to 332)
                        92      UNPACK_SEQUENCE                 2
                        94      STORE_FAST                      12: i
                        96      STORE_FAST                      13: line
                        98      LOAD_GLOBAL                     2: repr
                        100     LOAD_FAST                       13: line
                        102     CALL_FUNCTION                   1
                        104     STORE_FAST                      14: rep
                        106     LOAD_FAST                       12: i
                        108     LOAD_GLOBAL                     1: len
                        110     LOAD_FAST                       9: lines
                        112     CALL_FUNCTION                   1
                        114     LOAD_CONST                      2: 1
                        116     BINARY_SUBTRACT                 
                        118     COMPARE_OP                      2 (==)
                        120     POP_JUMP_IF_FALSE               65 (to 130)
                        122     LOAD_FAST                       10: max_width1
                        124     LOAD_FAST                       4: allowance
                        126     INPLACE_SUBTRACT                
                        128     STORE_FAST                      10: max_width1
                        130     LOAD_GLOBAL                     1: len
                        132     LOAD_FAST                       14: rep
                        134     CALL_FUNCTION                   1
                        136     LOAD_FAST                       10: max_width1
                        138     COMPARE_OP                      1 (<=)
                        140     POP_JUMP_IF_FALSE               77 (to 154)
                        142     LOAD_FAST                       8: chunks
                        144     LOAD_METHOD                     6: append
                        146     LOAD_FAST                       14: rep
                        148     CALL_METHOD                     1
                        150     POP_TOP                         
                        152     JUMP_ABSOLUTE                   45 (to 90)
                        154     LOAD_GLOBAL                     7: re
                        156     LOAD_METHOD                     8: findall
                        158     LOAD_CONST                      3: '\\S*\\s*'
                        160     LOAD_FAST                       13: line
                        162     CALL_METHOD                     2
                        164     STORE_FAST                      15: parts
                        166     LOAD_FAST                       15: parts
                        168     POP_JUMP_IF_TRUE                87 (to 174)
                        170     LOAD_ASSERTION_ERROR            
                        172     RAISE_VARARGS                   1
                        174     LOAD_FAST                       15: parts
                        176     LOAD_CONST                      4: -1
                        178     BINARY_SUBSCR                   
                        180     POP_JUMP_IF_FALSE               93 (to 186)
                        182     LOAD_ASSERTION_ERROR            
                        184     RAISE_VARARGS                   1
                        186     LOAD_FAST                       15: parts
                        188     LOAD_METHOD                     9: pop
                        190     CALL_METHOD                     0
                        192     POP_TOP                         
                        194     LOAD_FAST                       11: max_width
                        196     STORE_FAST                      16: max_width2
                        198     LOAD_CONST                      5: ''
                        200     STORE_FAST                      17: current
                        202     LOAD_GLOBAL                     5: enumerate
                        204     LOAD_FAST                       15: parts
                        206     CALL_FUNCTION                   1
                        208     GET_ITER                        
                        210     FOR_ITER                        50 (to 312)
                        212     UNPACK_SEQUENCE                 2
                        214     STORE_FAST                      18: j
                        216     STORE_FAST                      19: part
                        218     LOAD_FAST                       17: current
                        220     LOAD_FAST                       19: part
                        222     BINARY_ADD                      
                        224     STORE_FAST                      20: candidate
                        226     LOAD_FAST                       18: j
                        228     LOAD_GLOBAL                     1: len
                        230     LOAD_FAST                       15: parts
                        232     CALL_FUNCTION                   1
                        234     LOAD_CONST                      2: 1
                        236     BINARY_SUBTRACT                 
                        238     COMPARE_OP                      2 (==)
                        240     POP_JUMP_IF_FALSE               133 (to 266)
                        242     LOAD_FAST                       12: i
                        244     LOAD_GLOBAL                     1: len
                        246     LOAD_FAST                       9: lines
                        248     CALL_FUNCTION                   1
                        250     LOAD_CONST                      2: 1
                        252     BINARY_SUBTRACT                 
                        254     COMPARE_OP                      2 (==)
                        256     POP_JUMP_IF_FALSE               133 (to 266)
                        258     LOAD_FAST                       16: max_width2
                        260     LOAD_FAST                       4: allowance
                        262     INPLACE_SUBTRACT                
                        264     STORE_FAST                      16: max_width2
                        266     LOAD_GLOBAL                     1: len
                        268     LOAD_GLOBAL                     2: repr
                        270     LOAD_FAST                       20: candidate
                        272     CALL_FUNCTION                   1
                        274     CALL_FUNCTION                   1
                        276     LOAD_FAST                       16: max_width2
                        278     COMPARE_OP                      4 (>)
                        280     POP_JUMP_IF_FALSE               153 (to 306)
                        282     LOAD_FAST                       17: current
                        284     POP_JUMP_IF_FALSE               150 (to 300)
                        286     LOAD_FAST                       8: chunks
                        288     LOAD_METHOD                     6: append
                        290     LOAD_GLOBAL                     2: repr
                        292     LOAD_FAST                       17: current
                        294     CALL_FUNCTION                   1
                        296     CALL_METHOD                     1
                        298     POP_TOP                         
                        300     LOAD_FAST                       19: part
                        302     STORE_FAST                      17: current
                        304     JUMP_ABSOLUTE                   105 (to 210)
                        306     LOAD_FAST                       20: candidate
                        308     STORE_FAST                      17: current
                        310     JUMP_ABSOLUTE                   105 (to 210)
                        312     LOAD_FAST                       17: current
                        314     POP_JUMP_IF_FALSE               165 (to 330)
                        316     LOAD_FAST                       8: chunks
                        318     LOAD_METHOD                     6: append
                        320     LOAD_GLOBAL                     2: repr
                        322     LOAD_FAST                       17: current
                        324     CALL_FUNCTION                   1
                        326     CALL_METHOD                     1
                        328     POP_TOP                         
                        330     JUMP_ABSOLUTE                   45 (to 90)
                        332     LOAD_GLOBAL                     1: len
                        334     LOAD_FAST                       8: chunks
                        336     CALL_FUNCTION                   1
                        338     LOAD_CONST                      2: 1
                        340     COMPARE_OP                      2 (==)
                        342     POP_JUMP_IF_FALSE               178 (to 356)
                        344     LOAD_FAST                       7: write
                        346     LOAD_FAST                       14: rep
                        348     CALL_FUNCTION                   1
                        350     POP_TOP                         
                        352     LOAD_CONST                      0: None
                        354     RETURN_VALUE                    
                        356     LOAD_FAST                       6: level
                        358     LOAD_CONST                      2: 1
                        360     COMPARE_OP                      2 (==)
                        362     POP_JUMP_IF_FALSE               186 (to 372)
                        364     LOAD_FAST                       7: write
                        366     LOAD_CONST                      6: '('
                        368     CALL_FUNCTION                   1
                        370     POP_TOP                         
                        372     LOAD_GLOBAL                     5: enumerate
                        374     LOAD_FAST                       8: chunks
                        376     CALL_FUNCTION                   1
                        378     GET_ITER                        
                        380     FOR_ITER                        20 (to 422)
                        382     UNPACK_SEQUENCE                 2
                        384     STORE_FAST                      12: i
                        386     STORE_FAST                      14: rep
                        388     LOAD_FAST                       12: i
                        390     LOAD_CONST                      7: 0
                        392     COMPARE_OP                      4 (>)
                        394     POP_JUMP_IF_FALSE               206 (to 412)
                        396     LOAD_FAST                       7: write
                        398     LOAD_CONST                      8: '\n'
                        400     LOAD_CONST                      9: ' '
                        402     LOAD_FAST                       3: indent
                        404     BINARY_MULTIPLY                 
                        406     BINARY_ADD                      
                        408     CALL_FUNCTION                   1
                        410     POP_TOP                         
                        412     LOAD_FAST                       7: write
                        414     LOAD_FAST                       14: rep
                        416     CALL_FUNCTION                   1
                        418     POP_TOP                         
                        420     JUMP_ABSOLUTE                   190 (to 380)
                        422     LOAD_FAST                       6: level
                        424     LOAD_CONST                      2: 1
                        426     COMPARE_OP                      2 (==)
                        428     POP_JUMP_IF_FALSE               221 (to 442)
                        430     LOAD_FAST                       7: write
                        432     LOAD_CONST                      10: ')'
                        434     CALL_FUNCTION                   1
                        436     POP_TOP                         
                        438     LOAD_CONST                      0: None
                        440     RETURN_VALUE                    
                        442     LOAD_CONST                      0: None
                        444     RETURN_VALUE                    
                'PrettyPrinter._pprint_str'
                [Code]
                    File Name: pprint.py
                    Object Name: _pprint_bytes
                    Arg Count: 7
                    Pos Only Arg Count: 0
                    KW Only Arg Count: 0
                    Locals: 11
                    Stack Size: 4
                    Flags: 0x00000043 (CO_OPTIMIZED | CO_NEWLOCALS | CO_NOFREE)
                    [Names]
                        'write'
                        'len'
                        'repr'
                        '_wrap_bytes_repr'
                        '_width'
                    [Var Names]
                        'self'
                        'object'
                        'stream'
                        'indent'
                        'allowance'
                        'context'
                        'level'
                        'write'
                        'parens'
                        'delim'
                        'rep'
                    [Free Vars]
                    [Cell Vars]
                    [Constants]
                        None
                        4
                        1
                        '('
                        ''
                        '\n'
                        ' '
                        ')'
                    [Disassembly]
                        0       LOAD_FAST                       2: stream
                        2       LOAD_ATTR                       0: write
                        4       STORE_FAST                      7: write
                        6       LOAD_GLOBAL                     1: len
                        8       LOAD_FAST                       1: object
                        10      CALL_FUNCTION                   1
                        12      LOAD_CONST                      1: 4
                        14      COMPARE_OP                      1 (<=)
                        16      POP_JUMP_IF_FALSE               17 (to 34)
                        18      LOAD_FAST                       7: write
                        20      LOAD_GLOBAL                     2: repr
                        22      LOAD_FAST                       1: object
                        24      CALL_FUNCTION                   1
                        26      CALL_FUNCTION                   1
                        28      POP_TOP                         
                        30      LOAD_CONST                      0: None
                        32      RETURN_VALUE                    
                        34      LOAD_FAST                       6: level
                        36      LOAD_CONST                      2: 1
                        38      COMPARE_OP                      2 (==)
                        40      STORE_FAST                      8: parens
                        42      LOAD_FAST                       8: parens
                        44      POP_JUMP_IF_FALSE               35 (to 70)
                        46      LOAD_FAST                       3: indent
                        48      LOAD_CONST                      2: 1
                        50      INPLACE_ADD                     
                        52      STORE_FAST                      3: indent
                        54      LOAD_FAST                       4: allowance
                        56      LOAD_CONST                      2: 1
                        58      INPLACE_ADD                     
                        60      STORE_FAST                      4: allowance
                        62      LOAD_FAST                       7: write
                        64      LOAD_CONST                      3: '('
                        66      CALL_FUNCTION                   1
                        68      POP_TOP                         
                        70      LOAD_CONST                      4: ''
                        72      STORE_FAST                      9: delim
                        74      LOAD_GLOBAL                     3: _wrap_bytes_repr
                        76      LOAD_FAST                       1: object
                        78      LOAD_FAST                       0: self
                        80      LOAD_ATTR                       4: _width
                        82      LOAD_FAST                       3: indent
                        84      BINARY_SUBTRACT                 
                        86      LOAD_FAST                       4: allowance
                        88      CALL_FUNCTION                   3
                        90      GET_ITER                        
                        92      FOR_ITER                        18 (to 130)
                        94      STORE_FAST                      10: rep
                        96      LOAD_FAST                       7: write
                        98      LOAD_FAST                       9: delim
                        100     CALL_FUNCTION                   1
                        102     POP_TOP                         
                        104     LOAD_FAST                       7: write
                        106     LOAD_FAST                       10: rep
                        108     CALL_FUNCTION                   1
                        110     POP_TOP                         
                        112     LOAD_FAST                       9: delim
                        114     POP_JUMP_IF_TRUE                64 (to 128)
                        116     LOAD_CONST                      5: '\n'
                        118     LOAD_CONST                      6: ' '
                        120     LOAD_FAST                       3: indent
                        122     BINARY_MULTIPLY                 
                        124     BINARY_ADD                      
                        126     STORE_FAST                      9: delim
                        128     JUMP_ABSOLUTE                   46 (to 92)
                        130     LOAD_FAST                       8: parens
                        132     POP_JUMP_IF_FALSE               73 (to 146)
                        134     LOAD_FAST                       7: write
                        136     LOAD_CONST                      7: ')'
                        138     CALL_FUNCTION                   1
                        140     POP_TOP                         
                        142     LOAD_CONST                      0: None
                        144     RETURN_VALUE                    
                        146     LOAD_CONST                      0: None
                        148     RETURN_VALUE                    
                'PrettyPrinter._pprint_bytes'
                [Code]
                    File Name: pprint.py
                    Object Name: _pprint_bytearray
                    Arg Count: 7
                    Pos Only Arg Count: 0
                    KW Only Arg Count: 0
                    Locals: 8
                    Stack Size: 9
                    Flags: 0x00000043 (CO_OPTIMIZED | CO_NEWLOCALS | CO_NOFREE)
                    [Names]
                        'write'
                        '_pprint_bytes'
                        'bytes'
                    [Var Names]
                        'self'
                        'object'
                        'stream'
                        'indent'
                        'allowance'
                        'context'
                        'level'
                        'write'
                    [Free Vars]
                    [Cell Vars]
                    [Constants]
                        None
                        'bytearray('
                        10
                        1
                        ')'
                    [Disassembly]
                        0       LOAD_FAST                       2: stream
                        2       LOAD_ATTR                       0: write
                        4       STORE_FAST                      7: write
                        6       LOAD_FAST                       7: write
                        8       LOAD_CONST                      1: 'bytearray('
                        10      CALL_FUNCTION                   1
                        12      POP_TOP                         
                        14      LOAD_FAST                       0: self
                        16      LOAD_METHOD                     1: _pprint_bytes
                        18      LOAD_GLOBAL                     2: bytes
                        20      LOAD_FAST                       1: object
                        22      CALL_FUNCTION                   1
                        24      LOAD_FAST                       2: stream
                        26      LOAD_FAST                       3: indent
                        28      LOAD_CONST                      2: 10
                        30      BINARY_ADD                      
                        32      LOAD_FAST                       4: allowance
                        34      LOAD_CONST                      3: 1
                        36      BINARY_ADD                      
                        38      LOAD_FAST                       5: context
                        40      LOAD_FAST                       6: level
                        42      LOAD_CONST                      3: 1
                        44      BINARY_ADD                      
                        46      CALL_METHOD                     6
                        48      POP_TOP                         
                        50      LOAD_FAST                       7: write
                        52      LOAD_CONST                      4: ')'
                        54      CALL_FUNCTION                   1
                        56      POP_TOP                         
                        58      LOAD_CONST                      0: None
                        60      RETURN_VALUE                    
                'PrettyPrinter._pprint_bytearray'
                [Code]
                    File Name: pprint.py
                    Object Name: _pprint_mappingproxy
                    Arg Count: 7
                    Pos Only Arg Count: 0
                    KW Only Arg Count: 0
                    Locals: 7
                    Stack Size: 8
                    Flags: 0x00000043 (CO_OPTIMIZED | CO_NEWLOCALS | CO_NOFREE)
                    [Names]
                        'write'
                        '_format'
                        'copy'
                    [Var Names]
                        'self'
                        'object'
                        'stream'
                        'indent'
                        'allowance'
                        'context'
                        'level'
                    [Free Vars]
                    [Cell Vars]
                    [Constants]
                        None
                        'mappingproxy('
                        13
                        1
                        ')'
                    [Disassembly]
                        0       LOAD_FAST                       2: stream
                        2       LOAD_METHOD                     0: write
                        4       LOAD_CONST                      1: 'mappingproxy('
                        6       CALL_METHOD                     1
                        8       POP_TOP                         
                        10      LOAD_FAST                       0: self
                        12      LOAD_METHOD                     1: _format
                        14      LOAD_FAST                       1: object
                        16      LOAD_METHOD                     2: copy
                        18      CALL_METHOD                     0
                        20      LOAD_FAST                       2: stream
                        22      LOAD_FAST                       3: indent
                        24      LOAD_CONST                      2: 13
                        26      BINARY_ADD                      
                        28      LOAD_FAST                       4: allowance
                        30      LOAD_CONST                      3: 1
                        32      BINARY_ADD                      
                        34      LOAD_FAST                       5: context
                        36      LOAD_FAST                       6: level
                        38      CALL_METHOD                     6
                        40      POP_TOP                         
                        42      LOAD_FAST                       2: stream
                        44      LOAD_METHOD                     0: write
                        46      LOAD_CONST                      4: ')'
                        48      CALL_METHOD                     1
                        50      POP_TOP                         
                        52      LOAD_CONST                      0: None
                        54      RETURN_VALUE                    
                'PrettyPrinter._pprint_mappingproxy'
                [Code]
                    File Name: pprint.py
                    Object Name: _pprint_simplenamespace
                    Arg Count: 7
                    Pos Only Arg Count: 0
                    KW Only Arg Count: 0
                    Locals: 9
                    Stack Size: 8
                    Flags: 0x00000043 (CO_OPTIMIZED | CO_NEWLOCALS | CO_NOFREE)
                    [Names]
                        'type'
                        '_types'
                        'SimpleNamespace'
                        '__class__'
                        '__name__'
                        'len'
                        '__dict__'
                        'items'
                        'write'
                        '_format_namespace_items'
                    [Var Names]
                        'self'
                        'object'
                        'stream'
                        'indent'
                        'allowance'
                        'context'
                        'level'
                        'cls_name'
                        'items'
                    [Free Vars]
                    [Cell Vars]
                    [Constants]
                        None
                        'namespace'
                        1
                        '('
                        ')'
                    [Disassembly]
                        0       LOAD_GLOBAL                     0: type
                        2       LOAD_FAST                       1: object
                        4       CALL_FUNCTION                   1
                        6       LOAD_GLOBAL                     1: _types
                        8       LOAD_ATTR                       2: SimpleNamespace
                        10      IS_OP                           0 (is)
                        12      POP_JUMP_IF_FALSE               10 (to 20)
                        14      LOAD_CONST                      1: 'namespace'
                        16      STORE_FAST                      7: cls_name
                        18      JUMP_FORWARD                    4 (to 28)
                        20      LOAD_FAST                       1: object
                        22      LOAD_ATTR                       3: __class__
                        24      LOAD_ATTR                       4: __name__
                        26      STORE_FAST                      7: cls_name
                        28      LOAD_FAST                       3: indent
                        30      LOAD_GLOBAL                     5: len
                        32      LOAD_FAST                       7: cls_name
                        34      CALL_FUNCTION                   1
                        36      LOAD_CONST                      2: 1
                        38      BINARY_ADD                      
                        40      INPLACE_ADD                     
                        42      STORE_FAST                      3: indent
                        44      LOAD_FAST                       1: object
                        46      LOAD_ATTR                       6: __dict__
                        48      LOAD_METHOD                     7: items
                        50      CALL_METHOD                     0
                        52      STORE_FAST                      8: items
                        54      LOAD_FAST                       2: stream
                        56      LOAD_METHOD                     8: write
                        58      LOAD_FAST                       7: cls_name
                        60      LOAD_CONST                      3: '('
                        62      BINARY_ADD                      
                        64      CALL_METHOD                     1
                        66      POP_TOP                         
                        68      LOAD_FAST                       0: self
                        70      LOAD_METHOD                     9: _format_namespace_items
                        72      LOAD_FAST                       8: items
                        74      LOAD_FAST                       2: stream
                        76      LOAD_FAST                       3: indent
                        78      LOAD_FAST                       4: allowance
                        80      LOAD_FAST                       5: context
                        82      LOAD_FAST                       6: level
                        84      CALL_METHOD                     6
                        86      POP_TOP                         
                        88      LOAD_FAST                       2: stream
                        90      LOAD_METHOD                     8: write
                        92      LOAD_CONST                      4: ')'
                        94      CALL_METHOD                     1
                        96      POP_TOP                         
                        98      LOAD_CONST                      0: None
                        100     RETURN_VALUE                    
                'PrettyPrinter._pprint_simplenamespace'
                [Code]
                    File Name: pprint.py
                    Object Name: _format_dict_items
                    Arg Count: 7
                    Pos Only Arg Count: 0
                    KW Only Arg Count: 0
                    Locals: 15
                    Stack Size: 9
                    Flags: 0x00000043 (CO_OPTIMIZED | CO_NEWLOCALS | CO_NOFREE)
                    [Names]
                        'write'
                        '_indent_per_level'
                        'len'
                        'enumerate'
                        '_repr'
                        '_format'
                    [Var Names]
                        'self'
                        'items'
                        'stream'
                        'indent'
                        'allowance'
                        'context'
                        'level'
                        'write'
                        'delimnl'
                        'last_index'
                        'i'
                        'key'
                        'ent'
                        'last'
                        'rep'
                    [Free Vars]
                    [Cell Vars]
                    [Constants]
                        None
                        ',\n'
                        ' '
                        1
                        ': '
                        2
                    [Disassembly]
                        0       LOAD_FAST                       2: stream
                        2       LOAD_ATTR                       0: write
                        4       STORE_FAST                      7: write
                        6       LOAD_FAST                       3: indent
                        8       LOAD_FAST                       0: self
                        10      LOAD_ATTR                       1: _indent_per_level
                        12      INPLACE_ADD                     
                        14      STORE_FAST                      3: indent
                        16      LOAD_CONST                      1: ',\n'
                        18      LOAD_CONST                      2: ' '
                        20      LOAD_FAST                       3: indent
                        22      BINARY_MULTIPLY                 
                        24      BINARY_ADD                      
                        26      STORE_FAST                      8: delimnl
                        28      LOAD_GLOBAL                     2: len
                        30      LOAD_FAST                       1: items
                        32      CALL_FUNCTION                   1
                        34      LOAD_CONST                      3: 1
                        36      BINARY_SUBTRACT                 
                        38      STORE_FAST                      9: last_index
                        40      LOAD_GLOBAL                     3: enumerate
                        42      LOAD_FAST                       1: items
                        44      CALL_FUNCTION                   1
                        46      GET_ITER                        
                        48      FOR_ITER                        51 (to 152)
                        50      UNPACK_SEQUENCE                 2
                        52      STORE_FAST                      10: i
                        54      UNPACK_SEQUENCE                 2
                        56      STORE_FAST                      11: key
                        58      STORE_FAST                      12: ent
                        60      LOAD_FAST                       10: i
                        62      LOAD_FAST                       9: last_index
                        64      COMPARE_OP                      2 (==)
                        66      STORE_FAST                      13: last
                        68      LOAD_FAST                       0: self
                        70      LOAD_METHOD                     4: _repr
                        72      LOAD_FAST                       11: key
                        74      LOAD_FAST                       5: context
                        76      LOAD_FAST                       6: level
                        78      CALL_METHOD                     3
                        80      STORE_FAST                      14: rep
                        82      LOAD_FAST                       7: write
                        84      LOAD_FAST                       14: rep
                        86      CALL_FUNCTION                   1
                        88      POP_TOP                         
                        90      LOAD_FAST                       7: write
                        92      LOAD_CONST                      4: ': '
                        94      CALL_FUNCTION                   1
                        96      POP_TOP                         
                        98      LOAD_FAST                       0: self
                        100     LOAD_METHOD                     5: _format
                        102     LOAD_FAST                       12: ent
                        104     LOAD_FAST                       2: stream
                        106     LOAD_FAST                       3: indent
                        108     LOAD_GLOBAL                     2: len
                        110     LOAD_FAST                       14: rep
                        112     CALL_FUNCTION                   1
                        114     BINARY_ADD                      
                        116     LOAD_CONST                      5: 2
                        118     BINARY_ADD                      
                        120     LOAD_FAST                       13: last
                        122     POP_JUMP_IF_FALSE               64 (to 128)
                        124     LOAD_FAST                       4: allowance
                        126     JUMP_FORWARD                    1 (to 130)
                        128     LOAD_CONST                      3: 1
                        130     LOAD_FAST                       5: context
                        132     LOAD_FAST                       6: level
                        134     CALL_METHOD                     6
                        136     POP_TOP                         
                        138     LOAD_FAST                       13: last
                        140     POP_JUMP_IF_TRUE                75 (to 150)
                        142     LOAD_FAST                       7: write
                        144     LOAD_FAST                       8: delimnl
                        146     CALL_FUNCTION                   1
                        148     POP_TOP                         
                        150     JUMP_ABSOLUTE                   24 (to 48)
                        152     LOAD_CONST                      0: None
                        154     RETURN_VALUE                    
                'PrettyPrinter._format_dict_items'
                [Code]
                    File Name: pprint.py
                    Object Name: _format_namespace_items
                    Arg Count: 7
                    Pos Only Arg Count: 0
                    KW Only Arg Count: 0
                    Locals: 14
                    Stack Size: 9
                    Flags: 0x00000043 (CO_OPTIMIZED | CO_NEWLOCALS | CO_NOFREE)
                    [Names]
                        'write'
                        'len'
                        'enumerate'
                        'id'
                        '_format'
                    [Var Names]
                        'self'
                        'items'
                        'stream'
                        'indent'
                        'allowance'
                        'context'
                        'level'
                        'write'
                        'delimnl'
                        'last_index'
                        'i'
                        'key'
                        'ent'
                        'last'
                    [Free Vars]
                    [Cell Vars]
                    [Constants]
                        None
                        ',\n'
                        ' '
                        1
                        '='
                        '...'
                    [Disassembly]
                        0       LOAD_FAST                       2: stream
                        2       LOAD_ATTR                       0: write
                        4       STORE_FAST                      7: write
                        6       LOAD_CONST                      1: ',\n'
                        8       LOAD_CONST                      2: ' '
                        10      LOAD_FAST                       3: indent
                        12      BINARY_MULTIPLY                 
                        14      BINARY_ADD                      
                        16      STORE_FAST                      8: delimnl
                        18      LOAD_GLOBAL                     1: len
                        20      LOAD_FAST                       1: items
                        22      CALL_FUNCTION                   1
                        24      LOAD_CONST                      3: 1
                        26      BINARY_SUBTRACT                 
                        28      STORE_FAST                      9: last_index
                        30      LOAD_GLOBAL                     2: enumerate
                        32      LOAD_FAST                       1: items
                        34      CALL_FUNCTION                   1
                        36      GET_ITER                        
                        38      FOR_ITER                        55 (to 150)
                        40      UNPACK_SEQUENCE                 2
                        42      STORE_FAST                      10: i
                        44      UNPACK_SEQUENCE                 2
                        46      STORE_FAST                      11: key
                        48      STORE_FAST                      12: ent
                        50      LOAD_FAST                       10: i
                        52      LOAD_FAST                       9: last_index
                        54      COMPARE_OP                      2 (==)
                        56      STORE_FAST                      13: last
                        58      LOAD_FAST                       7: write
                        60      LOAD_FAST                       11: key
                        62      CALL_FUNCTION                   1
                        64      POP_TOP                         
                        66      LOAD_FAST                       7: write
                        68      LOAD_CONST                      4: '='
                        70      CALL_FUNCTION                   1
                        72      POP_TOP                         
                        74      LOAD_GLOBAL                     3: id
                        76      LOAD_FAST                       12: ent
                        78      CALL_FUNCTION                   1
                        80      LOAD_FAST                       5: context
                        82      CONTAINS_OP                     0 (in)
                        84      POP_JUMP_IF_FALSE               48 (to 96)
                        86      LOAD_FAST                       7: write
                        88      LOAD_CONST                      5: '...'
                        90      CALL_FUNCTION                   1
                        92      POP_TOP                         
                        94      JUMP_FORWARD                    20 (to 136)
                        96      LOAD_FAST                       0: self
                        98      LOAD_METHOD                     4: _format
                        100     LOAD_FAST                       12: ent
                        102     LOAD_FAST                       2: stream
                        104     LOAD_FAST                       3: indent
                        106     LOAD_GLOBAL                     1: len
                        108     LOAD_FAST                       11: key
                        110     CALL_FUNCTION                   1
                        112     BINARY_ADD                      
                        114     LOAD_CONST                      3: 1
                        116     BINARY_ADD                      
                        118     LOAD_FAST                       13: last
                        120     POP_JUMP_IF_FALSE               63 (to 126)
                        122     LOAD_FAST                       4: allowance
                        124     JUMP_FORWARD                    1 (to 128)
                        126     LOAD_CONST                      3: 1
                        128     LOAD_FAST                       5: context
                        130     LOAD_FAST                       6: level
                        132     CALL_METHOD                     6
                        134     POP_TOP                         
                        136     LOAD_FAST                       13: last
                        138     POP_JUMP_IF_TRUE                74 (to 148)
                        140     LOAD_FAST                       7: write
                        142     LOAD_FAST                       8: delimnl
                        144     CALL_FUNCTION                   1
                        146     POP_TOP                         
                        148     JUMP_ABSOLUTE                   19 (to 38)
                        150     LOAD_CONST                      0: None
                        152     RETURN_VALUE                    
                'PrettyPrinter._format_namespace_items'
                [Code]
                    File Name: pprint.py
                    Object Name: _format_items
                    Arg Count: 7
                    Pos Only Arg Count: 0
                    KW Only Arg Count: 0
                    Locals: 18
                    Stack Size: 8
                    Flags: 0x00000043 (CO_OPTIMIZED | CO_NEWLOCALS | CO_NOFREE)
                    [Names]
                        'write'
                        '_indent_per_level'
                        '_width'
                        'iter'
                        'next'
                        'StopIteration'
                        '_compact'
                        '_repr'
                        'len'
                        '_format'
                    [Var Names]
                        'self'
                        'items'
                        'stream'
                        'indent'
                        'allowance'
                        'context'
                        'level'
                        'write'
                        'delimnl'
                        'delim'
                        'width'
                        'max_width'
                        'it'
                        'next_ent'
                        'last'
                        'ent'
                        'rep'
                        'w'
                    [Free Vars]
                    [Cell Vars]
                    [Constants]
                        None
                        1
                        ' '
                        ',\n'
                        ''
                        False
                        True
                        2
                        ', '
                    [Disassembly]
                        0       LOAD_FAST                       2: stream
                        2       LOAD_ATTR                       0: write
                        4       STORE_FAST                      7: write
                        6       LOAD_FAST                       3: indent
                        8       LOAD_FAST                       0: self
                        10      LOAD_ATTR                       1: _indent_per_level
                        12      INPLACE_ADD                     
                        14      STORE_FAST                      3: indent
                        16      LOAD_FAST                       0: self
                        18      LOAD_ATTR                       1: _indent_per_level
                        20      LOAD_CONST                      1: 1
                        22      COMPARE_OP                      4 (>)
                        24      POP_JUMP_IF_FALSE               22 (to 44)
                        26      LOAD_FAST                       7: write
                        28      LOAD_FAST                       0: self
                        30      LOAD_ATTR                       1: _indent_per_level
                        32      LOAD_CONST                      1: 1
                        34      BINARY_SUBTRACT                 
                        36      LOAD_CONST                      2: ' '
                        38      BINARY_MULTIPLY                 
                        40      CALL_FUNCTION                   1
                        42      POP_TOP                         
                        44      LOAD_CONST                      3: ',\n'
                        46      LOAD_CONST                      2: ' '
                        48      LOAD_FAST                       3: indent
                        50      BINARY_MULTIPLY                 
                        52      BINARY_ADD                      
                        54      STORE_FAST                      8: delimnl
                        56      LOAD_CONST                      4: ''
                        58      STORE_FAST                      9: delim
                        60      LOAD_FAST                       0: self
                        62      LOAD_ATTR                       2: _width
                        64      LOAD_FAST                       3: indent
                        66      BINARY_SUBTRACT                 
                        68      LOAD_CONST                      1: 1
                        70      BINARY_ADD                      
                        72      DUP_TOP                         
                        74      STORE_FAST                      10: width
                        76      STORE_FAST                      11: max_width
                        78      LOAD_GLOBAL                     3: iter
                        80      LOAD_FAST                       1: items
                        82      CALL_FUNCTION                   1
                        84      STORE_FAST                      12: it
                        86      SETUP_FINALLY                   6 (to 100)
                        88      LOAD_GLOBAL                     4: next
                        90      LOAD_FAST                       12: it
                        92      CALL_FUNCTION                   1
                        94      STORE_FAST                      13: next_ent
                        96      POP_BLOCK                       
                        98      JUMP_FORWARD                    10 (to 120)
                        100     DUP_TOP                         
                        102     LOAD_GLOBAL                     5: StopIteration
                        104     JUMP_IF_NOT_EXC_MATCH           59 (to 118)
                        106     POP_TOP                         
                        108     POP_TOP                         
                        110     POP_TOP                         
                        112     POP_EXCEPT                      
                        114     LOAD_CONST                      0: None
                        116     RETURN_VALUE                    
                        118     RERAISE                         0
                        120     LOAD_CONST                      5: False
                        122     STORE_FAST                      14: last
                        124     LOAD_FAST                       14: last
                        126     POP_JUMP_IF_TRUE                161 (to 322)
                        128     LOAD_FAST                       13: next_ent
                        130     STORE_FAST                      15: ent
                        132     SETUP_FINALLY                   6 (to 146)
                        134     LOAD_GLOBAL                     4: next
                        136     LOAD_FAST                       12: it
                        138     CALL_FUNCTION                   1
                        140     STORE_FAST                      13: next_ent
                        142     POP_BLOCK                       
                        144     JUMP_FORWARD                    19 (to 184)
                        146     DUP_TOP                         
                        148     LOAD_GLOBAL                     5: StopIteration
                        150     JUMP_IF_NOT_EXC_MATCH           91 (to 182)
                        152     POP_TOP                         
                        154     POP_TOP                         
                        156     POP_TOP                         
                        158     LOAD_CONST                      6: True
                        160     STORE_FAST                      14: last
                        162     LOAD_FAST                       11: max_width
                        164     LOAD_FAST                       4: allowance
                        166     INPLACE_SUBTRACT                
                        168     STORE_FAST                      11: max_width
                        170     LOAD_FAST                       10: width
                        172     LOAD_FAST                       4: allowance
                        174     INPLACE_SUBTRACT                
                        176     STORE_FAST                      10: width
                        178     POP_EXCEPT                      
                        180     JUMP_FORWARD                    1 (to 184)
                        182     RERAISE                         0
                        184     LOAD_FAST                       0: self
                        186     LOAD_ATTR                       6: _compact
                        188     POP_JUMP_IF_FALSE               137 (to 274)
                        190     LOAD_FAST                       0: self
                        192     LOAD_METHOD                     7: _repr
                        194     LOAD_FAST                       15: ent
                        196     LOAD_FAST                       5: context
                        198     LOAD_FAST                       6: level
                        200     CALL_METHOD                     3
                        202     STORE_FAST                      16: rep
                        204     LOAD_GLOBAL                     8: len
                        206     LOAD_FAST                       16: rep
                        208     CALL_FUNCTION                   1
                        210     LOAD_CONST                      7: 2
                        212     BINARY_ADD                      
                        214     STORE_FAST                      17: w
                        216     LOAD_FAST                       10: width
                        218     LOAD_FAST                       17: w
                        220     COMPARE_OP                      0 (<)
                        222     POP_JUMP_IF_FALSE               118 (to 236)
                        224     LOAD_FAST                       11: max_width
                        226     STORE_FAST                      10: width
                        228     LOAD_FAST                       9: delim
                        230     POP_JUMP_IF_FALSE               118 (to 236)
                        232     LOAD_FAST                       8: delimnl
                        234     STORE_FAST                      9: delim
                        236     LOAD_FAST                       10: width
                        238     LOAD_FAST                       17: w
                        240     COMPARE_OP                      5 (>=)
                        242     POP_JUMP_IF_FALSE               137 (to 274)
                        244     LOAD_FAST                       10: width
                        246     LOAD_FAST                       17: w
                        248     INPLACE_SUBTRACT                
                        250     STORE_FAST                      10: width
                        252     LOAD_FAST                       7: write
                        254     LOAD_FAST                       9: delim
                        256     CALL_FUNCTION                   1
                        258     POP_TOP                         
                        260     LOAD_CONST                      8: ', '
                        262     STORE_FAST                      9: delim
                        264     LOAD_FAST                       7: write
                        266     LOAD_FAST                       16: rep
                        268     CALL_FUNCTION                   1
                        270     POP_TOP                         
                        272     JUMP_ABSOLUTE                   62 (to 124)
                        274     LOAD_FAST                       7: write
                        276     LOAD_FAST                       9: delim
                        278     CALL_FUNCTION                   1
                        280     POP_TOP                         
                        282     LOAD_FAST                       8: delimnl
                        284     STORE_FAST                      9: delim
                        286     LOAD_FAST                       0: self
                        288     LOAD_METHOD                     9: _format
                        290     LOAD_FAST                       15: ent
                        292     LOAD_FAST                       2: stream
                        294     LOAD_FAST                       3: indent
                        296     LOAD_FAST                       14: last
                        298     POP_JUMP_IF_FALSE               152 (to 304)
                        300     LOAD_FAST                       4: allowance
                        302     JUMP_FORWARD                    1 (to 306)
                        304     LOAD_CONST                      1: 1
                        306     LOAD_FAST                       5: context
                        308     LOAD_FAST                       6: level
                        310     CALL_METHOD                     6
                        312     POP_TOP                         
                        314     LOAD_FAST                       14: last
                        316     POP_JUMP_IF_FALSE               64 (to 128)
                        318     LOAD_CONST                      0: None
                        320     RETURN_VALUE                    
                        322     LOAD_CONST                      0: None
                        324     RETURN_VALUE                    
                'PrettyPrinter._format_items'
                [Code]
                    File Name: pprint.py
                    Object Name: _repr
                    Arg Count: 4
                    Pos Only Arg Count: 0
                    KW Only Arg Count: 0
                    Locals: 7
                    Stack Size: 6
                    Flags: 0x00000043 (CO_OPTIMIZED | CO_NEWLOCALS | CO_NOFREE)
                    [Names]
                        'format'
                        'copy'
                        '_depth'
                        '_readable'
                        '_recursive'
                    [Var Names]
                        'self'
                        'object'
                        'context'
                        'level'
                        'repr'
                        'readable'
                        'recursive'
                    [Free Vars]
                    [Cell Vars]
                    [Constants]
                        None
                        False
                        True
                    [Disassembly]
                        0       LOAD_FAST                       0: self
                        2       LOAD_METHOD                     0: format
                        4       LOAD_FAST                       1: object
                        6       LOAD_FAST                       2: context
                        8       LOAD_METHOD                     1: copy
                        10      CALL_METHOD                     0
                        12      LOAD_FAST                       0: self
                        14      LOAD_ATTR                       2: _depth
                        16      LOAD_FAST                       3: level
                        18      CALL_METHOD                     4
                        20      UNPACK_SEQUENCE                 3
                        22      STORE_FAST                      4: repr
                        24      STORE_FAST                      5: readable
                        26      STORE_FAST                      6: recursive
                        28      LOAD_FAST                       5: readable
                        30      POP_JUMP_IF_TRUE                19 (to 38)
                        32      LOAD_CONST                      1: False
                        34      LOAD_FAST                       0: self
                        36      STORE_ATTR                      3: _readable
                        38      LOAD_FAST                       6: recursive
                        40      POP_JUMP_IF_FALSE               24 (to 48)
                        42      LOAD_CONST                      2: True
                        44      LOAD_FAST                       0: self
                        46      STORE_ATTR                      4: _recursive
                        48      LOAD_FAST                       4: repr
                        50      RETURN_VALUE                    
                'PrettyPrinter._repr'
                [Code]
                    File Name: pprint.py
                    Object Name: format
                    Arg Count: 5
                    Pos Only Arg Count: 0
                    KW Only Arg Count: 0
                    Locals: 5
                    Stack Size: 6
                    Flags: 0x00000043 (CO_OPTIMIZED | CO_NEWLOCALS | CO_NOFREE)
                    [Names]
                        '_safe_repr'
                    [Var Names]
                        'self'
                        'object'
                        'context'
                        'maxlevels'
                        'level'
                    [Free Vars]
                    [Cell Vars]
                    [Constants]
                        "Format object for a specific context, returning a string\n        and flags indicating whether the representation is 'readable'\n        and whether the object represents a recursive construct.\n        "
                    [Disassembly]
                        0       LOAD_FAST                       0: self
                        2       LOAD_METHOD                     0: _safe_repr
                        4       LOAD_FAST                       1: object
                        6       LOAD_FAST                       2: context
                        8       LOAD_FAST                       3: maxlevels
                        10      LOAD_FAST                       4: level
                        12      CALL_METHOD                     4
                        14      RETURN_VALUE                    
                'PrettyPrinter.format'
                [Code]
                    File Name: pprint.py
                    Object Name: _pprint_default_dict
                    Arg Count: 7
                    Pos Only Arg Count: 0
                    KW Only Arg Count: 0
                    Locals: 9
                    Stack Size: 8
                    Flags: 0x00000043 (CO_OPTIMIZED | CO_NEWLOCALS | CO_NOFREE)
                    [Names]
                        'len'
                        'write'
                        'repr'
                        '_repr'
                        'default_factory'
                        '__class__'
                        '__name__'
                        '_pprint_dict'
                    [Var Names]
                        'self'
                        'object'
                        'stream'
                        'indent'
                        'allowance'
                        'context'
                        'level'
                        'rdf'
                        'cls'
                    [Free Vars]
                    [Cell Vars]
                    [Constants]
                        None
                        1
                        '%s(%s,\n%s'
                        ' '
                        ')'
                    [Disassembly]
                        0       LOAD_GLOBAL                     0: len
                        2       LOAD_FAST                       1: object
                        4       CALL_FUNCTION                   1
                        6       POP_JUMP_IF_TRUE                13 (to 26)
                        8       LOAD_FAST                       2: stream
                        10      LOAD_METHOD                     1: write
                        12      LOAD_GLOBAL                     2: repr
                        14      LOAD_FAST                       1: object
                        16      CALL_FUNCTION                   1
                        18      CALL_METHOD                     1
                        20      POP_TOP                         
                        22      LOAD_CONST                      0: None
                        24      RETURN_VALUE                    
                        26      LOAD_FAST                       0: self
                        28      LOAD_METHOD                     3: _repr
                        30      LOAD_FAST                       1: object
                        32      LOAD_ATTR                       4: default_factory
                        34      LOAD_FAST                       5: context
                        36      LOAD_FAST                       6: level
                        38      CALL_METHOD                     3
                        40      STORE_FAST                      7: rdf
                        42      LOAD_FAST                       1: object
                        44      LOAD_ATTR                       5: __class__
                        46      STORE_FAST                      8: cls
                        48      LOAD_FAST                       3: indent
                        50      LOAD_GLOBAL                     0: len
                        52      LOAD_FAST                       8: cls
                        54      LOAD_ATTR                       6: __name__
                        56      CALL_FUNCTION                   1
                        58      LOAD_CONST                      1: 1
                        60      BINARY_ADD                      
                        62      INPLACE_ADD                     
                        64      STORE_FAST                      3: indent
                        66      LOAD_FAST                       2: stream
                        68      LOAD_METHOD                     1: write
                        70      LOAD_CONST                      2: '%s(%s,\n%s'
                        72      LOAD_FAST                       8: cls
                        74      LOAD_ATTR                       6: __name__
                        76      LOAD_FAST                       7: rdf
                        78      LOAD_CONST                      3: ' '
                        80      LOAD_FAST                       3: indent
                        82      BINARY_MULTIPLY                 
                        84      BUILD_TUPLE                     3
                        86      BINARY_MODULO                   
                        88      CALL_METHOD                     1
                        90      POP_TOP                         
                        92      LOAD_FAST                       0: self
                        94      LOAD_METHOD                     7: _pprint_dict
                        96      LOAD_FAST                       1: object
                        98      LOAD_FAST                       2: stream
                        100     LOAD_FAST                       3: indent
                        102     LOAD_FAST                       4: allowance
                        104     LOAD_CONST                      1: 1
                        106     BINARY_ADD                      
                        108     LOAD_FAST                       5: context
                        110     LOAD_FAST                       6: level
                        112     CALL_METHOD                     6
                        114     POP_TOP                         
                        116     LOAD_FAST                       2: stream
                        118     LOAD_METHOD                     1: write
                        120     LOAD_CONST                      4: ')'
                        122     CALL_METHOD                     1
                        124     POP_TOP                         
                        126     LOAD_CONST                      0: None
                        128     RETURN_VALUE                    
                'PrettyPrinter._pprint_default_dict'
                [Code]
                    File Name: pprint.py
                    Object Name: _pprint_counter
                    Arg Count: 7
                    Pos Only Arg Count: 0
                    KW Only Arg Count: 0
                    Locals: 9
                    Stack Size: 8
                    Flags: 0x00000043 (CO_OPTIMIZED | CO_NEWLOCALS | CO_NOFREE)
                    [Names]
                        'len'
                        'write'
                        'repr'
                        '__class__'
                        '__name__'
                        '_indent_per_level'
                        'most_common'
                        '_format_dict_items'
                    [Var Names]
                        'self'
                        'object'
                        'stream'
                        'indent'
                        'allowance'
                        'context'
                        'level'
                        'cls'
                        'items'
                    [Free Vars]
                    [Cell Vars]
                    [Constants]
                        None
                        '({'
                        1
                        ' '
                        2
                        '})'
                    [Disassembly]
                        0       LOAD_GLOBAL                     0: len
                        2       LOAD_FAST                       1: object
                        4       CALL_FUNCTION                   1
                        6       POP_JUMP_IF_TRUE                13 (to 26)
                        8       LOAD_FAST                       2: stream
                        10      LOAD_METHOD                     1: write
                        12      LOAD_GLOBAL                     2: repr
                        14      LOAD_FAST                       1: object
                        16      CALL_FUNCTION                   1
                        18      CALL_METHOD                     1
                        20      POP_TOP                         
                        22      LOAD_CONST                      0: None
                        24      RETURN_VALUE                    
                        26      LOAD_FAST                       1: object
                        28      LOAD_ATTR                       3: __class__
                        30      STORE_FAST                      7: cls
                        32      LOAD_FAST                       2: stream
                        34      LOAD_METHOD                     1: write
                        36      LOAD_FAST                       7: cls
                        38      LOAD_ATTR                       4: __name__
                        40      LOAD_CONST                      1: '({'
                        42      BINARY_ADD                      
                        44      CALL_METHOD                     1
                        46      POP_TOP                         
                        48      LOAD_FAST                       0: self
                        50      LOAD_ATTR                       5: _indent_per_level
                        52      LOAD_CONST                      2: 1
                        54      COMPARE_OP                      4 (>)
                        56      POP_JUMP_IF_FALSE               39 (to 78)
                        58      LOAD_FAST                       2: stream
                        60      LOAD_METHOD                     1: write
                        62      LOAD_FAST                       0: self
                        64      LOAD_ATTR                       5: _indent_per_level
                        66      LOAD_CONST                      2: 1
                        68      BINARY_SUBTRACT                 
                        70      LOAD_CONST                      3: ' '
                        72      BINARY_MULTIPLY                 
                        74      CALL_METHOD                     1
                        76      POP_TOP                         
                        78      LOAD_FAST                       1: object
                        80      LOAD_METHOD                     6: most_common
                        82      CALL_METHOD                     0
                        84      STORE_FAST                      8: items
                        86      LOAD_FAST                       0: self
                        88      LOAD_METHOD                     7: _format_dict_items
                        90      LOAD_FAST                       8: items
                        92      LOAD_FAST                       2: stream
                        94      LOAD_FAST                       3: indent
                        96      LOAD_GLOBAL                     0: len
                        98      LOAD_FAST                       7: cls
                        100     LOAD_ATTR                       4: __name__
                        102     CALL_FUNCTION                   1
                        104     BINARY_ADD                      
                        106     LOAD_CONST                      2: 1
                        108     BINARY_ADD                      
                        110     LOAD_FAST                       4: allowance
                        112     LOAD_CONST                      4: 2
                        114     BINARY_ADD                      
                        116     LOAD_FAST                       5: context
                        118     LOAD_FAST                       6: level
                        120     CALL_METHOD                     6
                        122     POP_TOP                         
                        124     LOAD_FAST                       2: stream
                        126     LOAD_METHOD                     1: write
                        128     LOAD_CONST                      5: '})'
                        130     CALL_METHOD                     1
                        132     POP_TOP                         
                        134     LOAD_CONST                      0: None
                        136     RETURN_VALUE                    
                'PrettyPrinter._pprint_counter'
                [Code]
                    File Name: pprint.py
                    Object Name: _pprint_chain_map
                    Arg Count: 7
                    Pos Only Arg Count: 0
                    KW Only Arg Count: 0
                    Locals: 10
                    Stack Size: 9
                    Flags: 0x00000043 (CO_OPTIMIZED | CO_NEWLOCALS | CO_NOFREE)
                    [Names]
                        'len'
                        'maps'
                        'write'
                        'repr'
                        '__class__'
                        '__name__'
                        'enumerate'
                        '_format'
                    [Var Names]
                        'self'
                        'object'
                        'stream'
                        'indent'
                        'allowance'
                        'context'
                        'level'
                        'cls'
                        'i'
                        'm'
                    [Free Vars]
                    [Cell Vars]
                    [Constants]
                        None
                        '('
                        1
                        ')'
                        ',\n'
                        ' '
                    [Disassembly]
                        0       LOAD_GLOBAL                     0: len
                        2       LOAD_FAST                       1: object
                        4       LOAD_ATTR                       1: maps
                        6       CALL_FUNCTION                   1
                        8       POP_JUMP_IF_TRUE                14 (to 28)
                        10      LOAD_FAST                       2: stream
                        12      LOAD_METHOD                     2: write
                        14      LOAD_GLOBAL                     3: repr
                        16      LOAD_FAST                       1: object
                        18      CALL_FUNCTION                   1
                        20      CALL_METHOD                     1
                        22      POP_TOP                         
                        24      LOAD_CONST                      0: None
                        26      RETURN_VALUE                    
                        28      LOAD_FAST                       1: object
                        30      LOAD_ATTR                       4: __class__
                        32      STORE_FAST                      7: cls
                        34      LOAD_FAST                       2: stream
                        36      LOAD_METHOD                     2: write
                        38      LOAD_FAST                       7: cls
                        40      LOAD_ATTR                       5: __name__
                        42      LOAD_CONST                      1: '('
                        44      BINARY_ADD                      
                        46      CALL_METHOD                     1
                        48      POP_TOP                         
                        50      LOAD_FAST                       3: indent
                        52      LOAD_GLOBAL                     0: len
                        54      LOAD_FAST                       7: cls
                        56      LOAD_ATTR                       5: __name__
                        58      CALL_FUNCTION                   1
                        60      LOAD_CONST                      2: 1
                        62      BINARY_ADD                      
                        64      INPLACE_ADD                     
                        66      STORE_FAST                      3: indent
                        68      LOAD_GLOBAL                     6: enumerate
                        70      LOAD_FAST                       1: object
                        72      LOAD_ATTR                       1: maps
                        74      CALL_FUNCTION                   1
                        76      GET_ITER                        
                        78      FOR_ITER                        50 (to 180)
                        80      UNPACK_SEQUENCE                 2
                        82      STORE_FAST                      8: i
                        84      STORE_FAST                      9: m
                        86      LOAD_FAST                       8: i
                        88      LOAD_GLOBAL                     0: len
                        90      LOAD_FAST                       1: object
                        92      LOAD_ATTR                       1: maps
                        94      CALL_FUNCTION                   1
                        96      LOAD_CONST                      2: 1
                        98      BINARY_SUBTRACT                 
                        100     COMPARE_OP                      2 (==)
                        102     POP_JUMP_IF_FALSE               70 (to 140)
                        104     LOAD_FAST                       0: self
                        106     LOAD_METHOD                     7: _format
                        108     LOAD_FAST                       9: m
                        110     LOAD_FAST                       2: stream
                        112     LOAD_FAST                       3: indent
                        114     LOAD_FAST                       4: allowance
                        116     LOAD_CONST                      2: 1
                        118     BINARY_ADD                      
                        120     LOAD_FAST                       5: context
                        122     LOAD_FAST                       6: level
                        124     CALL_METHOD                     6
                        126     POP_TOP                         
                        128     LOAD_FAST                       2: stream
                        130     LOAD_METHOD                     2: write
                        132     LOAD_CONST                      3: ')'
                        134     CALL_METHOD                     1
                        136     POP_TOP                         
                        138     JUMP_ABSOLUTE                   39 (to 78)
                        140     LOAD_FAST                       0: self
                        142     LOAD_METHOD                     7: _format
                        144     LOAD_FAST                       9: m
                        146     LOAD_FAST                       2: stream
                        148     LOAD_FAST                       3: indent
                        150     LOAD_CONST                      2: 1
                        152     LOAD_FAST                       5: context
                        154     LOAD_FAST                       6: level
                        156     CALL_METHOD                     6
                        158     POP_TOP                         
                        160     LOAD_FAST                       2: stream
                        162     LOAD_METHOD                     2: write
                        164     LOAD_CONST                      4: ',\n'
                        166     LOAD_CONST                      5: ' '
                        168     LOAD_FAST                       3: indent
                        170     BINARY_MULTIPLY                 
                        172     BINARY_ADD                      
                        174     CALL_METHOD                     1
                        176     POP_TOP                         
                        178     JUMP_ABSOLUTE                   39 (to 78)
                        180     LOAD_CONST                      0: None
                        182     RETURN_VALUE                    
                'PrettyPrinter._pprint_chain_map'
                [Code]
                    File Name: pprint.py
                    Object Name: _pprint_deque
                    Arg Count: 7
                    Pos Only Arg Count: 0
                    KW Only Arg Count: 0
                    Locals: 9
                    Stack Size: 8
                    Flags: 0x00000043 (CO_OPTIMIZED | CO_NEWLOCALS | CO_NOFREE)
                    [Names]
                        'len'
                        'write'
                        'repr'
                        '__class__'
                        '__name__'
                        'maxlen'
                        '_format_items'
                        '_repr'
                    [Var Names]
                        'self'
                        'object'
                        'stream'
                        'indent'
                        'allowance'
                        'context'
                        'level'
                        'cls'
                        'rml'
                    [Free Vars]
                    [Cell Vars]
                    [Constants]
                        None
                        '('
                        1
                        '['
                        2
                        '])'
                        '],\n%smaxlen=%s)'
                        ' '
                    [Disassembly]
                        0       LOAD_GLOBAL                     0: len
                        2       LOAD_FAST                       1: object
                        4       CALL_FUNCTION                   1
                        6       POP_JUMP_IF_TRUE                13 (to 26)
                        8       LOAD_FAST                       2: stream
                        10      LOAD_METHOD                     1: write
                        12      LOAD_GLOBAL                     2: repr
                        14      LOAD_FAST                       1: object
                        16      CALL_FUNCTION                   1
                        18      CALL_METHOD                     1
                        20      POP_TOP                         
                        22      LOAD_CONST                      0: None
                        24      RETURN_VALUE                    
                        26      LOAD_FAST                       1: object
                        28      LOAD_ATTR                       3: __class__
                        30      STORE_FAST                      7: cls
                        32      LOAD_FAST                       2: stream
                        34      LOAD_METHOD                     1: write
                        36      LOAD_FAST                       7: cls
                        38      LOAD_ATTR                       4: __name__
                        40      LOAD_CONST                      1: '('
                        42      BINARY_ADD                      
                        44      CALL_METHOD                     1
                        46      POP_TOP                         
                        48      LOAD_FAST                       3: indent
                        50      LOAD_GLOBAL                     0: len
                        52      LOAD_FAST                       7: cls
                        54      LOAD_ATTR                       4: __name__
                        56      CALL_FUNCTION                   1
                        58      LOAD_CONST                      2: 1
                        60      BINARY_ADD                      
                        62      INPLACE_ADD                     
                        64      STORE_FAST                      3: indent
                        66      LOAD_FAST                       2: stream
                        68      LOAD_METHOD                     1: write
                        70      LOAD_CONST                      3: '['
                        72      CALL_METHOD                     1
                        74      POP_TOP                         
                        76      LOAD_FAST                       1: object
                        78      LOAD_ATTR                       5: maxlen
                        80      LOAD_CONST                      0: None
                        82      IS_OP                           0 (is)
                        84      POP_JUMP_IF_FALSE               62 (to 124)
                        86      LOAD_FAST                       0: self
                        88      LOAD_METHOD                     6: _format_items
                        90      LOAD_FAST                       1: object
                        92      LOAD_FAST                       2: stream
                        94      LOAD_FAST                       3: indent
                        96      LOAD_FAST                       4: allowance
                        98      LOAD_CONST                      4: 2
                        100     BINARY_ADD                      
                        102     LOAD_FAST                       5: context
                        104     LOAD_FAST                       6: level
                        106     CALL_METHOD                     6
                        108     POP_TOP                         
                        110     LOAD_FAST                       2: stream
                        112     LOAD_METHOD                     1: write
                        114     LOAD_CONST                      5: '])'
                        116     CALL_METHOD                     1
                        118     POP_TOP                         
                        120     LOAD_CONST                      0: None
                        122     RETURN_VALUE                    
                        124     LOAD_FAST                       0: self
                        126     LOAD_METHOD                     6: _format_items
                        128     LOAD_FAST                       1: object
                        130     LOAD_FAST                       2: stream
                        132     LOAD_FAST                       3: indent
                        134     LOAD_CONST                      4: 2
                        136     LOAD_FAST                       5: context
                        138     LOAD_FAST                       6: level
                        140     CALL_METHOD                     6
                        142     POP_TOP                         
                        144     LOAD_FAST                       0: self
                        146     LOAD_METHOD                     7: _repr
                        148     LOAD_FAST                       1: object
                        150     LOAD_ATTR                       5: maxlen
                        152     LOAD_FAST                       5: context
                        154     LOAD_FAST                       6: level
                        156     CALL_METHOD                     3
                        158     STORE_FAST                      8: rml
                        160     LOAD_FAST                       2: stream
                        162     LOAD_METHOD                     1: write
                        164     LOAD_CONST                      6: '],\n%smaxlen=%s)'
                        166     LOAD_CONST                      7: ' '
                        168     LOAD_FAST                       3: indent
                        170     BINARY_MULTIPLY                 
                        172     LOAD_FAST                       8: rml
                        174     BUILD_TUPLE                     2
                        176     BINARY_MODULO                   
                        178     CALL_METHOD                     1
                        180     POP_TOP                         
                        182     LOAD_CONST                      0: None
                        184     RETURN_VALUE                    
                'PrettyPrinter._pprint_deque'
                [Code]
                    File Name: pprint.py
                    Object Name: _pprint_user_dict
                    Arg Count: 7
                    Pos Only Arg Count: 0
                    KW Only Arg Count: 0
                    Locals: 7
                    Stack Size: 9
                    Flags: 0x00000043 (CO_OPTIMIZED | CO_NEWLOCALS | CO_NOFREE)
                    [Names]
                        '_format'
                        'data'
                    [Var Names]
                        'self'
                        'object'
                        'stream'
                        'indent'
                        'allowance'
                        'context'
                        'level'
                    [Free Vars]
                    [Cell Vars]
                    [Constants]
                        None
                        1
                    [Disassembly]
                        0       LOAD_FAST                       0: self
                        2       LOAD_METHOD                     0: _format
                        4       LOAD_FAST                       1: object
                        6       LOAD_ATTR                       1: data
                        8       LOAD_FAST                       2: stream
                        10      LOAD_FAST                       3: indent
                        12      LOAD_FAST                       4: allowance
                        14      LOAD_FAST                       5: context
                        16      LOAD_FAST                       6: level
                        18      LOAD_CONST                      1: 1
                        20      BINARY_SUBTRACT                 
                        22      CALL_METHOD                     6
                        24      POP_TOP                         
                        26      LOAD_CONST                      0: None
                        28      RETURN_VALUE                    
                'PrettyPrinter._pprint_user_dict'
                [Code]
                    File Name: pprint.py
                    Object Name: _pprint_user_list
                    Arg Count: 7
                    Pos Only Arg Count: 0
                    KW Only Arg Count: 0
                    Locals: 7
                    Stack Size: 9
                    Flags: 0x00000043 (CO_OPTIMIZED | CO_NEWLOCALS | CO_NOFREE)
                    [Names]
                        '_format'
                        'data'
                    [Var Names]
                        'self'
                        'object'
                        'stream'
                        'indent'
                        'allowance'
                        'context'
                        'level'
                    [Free Vars]
                    [Cell Vars]
                    [Constants]
                        None
                        1
                    [Disassembly]
                        0       LOAD_FAST                       0: self
                        2       LOAD_METHOD                     0: _format
                        4       LOAD_FAST                       1: object
                        6       LOAD_ATTR                       1: data
                        8       LOAD_FAST                       2: stream
                        10      LOAD_FAST                       3: indent
                        12      LOAD_FAST                       4: allowance
                        14      LOAD_FAST                       5: context
                        16      LOAD_FAST                       6: level
                        18      LOAD_CONST                      1: 1
                        20      BINARY_SUBTRACT                 
                        22      CALL_METHOD                     6
                        24      POP_TOP                         
                        26      LOAD_CONST                      0: None
                        28      RETURN_VALUE                    
                'PrettyPrinter._pprint_user_list'
                [Code]
                    File Name: pprint.py
                    Object Name: _pprint_user_string
                    Arg Count: 7
                    Pos Only Arg Count: 0
                    KW Only Arg Count: 0
                    Locals: 7
                    Stack Size: 9
                    Flags: 0x00000043 (CO_OPTIMIZED | CO_NEWLOCALS | CO_NOFREE)
                    [Names]
                        '_format'
                        'data'
                    [Var Names]
                        'self'
                        'object'
                        'stream'
                        'indent'
                        'allowance'
                        'context'
                        'level'
                    [Free Vars]
                    [Cell Vars]
                    [Constants]
                        None
                        1
                    [Disassembly]
                        0       LOAD_FAST                       0: self
                        2       LOAD_METHOD                     0: _format
                        4       LOAD_FAST                       1: object
                        6       LOAD_ATTR                       1: data
                        8       LOAD_FAST                       2: stream
                        10      LOAD_FAST                       3: indent
                        12      LOAD_FAST                       4: allowance
                        14      LOAD_FAST                       5: context
                        16      LOAD_FAST                       6: level
                        18      LOAD_CONST                      1: 1
                        20      BINARY_SUBTRACT                 
                        22      CALL_METHOD                     6
                        24      POP_TOP                         
                        26      LOAD_CONST                      0: None
                        28      RETURN_VALUE                    
                'PrettyPrinter._pprint_user_string'
                [Code]
                    File Name: pprint.py
                    Object Name: _safe_repr
                    Arg Count: 5
                    Pos Only Arg Count: 0
                    KW Only Arg Count: 0
                    Locals: 27
                    Stack Size: 7
                    Flags: 0x00000043 (CO_OPTIMIZED | CO_NEWLOCALS | CO_NOFREE)
                    [Names]
                        'type'
                        '_builtin_scalars'
                        'repr'
                        'getattr'
                        'issubclass'
                        'int'
                        '__repr__'
                        '_underscore_numbers'
                        'dict'
                        'id'
                        '_recursion'
                        'append'
                        '_sort_dicts'
                        'sorted'
                        'items'
                        '_safe_tuple'
                        'format'
                        'join'
                        'list'
                        'tuple'
                        'len'
                        'startswith'
                    [Var Names]
                        'self'
                        'object'
                        'context'
                        'maxlevels'
                        'level'
                        'typ'
                        'r'
                        'objid'
                        'readable'
                        'recursive'
                        'components'
                        'append'
                        'items'
                        'k'
                        'v'
                        'krepr'
                        'kreadable'
                        'krecur'
                        'vrepr'
                        'vreadable'
                        'vrecur'
                        'format'
                        'o'
                        'orepr'
                        'oreadable'
                        'orecur'
                        'rep'
                    [Free Vars]
                    [Cell Vars]
                    [Constants]
                        None
                        True
                        False
                        '__repr__'
                        '_d'
                        (
                            '{}'
                            True
                            False
                        )
                        '{...}'
                        1
                        (
                            'key'
                        )
                        '%s: %s'
                        '{%s}'
                        ', '
                        (
                            '[]'
                            True
                            False
                        )
                        '[%s]'
                        '(%s,)'
                        (
                            '()'
                            True
                            False
                        )
                        '(%s)'
                        '...'
                        '<'
                    [Disassembly]
                        0       LOAD_GLOBAL                     0: type
                        2       LOAD_FAST                       1: object
                        4       CALL_FUNCTION                   1
                        6       STORE_FAST                      5: typ
                        8       LOAD_FAST                       5: typ
                        10      LOAD_GLOBAL                     1: _builtin_scalars
                        12      CONTAINS_OP                     0 (in)
                        14      POP_JUMP_IF_FALSE               15 (to 30)
                        16      LOAD_GLOBAL                     2: repr
                        18      LOAD_FAST                       1: object
                        20      CALL_FUNCTION                   1
                        22      LOAD_CONST                      1: True
                        24      LOAD_CONST                      2: False
                        26      BUILD_TUPLE                     3
                        28      RETURN_VALUE                    
                        30      LOAD_GLOBAL                     3: getattr
                        32      LOAD_FAST                       5: typ
                        34      LOAD_CONST                      3: '__repr__'
                        36      LOAD_CONST                      0: None
                        38      CALL_FUNCTION                   3
                        40      STORE_FAST                      6: r
                        42      LOAD_GLOBAL                     4: issubclass
                        44      LOAD_FAST                       5: typ
                        46      LOAD_GLOBAL                     5: int
                        48      CALL_FUNCTION                   2
                        50      POP_JUMP_IF_FALSE               48 (to 96)
                        52      LOAD_FAST                       6: r
                        54      LOAD_GLOBAL                     5: int
                        56      LOAD_ATTR                       6: __repr__
                        58      IS_OP                           0 (is)
                        60      POP_JUMP_IF_FALSE               48 (to 96)
                        62      LOAD_FAST                       0: self
                        64      LOAD_ATTR                       7: _underscore_numbers
                        66      POP_JUMP_IF_FALSE               41 (to 82)
                        68      LOAD_FAST                       1: object
                        70      LOAD_CONST                      4: '_d'
                        72      FORMAT_VALUE                    4 (FVC_NONE | FVS_HAVE_SPEC)
                        74      LOAD_CONST                      1: True
                        76      LOAD_CONST                      2: False
                        78      BUILD_TUPLE                     3
                        80      RETURN_VALUE                    
                        82      LOAD_GLOBAL                     2: repr
                        84      LOAD_FAST                       1: object
                        86      CALL_FUNCTION                   1
                        88      LOAD_CONST                      1: True
                        90      LOAD_CONST                      2: False
                        92      BUILD_TUPLE                     3
                        94      RETURN_VALUE                    
                        96      LOAD_GLOBAL                     4: issubclass
                        98      LOAD_FAST                       5: typ
                        100     LOAD_GLOBAL                     8: dict
                        102     CALL_FUNCTION                   2
                        104     POP_JUMP_IF_FALSE               185 (to 370)
                        106     LOAD_FAST                       6: r
                        108     LOAD_GLOBAL                     8: dict
                        110     LOAD_ATTR                       6: __repr__
                        112     IS_OP                           0 (is)
                        114     POP_JUMP_IF_FALSE               185 (to 370)
                        116     LOAD_FAST                       1: object
                        118     POP_JUMP_IF_TRUE                62 (to 124)
                        120     LOAD_CONST                      5: ('{}', True, False)
                        122     RETURN_VALUE                    
                        124     LOAD_GLOBAL                     9: id
                        126     LOAD_FAST                       1: object
                        128     CALL_FUNCTION                   1
                        130     STORE_FAST                      7: objid
                        132     LOAD_FAST                       3: maxlevels
                        134     POP_JUMP_IF_FALSE               79 (to 158)
                        136     LOAD_FAST                       4: level
                        138     LOAD_FAST                       3: maxlevels
                        140     COMPARE_OP                      5 (>=)
                        142     POP_JUMP_IF_FALSE               79 (to 158)
                        144     LOAD_CONST                      6: '{...}'
                        146     LOAD_CONST                      2: False
                        148     LOAD_FAST                       7: objid
                        150     LOAD_FAST                       2: context
                        152     CONTAINS_OP                     0 (in)
                        154     BUILD_TUPLE                     3
                        156     RETURN_VALUE                    
                        158     LOAD_FAST                       7: objid
                        160     LOAD_FAST                       2: context
                        162     CONTAINS_OP                     0 (in)
                        164     POP_JUMP_IF_FALSE               90 (to 180)
                        166     LOAD_GLOBAL                     10: _recursion
                        168     LOAD_FAST                       1: object
                        170     CALL_FUNCTION                   1
                        172     LOAD_CONST                      2: False
                        174     LOAD_CONST                      1: True
                        176     BUILD_TUPLE                     3
                        178     RETURN_VALUE                    
                        180     LOAD_CONST                      7: 1
                        182     LOAD_FAST                       2: context
                        184     LOAD_FAST                       7: objid
                        186     STORE_SUBSCR                    
                        188     LOAD_CONST                      1: True
                        190     STORE_FAST                      8: readable
                        192     LOAD_CONST                      2: False
                        194     STORE_FAST                      9: recursive
                        196     BUILD_LIST                      0
                        198     STORE_FAST                      10: components
                        200     LOAD_FAST                       10: components
                        202     LOAD_ATTR                       11: append
                        204     STORE_FAST                      11: append
                        206     LOAD_FAST                       4: level
                        208     LOAD_CONST                      7: 1
                        210     INPLACE_ADD                     
                        212     STORE_FAST                      4: level
                        214     LOAD_FAST                       0: self
                        216     LOAD_ATTR                       12: _sort_dicts
                        218     POP_JUMP_IF_FALSE               119 (to 238)
                        220     LOAD_GLOBAL                     13: sorted
                        222     LOAD_FAST                       1: object
                        224     LOAD_METHOD                     14: items
                        226     CALL_METHOD                     0
                        228     LOAD_GLOBAL                     15: _safe_tuple
                        230     LOAD_CONST                      8: ('key',)
                        232     CALL_FUNCTION_KW                2
                        234     STORE_FAST                      12: items
                        236     JUMP_FORWARD                    4 (to 246)
                        238     LOAD_FAST                       1: object
                        240     LOAD_METHOD                     14: items
                        242     CALL_METHOD                     0
                        244     STORE_FAST                      12: items
                        246     LOAD_FAST                       12: items
                        248     GET_ITER                        
                        250     FOR_ITER                        46 (to 344)
                        252     UNPACK_SEQUENCE                 2
                        254     STORE_FAST                      13: k
                        256     STORE_FAST                      14: v
                        258     LOAD_FAST                       0: self
                        260     LOAD_METHOD                     16: format
                        262     LOAD_FAST                       13: k
                        264     LOAD_FAST                       2: context
                        266     LOAD_FAST                       3: maxlevels
                        268     LOAD_FAST                       4: level
                        270     CALL_METHOD                     4
                        272     UNPACK_SEQUENCE                 3
                        274     STORE_FAST                      15: krepr
                        276     STORE_FAST                      16: kreadable
                        278     STORE_FAST                      17: krecur
                        280     LOAD_FAST                       0: self
                        282     LOAD_METHOD                     16: format
                        284     LOAD_FAST                       14: v
                        286     LOAD_FAST                       2: context
                        288     LOAD_FAST                       3: maxlevels
                        290     LOAD_FAST                       4: level
                        292     CALL_METHOD                     4
                        294     UNPACK_SEQUENCE                 3
                        296     STORE_FAST                      18: vrepr
                        298     STORE_FAST                      19: vreadable
                        300     STORE_FAST                      20: vrecur
                        302     LOAD_FAST                       11: append
                        304     LOAD_CONST                      9: '%s: %s'
                        306     LOAD_FAST                       15: krepr
                        308     LOAD_FAST                       18: vrepr
                        310     BUILD_TUPLE                     2
                        312     BINARY_MODULO                   
                        314     CALL_FUNCTION                   1
                        316     POP_TOP                         
                        318     LOAD_FAST                       8: readable
                        320     JUMP_IF_FALSE_OR_POP            164 (to 328)
                        322     LOAD_FAST                       16: kreadable
                        324     JUMP_IF_FALSE_OR_POP            164 (to 328)
                        326     LOAD_FAST                       19: vreadable
                        328     STORE_FAST                      8: readable
                        330     LOAD_FAST                       17: krecur
                        332     POP_JUMP_IF_TRUE                169 (to 338)
                        334     LOAD_FAST                       20: vrecur
                        336     POP_JUMP_IF_FALSE               171 (to 342)
                        338     LOAD_CONST                      1: True
                        340     STORE_FAST                      9: recursive
                        342     JUMP_ABSOLUTE                   125 (to 250)
                        344     LOAD_FAST                       2: context
                        346     LOAD_FAST                       7: objid
                        348     DELETE_SUBSCR                   
                        350     LOAD_CONST                      10: '{%s}'
                        352     LOAD_CONST                      11: ', '
                        354     LOAD_METHOD                     17: join
                        356     LOAD_FAST                       10: components
                        358     CALL_METHOD                     1
                        360     BINARY_MODULO                   
                        362     LOAD_FAST                       8: readable
                        364     LOAD_FAST                       9: recursive
                        366     BUILD_TUPLE                     3
                        368     RETURN_VALUE                    
                        370     LOAD_GLOBAL                     4: issubclass
                        372     LOAD_FAST                       5: typ
                        374     LOAD_GLOBAL                     18: list
                        376     CALL_FUNCTION                   2
                        378     POP_JUMP_IF_FALSE               195 (to 390)
                        380     LOAD_FAST                       6: r
                        382     LOAD_GLOBAL                     18: list
                        384     LOAD_ATTR                       6: __repr__
                        386     IS_OP                           0 (is)
                        388     POP_JUMP_IF_TRUE                207 (to 414)
                        390     LOAD_GLOBAL                     4: issubclass
                        392     LOAD_FAST                       5: typ
                        394     LOAD_GLOBAL                     19: tuple
                        396     CALL_FUNCTION                   2
                        398     POP_JUMP_IF_FALSE               326 (to 652)
                        402     LOAD_FAST                       6: r
                        404     LOAD_GLOBAL                     19: tuple
                        406     LOAD_ATTR                       6: __repr__
                        408     IS_OP                           0 (is)
                        410     POP_JUMP_IF_FALSE               326 (to 652)
                        414     LOAD_GLOBAL                     4: issubclass
                        416     LOAD_FAST                       5: typ
                        418     LOAD_GLOBAL                     18: list
                        420     CALL_FUNCTION                   2
                        422     POP_JUMP_IF_FALSE               219 (to 438)
                        424     LOAD_FAST                       1: object
                        426     POP_JUMP_IF_TRUE                216 (to 432)
                        428     LOAD_CONST                      12: ('[]', True, False)
                        430     RETURN_VALUE                    
                        432     LOAD_CONST                      13: '[%s]'
                        434     STORE_FAST                      21: format
                        436     JUMP_FORWARD                    15 (to 468)
                        438     LOAD_GLOBAL                     20: len
                        440     LOAD_FAST                       1: object
                        442     CALL_FUNCTION                   1
                        444     LOAD_CONST                      7: 1
                        446     COMPARE_OP                      2 (==)
                        448     POP_JUMP_IF_FALSE               228 (to 456)
                        450     LOAD_CONST                      14: '(%s,)'
                        452     STORE_FAST                      21: format
                        454     JUMP_FORWARD                    6 (to 468)
                        456     LOAD_FAST                       1: object
                        458     POP_JUMP_IF_TRUE                232 (to 464)
                        460     LOAD_CONST                      15: ('()', True, False)
                        462     RETURN_VALUE                    
                        464     LOAD_CONST                      16: '(%s)'
                        466     STORE_FAST                      21: format
                        468     LOAD_GLOBAL                     9: id
                        470     LOAD_FAST                       1: object
                        472     CALL_FUNCTION                   1
                        474     STORE_FAST                      7: objid
                        476     LOAD_FAST                       3: maxlevels
                        478     POP_JUMP_IF_FALSE               253 (to 506)
                        480     LOAD_FAST                       4: level
                        482     LOAD_FAST                       3: maxlevels
                        484     COMPARE_OP                      5 (>=)
                        486     POP_JUMP_IF_FALSE               253 (to 506)
                        488     LOAD_FAST                       21: format
                        490     LOAD_CONST                      17: '...'
                        492     BINARY_MODULO                   
                        494     LOAD_CONST                      2: False
                        496     LOAD_FAST                       7: objid
                        498     LOAD_FAST                       2: context
                        500     CONTAINS_OP                     0 (in)
                        502     BUILD_TUPLE                     3
                        504     RETURN_VALUE                    
                        506     LOAD_FAST                       7: objid
                        508     LOAD_FAST                       2: context
                        510     CONTAINS_OP                     0 (in)
                        512     POP_JUMP_IF_FALSE               265 (to 530)
                        516     LOAD_GLOBAL                     10: _recursion
                        518     LOAD_FAST                       1: object
                        520     CALL_FUNCTION                   1
                        522     LOAD_CONST                      2: False
                        524     LOAD_CONST                      1: True
                        526     BUILD_TUPLE                     3
                        528     RETURN_VALUE                    
                        530     LOAD_CONST                      7: 1
                        532     LOAD_FAST                       2: context
                        534     LOAD_FAST                       7: objid
                        536     STORE_SUBSCR                    
                        538     LOAD_CONST                      1: True
                        540     STORE_FAST                      8: readable
                        542     LOAD_CONST                      2: False
                        544     STORE_FAST                      9: recursive
                        546     BUILD_LIST                      0
                        548     STORE_FAST                      10: components
                        550     LOAD_FAST                       10: components
                        552     LOAD_ATTR                       11: append
                        554     STORE_FAST                      11: append
                        556     LOAD_FAST                       4: level
                        558     LOAD_CONST                      7: 1
                        560     INPLACE_ADD                     
                        562     STORE_FAST                      4: level
                        564     LOAD_FAST                       1: object
                        566     GET_ITER                        
                        568     FOR_ITER                        28 (to 626)
                        570     STORE_FAST                      22: o
                        572     LOAD_FAST                       0: self
                        574     LOAD_METHOD                     16: format
                        576     LOAD_FAST                       22: o
                        578     LOAD_FAST                       2: context
                        580     LOAD_FAST                       3: maxlevels
                        582     LOAD_FAST                       4: level
                        584     CALL_METHOD                     4
                        586     UNPACK_SEQUENCE                 3
                        588     STORE_FAST                      23: orepr
                        590     STORE_FAST                      24: oreadable
                        592     STORE_FAST                      25: orecur
                        594     LOAD_FAST                       11: append
                        596     LOAD_FAST                       23: orepr
                        598     CALL_FUNCTION                   1
                        600     POP_TOP                         
                        602     LOAD_FAST                       24: oreadable
                        604     POP_JUMP_IF_TRUE                306 (to 612)
                        608     LOAD_CONST                      2: False
                        610     STORE_FAST                      8: readable
                        612     LOAD_FAST                       25: orecur
                        614     POP_JUMP_IF_FALSE               311 (to 622)
                        618     LOAD_CONST                      1: True
                        620     STORE_FAST                      9: recursive
                        622     JUMP_ABSOLUTE                   284 (to 568)
                        626     LOAD_FAST                       2: context
                        628     LOAD_FAST                       7: objid
                        630     DELETE_SUBSCR                   
                        632     LOAD_FAST                       21: format
                        634     LOAD_CONST                      11: ', '
                        636     LOAD_METHOD                     17: join
                        638     LOAD_FAST                       10: components
                        640     CALL_METHOD                     1
                        642     BINARY_MODULO                   
                        644     LOAD_FAST                       8: readable
                        646     LOAD_FAST                       9: recursive
                        648     BUILD_TUPLE                     3
                        650     RETURN_VALUE                    
                        652     LOAD_GLOBAL                     2: repr
                        654     LOAD_FAST                       1: object
                        656     CALL_FUNCTION                   1
                        658     STORE_FAST                      26: rep
                        660     LOAD_FAST                       26: rep
                        662     LOAD_FAST                       26: rep
                        664     JUMP_IF_FALSE_OR_POP            339 (to 678)
                        668     LOAD_FAST                       26: rep
                        670     LOAD_METHOD                     21: startswith
                        672     LOAD_CONST                      18: '<'
                        674     CALL_METHOD                     1
                        676     UNARY_NOT                       
                        678     LOAD_CONST                      2: False
                        680     BUILD_TUPLE                     3
                        682     RETURN_VALUE                    
                'PrettyPrinter._safe_repr'
                (
                    1
                    80
                    None
                    None
                )
            [Disassembly]
                0       LOAD_NAME                       0: __name__
                2       STORE_NAME                      1: __module__
                4       LOAD_CONST                      0: 'PrettyPrinter'
                6       STORE_NAME                      2: __qualname__
                8       LOAD_CONST                      67: (1, 80, None, None)
                10      LOAD_CONST                      4: False
                12      LOAD_CONST                      5: True
                14      LOAD_CONST                      4: False
                16      LOAD_CONST                      6: ('compact', 'sort_dicts', 'underscore_numbers')
                18      BUILD_CONST_KEY_MAP             3
                20      LOAD_CONST                      7: <CODE> __init__
                22      LOAD_CONST                      8: 'PrettyPrinter.__init__'
                24      MAKE_FUNCTION                   3
                26      STORE_NAME                      3: __init__
                28      LOAD_CONST                      9: <CODE> pprint
                30      LOAD_CONST                      10: 'PrettyPrinter.pprint'
                32      MAKE_FUNCTION                   0
                34      STORE_NAME                      4: pprint
                36      LOAD_CONST                      11: <CODE> pformat
                38      LOAD_CONST                      12: 'PrettyPrinter.pformat'
                40      MAKE_FUNCTION                   0
                42      STORE_NAME                      5: pformat
                44      LOAD_CONST                      13: <CODE> isrecursive
                46      LOAD_CONST                      14: 'PrettyPrinter.isrecursive'
                48      MAKE_FUNCTION                   0
                50      STORE_NAME                      6: isrecursive
                52      LOAD_CONST                      15: <CODE> isreadable
                54      LOAD_CONST                      16: 'PrettyPrinter.isreadable'
                56      MAKE_FUNCTION                   0
                58      STORE_NAME                      7: isreadable
                60      LOAD_CONST                      17: <CODE> _format
                62      LOAD_CONST                      18: 'PrettyPrinter._format'
                64      MAKE_FUNCTION                   0
                66      STORE_NAME                      8: _format
                68      LOAD_CONST                      19: <CODE> _pprint_dataclass
                70      LOAD_CONST                      20: 'PrettyPrinter._pprint_dataclass'
                72      MAKE_FUNCTION                   0
                74      STORE_NAME                      9: _pprint_dataclass
                76      BUILD_MAP                       0
                78      STORE_NAME                      10: _dispatch
                80      LOAD_CONST                      21: <CODE> _pprint_dict
                82      LOAD_CONST                      22: 'PrettyPrinter._pprint_dict'
                84      MAKE_FUNCTION                   0
                86      STORE_NAME                      11: _pprint_dict
                88      LOAD_NAME                       11: _pprint_dict
                90      LOAD_NAME                       10: _dispatch
                92      LOAD_NAME                       12: dict
                94      LOAD_ATTR                       13: __repr__
                96      STORE_SUBSCR                    
                98      LOAD_CONST                      23: <CODE> _pprint_ordered_dict
                100     LOAD_CONST                      24: 'PrettyPrinter._pprint_ordered_dict'
                102     MAKE_FUNCTION                   0
                104     STORE_NAME                      14: _pprint_ordered_dict
                106     LOAD_NAME                       14: _pprint_ordered_dict
                108     LOAD_NAME                       10: _dispatch
                110     LOAD_NAME                       15: _collections
                112     LOAD_ATTR                       16: OrderedDict
                114     LOAD_ATTR                       13: __repr__
                116     STORE_SUBSCR                    
                118     LOAD_CONST                      25: <CODE> _pprint_list
                120     LOAD_CONST                      26: 'PrettyPrinter._pprint_list'
                122     MAKE_FUNCTION                   0
                124     STORE_NAME                      17: _pprint_list
                126     LOAD_NAME                       17: _pprint_list
                128     LOAD_NAME                       10: _dispatch
                130     LOAD_NAME                       18: list
                132     LOAD_ATTR                       13: __repr__
                134     STORE_SUBSCR                    
                136     LOAD_CONST                      27: <CODE> _pprint_tuple
                138     LOAD_CONST                      28: 'PrettyPrinter._pprint_tuple'
                140     MAKE_FUNCTION                   0
                142     STORE_NAME                      19: _pprint_tuple
                144     LOAD_NAME                       19: _pprint_tuple
                146     LOAD_NAME                       10: _dispatch
                148     LOAD_NAME                       20: tuple
                150     LOAD_ATTR                       13: __repr__
                152     STORE_SUBSCR                    
                154     LOAD_CONST                      29: <CODE> _pprint_set
                156     LOAD_CONST                      30: 'PrettyPrinter._pprint_set'
                158     MAKE_FUNCTION                   0
                160     STORE_NAME                      21: _pprint_set
                162     LOAD_NAME                       21: _pprint_set
                164     LOAD_NAME                       10: _dispatch
                166     LOAD_NAME                       22: set
                168     LOAD_ATTR                       13: __repr__
                170     STORE_SUBSCR                    
                172     LOAD_NAME                       21: _pprint_set
                174     LOAD_NAME                       10: _dispatch
                176     LOAD_NAME                       23: frozenset
                178     LOAD_ATTR                       13: __repr__
                180     STORE_SUBSCR                    
                182     LOAD_CONST                      31: <CODE> _pprint_str
                184     LOAD_CONST                      32: 'PrettyPrinter._pprint_str'
                186     MAKE_FUNCTION                   0
                188     STORE_NAME                      24: _pprint_str
                190     LOAD_NAME                       24: _pprint_str
                192     LOAD_NAME                       10: _dispatch
                194     LOAD_NAME                       25: str
                196     LOAD_ATTR                       13: __repr__
                198     STORE_SUBSCR                    
                200     LOAD_CONST                      33: <CODE> _pprint_bytes
                202     LOAD_CONST                      34: 'PrettyPrinter._pprint_bytes'
                204     MAKE_FUNCTION                   0
                206     STORE_NAME                      26: _pprint_bytes
                208     LOAD_NAME                       26: _pprint_bytes
                210     LOAD_NAME                       10: _dispatch
                212     LOAD_NAME                       27: bytes
                214     LOAD_ATTR                       13: __repr__
                216     STORE_SUBSCR                    
                218     LOAD_CONST                      35: <CODE> _pprint_bytearray
                220     LOAD_CONST                      36: 'PrettyPrinter._pprint_bytearray'
                222     MAKE_FUNCTION                   0
                224     STORE_NAME                      28: _pprint_bytearray
                226     LOAD_NAME                       28: _pprint_bytearray
                228     LOAD_NAME                       10: _dispatch
                230     LOAD_NAME                       29: bytearray
                232     LOAD_ATTR                       13: __repr__
                234     STORE_SUBSCR                    
                236     LOAD_CONST                      37: <CODE> _pprint_mappingproxy
                238     LOAD_CONST                      38: 'PrettyPrinter._pprint_mappingproxy'
                240     MAKE_FUNCTION                   0
                242     STORE_NAME                      30: _pprint_mappingproxy
                244     LOAD_NAME                       30: _pprint_mappingproxy
                246     LOAD_NAME                       10: _dispatch
                248     LOAD_NAME                       31: _types
                250     LOAD_ATTR                       32: MappingProxyType
                252     LOAD_ATTR                       13: __repr__
                254     STORE_SUBSCR                    
                256     LOAD_CONST                      39: <CODE> _pprint_simplenamespace
                258     LOAD_CONST                      40: 'PrettyPrinter._pprint_simplenamespace'
                260     MAKE_FUNCTION                   0
                262     STORE_NAME                      33: _pprint_simplenamespace
                264     LOAD_NAME                       33: _pprint_simplenamespace
                266     LOAD_NAME                       10: _dispatch
                268     LOAD_NAME                       31: _types
                270     LOAD_ATTR                       34: SimpleNamespace
                272     LOAD_ATTR                       13: __repr__
                274     STORE_SUBSCR                    
                276     LOAD_CONST                      41: <CODE> _format_dict_items
                278     LOAD_CONST                      42: 'PrettyPrinter._format_dict_items'
                280     MAKE_FUNCTION                   0
                282     STORE_NAME                      35: _format_dict_items
                284     LOAD_CONST                      43: <CODE> _format_namespace_items
                286     LOAD_CONST                      44: 'PrettyPrinter._format_namespace_items'
                288     MAKE_FUNCTION                   0
                290     STORE_NAME                      36: _format_namespace_items
                292     LOAD_CONST                      45: <CODE> _format_items
                294     LOAD_CONST                      46: 'PrettyPrinter._format_items'
                296     MAKE_FUNCTION                   0
                298     STORE_NAME                      37: _format_items
                300     LOAD_CONST                      47: <CODE> _repr
                302     LOAD_CONST                      48: 'PrettyPrinter._repr'
                304     MAKE_FUNCTION                   0
                306     STORE_NAME                      38: _repr
                308     LOAD_CONST                      49: <CODE> format
                310     LOAD_CONST                      50: 'PrettyPrinter.format'
                312     MAKE_FUNCTION                   0
                314     STORE_NAME                      39: format
                316     LOAD_CONST                      51: <CODE> _pprint_default_dict
                318     LOAD_CONST                      52: 'PrettyPrinter._pprint_default_dict'
                320     MAKE_FUNCTION                   0
                322     STORE_NAME                      40: _pprint_default_dict
                324     LOAD_NAME                       40: _pprint_default_dict
                326     LOAD_NAME                       10: _dispatch
                328     LOAD_NAME                       15: _collections
                330     LOAD_ATTR                       41: defaultdict
                332     LOAD_ATTR                       13: __repr__
                334     STORE_SUBSCR                    
                336     LOAD_CONST                      53: <CODE> _pprint_counter
                338     LOAD_CONST                      54: 'PrettyPrinter._pprint_counter'
                340     MAKE_FUNCTION                   0
                342     STORE_NAME                      42: _pprint_counter
                344     LOAD_NAME                       42: _pprint_counter
                346     LOAD_NAME                       10: _dispatch
                348     LOAD_NAME                       15: _collections
                350     LOAD_ATTR                       43: Counter
                352     LOAD_ATTR                       13: __repr__
                354     STORE_SUBSCR                    
                356     LOAD_CONST                      55: <CODE> _pprint_chain_map
                358     LOAD_CONST                      56: 'PrettyPrinter._pprint_chain_map'
                360     MAKE_FUNCTION                   0
                362     STORE_NAME                      44: _pprint_chain_map
                364     LOAD_NAME                       44: _pprint_chain_map
                366     LOAD_NAME                       10: _dispatch
                368     LOAD_NAME                       15: _collections
                370     LOAD_ATTR                       45: ChainMap
                372     LOAD_ATTR                       13: __repr__
                374     STORE_SUBSCR                    
                376     LOAD_CONST                      57: <CODE> _pprint_deque
                378     LOAD_CONST                      58: 'PrettyPrinter._pprint_deque'
                380     MAKE_FUNCTION                   0
                382     STORE_NAME                      46: _pprint_deque
                384     LOAD_NAME                       46: _pprint_deque
                386     LOAD_NAME                       10: _dispatch
                388     LOAD_NAME                       15: _collections
                390     LOAD_ATTR                       47: deque
                392     LOAD_ATTR                       13: __repr__
                394     STORE_SUBSCR                    
                396     LOAD_CONST                      59: <CODE> _pprint_user_dict
                398     LOAD_CONST                      60: 'PrettyPrinter._pprint_user_dict'
                400     MAKE_FUNCTION                   0
                402     STORE_NAME                      48: _pprint_user_dict
                404     LOAD_NAME                       48: _pprint_user_dict
                406     LOAD_NAME                       10: _dispatch
                408     LOAD_NAME                       15: _collections
                410     LOAD_ATTR                       49: UserDict
                412     LOAD_ATTR                       13: __repr__
                414     STORE_SUBSCR                    
                416     LOAD_CONST                      61: <CODE> _pprint_user_list
                418     LOAD_CONST                      62: 'PrettyPrinter._pprint_user_list'
                420     MAKE_FUNCTION                   0
                422     STORE_NAME                      50: _pprint_user_list
                424     LOAD_NAME                       50: _pprint_user_list
                426     LOAD_NAME                       10: _dispatch
                428     LOAD_NAME                       15: _collections
                430     LOAD_ATTR                       51: UserList
                432     LOAD_ATTR                       13: __repr__
                434     STORE_SUBSCR                    
                436     LOAD_CONST                      63: <CODE> _pprint_user_string
                438     LOAD_CONST                      64: 'PrettyPrinter._pprint_user_string'
                440     MAKE_FUNCTION                   0
                442     STORE_NAME                      52: _pprint_user_string
                444     LOAD_NAME                       52: _pprint_user_string
                446     LOAD_NAME                       10: _dispatch
                448     LOAD_NAME                       15: _collections
                450     LOAD_ATTR                       53: UserString
                452     LOAD_ATTR                       13: __repr__
                454     STORE_SUBSCR                    
                456     LOAD_CONST                      65: <CODE> _safe_repr
                458     LOAD_CONST                      66: 'PrettyPrinter._safe_repr'
                460     MAKE_FUNCTION                   0
                462     STORE_NAME                      54: _safe_repr
                464     LOAD_CONST                      3: None
                466     RETURN_VALUE                    
        'PrettyPrinter'
        [Code]
            File Name: pprint.py
            Object Name: _recursion
            Arg Count: 1
            Pos Only Arg Count: 0
            KW Only Arg Count: 0
            Locals: 1
            Stack Size: 4
            Flags: 0x00000043 (CO_OPTIMIZED | CO_NEWLOCALS | CO_NOFREE)
            [Names]
                'type'
                '__name__'
                'id'
            [Var Names]
                'object'
            [Free Vars]
            [Cell Vars]
            [Constants]
                None
                '<Recursion on %s with id=%s>'
            [Disassembly]
                0       LOAD_CONST                      1: '<Recursion on %s with id=%s>'
                2       LOAD_GLOBAL                     0: type
                4       LOAD_FAST                       0: object
                6       CALL_FUNCTION                   1
                8       LOAD_ATTR                       1: __name__
                10      LOAD_GLOBAL                     2: id
                12      LOAD_FAST                       0: object
                14      CALL_FUNCTION                   1
                16      BUILD_TUPLE                     2
                18      BINARY_MODULO                   
                20      RETURN_VALUE                    
        '_recursion'
        [Code]
            File Name: pprint.py
            Object Name: _perfcheck
            Arg Count: 1
            Pos Only Arg Count: 0
            KW Only Arg Count: 0
            Locals: 6
            Stack Size: 7
            Flags: 0x00000043 (CO_OPTIMIZED | CO_NEWLOCALS | CO_NOFREE)
            [Names]
                'time'
                'PrettyPrinter'
                'perf_counter'
                '_safe_repr'
                'pformat'
                'print'
            [Var Names]
                'object'
                'time'
                'p'
                't1'
                't2'
                't3'
            [Free Vars]
            [Cell Vars]
            [Constants]
                None
                0
                'string'
                (
                    1
                    2
                )
                3
                4
                6
                8
                (
                    5
                    7
                )
                100000
                True
                '_safe_repr:'
                'pformat:'
            [Disassembly]
                0       LOAD_CONST                      1: 0
                2       LOAD_CONST                      0: None
                4       IMPORT_NAME                     0: time
                6       STORE_FAST                      1: time
                8       LOAD_FAST                       0: object
                10      LOAD_CONST                      0: None
                12      IS_OP                           0 (is)
                14      POP_JUMP_IF_FALSE               22 (to 44)
                16      LOAD_CONST                      2: 'string'
                18      LOAD_CONST                      3: (1, 2)
                20      LOAD_CONST                      4: 3
                22      LOAD_CONST                      5: 4
                24      BUILD_LIST                      2
                26      LOAD_CONST                      6: 6
                28      LOAD_CONST                      7: 8
                30      LOAD_CONST                      8: (5, 7)
                32      BUILD_CONST_KEY_MAP             2
                34      BUILD_TUPLE                     4
                36      BUILD_LIST                      1
                38      LOAD_CONST                      9: 100000
                40      BINARY_MULTIPLY                 
                42      STORE_FAST                      0: object
                44      LOAD_GLOBAL                     1: PrettyPrinter
                46      CALL_FUNCTION                   0
                48      STORE_FAST                      2: p
                50      LOAD_FAST                       1: time
                52      LOAD_METHOD                     2: perf_counter
                54      CALL_METHOD                     0
                56      STORE_FAST                      3: t1
                58      LOAD_FAST                       2: p
                60      LOAD_METHOD                     3: _safe_repr
                62      LOAD_FAST                       0: object
                64      BUILD_MAP                       0
                66      LOAD_CONST                      0: None
                68      LOAD_CONST                      1: 0
                70      LOAD_CONST                      10: True
                72      CALL_METHOD                     5
                74      POP_TOP                         
                76      LOAD_FAST                       1: time
                78      LOAD_METHOD                     2: perf_counter
                80      CALL_METHOD                     0
                82      STORE_FAST                      4: t2
                84      LOAD_FAST                       2: p
                86      LOAD_METHOD                     4: pformat
                88      LOAD_FAST                       0: object
                90      CALL_METHOD                     1
                92      POP_TOP                         
                94      LOAD_FAST                       1: time
                96      LOAD_METHOD                     2: perf_counter
                98      CALL_METHOD                     0
                100     STORE_FAST                      5: t3
                102     LOAD_GLOBAL                     5: print
                104     LOAD_CONST                      11: '_safe_repr:'
                106     LOAD_FAST                       4: t2
                108     LOAD_FAST                       3: t1
                110     BINARY_SUBTRACT                 
                112     CALL_FUNCTION                   2
                114     POP_TOP                         
                116     LOAD_GLOBAL                     5: print
                118     LOAD_CONST                      12: 'pformat:'
                120     LOAD_FAST                       5: t3
                122     LOAD_FAST                       4: t2
                124     BINARY_SUBTRACT                 
                126     CALL_FUNCTION                   2
                128     POP_TOP                         
                130     LOAD_CONST                      0: None
                132     RETURN_VALUE                    
        '_perfcheck'
        [Code]
            File Name: pprint.py
            Object Name: _wrap_bytes_repr
            Arg Count: 3
            Pos Only Arg Count: 0
            KW Only Arg Count: 0
            Locals: 8
            Stack Size: 5
            Flags: 0x00000063 (CO_OPTIMIZED | CO_NEWLOCALS | CO_GENERATOR | CO_NOFREE)
            [Names]
                'len'
                'range'
                'repr'
            [Var Names]
                'object'
                'width'
                'allowance'
                'current'
                'last'
                'i'
                'part'
                'candidate'
            [Free Vars]
            [Cell Vars]
            [Constants]
                None
                b''
                4
                0
            [Disassembly]
                0       GEN_START                       0
                2       LOAD_CONST                      1: b''
                4       STORE_FAST                      3: current
                6       LOAD_GLOBAL                     0: len
                8       LOAD_FAST                       0: object
                10      CALL_FUNCTION                   1
                12      LOAD_CONST                      2: 4
                14      BINARY_FLOOR_DIVIDE             
                16      LOAD_CONST                      2: 4
                18      BINARY_MULTIPLY                 
                20      STORE_FAST                      4: last
                22      LOAD_GLOBAL                     1: range
                24      LOAD_CONST                      3: 0
                26      LOAD_GLOBAL                     0: len
                28      LOAD_FAST                       0: object
                30      CALL_FUNCTION                   1
                32      LOAD_CONST                      2: 4
                34      CALL_FUNCTION                   3
                36      GET_ITER                        
                38      FOR_ITER                        42 (to 124)
                40      STORE_FAST                      5: i
                42      LOAD_FAST                       0: object
                44      LOAD_FAST                       5: i
                46      LOAD_FAST                       5: i
                48      LOAD_CONST                      2: 4
                50      BINARY_ADD                      
                52      BUILD_SLICE                     2
                54      BINARY_SUBSCR                   
                56      STORE_FAST                      6: part
                58      LOAD_FAST                       3: current
                60      LOAD_FAST                       6: part
                62      BINARY_ADD                      
                64      STORE_FAST                      7: candidate
                66      LOAD_FAST                       5: i
                68      LOAD_FAST                       4: last
                70      COMPARE_OP                      2 (==)
                72      POP_JUMP_IF_FALSE               41 (to 82)
                74      LOAD_FAST                       1: width
                76      LOAD_FAST                       2: allowance
                78      INPLACE_SUBTRACT                
                80      STORE_FAST                      1: width
                82      LOAD_GLOBAL                     0: len
                84      LOAD_GLOBAL                     2: repr
                86      LOAD_FAST                       7: candidate
                88      CALL_FUNCTION                   1
                90      CALL_FUNCTION                   1
                92      LOAD_FAST                       1: width
                94      COMPARE_OP                      4 (>)
                96      POP_JUMP_IF_FALSE               59 (to 118)
                98      LOAD_FAST                       3: current
                100     POP_JUMP_IF_FALSE               56 (to 112)
                102     LOAD_GLOBAL                     2: repr
                104     LOAD_FAST                       3: current
                106     CALL_FUNCTION                   1
                108     YIELD_VALUE                     
                110     POP_TOP                         
                112     LOAD_FAST                       6: part
                114     STORE_FAST                      3: current
                116     JUMP_ABSOLUTE                   19 (to 38)
                118     LOAD_FAST                       7: candidate
                120     STORE_FAST                      3: current
                122     JUMP_ABSOLUTE                   19 (to 38)
                124     LOAD_FAST                       3: current
                126     POP_JUMP_IF_FALSE               71 (to 142)
                128     LOAD_GLOBAL                     2: repr
                130     LOAD_FAST                       3: current
                132     CALL_FUNCTION                   1
                134     YIELD_VALUE                     
                136     POP_TOP                         
                138     LOAD_CONST                      0: None
                140     RETURN_VALUE                    
                142     LOAD_CONST                      0: None
                144     RETURN_VALUE                    
        '_wrap_bytes_repr'
        '__main__'
        (
            None
            1
            80
            None
        )
        (
            1
            80
            None
        )
        (
            None
        )
    [Disassembly]
        0       LOAD_CONST                      0: "Support to pretty-print lists, tuples, & dictionaries recursively.\n\nVery simple, but useful, especially in debugging data structures.\n\nClasses\n-------\n\nPrettyPrinter()\n    Handle pretty-printing operations onto a stream using a configured\n    set of formatting parameters.\n\nFunctions\n---------\n\npformat()\n    Format a Python object into a pretty-printed representation.\n\npprint()\n    Pretty-print a Python object to a stream [default is sys.stdout].\n\nsaferepr()\n    Generate a 'standard' repr()-like value, but protect against recursive\n    data structures.\n\n"
        2       STORE_NAME                      0: __doc__
        4       LOAD_CONST                      1: 0
        6       LOAD_CONST                      2: None
        8       IMPORT_NAME                     1: collections
        10      STORE_NAME                      2: _collections
        12      LOAD_CONST                      1: 0
        14      LOAD_CONST                      2: None
        16      IMPORT_NAME                     3: dataclasses
        18      STORE_NAME                      4: _dataclasses
        20      LOAD_CONST                      1: 0
        22      LOAD_CONST                      2: None
        24      IMPORT_NAME                     5: re
        26      STORE_NAME                      5: re
        28      LOAD_CONST                      1: 0
        30      LOAD_CONST                      2: None
        32      IMPORT_NAME                     6: sys
        34      STORE_NAME                      7: _sys
        36      LOAD_CONST                      1: 0
        38      LOAD_CONST                      2: None
        40      IMPORT_NAME                     8: types
        42      STORE_NAME                      9: _types
        44      LOAD_CONST                      1: 0
        46      LOAD_CONST                      3: ('StringIO',)
        48      IMPORT_NAME                     10: io
        50      IMPORT_FROM                     11: StringIO
        52      STORE_NAME                      12: _StringIO
        54      POP_TOP                         
        56      BUILD_LIST                      0
        58      LOAD_CONST                      4: ('pprint', 'pformat', 'isreadable', 'isrecursive', 'saferepr', 'PrettyPrinter', 'pp')
        60      LIST_EXTEND                     1
        62      STORE_NAME                      13: __all__
        64      LOAD_CONST                      36: (None, 1, 80, None)
        66      LOAD_CONST                      7: False
        68      LOAD_CONST                      8: True
        70      LOAD_CONST                      7: False
        72      LOAD_CONST                      9: ('compact', 'sort_dicts', 'underscore_numbers')
        74      BUILD_CONST_KEY_MAP             3
        76      LOAD_CONST                      10: <CODE> pprint
        78      LOAD_CONST                      11: 'pprint'
        80      MAKE_FUNCTION                   3
        82      STORE_NAME                      14: pprint
        84      LOAD_CONST                      37: (1, 80, None)
        86      LOAD_CONST                      7: False
        88      LOAD_CONST                      8: True
        90      LOAD_CONST                      7: False
        92      LOAD_CONST                      9: ('compact', 'sort_dicts', 'underscore_numbers')
        94      BUILD_CONST_KEY_MAP             3
        96      LOAD_CONST                      12: <CODE> pformat
        98      LOAD_CONST                      13: 'pformat'
        100     MAKE_FUNCTION                   3
        102     STORE_NAME                      15: pformat
        104     LOAD_CONST                      7: False
        106     LOAD_CONST                      14: ('sort_dicts',)
        108     BUILD_CONST_KEY_MAP             1
        110     LOAD_CONST                      15: <CODE> pp
        112     LOAD_CONST                      16: 'pp'
        114     MAKE_FUNCTION                   2
        116     STORE_NAME                      16: pp
        118     LOAD_CONST                      17: <CODE> saferepr
        120     LOAD_CONST                      18: 'saferepr'
        122     MAKE_FUNCTION                   0
        124     STORE_NAME                      17: saferepr
        126     LOAD_CONST                      19: <CODE> isreadable
        128     LOAD_CONST                      20: 'isreadable'
        130     MAKE_FUNCTION                   0
        132     STORE_NAME                      18: isreadable
        134     LOAD_CONST                      21: <CODE> isrecursive
        136     LOAD_CONST                      22: 'isrecursive'
        138     MAKE_FUNCTION                   0
        140     STORE_NAME                      19: isrecursive
        142     LOAD_BUILD_CLASS                
        144     LOAD_CONST                      23: <CODE> _safe_key
        146     LOAD_CONST                      24: '_safe_key'
        148     MAKE_FUNCTION                   0
        150     LOAD_CONST                      24: '_safe_key'
        152     CALL_FUNCTION                   2
        154     STORE_NAME                      20: _safe_key
        156     LOAD_CONST                      25: <CODE> _safe_tuple
        158     LOAD_CONST                      26: '_safe_tuple'
        160     MAKE_FUNCTION                   0
        162     STORE_NAME                      21: _safe_tuple
        164     LOAD_BUILD_CLASS                
        166     LOAD_CONST                      27: <CODE> PrettyPrinter
        168     LOAD_CONST                      28: 'PrettyPrinter'
        170     MAKE_FUNCTION                   0
        172     LOAD_CONST                      28: 'PrettyPrinter'
        174     CALL_FUNCTION                   2
        176     STORE_NAME                      22: PrettyPrinter
        178     LOAD_NAME                       23: frozenset
        180     LOAD_NAME                       24: str
        182     LOAD_NAME                       25: bytes
        184     LOAD_NAME                       26: bytearray
        186     LOAD_NAME                       27: float
        188     LOAD_NAME                       28: complex
        190     LOAD_NAME                       29: bool
        192     LOAD_NAME                       30: type
        194     LOAD_CONST                      2: None
        196     CALL_FUNCTION                   1
        198     BUILD_SET                       7
        200     CALL_FUNCTION                   1
        202     STORE_NAME                      31: _builtin_scalars
        204     LOAD_CONST                      29: <CODE> _recursion
        206     LOAD_CONST                      30: '_recursion'
        208     MAKE_FUNCTION                   0
        210     STORE_NAME                      32: _recursion
        212     LOAD_CONST                      38: (None,)
        214     LOAD_CONST                      31: <CODE> _perfcheck
        216     LOAD_CONST                      32: '_perfcheck'
        218     MAKE_FUNCTION                   1
        220     STORE_NAME                      33: _perfcheck
        222     LOAD_CONST                      33: <CODE> _wrap_bytes_repr
        224     LOAD_CONST                      34: '_wrap_bytes_repr'
        226     MAKE_FUNCTION                   0
        228     STORE_NAME                      34: _wrap_bytes_repr
        230     LOAD_NAME                       35: __name__
        232     LOAD_CONST                      35: '__main__'
        234     COMPARE_OP                      2 (==)
        236     POP_JUMP_IF_FALSE               124 (to 248)
        238     LOAD_NAME                       33: _perfcheck
        240     CALL_FUNCTION                   0
        242     POP_TOP                         
        244     LOAD_CONST                      2: None
        246     RETURN_VALUE                    
        248     LOAD_CONST                      2: None
        250     RETURN_VALUE                    
