tracemalloc.pyc (Python 3.10)
[Code]
    File Name: tracemalloc.py
    Object Name: <module>
    Arg Count: 0
    Pos Only Arg Count: 0
    KW Only Arg Count: 0
    Locals: 0
    Stack Size: 5
    Flags: 0x00000040 (CO_NOFREE)
    [Names]
        'collections.abc'
        'Sequence'
        'Iterable'
        'functools'
        'total_ordering'
        'fnmatch'
        'linecache'
        'os.path'
        'os'
        'pickle'
        '_tracemalloc'
        '_get_object_traceback'
        '_get_traces'
        '_format_size'
        'Statistic'
        'StatisticDiff'
        '_compare_grouped_stats'
        'Frame'
        'Traceback'
        'get_object_traceback'
        'Trace'
        '_Traces'
        '_normalize_filename'
        'BaseFilter'
        'Filter'
        'DomainFilter'
        'Snapshot'
        'take_snapshot'
    [Var Names]
    [Free Vars]
    [Cell Vars]
    [Constants]
        0
        (
            'Sequence'
            'Iterable'
        )
        (
            'total_ordering'
        )
        None
        (
            '*'
        )
        (
            '_get_object_traceback'
            '_get_traces'
        )
        [Code]
            File Name: tracemalloc.py
            Object Name: _format_size
            Arg Count: 2
            Pos Only Arg Count: 0
            KW Only Arg Count: 0
            Locals: 3
            Stack Size: 4
            Flags: 0x00000043 (CO_OPTIMIZED | CO_NEWLOCALS | CO_NOFREE)
            [Names]
                'abs'
            [Var Names]
                'size'
                'sign'
                'unit'
            [Free Vars]
            [Cell Vars]
            [Constants]
                None
                (
                    'B'
                    'KiB'
                    'MiB'
                    'GiB'
                    'TiB'
                )
                100
                'B'
                '%+.1f %s'
                '%.1f %s'
                10240
                'TiB'
                '%+.0f %s'
                '%.0f %s'
                1024
            [Disassembly]
                0       LOAD_CONST                      1: ('B', 'KiB', 'MiB', 'GiB', 'TiB')
                2       GET_ITER                        
                4       FOR_ITER                        62 (to 130)
                6       STORE_FAST                      2: unit
                8       LOAD_GLOBAL                     0: abs
                10      LOAD_FAST                       0: size
                12      CALL_FUNCTION                   1
                14      LOAD_CONST                      2: 100
                16      COMPARE_OP                      0 (<)
                18      POP_JUMP_IF_FALSE               32 (to 64)
                20      LOAD_FAST                       2: unit
                22      LOAD_CONST                      3: 'B'
                24      COMPARE_OP                      3 (!=)
                26      POP_JUMP_IF_FALSE               32 (to 64)
                28      LOAD_FAST                       1: sign
                30      POP_JUMP_IF_FALSE               24 (to 48)
                32      LOAD_CONST                      4: '%+.1f %s'
                34      LOAD_FAST                       0: size
                36      LOAD_FAST                       2: unit
                38      BUILD_TUPLE                     2
                40      BINARY_MODULO                   
                42      ROT_TWO                         
                44      POP_TOP                         
                46      RETURN_VALUE                    
                48      LOAD_CONST                      5: '%.1f %s'
                50      LOAD_FAST                       0: size
                52      LOAD_FAST                       2: unit
                54      BUILD_TUPLE                     2
                56      BINARY_MODULO                   
                58      ROT_TWO                         
                60      POP_TOP                         
                62      RETURN_VALUE                    
                64      LOAD_GLOBAL                     0: abs
                66      LOAD_FAST                       0: size
                68      CALL_FUNCTION                   1
                70      LOAD_CONST                      6: 10240
                72      COMPARE_OP                      0 (<)
                74      POP_JUMP_IF_TRUE                42 (to 84)
                76      LOAD_FAST                       2: unit
                78      LOAD_CONST                      7: 'TiB'
                80      COMPARE_OP                      2 (==)
                82      POP_JUMP_IF_FALSE               60 (to 120)
                84      LOAD_FAST                       1: sign
                86      POP_JUMP_IF_FALSE               52 (to 104)
                88      LOAD_CONST                      8: '%+.0f %s'
                90      LOAD_FAST                       0: size
                92      LOAD_FAST                       2: unit
                94      BUILD_TUPLE                     2
                96      BINARY_MODULO                   
                98      ROT_TWO                         
                100     POP_TOP                         
                102     RETURN_VALUE                    
                104     LOAD_CONST                      9: '%.0f %s'
                106     LOAD_FAST                       0: size
                108     LOAD_FAST                       2: unit
                110     BUILD_TUPLE                     2
                112     BINARY_MODULO                   
                114     ROT_TWO                         
                116     POP_TOP                         
                118     RETURN_VALUE                    
                120     LOAD_FAST                       0: size
                122     LOAD_CONST                      10: 1024
                124     INPLACE_TRUE_DIVIDE             
                126     STORE_FAST                      0: size
                128     JUMP_ABSOLUTE                   2 (to 4)
                130     LOAD_CONST                      0: None
                132     RETURN_VALUE                    
        '_format_size'
        [Code]
            File Name: tracemalloc.py
            Object Name: Statistic
            Arg Count: 0
            Pos Only Arg Count: 0
            KW Only Arg Count: 0
            Locals: 0
            Stack Size: 2
            Flags: 0x00000040 (CO_NOFREE)
            [Names]
                '__name__'
                '__module__'
                '__qualname__'
                '__doc__'
                '__slots__'
                '__init__'
                '__hash__'
                '__eq__'
                '__str__'
                '__repr__'
                '_sort_key'
            [Var Names]
            [Free Vars]
            [Cell Vars]
            [Constants]
                'Statistic'
                '\n    Statistic difference on memory allocations between two Snapshot instance.\n    '
                (
                    'traceback'
                    'size'
                    'count'
                )
                [Code]
                    File Name: tracemalloc.py
                    Object Name: __init__
                    Arg Count: 4
                    Pos Only Arg Count: 0
                    KW Only Arg Count: 0
                    Locals: 4
                    Stack Size: 2
                    Flags: 0x00000043 (CO_OPTIMIZED | CO_NEWLOCALS | CO_NOFREE)
                    [Names]
                        'traceback'
                        'size'
                        'count'
                    [Var Names]
                        'self'
                        'traceback'
                        'size'
                        'count'
                    [Free Vars]
                    [Cell Vars]
                    [Constants]
                        None
                    [Disassembly]
                        0       LOAD_FAST                       1: traceback
                        2       LOAD_FAST                       0: self
                        4       STORE_ATTR                      0: traceback
                        6       LOAD_FAST                       2: size
                        8       LOAD_FAST                       0: self
                        10      STORE_ATTR                      1: size
                        12      LOAD_FAST                       3: count
                        14      LOAD_FAST                       0: self
                        16      STORE_ATTR                      2: count
                        18      LOAD_CONST                      0: None
                        20      RETURN_VALUE                    
                'Statistic.__init__'
                [Code]
                    File Name: tracemalloc.py
                    Object Name: __hash__
                    Arg Count: 1
                    Pos Only Arg Count: 0
                    KW Only Arg Count: 0
                    Locals: 1
                    Stack Size: 4
                    Flags: 0x00000043 (CO_OPTIMIZED | CO_NEWLOCALS | CO_NOFREE)
                    [Names]
                        'hash'
                        'traceback'
                        'size'
                        'count'
                    [Var Names]
                        'self'
                    [Free Vars]
                    [Cell Vars]
                    [Constants]
                        None
                    [Disassembly]
                        0       LOAD_GLOBAL                     0: hash
                        2       LOAD_FAST                       0: self
                        4       LOAD_ATTR                       1: traceback
                        6       LOAD_FAST                       0: self
                        8       LOAD_ATTR                       2: size
                        10      LOAD_FAST                       0: self
                        12      LOAD_ATTR                       3: count
                        14      BUILD_TUPLE                     3
                        16      CALL_FUNCTION                   1
                        18      RETURN_VALUE                    
                'Statistic.__hash__'
                [Code]
                    File Name: tracemalloc.py
                    Object Name: __eq__
                    Arg Count: 2
                    Pos Only Arg Count: 0
                    KW Only Arg Count: 0
                    Locals: 2
                    Stack Size: 3
                    Flags: 0x00000043 (CO_OPTIMIZED | CO_NEWLOCALS | CO_NOFREE)
                    [Names]
                        'isinstance'
                        'Statistic'
                        'NotImplemented'
                        'traceback'
                        'size'
                        'count'
                    [Var Names]
                        'self'
                        'other'
                    [Free Vars]
                    [Cell Vars]
                    [Constants]
                        None
                    [Disassembly]
                        0       LOAD_GLOBAL                     0: isinstance
                        2       LOAD_FAST                       1: other
                        4       LOAD_GLOBAL                     1: Statistic
                        6       CALL_FUNCTION                   2
                        8       POP_JUMP_IF_TRUE                7 (to 14)
                        10      LOAD_GLOBAL                     2: NotImplemented
                        12      RETURN_VALUE                    
                        14      LOAD_FAST                       0: self
                        16      LOAD_ATTR                       3: traceback
                        18      LOAD_FAST                       1: other
                        20      LOAD_ATTR                       3: traceback
                        22      COMPARE_OP                      2 (==)
                        24      JUMP_IF_FALSE_OR_POP            24 (to 48)
                        26      LOAD_FAST                       0: self
                        28      LOAD_ATTR                       4: size
                        30      LOAD_FAST                       1: other
                        32      LOAD_ATTR                       4: size
                        34      COMPARE_OP                      2 (==)
                        36      JUMP_IF_FALSE_OR_POP            24 (to 48)
                        38      LOAD_FAST                       0: self
                        40      LOAD_ATTR                       5: count
                        42      LOAD_FAST                       1: other
                        44      LOAD_ATTR                       5: count
                        46      COMPARE_OP                      2 (==)
                        48      RETURN_VALUE                    
                'Statistic.__eq__'
                [Code]
                    File Name: tracemalloc.py
                    Object Name: __str__
                    Arg Count: 1
                    Pos Only Arg Count: 0
                    KW Only Arg Count: 0
                    Locals: 3
                    Stack Size: 5
                    Flags: 0x00000043 (CO_OPTIMIZED | CO_NEWLOCALS | CO_NOFREE)
                    [Names]
                        'traceback'
                        '_format_size'
                        'size'
                        'count'
                    [Var Names]
                        'self'
                        'text'
                        'average'
                    [Free Vars]
                    [Cell Vars]
                    [Constants]
                        None
                        '%s: size=%s, count=%i'
                        False
                        ', average=%s'
                    [Disassembly]
                        0       LOAD_CONST                      1: '%s: size=%s, count=%i'
                        2       LOAD_FAST                       0: self
                        4       LOAD_ATTR                       0: traceback
                        6       LOAD_GLOBAL                     1: _format_size
                        8       LOAD_FAST                       0: self
                        10      LOAD_ATTR                       2: size
                        12      LOAD_CONST                      2: False
                        14      CALL_FUNCTION                   2
                        16      LOAD_FAST                       0: self
                        18      LOAD_ATTR                       3: count
                        20      BUILD_TUPLE                     3
                        22      BINARY_MODULO                   
                        24      STORE_FAST                      1: text
                        26      LOAD_FAST                       0: self
                        28      LOAD_ATTR                       3: count
                        30      POP_JUMP_IF_FALSE               31 (to 62)
                        32      LOAD_FAST                       0: self
                        34      LOAD_ATTR                       2: size
                        36      LOAD_FAST                       0: self
                        38      LOAD_ATTR                       3: count
                        40      BINARY_TRUE_DIVIDE              
                        42      STORE_FAST                      2: average
                        44      LOAD_FAST                       1: text
                        46      LOAD_CONST                      3: ', average=%s'
                        48      LOAD_GLOBAL                     1: _format_size
                        50      LOAD_FAST                       2: average
                        52      LOAD_CONST                      2: False
                        54      CALL_FUNCTION                   2
                        56      BINARY_MODULO                   
                        58      INPLACE_ADD                     
                        60      STORE_FAST                      1: text
                        62      LOAD_FAST                       1: text
                        64      RETURN_VALUE                    
                'Statistic.__str__'
                [Code]
                    File Name: tracemalloc.py
                    Object Name: __repr__
                    Arg Count: 1
                    Pos Only Arg Count: 0
                    KW Only Arg Count: 0
                    Locals: 1
                    Stack Size: 4
                    Flags: 0x00000043 (CO_OPTIMIZED | CO_NEWLOCALS | CO_NOFREE)
                    [Names]
                        'traceback'
                        'size'
                        'count'
                    [Var Names]
                        'self'
                    [Free Vars]
                    [Cell Vars]
                    [Constants]
                        None
                        '<Statistic traceback=%r size=%i count=%i>'
                    [Disassembly]
                        0       LOAD_CONST                      1: '<Statistic traceback=%r size=%i count=%i>'
                        2       LOAD_FAST                       0: self
                        4       LOAD_ATTR                       0: traceback
                        6       LOAD_FAST                       0: self
                        8       LOAD_ATTR                       1: size
                        10      LOAD_FAST                       0: self
                        12      LOAD_ATTR                       2: count
                        14      BUILD_TUPLE                     3
                        16      BINARY_MODULO                   
                        18      RETURN_VALUE                    
                'Statistic.__repr__'
                [Code]
                    File Name: tracemalloc.py
                    Object Name: _sort_key
                    Arg Count: 1
                    Pos Only Arg Count: 0
                    KW Only Arg Count: 0
                    Locals: 1
                    Stack Size: 3
                    Flags: 0x00000043 (CO_OPTIMIZED | CO_NEWLOCALS | CO_NOFREE)
                    [Names]
                        'size'
                        'count'
                        'traceback'
                    [Var Names]
                        'self'
                    [Free Vars]
                    [Cell Vars]
                    [Constants]
                        None
                    [Disassembly]
                        0       LOAD_FAST                       0: self
                        2       LOAD_ATTR                       0: size
                        4       LOAD_FAST                       0: self
                        6       LOAD_ATTR                       1: count
                        8       LOAD_FAST                       0: self
                        10      LOAD_ATTR                       2: traceback
                        12      BUILD_TUPLE                     3
                        14      RETURN_VALUE                    
                'Statistic._sort_key'
                None
            [Disassembly]
                0       LOAD_NAME                       0: __name__
                2       STORE_NAME                      1: __module__
                4       LOAD_CONST                      0: 'Statistic'
                6       STORE_NAME                      2: __qualname__
                8       LOAD_CONST                      1: '\n    Statistic difference on memory allocations between two Snapshot instance.\n    '
                10      STORE_NAME                      3: __doc__
                12      LOAD_CONST                      2: ('traceback', 'size', 'count')
                14      STORE_NAME                      4: __slots__
                16      LOAD_CONST                      3: <CODE> __init__
                18      LOAD_CONST                      4: 'Statistic.__init__'
                20      MAKE_FUNCTION                   0
                22      STORE_NAME                      5: __init__
                24      LOAD_CONST                      5: <CODE> __hash__
                26      LOAD_CONST                      6: 'Statistic.__hash__'
                28      MAKE_FUNCTION                   0
                30      STORE_NAME                      6: __hash__
                32      LOAD_CONST                      7: <CODE> __eq__
                34      LOAD_CONST                      8: 'Statistic.__eq__'
                36      MAKE_FUNCTION                   0
                38      STORE_NAME                      7: __eq__
                40      LOAD_CONST                      9: <CODE> __str__
                42      LOAD_CONST                      10: 'Statistic.__str__'
                44      MAKE_FUNCTION                   0
                46      STORE_NAME                      8: __str__
                48      LOAD_CONST                      11: <CODE> __repr__
                50      LOAD_CONST                      12: 'Statistic.__repr__'
                52      MAKE_FUNCTION                   0
                54      STORE_NAME                      9: __repr__
                56      LOAD_CONST                      13: <CODE> _sort_key
                58      LOAD_CONST                      14: 'Statistic._sort_key'
                60      MAKE_FUNCTION                   0
                62      STORE_NAME                      10: _sort_key
                64      LOAD_CONST                      15: None
                66      RETURN_VALUE                    
        'Statistic'
        [Code]
            File Name: tracemalloc.py
            Object Name: StatisticDiff
            Arg Count: 0
            Pos Only Arg Count: 0
            KW Only Arg Count: 0
            Locals: 0
            Stack Size: 2
            Flags: 0x00000040 (CO_NOFREE)
            [Names]
                '__name__'
                '__module__'
                '__qualname__'
                '__doc__'
                '__slots__'
                '__init__'
                '__hash__'
                '__eq__'
                '__str__'
                '__repr__'
                '_sort_key'
            [Var Names]
            [Free Vars]
            [Cell Vars]
            [Constants]
                'StatisticDiff'
                '\n    Statistic difference on memory allocations between an old and a new\n    Snapshot instance.\n    '
                (
                    'traceback'
                    'size'
                    'size_diff'
                    'count'
                    'count_diff'
                )
                [Code]
                    File Name: tracemalloc.py
                    Object Name: __init__
                    Arg Count: 6
                    Pos Only Arg Count: 0
                    KW Only Arg Count: 0
                    Locals: 6
                    Stack Size: 2
                    Flags: 0x00000043 (CO_OPTIMIZED | CO_NEWLOCALS | CO_NOFREE)
                    [Names]
                        'traceback'
                        'size'
                        'size_diff'
                        'count'
                        'count_diff'
                    [Var Names]
                        'self'
                        'traceback'
                        'size'
                        'size_diff'
                        'count'
                        'count_diff'
                    [Free Vars]
                    [Cell Vars]
                    [Constants]
                        None
                    [Disassembly]
                        0       LOAD_FAST                       1: traceback
                        2       LOAD_FAST                       0: self
                        4       STORE_ATTR                      0: traceback
                        6       LOAD_FAST                       2: size
                        8       LOAD_FAST                       0: self
                        10      STORE_ATTR                      1: size
                        12      LOAD_FAST                       3: size_diff
                        14      LOAD_FAST                       0: self
                        16      STORE_ATTR                      2: size_diff
                        18      LOAD_FAST                       4: count
                        20      LOAD_FAST                       0: self
                        22      STORE_ATTR                      3: count
                        24      LOAD_FAST                       5: count_diff
                        26      LOAD_FAST                       0: self
                        28      STORE_ATTR                      4: count_diff
                        30      LOAD_CONST                      0: None
                        32      RETURN_VALUE                    
                'StatisticDiff.__init__'
                [Code]
                    File Name: tracemalloc.py
                    Object Name: __hash__
                    Arg Count: 1
                    Pos Only Arg Count: 0
                    KW Only Arg Count: 0
                    Locals: 1
                    Stack Size: 6
                    Flags: 0x00000043 (CO_OPTIMIZED | CO_NEWLOCALS | CO_NOFREE)
                    [Names]
                        'hash'
                        'traceback'
                        'size'
                        'size_diff'
                        'count'
                        'count_diff'
                    [Var Names]
                        'self'
                    [Free Vars]
                    [Cell Vars]
                    [Constants]
                        None
                    [Disassembly]
                        0       LOAD_GLOBAL                     0: hash
                        2       LOAD_FAST                       0: self
                        4       LOAD_ATTR                       1: traceback
                        6       LOAD_FAST                       0: self
                        8       LOAD_ATTR                       2: size
                        10      LOAD_FAST                       0: self
                        12      LOAD_ATTR                       3: size_diff
                        14      LOAD_FAST                       0: self
                        16      LOAD_ATTR                       4: count
                        18      LOAD_FAST                       0: self
                        20      LOAD_ATTR                       5: count_diff
                        22      BUILD_TUPLE                     5
                        24      CALL_FUNCTION                   1
                        26      RETURN_VALUE                    
                'StatisticDiff.__hash__'
                [Code]
                    File Name: tracemalloc.py
                    Object Name: __eq__
                    Arg Count: 2
                    Pos Only Arg Count: 0
                    KW Only Arg Count: 0
                    Locals: 2
                    Stack Size: 3
                    Flags: 0x00000043 (CO_OPTIMIZED | CO_NEWLOCALS | CO_NOFREE)
                    [Names]
                        'isinstance'
                        'StatisticDiff'
                        'NotImplemented'
                        'traceback'
                        'size'
                        'size_diff'
                        'count'
                        'count_diff'
                    [Var Names]
                        'self'
                        'other'
                    [Free Vars]
                    [Cell Vars]
                    [Constants]
                        None
                    [Disassembly]
                        0       LOAD_GLOBAL                     0: isinstance
                        2       LOAD_FAST                       1: other
                        4       LOAD_GLOBAL                     1: StatisticDiff
                        6       CALL_FUNCTION                   2
                        8       POP_JUMP_IF_TRUE                7 (to 14)
                        10      LOAD_GLOBAL                     2: NotImplemented
                        12      RETURN_VALUE                    
                        14      LOAD_FAST                       0: self
                        16      LOAD_ATTR                       3: traceback
                        18      LOAD_FAST                       1: other
                        20      LOAD_ATTR                       3: traceback
                        22      COMPARE_OP                      2 (==)
                        24      JUMP_IF_FALSE_OR_POP            36 (to 72)
                        26      LOAD_FAST                       0: self
                        28      LOAD_ATTR                       4: size
                        30      LOAD_FAST                       1: other
                        32      LOAD_ATTR                       4: size
                        34      COMPARE_OP                      2 (==)
                        36      JUMP_IF_FALSE_OR_POP            36 (to 72)
                        38      LOAD_FAST                       0: self
                        40      LOAD_ATTR                       5: size_diff
                        42      LOAD_FAST                       1: other
                        44      LOAD_ATTR                       5: size_diff
                        46      COMPARE_OP                      2 (==)
                        48      JUMP_IF_FALSE_OR_POP            36 (to 72)
                        50      LOAD_FAST                       0: self
                        52      LOAD_ATTR                       6: count
                        54      LOAD_FAST                       1: other
                        56      LOAD_ATTR                       6: count
                        58      COMPARE_OP                      2 (==)
                        60      JUMP_IF_FALSE_OR_POP            36 (to 72)
                        62      LOAD_FAST                       0: self
                        64      LOAD_ATTR                       7: count_diff
                        66      LOAD_FAST                       1: other
                        68      LOAD_ATTR                       7: count_diff
                        70      COMPARE_OP                      2 (==)
                        72      RETURN_VALUE                    
                'StatisticDiff.__eq__'
                [Code]
                    File Name: tracemalloc.py
                    Object Name: __str__
                    Arg Count: 1
                    Pos Only Arg Count: 0
                    KW Only Arg Count: 0
                    Locals: 3
                    Stack Size: 6
                    Flags: 0x00000043 (CO_OPTIMIZED | CO_NEWLOCALS | CO_NOFREE)
                    [Names]
                        'traceback'
                        '_format_size'
                        'size'
                        'size_diff'
                        'count'
                        'count_diff'
                    [Var Names]
                        'self'
                        'text'
                        'average'
                    [Free Vars]
                    [Cell Vars]
                    [Constants]
                        None
                        '%s: size=%s (%s), count=%i (%+i)'
                        False
                        True
                        ', average=%s'
                    [Disassembly]
                        0       LOAD_CONST                      1: '%s: size=%s (%s), count=%i (%+i)'
                        2       LOAD_FAST                       0: self
                        4       LOAD_ATTR                       0: traceback
                        6       LOAD_GLOBAL                     1: _format_size
                        8       LOAD_FAST                       0: self
                        10      LOAD_ATTR                       2: size
                        12      LOAD_CONST                      2: False
                        14      CALL_FUNCTION                   2
                        16      LOAD_GLOBAL                     1: _format_size
                        18      LOAD_FAST                       0: self
                        20      LOAD_ATTR                       3: size_diff
                        22      LOAD_CONST                      3: True
                        24      CALL_FUNCTION                   2
                        26      LOAD_FAST                       0: self
                        28      LOAD_ATTR                       4: count
                        30      LOAD_FAST                       0: self
                        32      LOAD_ATTR                       5: count_diff
                        34      BUILD_TUPLE                     5
                        36      BINARY_MODULO                   
                        38      STORE_FAST                      1: text
                        40      LOAD_FAST                       0: self
                        42      LOAD_ATTR                       4: count
                        44      POP_JUMP_IF_FALSE               38 (to 76)
                        46      LOAD_FAST                       0: self
                        48      LOAD_ATTR                       2: size
                        50      LOAD_FAST                       0: self
                        52      LOAD_ATTR                       4: count
                        54      BINARY_TRUE_DIVIDE              
                        56      STORE_FAST                      2: average
                        58      LOAD_FAST                       1: text
                        60      LOAD_CONST                      4: ', average=%s'
                        62      LOAD_GLOBAL                     1: _format_size
                        64      LOAD_FAST                       2: average
                        66      LOAD_CONST                      2: False
                        68      CALL_FUNCTION                   2
                        70      BINARY_MODULO                   
                        72      INPLACE_ADD                     
                        74      STORE_FAST                      1: text
                        76      LOAD_FAST                       1: text
                        78      RETURN_VALUE                    
                'StatisticDiff.__str__'
                [Code]
                    File Name: tracemalloc.py
                    Object Name: __repr__
                    Arg Count: 1
                    Pos Only Arg Count: 0
                    KW Only Arg Count: 0
                    Locals: 1
                    Stack Size: 6
                    Flags: 0x00000043 (CO_OPTIMIZED | CO_NEWLOCALS | CO_NOFREE)
                    [Names]
                        'traceback'
                        'size'
                        'size_diff'
                        'count'
                        'count_diff'
                    [Var Names]
                        'self'
                    [Free Vars]
                    [Cell Vars]
                    [Constants]
                        None
                        '<StatisticDiff traceback=%r size=%i (%+i) count=%i (%+i)>'
                    [Disassembly]
                        0       LOAD_CONST                      1: '<StatisticDiff traceback=%r size=%i (%+i) count=%i (%+i)>'
                        2       LOAD_FAST                       0: self
                        4       LOAD_ATTR                       0: traceback
                        6       LOAD_FAST                       0: self
                        8       LOAD_ATTR                       1: size
                        10      LOAD_FAST                       0: self
                        12      LOAD_ATTR                       2: size_diff
                        14      LOAD_FAST                       0: self
                        16      LOAD_ATTR                       3: count
                        18      LOAD_FAST                       0: self
                        20      LOAD_ATTR                       4: count_diff
                        22      BUILD_TUPLE                     5
                        24      BINARY_MODULO                   
                        26      RETURN_VALUE                    
                'StatisticDiff.__repr__'
                [Code]
                    File Name: tracemalloc.py
                    Object Name: _sort_key
                    Arg Count: 1
                    Pos Only Arg Count: 0
                    KW Only Arg Count: 0
                    Locals: 1
                    Stack Size: 5
                    Flags: 0x00000043 (CO_OPTIMIZED | CO_NEWLOCALS | CO_NOFREE)
                    [Names]
                        'abs'
                        'size_diff'
                        'size'
                        'count_diff'
                        'count'
                        'traceback'
                    [Var Names]
                        'self'
                    [Free Vars]
                    [Cell Vars]
                    [Constants]
                        None
                    [Disassembly]
                        0       LOAD_GLOBAL                     0: abs
                        2       LOAD_FAST                       0: self
                        4       LOAD_ATTR                       1: size_diff
                        6       CALL_FUNCTION                   1
                        8       LOAD_FAST                       0: self
                        10      LOAD_ATTR                       2: size
                        12      LOAD_GLOBAL                     0: abs
                        14      LOAD_FAST                       0: self
                        16      LOAD_ATTR                       3: count_diff
                        18      CALL_FUNCTION                   1
                        20      LOAD_FAST                       0: self
                        22      LOAD_ATTR                       4: count
                        24      LOAD_FAST                       0: self
                        26      LOAD_ATTR                       5: traceback
                        28      BUILD_TUPLE                     5
                        30      RETURN_VALUE                    
                'StatisticDiff._sort_key'
                None
            [Disassembly]
                0       LOAD_NAME                       0: __name__
                2       STORE_NAME                      1: __module__
                4       LOAD_CONST                      0: 'StatisticDiff'
                6       STORE_NAME                      2: __qualname__
                8       LOAD_CONST                      1: '\n    Statistic difference on memory allocations between an old and a new\n    Snapshot instance.\n    '
                10      STORE_NAME                      3: __doc__
                12      LOAD_CONST                      2: ('traceback', 'size', 'size_diff', 'count', 'count_diff')
                14      STORE_NAME                      4: __slots__
                16      LOAD_CONST                      3: <CODE> __init__
                18      LOAD_CONST                      4: 'StatisticDiff.__init__'
                20      MAKE_FUNCTION                   0
                22      STORE_NAME                      5: __init__
                24      LOAD_CONST                      5: <CODE> __hash__
                26      LOAD_CONST                      6: 'StatisticDiff.__hash__'
                28      MAKE_FUNCTION                   0
                30      STORE_NAME                      6: __hash__
                32      LOAD_CONST                      7: <CODE> __eq__
                34      LOAD_CONST                      8: 'StatisticDiff.__eq__'
                36      MAKE_FUNCTION                   0
                38      STORE_NAME                      7: __eq__
                40      LOAD_CONST                      9: <CODE> __str__
                42      LOAD_CONST                      10: 'StatisticDiff.__str__'
                44      MAKE_FUNCTION                   0
                46      STORE_NAME                      8: __str__
                48      LOAD_CONST                      11: <CODE> __repr__
                50      LOAD_CONST                      12: 'StatisticDiff.__repr__'
                52      MAKE_FUNCTION                   0
                54      STORE_NAME                      9: __repr__
                56      LOAD_CONST                      13: <CODE> _sort_key
                58      LOAD_CONST                      14: 'StatisticDiff._sort_key'
                60      MAKE_FUNCTION                   0
                62      STORE_NAME                      10: _sort_key
                64      LOAD_CONST                      15: None
                66      RETURN_VALUE                    
        'StatisticDiff'
        [Code]
            File Name: tracemalloc.py
            Object Name: _compare_grouped_stats
            Arg Count: 2
            Pos Only Arg Count: 0
            KW Only Arg Count: 0
            Locals: 6
            Stack Size: 8
            Flags: 0x00000043 (CO_OPTIMIZED | CO_NEWLOCALS | CO_NOFREE)
            [Names]
                'items'
                'pop'
                'StatisticDiff'
                'size'
                'count'
                'append'
            [Var Names]
                'old_group'
                'new_group'
                'statistics'
                'traceback'
                'stat'
                'previous'
            [Free Vars]
            [Cell Vars]
            [Constants]
                None
                0
            [Disassembly]
                0       BUILD_LIST                      0
                2       STORE_FAST                      2: statistics
                4       LOAD_FAST                       1: new_group
                6       LOAD_METHOD                     0: items
                8       CALL_METHOD                     0
                10      GET_ITER                        
                12      FOR_ITER                        50 (to 114)
                14      UNPACK_SEQUENCE                 2
                16      STORE_FAST                      3: traceback
                18      STORE_FAST                      4: stat
                20      LOAD_FAST                       0: old_group
                22      LOAD_METHOD                     1: pop
                24      LOAD_FAST                       3: traceback
                26      LOAD_CONST                      0: None
                28      CALL_METHOD                     2
                30      STORE_FAST                      5: previous
                32      LOAD_FAST                       5: previous
                34      LOAD_CONST                      0: None
                36      IS_OP                           1 (is not)
                38      POP_JUMP_IF_FALSE               39 (to 78)
                40      LOAD_GLOBAL                     2: StatisticDiff
                42      LOAD_FAST                       3: traceback
                44      LOAD_FAST                       4: stat
                46      LOAD_ATTR                       3: size
                48      LOAD_FAST                       4: stat
                50      LOAD_ATTR                       3: size
                52      LOAD_FAST                       5: previous
                54      LOAD_ATTR                       3: size
                56      BINARY_SUBTRACT                 
                58      LOAD_FAST                       4: stat
                60      LOAD_ATTR                       4: count
                62      LOAD_FAST                       4: stat
                64      LOAD_ATTR                       4: count
                66      LOAD_FAST                       5: previous
                68      LOAD_ATTR                       4: count
                70      BINARY_SUBTRACT                 
                72      CALL_FUNCTION                   5
                74      STORE_FAST                      4: stat
                76      JUMP_FORWARD                    12 (to 102)
                78      LOAD_GLOBAL                     2: StatisticDiff
                80      LOAD_FAST                       3: traceback
                82      LOAD_FAST                       4: stat
                84      LOAD_ATTR                       3: size
                86      LOAD_FAST                       4: stat
                88      LOAD_ATTR                       3: size
                90      LOAD_FAST                       4: stat
                92      LOAD_ATTR                       4: count
                94      LOAD_FAST                       4: stat
                96      LOAD_ATTR                       4: count
                98      CALL_FUNCTION                   5
                100     STORE_FAST                      4: stat
                102     LOAD_FAST                       2: statistics
                104     LOAD_METHOD                     5: append
                106     LOAD_FAST                       4: stat
                108     CALL_METHOD                     1
                110     POP_TOP                         
                112     JUMP_ABSOLUTE                   6 (to 12)
                114     LOAD_FAST                       0: old_group
                116     LOAD_METHOD                     0: items
                118     CALL_METHOD                     0
                120     GET_ITER                        
                122     FOR_ITER                        21 (to 166)
                124     UNPACK_SEQUENCE                 2
                126     STORE_FAST                      3: traceback
                128     STORE_FAST                      4: stat
                130     LOAD_GLOBAL                     2: StatisticDiff
                132     LOAD_FAST                       3: traceback
                134     LOAD_CONST                      1: 0
                136     LOAD_FAST                       4: stat
                138     LOAD_ATTR                       3: size
                140     UNARY_NEGATIVE                  
                142     LOAD_CONST                      1: 0
                144     LOAD_FAST                       4: stat
                146     LOAD_ATTR                       4: count
                148     UNARY_NEGATIVE                  
                150     CALL_FUNCTION                   5
                152     STORE_FAST                      4: stat
                154     LOAD_FAST                       2: statistics
                156     LOAD_METHOD                     5: append
                158     LOAD_FAST                       4: stat
                160     CALL_METHOD                     1
                162     POP_TOP                         
                164     JUMP_ABSOLUTE                   61 (to 122)
                166     LOAD_FAST                       2: statistics
                168     RETURN_VALUE                    
        '_compare_grouped_stats'
        [Code]
            File Name: tracemalloc.py
            Object Name: Frame
            Arg Count: 0
            Pos Only Arg Count: 0
            KW Only Arg Count: 0
            Locals: 0
            Stack Size: 3
            Flags: 0x00000040 (CO_NOFREE)
            [Names]
                '__name__'
                '__module__'
                '__qualname__'
                '__doc__'
                '__slots__'
                '__init__'
                'property'
                'filename'
                'lineno'
                '__eq__'
                '__lt__'
                '__hash__'
                '__str__'
                '__repr__'
            [Var Names]
            [Free Vars]
            [Cell Vars]
            [Constants]
                'Frame'
                '\n    Frame of a traceback.\n    '
                (
                    '_frame'
                )
                [Code]
                    File Name: tracemalloc.py
                    Object Name: __init__
                    Arg Count: 2
                    Pos Only Arg Count: 0
                    KW Only Arg Count: 0
                    Locals: 2
                    Stack Size: 2
                    Flags: 0x00000043 (CO_OPTIMIZED | CO_NEWLOCALS | CO_NOFREE)
                    [Names]
                        '_frame'
                    [Var Names]
                        'self'
                        'frame'
                    [Free Vars]
                    [Cell Vars]
                    [Constants]
                        None
                    [Disassembly]
                        0       LOAD_FAST                       1: frame
                        2       LOAD_FAST                       0: self
                        4       STORE_ATTR                      0: _frame
                        6       LOAD_CONST                      0: None
                        8       RETURN_VALUE                    
                'Frame.__init__'
                [Code]
                    File Name: tracemalloc.py
                    Object Name: filename
                    Arg Count: 1
                    Pos Only Arg Count: 0
                    KW Only Arg Count: 0
                    Locals: 1
                    Stack Size: 2
                    Flags: 0x00000043 (CO_OPTIMIZED | CO_NEWLOCALS | CO_NOFREE)
                    [Names]
                        '_frame'
                    [Var Names]
                        'self'
                    [Free Vars]
                    [Cell Vars]
                    [Constants]
                        None
                        0
                    [Disassembly]
                        0       LOAD_FAST                       0: self
                        2       LOAD_ATTR                       0: _frame
                        4       LOAD_CONST                      1: 0
                        6       BINARY_SUBSCR                   
                        8       RETURN_VALUE                    
                'Frame.filename'
                [Code]
                    File Name: tracemalloc.py
                    Object Name: lineno
                    Arg Count: 1
                    Pos Only Arg Count: 0
                    KW Only Arg Count: 0
                    Locals: 1
                    Stack Size: 2
                    Flags: 0x00000043 (CO_OPTIMIZED | CO_NEWLOCALS | CO_NOFREE)
                    [Names]
                        '_frame'
                    [Var Names]
                        'self'
                    [Free Vars]
                    [Cell Vars]
                    [Constants]
                        None
                        1
                    [Disassembly]
                        0       LOAD_FAST                       0: self
                        2       LOAD_ATTR                       0: _frame
                        4       LOAD_CONST                      1: 1
                        6       BINARY_SUBSCR                   
                        8       RETURN_VALUE                    
                'Frame.lineno'
                [Code]
                    File Name: tracemalloc.py
                    Object Name: __eq__
                    Arg Count: 2
                    Pos Only Arg Count: 0
                    KW Only Arg Count: 0
                    Locals: 2
                    Stack Size: 3
                    Flags: 0x00000043 (CO_OPTIMIZED | CO_NEWLOCALS | CO_NOFREE)
                    [Names]
                        'isinstance'
                        'Frame'
                        'NotImplemented'
                        '_frame'
                    [Var Names]
                        'self'
                        'other'
                    [Free Vars]
                    [Cell Vars]
                    [Constants]
                        None
                    [Disassembly]
                        0       LOAD_GLOBAL                     0: isinstance
                        2       LOAD_FAST                       1: other
                        4       LOAD_GLOBAL                     1: Frame
                        6       CALL_FUNCTION                   2
                        8       POP_JUMP_IF_TRUE                7 (to 14)
                        10      LOAD_GLOBAL                     2: NotImplemented
                        12      RETURN_VALUE                    
                        14      LOAD_FAST                       0: self
                        16      LOAD_ATTR                       3: _frame
                        18      LOAD_FAST                       1: other
                        20      LOAD_ATTR                       3: _frame
                        22      COMPARE_OP                      2 (==)
                        24      RETURN_VALUE                    
                'Frame.__eq__'
                [Code]
                    File Name: tracemalloc.py
                    Object Name: __lt__
                    Arg Count: 2
                    Pos Only Arg Count: 0
                    KW Only Arg Count: 0
                    Locals: 2
                    Stack Size: 3
                    Flags: 0x00000043 (CO_OPTIMIZED | CO_NEWLOCALS | CO_NOFREE)
                    [Names]
                        'isinstance'
                        'Frame'
                        'NotImplemented'
                        '_frame'
                    [Var Names]
                        'self'
                        'other'
                    [Free Vars]
                    [Cell Vars]
                    [Constants]
                        None
                    [Disassembly]
                        0       LOAD_GLOBAL                     0: isinstance
                        2       LOAD_FAST                       1: other
                        4       LOAD_GLOBAL                     1: Frame
                        6       CALL_FUNCTION                   2
                        8       POP_JUMP_IF_TRUE                7 (to 14)
                        10      LOAD_GLOBAL                     2: NotImplemented
                        12      RETURN_VALUE                    
                        14      LOAD_FAST                       0: self
                        16      LOAD_ATTR                       3: _frame
                        18      LOAD_FAST                       1: other
                        20      LOAD_ATTR                       3: _frame
                        22      COMPARE_OP                      0 (<)
                        24      RETURN_VALUE                    
                'Frame.__lt__'
                [Code]
                    File Name: tracemalloc.py
                    Object Name: __hash__
                    Arg Count: 1
                    Pos Only Arg Count: 0
                    KW Only Arg Count: 0
                    Locals: 1
                    Stack Size: 2
                    Flags: 0x00000043 (CO_OPTIMIZED | CO_NEWLOCALS | CO_NOFREE)
                    [Names]
                        'hash'
                        '_frame'
                    [Var Names]
                        'self'
                    [Free Vars]
                    [Cell Vars]
                    [Constants]
                        None
                    [Disassembly]
                        0       LOAD_GLOBAL                     0: hash
                        2       LOAD_FAST                       0: self
                        4       LOAD_ATTR                       1: _frame
                        6       CALL_FUNCTION                   1
                        8       RETURN_VALUE                    
                'Frame.__hash__'
                [Code]
                    File Name: tracemalloc.py
                    Object Name: __str__
                    Arg Count: 1
                    Pos Only Arg Count: 0
                    KW Only Arg Count: 0
                    Locals: 1
                    Stack Size: 3
                    Flags: 0x00000043 (CO_OPTIMIZED | CO_NEWLOCALS | CO_NOFREE)
                    [Names]
                        'filename'
                        'lineno'
                    [Var Names]
                        'self'
                    [Free Vars]
                    [Cell Vars]
                    [Constants]
                        None
                        '%s:%s'
                    [Disassembly]
                        0       LOAD_CONST                      1: '%s:%s'
                        2       LOAD_FAST                       0: self
                        4       LOAD_ATTR                       0: filename
                        6       LOAD_FAST                       0: self
                        8       LOAD_ATTR                       1: lineno
                        10      BUILD_TUPLE                     2
                        12      BINARY_MODULO                   
                        14      RETURN_VALUE                    
                'Frame.__str__'
                [Code]
                    File Name: tracemalloc.py
                    Object Name: __repr__
                    Arg Count: 1
                    Pos Only Arg Count: 0
                    KW Only Arg Count: 0
                    Locals: 1
                    Stack Size: 3
                    Flags: 0x00000043 (CO_OPTIMIZED | CO_NEWLOCALS | CO_NOFREE)
                    [Names]
                        'filename'
                        'lineno'
                    [Var Names]
                        'self'
                    [Free Vars]
                    [Cell Vars]
                    [Constants]
                        None
                        '<Frame filename=%r lineno=%r>'
                    [Disassembly]
                        0       LOAD_CONST                      1: '<Frame filename=%r lineno=%r>'
                        2       LOAD_FAST                       0: self
                        4       LOAD_ATTR                       0: filename
                        6       LOAD_FAST                       0: self
                        8       LOAD_ATTR                       1: lineno
                        10      BUILD_TUPLE                     2
                        12      BINARY_MODULO                   
                        14      RETURN_VALUE                    
                'Frame.__repr__'
                None
            [Disassembly]
                0       LOAD_NAME                       0: __name__
                2       STORE_NAME                      1: __module__
                4       LOAD_CONST                      0: 'Frame'
                6       STORE_NAME                      2: __qualname__
                8       LOAD_CONST                      1: '\n    Frame of a traceback.\n    '
                10      STORE_NAME                      3: __doc__
                12      LOAD_CONST                      2: ('_frame',)
                14      STORE_NAME                      4: __slots__
                16      LOAD_CONST                      3: <CODE> __init__
                18      LOAD_CONST                      4: 'Frame.__init__'
                20      MAKE_FUNCTION                   0
                22      STORE_NAME                      5: __init__
                24      LOAD_NAME                       6: property
                26      LOAD_CONST                      5: <CODE> filename
                28      LOAD_CONST                      6: 'Frame.filename'
                30      MAKE_FUNCTION                   0
                32      CALL_FUNCTION                   1
                34      STORE_NAME                      7: filename
                36      LOAD_NAME                       6: property
                38      LOAD_CONST                      7: <CODE> lineno
                40      LOAD_CONST                      8: 'Frame.lineno'
                42      MAKE_FUNCTION                   0
                44      CALL_FUNCTION                   1
                46      STORE_NAME                      8: lineno
                48      LOAD_CONST                      9: <CODE> __eq__
                50      LOAD_CONST                      10: 'Frame.__eq__'
                52      MAKE_FUNCTION                   0
                54      STORE_NAME                      9: __eq__
                56      LOAD_CONST                      11: <CODE> __lt__
                58      LOAD_CONST                      12: 'Frame.__lt__'
                60      MAKE_FUNCTION                   0
                62      STORE_NAME                      10: __lt__
                64      LOAD_CONST                      13: <CODE> __hash__
                66      LOAD_CONST                      14: 'Frame.__hash__'
                68      MAKE_FUNCTION                   0
                70      STORE_NAME                      11: __hash__
                72      LOAD_CONST                      15: <CODE> __str__
                74      LOAD_CONST                      16: 'Frame.__str__'
                76      MAKE_FUNCTION                   0
                78      STORE_NAME                      12: __str__
                80      LOAD_CONST                      17: <CODE> __repr__
                82      LOAD_CONST                      18: 'Frame.__repr__'
                84      MAKE_FUNCTION                   0
                86      STORE_NAME                      13: __repr__
                88      LOAD_CONST                      19: None
                90      RETURN_VALUE                    
        'Frame'
        [Code]
            File Name: tracemalloc.py
            Object Name: Traceback
            Arg Count: 0
            Pos Only Arg Count: 0
            KW Only Arg Count: 0
            Locals: 0
            Stack Size: 3
            Flags: 0x00000040 (CO_NOFREE)
            [Names]
                '__name__'
                '__module__'
                '__qualname__'
                '__doc__'
                '__slots__'
                '__init__'
                'property'
                'total_nframe'
                '__len__'
                '__getitem__'
                '__contains__'
                '__hash__'
                '__eq__'
                '__lt__'
                '__str__'
                '__repr__'
                'format'
            [Var Names]
            [Free Vars]
            [Cell Vars]
            [Constants]
                'Traceback'
                '\n    Sequence of Frame instances sorted from the oldest frame\n    to the most recent frame.\n    '
                (
                    '_frames'
                    '_total_nframe'
                )
                None
                [Code]
                    File Name: tracemalloc.py
                    Object Name: __init__
                    Arg Count: 3
                    Pos Only Arg Count: 0
                    KW Only Arg Count: 0
                    Locals: 3
                    Stack Size: 3
                    Flags: 0x00000043 (CO_OPTIMIZED | CO_NEWLOCALS | CO_NOFREE)
                    [Names]
                        'Sequence'
                        '__init__'
                        'tuple'
                        'reversed'
                        '_frames'
                        '_total_nframe'
                    [Var Names]
                        'self'
                        'frames'
                        'total_nframe'
                    [Free Vars]
                    [Cell Vars]
                    [Constants]
                        None
                    [Disassembly]
                        0       LOAD_GLOBAL                     0: Sequence
                        2       LOAD_METHOD                     1: __init__
                        4       LOAD_FAST                       0: self
                        6       CALL_METHOD                     1
                        8       POP_TOP                         
                        10      LOAD_GLOBAL                     2: tuple
                        12      LOAD_GLOBAL                     3: reversed
                        14      LOAD_FAST                       1: frames
                        16      CALL_FUNCTION                   1
                        18      CALL_FUNCTION                   1
                        20      LOAD_FAST                       0: self
                        22      STORE_ATTR                      4: _frames
                        24      LOAD_FAST                       2: total_nframe
                        26      LOAD_FAST                       0: self
                        28      STORE_ATTR                      5: _total_nframe
                        30      LOAD_CONST                      0: None
                        32      RETURN_VALUE                    
                'Traceback.__init__'
                [Code]
                    File Name: tracemalloc.py
                    Object Name: total_nframe
                    Arg Count: 1
                    Pos Only Arg Count: 0
                    KW Only Arg Count: 0
                    Locals: 1
                    Stack Size: 1
                    Flags: 0x00000043 (CO_OPTIMIZED | CO_NEWLOCALS | CO_NOFREE)
                    [Names]
                        '_total_nframe'
                    [Var Names]
                        'self'
                    [Free Vars]
                    [Cell Vars]
                    [Constants]
                        None
                    [Disassembly]
                        0       LOAD_FAST                       0: self
                        2       LOAD_ATTR                       0: _total_nframe
                        4       RETURN_VALUE                    
                'Traceback.total_nframe'
                [Code]
                    File Name: tracemalloc.py
                    Object Name: __len__
                    Arg Count: 1
                    Pos Only Arg Count: 0
                    KW Only Arg Count: 0
                    Locals: 1
                    Stack Size: 2
                    Flags: 0x00000043 (CO_OPTIMIZED | CO_NEWLOCALS | CO_NOFREE)
                    [Names]
                        'len'
                        '_frames'
                    [Var Names]
                        'self'
                    [Free Vars]
                    [Cell Vars]
                    [Constants]
                        None
                    [Disassembly]
                        0       LOAD_GLOBAL                     0: len
                        2       LOAD_FAST                       0: self
                        4       LOAD_ATTR                       1: _frames
                        6       CALL_FUNCTION                   1
                        8       RETURN_VALUE                    
                'Traceback.__len__'
                [Code]
                    File Name: tracemalloc.py
                    Object Name: __getitem__
                    Arg Count: 2
                    Pos Only Arg Count: 0
                    KW Only Arg Count: 0
                    Locals: 2
                    Stack Size: 4
                    Flags: 0x00000043 (CO_OPTIMIZED | CO_NEWLOCALS | CO_NOFREE)
                    [Names]
                        'isinstance'
                        'slice'
                        'tuple'
                        '_frames'
                        'Frame'
                    [Var Names]
                        'self'
                        'index'
                    [Free Vars]
                    [Cell Vars]
                    [Constants]
                        None
                        [Code]
                            File Name: tracemalloc.py
                            Object Name: <genexpr>
                            Arg Count: 1
                            Pos Only Arg Count: 0
                            KW Only Arg Count: 0
                            Locals: 2
                            Stack Size: 3
                            Flags: 0x00000073 (CO_OPTIMIZED | CO_NEWLOCALS | CO_NESTED | CO_GENERATOR | CO_NOFREE)
                            [Names]
                                'Frame'
                            [Var Names]
                                '.0'
                                'trace'
                            [Free Vars]
                            [Cell Vars]
                            [Constants]
                                None
                            [Disassembly]
                                0       GEN_START                       0
                                2       LOAD_FAST                       0: .0
                                4       FOR_ITER                        7 (to 20)
                                6       STORE_FAST                      1: trace
                                8       LOAD_GLOBAL                     0: Frame
                                10      LOAD_FAST                       1: trace
                                12      CALL_FUNCTION                   1
                                14      YIELD_VALUE                     
                                16      POP_TOP                         
                                18      JUMP_ABSOLUTE                   2 (to 4)
                                20      LOAD_CONST                      0: None
                                22      RETURN_VALUE                    
                        'Traceback.__getitem__.<locals>.<genexpr>'
                    [Disassembly]
                        0       LOAD_GLOBAL                     0: isinstance
                        2       LOAD_FAST                       1: index
                        4       LOAD_GLOBAL                     1: slice
                        6       CALL_FUNCTION                   2
                        8       POP_JUMP_IF_FALSE               17 (to 34)
                        10      LOAD_GLOBAL                     2: tuple
                        12      LOAD_CONST                      1: <CODE> <genexpr>
                        14      LOAD_CONST                      2: 'Traceback.__getitem__.<locals>.<genexpr>'
                        16      MAKE_FUNCTION                   0
                        18      LOAD_FAST                       0: self
                        20      LOAD_ATTR                       3: _frames
                        22      LOAD_FAST                       1: index
                        24      BINARY_SUBSCR                   
                        26      GET_ITER                        
                        28      CALL_FUNCTION                   1
                        30      CALL_FUNCTION                   1
                        32      RETURN_VALUE                    
                        34      LOAD_GLOBAL                     4: Frame
                        36      LOAD_FAST                       0: self
                        38      LOAD_ATTR                       3: _frames
                        40      LOAD_FAST                       1: index
                        42      BINARY_SUBSCR                   
                        44      CALL_FUNCTION                   1
                        46      RETURN_VALUE                    
                'Traceback.__getitem__'
                [Code]
                    File Name: tracemalloc.py
                    Object Name: __contains__
                    Arg Count: 2
                    Pos Only Arg Count: 0
                    KW Only Arg Count: 0
                    Locals: 2
                    Stack Size: 2
                    Flags: 0x00000043 (CO_OPTIMIZED | CO_NEWLOCALS | CO_NOFREE)
                    [Names]
                        '_frame'
                        '_frames'
                    [Var Names]
                        'self'
                        'frame'
                    [Free Vars]
                    [Cell Vars]
                    [Constants]
                        None
                    [Disassembly]
                        0       LOAD_FAST                       1: frame
                        2       LOAD_ATTR                       0: _frame
                        4       LOAD_FAST                       0: self
                        6       LOAD_ATTR                       1: _frames
                        8       CONTAINS_OP                     0 (in)
                        10      RETURN_VALUE                    
                'Traceback.__contains__'
                [Code]
                    File Name: tracemalloc.py
                    Object Name: __hash__
                    Arg Count: 1
                    Pos Only Arg Count: 0
                    KW Only Arg Count: 0
                    Locals: 1
                    Stack Size: 2
                    Flags: 0x00000043 (CO_OPTIMIZED | CO_NEWLOCALS | CO_NOFREE)
                    [Names]
                        'hash'
                        '_frames'
                    [Var Names]
                        'self'
                    [Free Vars]
                    [Cell Vars]
                    [Constants]
                        None
                    [Disassembly]
                        0       LOAD_GLOBAL                     0: hash
                        2       LOAD_FAST                       0: self
                        4       LOAD_ATTR                       1: _frames
                        6       CALL_FUNCTION                   1
                        8       RETURN_VALUE                    
                'Traceback.__hash__'
                [Code]
                    File Name: tracemalloc.py
                    Object Name: __eq__
                    Arg Count: 2
                    Pos Only Arg Count: 0
                    KW Only Arg Count: 0
                    Locals: 2
                    Stack Size: 3
                    Flags: 0x00000043 (CO_OPTIMIZED | CO_NEWLOCALS | CO_NOFREE)
                    [Names]
                        'isinstance'
                        'Traceback'
                        'NotImplemented'
                        '_frames'
                    [Var Names]
                        'self'
                        'other'
                    [Free Vars]
                    [Cell Vars]
                    [Constants]
                        None
                    [Disassembly]
                        0       LOAD_GLOBAL                     0: isinstance
                        2       LOAD_FAST                       1: other
                        4       LOAD_GLOBAL                     1: Traceback
                        6       CALL_FUNCTION                   2
                        8       POP_JUMP_IF_TRUE                7 (to 14)
                        10      LOAD_GLOBAL                     2: NotImplemented
                        12      RETURN_VALUE                    
                        14      LOAD_FAST                       0: self
                        16      LOAD_ATTR                       3: _frames
                        18      LOAD_FAST                       1: other
                        20      LOAD_ATTR                       3: _frames
                        22      COMPARE_OP                      2 (==)
                        24      RETURN_VALUE                    
                'Traceback.__eq__'
                [Code]
                    File Name: tracemalloc.py
                    Object Name: __lt__
                    Arg Count: 2
                    Pos Only Arg Count: 0
                    KW Only Arg Count: 0
                    Locals: 2
                    Stack Size: 3
                    Flags: 0x00000043 (CO_OPTIMIZED | CO_NEWLOCALS | CO_NOFREE)
                    [Names]
                        'isinstance'
                        'Traceback'
                        'NotImplemented'
                        '_frames'
                    [Var Names]
                        'self'
                        'other'
                    [Free Vars]
                    [Cell Vars]
                    [Constants]
                        None
                    [Disassembly]
                        0       LOAD_GLOBAL                     0: isinstance
                        2       LOAD_FAST                       1: other
                        4       LOAD_GLOBAL                     1: Traceback
                        6       CALL_FUNCTION                   2
                        8       POP_JUMP_IF_TRUE                7 (to 14)
                        10      LOAD_GLOBAL                     2: NotImplemented
                        12      RETURN_VALUE                    
                        14      LOAD_FAST                       0: self
                        16      LOAD_ATTR                       3: _frames
                        18      LOAD_FAST                       1: other
                        20      LOAD_ATTR                       3: _frames
                        22      COMPARE_OP                      0 (<)
                        24      RETURN_VALUE                    
                'Traceback.__lt__'
                [Code]
                    File Name: tracemalloc.py
                    Object Name: __str__
                    Arg Count: 1
                    Pos Only Arg Count: 0
                    KW Only Arg Count: 0
                    Locals: 1
                    Stack Size: 3
                    Flags: 0x00000043 (CO_OPTIMIZED | CO_NEWLOCALS | CO_NOFREE)
                    [Names]
                        'str'
                    [Var Names]
                        'self'
                    [Free Vars]
                    [Cell Vars]
                    [Constants]
                        None
                        0
                    [Disassembly]
                        0       LOAD_GLOBAL                     0: str
                        2       LOAD_FAST                       0: self
                        4       LOAD_CONST                      1: 0
                        6       BINARY_SUBSCR                   
                        8       CALL_FUNCTION                   1
                        10      RETURN_VALUE                    
                'Traceback.__str__'
                [Code]
                    File Name: tracemalloc.py
                    Object Name: __repr__
                    Arg Count: 1
                    Pos Only Arg Count: 0
                    KW Only Arg Count: 0
                    Locals: 2
                    Stack Size: 4
                    Flags: 0x00000043 (CO_OPTIMIZED | CO_NEWLOCALS | CO_NOFREE)
                    [Names]
                        'tuple'
                        '_total_nframe'
                        'total_nframe'
                    [Var Names]
                        'self'
                        's'
                    [Free Vars]
                    [Cell Vars]
                    [Constants]
                        None
                        '<Traceback '
                        '>'
                        ' total_nframe='
                    [Disassembly]
                        0       LOAD_CONST                      1: '<Traceback '
                        2       LOAD_GLOBAL                     0: tuple
                        4       LOAD_FAST                       0: self
                        6       CALL_FUNCTION                   1
                        8       FORMAT_VALUE                    0 (FVC_NONE)
                        10      BUILD_STRING                    2
                        12      STORE_FAST                      1: s
                        14      LOAD_FAST                       0: self
                        16      LOAD_ATTR                       1: _total_nframe
                        18      LOAD_CONST                      0: None
                        20      IS_OP                           0 (is)
                        22      POP_JUMP_IF_FALSE               18 (to 36)
                        24      LOAD_FAST                       1: s
                        26      LOAD_CONST                      2: '>'
                        28      INPLACE_ADD                     
                        30      STORE_FAST                      1: s
                        32      LOAD_FAST                       1: s
                        34      RETURN_VALUE                    
                        36      LOAD_FAST                       1: s
                        38      LOAD_CONST                      3: ' total_nframe='
                        40      LOAD_FAST                       0: self
                        42      LOAD_ATTR                       2: total_nframe
                        44      FORMAT_VALUE                    0 (FVC_NONE)
                        46      LOAD_CONST                      2: '>'
                        48      BUILD_STRING                    3
                        50      INPLACE_ADD                     
                        52      STORE_FAST                      1: s
                        54      LOAD_FAST                       1: s
                        56      RETURN_VALUE                    
                'Traceback.__repr__'
                False
                [Code]
                    File Name: tracemalloc.py
                    Object Name: format
                    Arg Count: 3
                    Pos Only Arg Count: 0
                    KW Only Arg Count: 0
                    Locals: 7
                    Stack Size: 6
                    Flags: 0x00000043 (CO_OPTIMIZED | CO_NEWLOCALS | CO_NOFREE)
                    [Names]
                        'reversed'
                        'append'
                        'filename'
                        'lineno'
                        'linecache'
                        'getline'
                        'strip'
                    [Var Names]
                        'self'
                        'limit'
                        'most_recent_first'
                        'lines'
                        'frame_slice'
                        'frame'
                        'line'
                    [Free Vars]
                    [Cell Vars]
                    [Constants]
                        None
                        0
                        '  File "%s", line %s'
                        '    %s'
                    [Disassembly]
                        0       BUILD_LIST                      0
                        2       STORE_FAST                      3: lines
                        4       LOAD_FAST                       1: limit
                        6       LOAD_CONST                      0: None
                        8       IS_OP                           1 (is not)
                        10      POP_JUMP_IF_FALSE               25 (to 50)
                        12      LOAD_FAST                       1: limit
                        14      LOAD_CONST                      1: 0
                        16      COMPARE_OP                      4 (>)
                        18      POP_JUMP_IF_FALSE               18 (to 36)
                        20      LOAD_FAST                       0: self
                        22      LOAD_FAST                       1: limit
                        24      UNARY_NEGATIVE                  
                        26      LOAD_CONST                      0: None
                        28      BUILD_SLICE                     2
                        30      BINARY_SUBSCR                   
                        32      STORE_FAST                      4: frame_slice
                        34      JUMP_FORWARD                    9 (to 54)
                        36      LOAD_FAST                       0: self
                        38      LOAD_CONST                      0: None
                        40      LOAD_FAST                       1: limit
                        42      BUILD_SLICE                     2
                        44      BINARY_SUBSCR                   
                        46      STORE_FAST                      4: frame_slice
                        48      JUMP_FORWARD                    2 (to 54)
                        50      LOAD_FAST                       0: self
                        52      STORE_FAST                      4: frame_slice
                        54      LOAD_FAST                       2: most_recent_first
                        56      POP_JUMP_IF_FALSE               33 (to 66)
                        58      LOAD_GLOBAL                     0: reversed
                        60      LOAD_FAST                       4: frame_slice
                        62      CALL_FUNCTION                   1
                        64      STORE_FAST                      4: frame_slice
                        66      LOAD_FAST                       4: frame_slice
                        68      GET_ITER                        
                        70      FOR_ITER                        32 (to 136)
                        72      STORE_FAST                      5: frame
                        74      LOAD_FAST                       3: lines
                        76      LOAD_METHOD                     1: append
                        78      LOAD_CONST                      2: '  File "%s", line %s'
                        80      LOAD_FAST                       5: frame
                        82      LOAD_ATTR                       2: filename
                        84      LOAD_FAST                       5: frame
                        86      LOAD_ATTR                       3: lineno
                        88      BUILD_TUPLE                     2
                        90      BINARY_MODULO                   
                        92      CALL_METHOD                     1
                        94      POP_TOP                         
                        96      LOAD_GLOBAL                     4: linecache
                        98      LOAD_METHOD                     5: getline
                        100     LOAD_FAST                       5: frame
                        102     LOAD_ATTR                       2: filename
                        104     LOAD_FAST                       5: frame
                        106     LOAD_ATTR                       3: lineno
                        108     CALL_METHOD                     2
                        110     LOAD_METHOD                     6: strip
                        112     CALL_METHOD                     0
                        114     STORE_FAST                      6: line
                        116     LOAD_FAST                       6: line
                        118     POP_JUMP_IF_FALSE               67 (to 134)
                        120     LOAD_FAST                       3: lines
                        122     LOAD_METHOD                     1: append
                        124     LOAD_CONST                      3: '    %s'
                        126     LOAD_FAST                       6: line
                        128     BINARY_MODULO                   
                        130     CALL_METHOD                     1
                        132     POP_TOP                         
                        134     JUMP_ABSOLUTE                   35 (to 70)
                        136     LOAD_FAST                       3: lines
                        138     RETURN_VALUE                    
                'Traceback.format'
                (
                    None
                )
                (
                    None
                    False
                )
            [Disassembly]
                0       LOAD_NAME                       0: __name__
                2       STORE_NAME                      1: __module__
                4       LOAD_CONST                      0: 'Traceback'
                6       STORE_NAME                      2: __qualname__
                8       LOAD_CONST                      1: '\n    Sequence of Frame instances sorted from the oldest frame\n    to the most recent frame.\n    '
                10      STORE_NAME                      3: __doc__
                12      LOAD_CONST                      2: ('_frames', '_total_nframe')
                14      STORE_NAME                      4: __slots__
                16      LOAD_CONST                      27: (None,)
                18      LOAD_CONST                      4: <CODE> __init__
                20      LOAD_CONST                      5: 'Traceback.__init__'
                22      MAKE_FUNCTION                   1
                24      STORE_NAME                      5: __init__
                26      LOAD_NAME                       6: property
                28      LOAD_CONST                      6: <CODE> total_nframe
                30      LOAD_CONST                      7: 'Traceback.total_nframe'
                32      MAKE_FUNCTION                   0
                34      CALL_FUNCTION                   1
                36      STORE_NAME                      7: total_nframe
                38      LOAD_CONST                      8: <CODE> __len__
                40      LOAD_CONST                      9: 'Traceback.__len__'
                42      MAKE_FUNCTION                   0
                44      STORE_NAME                      8: __len__
                46      LOAD_CONST                      10: <CODE> __getitem__
                48      LOAD_CONST                      11: 'Traceback.__getitem__'
                50      MAKE_FUNCTION                   0
                52      STORE_NAME                      9: __getitem__
                54      LOAD_CONST                      12: <CODE> __contains__
                56      LOAD_CONST                      13: 'Traceback.__contains__'
                58      MAKE_FUNCTION                   0
                60      STORE_NAME                      10: __contains__
                62      LOAD_CONST                      14: <CODE> __hash__
                64      LOAD_CONST                      15: 'Traceback.__hash__'
                66      MAKE_FUNCTION                   0
                68      STORE_NAME                      11: __hash__
                70      LOAD_CONST                      16: <CODE> __eq__
                72      LOAD_CONST                      17: 'Traceback.__eq__'
                74      MAKE_FUNCTION                   0
                76      STORE_NAME                      12: __eq__
                78      LOAD_CONST                      18: <CODE> __lt__
                80      LOAD_CONST                      19: 'Traceback.__lt__'
                82      MAKE_FUNCTION                   0
                84      STORE_NAME                      13: __lt__
                86      LOAD_CONST                      20: <CODE> __str__
                88      LOAD_CONST                      21: 'Traceback.__str__'
                90      MAKE_FUNCTION                   0
                92      STORE_NAME                      14: __str__
                94      LOAD_CONST                      22: <CODE> __repr__
                96      LOAD_CONST                      23: 'Traceback.__repr__'
                98      MAKE_FUNCTION                   0
                100     STORE_NAME                      15: __repr__
                102     LOAD_CONST                      28: (None, False)
                104     LOAD_CONST                      25: <CODE> format
                106     LOAD_CONST                      26: 'Traceback.format'
                108     MAKE_FUNCTION                   1
                110     STORE_NAME                      16: format
                112     LOAD_CONST                      3: None
                114     RETURN_VALUE                    
        'Traceback'
        [Code]
            File Name: tracemalloc.py
            Object Name: get_object_traceback
            Arg Count: 1
            Pos Only Arg Count: 0
            KW Only Arg Count: 0
            Locals: 2
            Stack Size: 2
            Flags: 0x00000043 (CO_OPTIMIZED | CO_NEWLOCALS | CO_NOFREE)
            [Names]
                '_get_object_traceback'
                'Traceback'
            [Var Names]
                'obj'
                'frames'
            [Free Vars]
            [Cell Vars]
            [Constants]
                '\n    Get the traceback where the Python object *obj* was allocated.\n    Return a Traceback instance.\n\n    Return None if the tracemalloc module is not tracing memory allocations or\n    did not trace the allocation of the object.\n    '
                None
            [Disassembly]
                0       LOAD_GLOBAL                     0: _get_object_traceback
                2       LOAD_FAST                       0: obj
                4       CALL_FUNCTION                   1
                6       STORE_FAST                      1: frames
                8       LOAD_FAST                       1: frames
                10      LOAD_CONST                      1: None
                12      IS_OP                           1 (is not)
                14      POP_JUMP_IF_FALSE               12 (to 24)
                16      LOAD_GLOBAL                     1: Traceback
                18      LOAD_FAST                       1: frames
                20      CALL_FUNCTION                   1
                22      RETURN_VALUE                    
                24      LOAD_CONST                      1: None
                26      RETURN_VALUE                    
        'get_object_traceback'
        [Code]
            File Name: tracemalloc.py
            Object Name: Trace
            Arg Count: 0
            Pos Only Arg Count: 0
            KW Only Arg Count: 0
            Locals: 0
            Stack Size: 3
            Flags: 0x00000040 (CO_NOFREE)
            [Names]
                '__name__'
                '__module__'
                '__qualname__'
                '__doc__'
                '__slots__'
                '__init__'
                'property'
                'domain'
                'size'
                'traceback'
                '__eq__'
                '__hash__'
                '__str__'
                '__repr__'
            [Var Names]
            [Free Vars]
            [Cell Vars]
            [Constants]
                'Trace'
                '\n    Trace of a memory block.\n    '
                (
                    '_trace'
                )
                [Code]
                    File Name: tracemalloc.py
                    Object Name: __init__
                    Arg Count: 2
                    Pos Only Arg Count: 0
                    KW Only Arg Count: 0
                    Locals: 2
                    Stack Size: 2
                    Flags: 0x00000043 (CO_OPTIMIZED | CO_NEWLOCALS | CO_NOFREE)
                    [Names]
                        '_trace'
                    [Var Names]
                        'self'
                        'trace'
                    [Free Vars]
                    [Cell Vars]
                    [Constants]
                        None
                    [Disassembly]
                        0       LOAD_FAST                       1: trace
                        2       LOAD_FAST                       0: self
                        4       STORE_ATTR                      0: _trace
                        6       LOAD_CONST                      0: None
                        8       RETURN_VALUE                    
                'Trace.__init__'
                [Code]
                    File Name: tracemalloc.py
                    Object Name: domain
                    Arg Count: 1
                    Pos Only Arg Count: 0
                    KW Only Arg Count: 0
                    Locals: 1
                    Stack Size: 2
                    Flags: 0x00000043 (CO_OPTIMIZED | CO_NEWLOCALS | CO_NOFREE)
                    [Names]
                        '_trace'
                    [Var Names]
                        'self'
                    [Free Vars]
                    [Cell Vars]
                    [Constants]
                        None
                        0
                    [Disassembly]
                        0       LOAD_FAST                       0: self
                        2       LOAD_ATTR                       0: _trace
                        4       LOAD_CONST                      1: 0
                        6       BINARY_SUBSCR                   
                        8       RETURN_VALUE                    
                'Trace.domain'
                [Code]
                    File Name: tracemalloc.py
                    Object Name: size
                    Arg Count: 1
                    Pos Only Arg Count: 0
                    KW Only Arg Count: 0
                    Locals: 1
                    Stack Size: 2
                    Flags: 0x00000043 (CO_OPTIMIZED | CO_NEWLOCALS | CO_NOFREE)
                    [Names]
                        '_trace'
                    [Var Names]
                        'self'
                    [Free Vars]
                    [Cell Vars]
                    [Constants]
                        None
                        1
                    [Disassembly]
                        0       LOAD_FAST                       0: self
                        2       LOAD_ATTR                       0: _trace
                        4       LOAD_CONST                      1: 1
                        6       BINARY_SUBSCR                   
                        8       RETURN_VALUE                    
                'Trace.size'
                [Code]
                    File Name: tracemalloc.py
                    Object Name: traceback
                    Arg Count: 1
                    Pos Only Arg Count: 0
                    KW Only Arg Count: 0
                    Locals: 1
                    Stack Size: 4
                    Flags: 0x00000043 (CO_OPTIMIZED | CO_NEWLOCALS | CO_NOFREE)
                    [Names]
                        'Traceback'
                        '_trace'
                    [Var Names]
                        'self'
                    [Free Vars]
                    [Cell Vars]
                    [Constants]
                        None
                        2
                    [Disassembly]
                        0       LOAD_GLOBAL                     0: Traceback
                        2       LOAD_FAST                       0: self
                        4       LOAD_ATTR                       1: _trace
                        6       LOAD_CONST                      1: 2
                        8       LOAD_CONST                      0: None
                        10      BUILD_SLICE                     2
                        12      BINARY_SUBSCR                   
                        14      CALL_FUNCTION_EX                0
                        16      RETURN_VALUE                    
                'Trace.traceback'
                [Code]
                    File Name: tracemalloc.py
                    Object Name: __eq__
                    Arg Count: 2
                    Pos Only Arg Count: 0
                    KW Only Arg Count: 0
                    Locals: 2
                    Stack Size: 3
                    Flags: 0x00000043 (CO_OPTIMIZED | CO_NEWLOCALS | CO_NOFREE)
                    [Names]
                        'isinstance'
                        'Trace'
                        'NotImplemented'
                        '_trace'
                    [Var Names]
                        'self'
                        'other'
                    [Free Vars]
                    [Cell Vars]
                    [Constants]
                        None
                    [Disassembly]
                        0       LOAD_GLOBAL                     0: isinstance
                        2       LOAD_FAST                       1: other
                        4       LOAD_GLOBAL                     1: Trace
                        6       CALL_FUNCTION                   2
                        8       POP_JUMP_IF_TRUE                7 (to 14)
                        10      LOAD_GLOBAL                     2: NotImplemented
                        12      RETURN_VALUE                    
                        14      LOAD_FAST                       0: self
                        16      LOAD_ATTR                       3: _trace
                        18      LOAD_FAST                       1: other
                        20      LOAD_ATTR                       3: _trace
                        22      COMPARE_OP                      2 (==)
                        24      RETURN_VALUE                    
                'Trace.__eq__'
                [Code]
                    File Name: tracemalloc.py
                    Object Name: __hash__
                    Arg Count: 1
                    Pos Only Arg Count: 0
                    KW Only Arg Count: 0
                    Locals: 1
                    Stack Size: 2
                    Flags: 0x00000043 (CO_OPTIMIZED | CO_NEWLOCALS | CO_NOFREE)
                    [Names]
                        'hash'
                        '_trace'
                    [Var Names]
                        'self'
                    [Free Vars]
                    [Cell Vars]
                    [Constants]
                        None
                    [Disassembly]
                        0       LOAD_GLOBAL                     0: hash
                        2       LOAD_FAST                       0: self
                        4       LOAD_ATTR                       1: _trace
                        6       CALL_FUNCTION                   1
                        8       RETURN_VALUE                    
                'Trace.__hash__'
                [Code]
                    File Name: tracemalloc.py
                    Object Name: __str__
                    Arg Count: 1
                    Pos Only Arg Count: 0
                    KW Only Arg Count: 0
                    Locals: 1
                    Stack Size: 5
                    Flags: 0x00000043 (CO_OPTIMIZED | CO_NEWLOCALS | CO_NOFREE)
                    [Names]
                        'traceback'
                        '_format_size'
                        'size'
                    [Var Names]
                        'self'
                    [Free Vars]
                    [Cell Vars]
                    [Constants]
                        None
                        '%s: %s'
                        False
                    [Disassembly]
                        0       LOAD_CONST                      1: '%s: %s'
                        2       LOAD_FAST                       0: self
                        4       LOAD_ATTR                       0: traceback
                        6       LOAD_GLOBAL                     1: _format_size
                        8       LOAD_FAST                       0: self
                        10      LOAD_ATTR                       2: size
                        12      LOAD_CONST                      2: False
                        14      CALL_FUNCTION                   2
                        16      BUILD_TUPLE                     2
                        18      BINARY_MODULO                   
                        20      RETURN_VALUE                    
                'Trace.__str__'
                [Code]
                    File Name: tracemalloc.py
                    Object Name: __repr__
                    Arg Count: 1
                    Pos Only Arg Count: 0
                    KW Only Arg Count: 0
                    Locals: 1
                    Stack Size: 5
                    Flags: 0x00000043 (CO_OPTIMIZED | CO_NEWLOCALS | CO_NOFREE)
                    [Names]
                        'domain'
                        '_format_size'
                        'size'
                        'traceback'
                    [Var Names]
                        'self'
                    [Free Vars]
                    [Cell Vars]
                    [Constants]
                        None
                        '<Trace domain=%s size=%s, traceback=%r>'
                        False
                    [Disassembly]
                        0       LOAD_CONST                      1: '<Trace domain=%s size=%s, traceback=%r>'
                        2       LOAD_FAST                       0: self
                        4       LOAD_ATTR                       0: domain
                        6       LOAD_GLOBAL                     1: _format_size
                        8       LOAD_FAST                       0: self
                        10      LOAD_ATTR                       2: size
                        12      LOAD_CONST                      2: False
                        14      CALL_FUNCTION                   2
                        16      LOAD_FAST                       0: self
                        18      LOAD_ATTR                       3: traceback
                        20      BUILD_TUPLE                     3
                        22      BINARY_MODULO                   
                        24      RETURN_VALUE                    
                'Trace.__repr__'
                None
            [Disassembly]
                0       LOAD_NAME                       0: __name__
                2       STORE_NAME                      1: __module__
                4       LOAD_CONST                      0: 'Trace'
                6       STORE_NAME                      2: __qualname__
                8       LOAD_CONST                      1: '\n    Trace of a memory block.\n    '
                10      STORE_NAME                      3: __doc__
                12      LOAD_CONST                      2: ('_trace',)
                14      STORE_NAME                      4: __slots__
                16      LOAD_CONST                      3: <CODE> __init__
                18      LOAD_CONST                      4: 'Trace.__init__'
                20      MAKE_FUNCTION                   0
                22      STORE_NAME                      5: __init__
                24      LOAD_NAME                       6: property
                26      LOAD_CONST                      5: <CODE> domain
                28      LOAD_CONST                      6: 'Trace.domain'
                30      MAKE_FUNCTION                   0
                32      CALL_FUNCTION                   1
                34      STORE_NAME                      7: domain
                36      LOAD_NAME                       6: property
                38      LOAD_CONST                      7: <CODE> size
                40      LOAD_CONST                      8: 'Trace.size'
                42      MAKE_FUNCTION                   0
                44      CALL_FUNCTION                   1
                46      STORE_NAME                      8: size
                48      LOAD_NAME                       6: property
                50      LOAD_CONST                      9: <CODE> traceback
                52      LOAD_CONST                      10: 'Trace.traceback'
                54      MAKE_FUNCTION                   0
                56      CALL_FUNCTION                   1
                58      STORE_NAME                      9: traceback
                60      LOAD_CONST                      11: <CODE> __eq__
                62      LOAD_CONST                      12: 'Trace.__eq__'
                64      MAKE_FUNCTION                   0
                66      STORE_NAME                      10: __eq__
                68      LOAD_CONST                      13: <CODE> __hash__
                70      LOAD_CONST                      14: 'Trace.__hash__'
                72      MAKE_FUNCTION                   0
                74      STORE_NAME                      11: __hash__
                76      LOAD_CONST                      15: <CODE> __str__
                78      LOAD_CONST                      16: 'Trace.__str__'
                80      MAKE_FUNCTION                   0
                82      STORE_NAME                      12: __str__
                84      LOAD_CONST                      17: <CODE> __repr__
                86      LOAD_CONST                      18: 'Trace.__repr__'
                88      MAKE_FUNCTION                   0
                90      STORE_NAME                      13: __repr__
                92      LOAD_CONST                      19: None
                94      RETURN_VALUE                    
        'Trace'
        [Code]
            File Name: tracemalloc.py
            Object Name: _Traces
            Arg Count: 0
            Pos Only Arg Count: 0
            KW Only Arg Count: 0
            Locals: 0
            Stack Size: 2
            Flags: 0x00000040 (CO_NOFREE)
            [Names]
                '__name__'
                '__module__'
                '__qualname__'
                '__init__'
                '__len__'
                '__getitem__'
                '__contains__'
                '__eq__'
                '__repr__'
            [Var Names]
            [Free Vars]
            [Cell Vars]
            [Constants]
                '_Traces'
                [Code]
                    File Name: tracemalloc.py
                    Object Name: __init__
                    Arg Count: 2
                    Pos Only Arg Count: 0
                    KW Only Arg Count: 0
                    Locals: 2
                    Stack Size: 3
                    Flags: 0x00000043 (CO_OPTIMIZED | CO_NEWLOCALS | CO_NOFREE)
                    [Names]
                        'Sequence'
                        '__init__'
                        '_traces'
                    [Var Names]
                        'self'
                        'traces'
                    [Free Vars]
                    [Cell Vars]
                    [Constants]
                        None
                    [Disassembly]
                        0       LOAD_GLOBAL                     0: Sequence
                        2       LOAD_METHOD                     1: __init__
                        4       LOAD_FAST                       0: self
                        6       CALL_METHOD                     1
                        8       POP_TOP                         
                        10      LOAD_FAST                       1: traces
                        12      LOAD_FAST                       0: self
                        14      STORE_ATTR                      2: _traces
                        16      LOAD_CONST                      0: None
                        18      RETURN_VALUE                    
                '_Traces.__init__'
                [Code]
                    File Name: tracemalloc.py
                    Object Name: __len__
                    Arg Count: 1
                    Pos Only Arg Count: 0
                    KW Only Arg Count: 0
                    Locals: 1
                    Stack Size: 2
                    Flags: 0x00000043 (CO_OPTIMIZED | CO_NEWLOCALS | CO_NOFREE)
                    [Names]
                        'len'
                        '_traces'
                    [Var Names]
                        'self'
                    [Free Vars]
                    [Cell Vars]
                    [Constants]
                        None
                    [Disassembly]
                        0       LOAD_GLOBAL                     0: len
                        2       LOAD_FAST                       0: self
                        4       LOAD_ATTR                       1: _traces
                        6       CALL_FUNCTION                   1
                        8       RETURN_VALUE                    
                '_Traces.__len__'
                [Code]
                    File Name: tracemalloc.py
                    Object Name: __getitem__
                    Arg Count: 2
                    Pos Only Arg Count: 0
                    KW Only Arg Count: 0
                    Locals: 2
                    Stack Size: 4
                    Flags: 0x00000043 (CO_OPTIMIZED | CO_NEWLOCALS | CO_NOFREE)
                    [Names]
                        'isinstance'
                        'slice'
                        'tuple'
                        '_traces'
                        'Trace'
                    [Var Names]
                        'self'
                        'index'
                    [Free Vars]
                    [Cell Vars]
                    [Constants]
                        None
                        [Code]
                            File Name: tracemalloc.py
                            Object Name: <genexpr>
                            Arg Count: 1
                            Pos Only Arg Count: 0
                            KW Only Arg Count: 0
                            Locals: 2
                            Stack Size: 3
                            Flags: 0x00000073 (CO_OPTIMIZED | CO_NEWLOCALS | CO_NESTED | CO_GENERATOR | CO_NOFREE)
                            [Names]
                                'Trace'
                            [Var Names]
                                '.0'
                                'trace'
                            [Free Vars]
                            [Cell Vars]
                            [Constants]
                                None
                            [Disassembly]
                                0       GEN_START                       0
                                2       LOAD_FAST                       0: .0
                                4       FOR_ITER                        7 (to 20)
                                6       STORE_FAST                      1: trace
                                8       LOAD_GLOBAL                     0: Trace
                                10      LOAD_FAST                       1: trace
                                12      CALL_FUNCTION                   1
                                14      YIELD_VALUE                     
                                16      POP_TOP                         
                                18      JUMP_ABSOLUTE                   2 (to 4)
                                20      LOAD_CONST                      0: None
                                22      RETURN_VALUE                    
                        '_Traces.__getitem__.<locals>.<genexpr>'
                    [Disassembly]
                        0       LOAD_GLOBAL                     0: isinstance
                        2       LOAD_FAST                       1: index
                        4       LOAD_GLOBAL                     1: slice
                        6       CALL_FUNCTION                   2
                        8       POP_JUMP_IF_FALSE               17 (to 34)
                        10      LOAD_GLOBAL                     2: tuple
                        12      LOAD_CONST                      1: <CODE> <genexpr>
                        14      LOAD_CONST                      2: '_Traces.__getitem__.<locals>.<genexpr>'
                        16      MAKE_FUNCTION                   0
                        18      LOAD_FAST                       0: self
                        20      LOAD_ATTR                       3: _traces
                        22      LOAD_FAST                       1: index
                        24      BINARY_SUBSCR                   
                        26      GET_ITER                        
                        28      CALL_FUNCTION                   1
                        30      CALL_FUNCTION                   1
                        32      RETURN_VALUE                    
                        34      LOAD_GLOBAL                     4: Trace
                        36      LOAD_FAST                       0: self
                        38      LOAD_ATTR                       3: _traces
                        40      LOAD_FAST                       1: index
                        42      BINARY_SUBSCR                   
                        44      CALL_FUNCTION                   1
                        46      RETURN_VALUE                    
                '_Traces.__getitem__'
                [Code]
                    File Name: tracemalloc.py
                    Object Name: __contains__
                    Arg Count: 2
                    Pos Only Arg Count: 0
                    KW Only Arg Count: 0
                    Locals: 2
                    Stack Size: 2
                    Flags: 0x00000043 (CO_OPTIMIZED | CO_NEWLOCALS | CO_NOFREE)
                    [Names]
                        '_trace'
                        '_traces'
                    [Var Names]
                        'self'
                        'trace'
                    [Free Vars]
                    [Cell Vars]
                    [Constants]
                        None
                    [Disassembly]
                        0       LOAD_FAST                       1: trace
                        2       LOAD_ATTR                       0: _trace
                        4       LOAD_FAST                       0: self
                        6       LOAD_ATTR                       1: _traces
                        8       CONTAINS_OP                     0 (in)
                        10      RETURN_VALUE                    
                '_Traces.__contains__'
                [Code]
                    File Name: tracemalloc.py
                    Object Name: __eq__
                    Arg Count: 2
                    Pos Only Arg Count: 0
                    KW Only Arg Count: 0
                    Locals: 2
                    Stack Size: 3
                    Flags: 0x00000043 (CO_OPTIMIZED | CO_NEWLOCALS | CO_NOFREE)
                    [Names]
                        'isinstance'
                        '_Traces'
                        'NotImplemented'
                        '_traces'
                    [Var Names]
                        'self'
                        'other'
                    [Free Vars]
                    [Cell Vars]
                    [Constants]
                        None
                    [Disassembly]
                        0       LOAD_GLOBAL                     0: isinstance
                        2       LOAD_FAST                       1: other
                        4       LOAD_GLOBAL                     1: _Traces
                        6       CALL_FUNCTION                   2
                        8       POP_JUMP_IF_TRUE                7 (to 14)
                        10      LOAD_GLOBAL                     2: NotImplemented
                        12      RETURN_VALUE                    
                        14      LOAD_FAST                       0: self
                        16      LOAD_ATTR                       3: _traces
                        18      LOAD_FAST                       1: other
                        20      LOAD_ATTR                       3: _traces
                        22      COMPARE_OP                      2 (==)
                        24      RETURN_VALUE                    
                '_Traces.__eq__'
                [Code]
                    File Name: tracemalloc.py
                    Object Name: __repr__
                    Arg Count: 1
                    Pos Only Arg Count: 0
                    KW Only Arg Count: 0
                    Locals: 1
                    Stack Size: 3
                    Flags: 0x00000043 (CO_OPTIMIZED | CO_NEWLOCALS | CO_NOFREE)
                    [Names]
                        'len'
                    [Var Names]
                        'self'
                    [Free Vars]
                    [Cell Vars]
                    [Constants]
                        None
                        '<Traces len=%s>'
                    [Disassembly]
                        0       LOAD_CONST                      1: '<Traces len=%s>'
                        2       LOAD_GLOBAL                     0: len
                        4       LOAD_FAST                       0: self
                        6       CALL_FUNCTION                   1
                        8       BINARY_MODULO                   
                        10      RETURN_VALUE                    
                '_Traces.__repr__'
                None
            [Disassembly]
                0       LOAD_NAME                       0: __name__
                2       STORE_NAME                      1: __module__
                4       LOAD_CONST                      0: '_Traces'
                6       STORE_NAME                      2: __qualname__
                8       LOAD_CONST                      1: <CODE> __init__
                10      LOAD_CONST                      2: '_Traces.__init__'
                12      MAKE_FUNCTION                   0
                14      STORE_NAME                      3: __init__
                16      LOAD_CONST                      3: <CODE> __len__
                18      LOAD_CONST                      4: '_Traces.__len__'
                20      MAKE_FUNCTION                   0
                22      STORE_NAME                      4: __len__
                24      LOAD_CONST                      5: <CODE> __getitem__
                26      LOAD_CONST                      6: '_Traces.__getitem__'
                28      MAKE_FUNCTION                   0
                30      STORE_NAME                      5: __getitem__
                32      LOAD_CONST                      7: <CODE> __contains__
                34      LOAD_CONST                      8: '_Traces.__contains__'
                36      MAKE_FUNCTION                   0
                38      STORE_NAME                      6: __contains__
                40      LOAD_CONST                      9: <CODE> __eq__
                42      LOAD_CONST                      10: '_Traces.__eq__'
                44      MAKE_FUNCTION                   0
                46      STORE_NAME                      7: __eq__
                48      LOAD_CONST                      11: <CODE> __repr__
                50      LOAD_CONST                      12: '_Traces.__repr__'
                52      MAKE_FUNCTION                   0
                54      STORE_NAME                      8: __repr__
                56      LOAD_CONST                      13: None
                58      RETURN_VALUE                    
        '_Traces'
        [Code]
            File Name: tracemalloc.py
            Object Name: _normalize_filename
            Arg Count: 1
            Pos Only Arg Count: 0
            KW Only Arg Count: 0
            Locals: 1
            Stack Size: 3
            Flags: 0x00000043 (CO_OPTIMIZED | CO_NEWLOCALS | CO_NOFREE)
            [Names]
                'os'
                'path'
                'normcase'
                'endswith'
            [Var Names]
                'filename'
            [Free Vars]
            [Cell Vars]
            [Constants]
                None
                '.pyc'
                -1
            [Disassembly]
                0       LOAD_GLOBAL                     0: os
                2       LOAD_ATTR                       1: path
                4       LOAD_METHOD                     2: normcase
                6       LOAD_FAST                       0: filename
                8       CALL_METHOD                     1
                10      STORE_FAST                      0: filename
                12      LOAD_FAST                       0: filename
                14      LOAD_METHOD                     3: endswith
                16      LOAD_CONST                      1: '.pyc'
                18      CALL_METHOD                     1
                20      POP_JUMP_IF_FALSE               17 (to 34)
                22      LOAD_FAST                       0: filename
                24      LOAD_CONST                      0: None
                26      LOAD_CONST                      2: -1
                28      BUILD_SLICE                     2
                30      BINARY_SUBSCR                   
                32      STORE_FAST                      0: filename
                34      LOAD_FAST                       0: filename
                36      RETURN_VALUE                    
        '_normalize_filename'
        [Code]
            File Name: tracemalloc.py
            Object Name: BaseFilter
            Arg Count: 0
            Pos Only Arg Count: 0
            KW Only Arg Count: 0
            Locals: 0
            Stack Size: 2
            Flags: 0x00000040 (CO_NOFREE)
            [Names]
                '__name__'
                '__module__'
                '__qualname__'
                '__init__'
                '_match'
            [Var Names]
            [Free Vars]
            [Cell Vars]
            [Constants]
                'BaseFilter'
                [Code]
                    File Name: tracemalloc.py
                    Object Name: __init__
                    Arg Count: 2
                    Pos Only Arg Count: 0
                    KW Only Arg Count: 0
                    Locals: 2
                    Stack Size: 2
                    Flags: 0x00000043 (CO_OPTIMIZED | CO_NEWLOCALS | CO_NOFREE)
                    [Names]
                        'inclusive'
                    [Var Names]
                        'self'
                        'inclusive'
                    [Free Vars]
                    [Cell Vars]
                    [Constants]
                        None
                    [Disassembly]
                        0       LOAD_FAST                       1: inclusive
                        2       LOAD_FAST                       0: self
                        4       STORE_ATTR                      0: inclusive
                        6       LOAD_CONST                      0: None
                        8       RETURN_VALUE                    
                'BaseFilter.__init__'
                [Code]
                    File Name: tracemalloc.py
                    Object Name: _match
                    Arg Count: 2
                    Pos Only Arg Count: 0
                    KW Only Arg Count: 0
                    Locals: 2
                    Stack Size: 1
                    Flags: 0x00000043 (CO_OPTIMIZED | CO_NEWLOCALS | CO_NOFREE)
                    [Names]
                        'NotImplementedError'
                    [Var Names]
                        'self'
                        'trace'
                    [Free Vars]
                    [Cell Vars]
                    [Constants]
                        None
                    [Disassembly]
                        0       LOAD_GLOBAL                     0: NotImplementedError
                        2       RAISE_VARARGS                   1
                'BaseFilter._match'
                None
            [Disassembly]
                0       LOAD_NAME                       0: __name__
                2       STORE_NAME                      1: __module__
                4       LOAD_CONST                      0: 'BaseFilter'
                6       STORE_NAME                      2: __qualname__
                8       LOAD_CONST                      1: <CODE> __init__
                10      LOAD_CONST                      2: 'BaseFilter.__init__'
                12      MAKE_FUNCTION                   0
                14      STORE_NAME                      3: __init__
                16      LOAD_CONST                      3: <CODE> _match
                18      LOAD_CONST                      4: 'BaseFilter._match'
                20      MAKE_FUNCTION                   0
                22      STORE_NAME                      4: _match
                24      LOAD_CONST                      5: None
                26      RETURN_VALUE                    
        'BaseFilter'
        [Code]
            File Name: tracemalloc.py
            Object Name: Filter
            Arg Count: 0
            Pos Only Arg Count: 0
            KW Only Arg Count: 0
            Locals: 0
            Stack Size: 4
            Flags: 0x00000000
            [Names]
                '__name__'
                '__module__'
                '__qualname__'
                '__init__'
                'property'
                'filename_pattern'
                '_match_frame_impl'
                '_match_frame'
                '_match_traceback'
                '_match'
                '__classcell__'
            [Var Names]
            [Free Vars]
            [Cell Vars]
                '__class__'
            [Constants]
                'Filter'
                None
                False
                [Code]
                    File Name: tracemalloc.py
                    Object Name: __init__
                    Arg Count: 6
                    Pos Only Arg Count: 0
                    KW Only Arg Count: 0
                    Locals: 6
                    Stack Size: 3
                    Flags: 0x00000003 (CO_OPTIMIZED | CO_NEWLOCALS)
                    [Names]
                        'super'
                        '__init__'
                        'inclusive'
                        '_normalize_filename'
                        '_filename_pattern'
                        'lineno'
                        'all_frames'
                        'domain'
                    [Var Names]
                        'self'
                        'inclusive'
                        'filename_pattern'
                        'lineno'
                        'all_frames'
                        'domain'
                    [Free Vars]
                        '__class__'
                    [Cell Vars]
                    [Constants]
                        None
                    [Disassembly]
                        0       LOAD_GLOBAL                     0: super
                        2       CALL_FUNCTION                   0
                        4       LOAD_METHOD                     1: __init__
                        6       LOAD_FAST                       1: inclusive
                        8       CALL_METHOD                     1
                        10      POP_TOP                         
                        12      LOAD_FAST                       1: inclusive
                        14      LOAD_FAST                       0: self
                        16      STORE_ATTR                      2: inclusive
                        18      LOAD_GLOBAL                     3: _normalize_filename
                        20      LOAD_FAST                       2: filename_pattern
                        22      CALL_FUNCTION                   1
                        24      LOAD_FAST                       0: self
                        26      STORE_ATTR                      4: _filename_pattern
                        28      LOAD_FAST                       3: lineno
                        30      LOAD_FAST                       0: self
                        32      STORE_ATTR                      5: lineno
                        34      LOAD_FAST                       4: all_frames
                        36      LOAD_FAST                       0: self
                        38      STORE_ATTR                      6: all_frames
                        40      LOAD_FAST                       5: domain
                        42      LOAD_FAST                       0: self
                        44      STORE_ATTR                      7: domain
                        46      LOAD_CONST                      0: None
                        48      RETURN_VALUE                    
                'Filter.__init__'
                [Code]
                    File Name: tracemalloc.py
                    Object Name: filename_pattern
                    Arg Count: 1
                    Pos Only Arg Count: 0
                    KW Only Arg Count: 0
                    Locals: 1
                    Stack Size: 1
                    Flags: 0x00000043 (CO_OPTIMIZED | CO_NEWLOCALS | CO_NOFREE)
                    [Names]
                        '_filename_pattern'
                    [Var Names]
                        'self'
                    [Free Vars]
                    [Cell Vars]
                    [Constants]
                        None
                    [Disassembly]
                        0       LOAD_FAST                       0: self
                        2       LOAD_ATTR                       0: _filename_pattern
                        4       RETURN_VALUE                    
                'Filter.filename_pattern'
                [Code]
                    File Name: tracemalloc.py
                    Object Name: _match_frame_impl
                    Arg Count: 3
                    Pos Only Arg Count: 0
                    KW Only Arg Count: 0
                    Locals: 3
                    Stack Size: 4
                    Flags: 0x00000043 (CO_OPTIMIZED | CO_NEWLOCALS | CO_NOFREE)
                    [Names]
                        '_normalize_filename'
                        'fnmatch'
                        '_filename_pattern'
                        'lineno'
                    [Var Names]
                        'self'
                        'filename'
                        'lineno'
                    [Free Vars]
                    [Cell Vars]
                    [Constants]
                        None
                        False
                        True
                    [Disassembly]
                        0       LOAD_GLOBAL                     0: _normalize_filename
                        2       LOAD_FAST                       1: filename
                        4       CALL_FUNCTION                   1
                        6       STORE_FAST                      1: filename
                        8       LOAD_GLOBAL                     1: fnmatch
                        10      LOAD_METHOD                     1: fnmatch
                        12      LOAD_FAST                       1: filename
                        14      LOAD_FAST                       0: self
                        16      LOAD_ATTR                       2: _filename_pattern
                        18      CALL_METHOD                     2
                        20      POP_JUMP_IF_TRUE                13 (to 26)
                        22      LOAD_CONST                      1: False
                        24      RETURN_VALUE                    
                        26      LOAD_FAST                       0: self
                        28      LOAD_ATTR                       3: lineno
                        30      LOAD_CONST                      0: None
                        32      IS_OP                           0 (is)
                        34      POP_JUMP_IF_FALSE               20 (to 40)
                        36      LOAD_CONST                      2: True
                        38      RETURN_VALUE                    
                        40      LOAD_FAST                       2: lineno
                        42      LOAD_FAST                       0: self
                        44      LOAD_ATTR                       3: lineno
                        46      COMPARE_OP                      2 (==)
                        48      RETURN_VALUE                    
                'Filter._match_frame_impl'
                [Code]
                    File Name: tracemalloc.py
                    Object Name: _match_frame
                    Arg Count: 3
                    Pos Only Arg Count: 0
                    KW Only Arg Count: 0
                    Locals: 3
                    Stack Size: 4
                    Flags: 0x00000043 (CO_OPTIMIZED | CO_NEWLOCALS | CO_NOFREE)
                    [Names]
                        '_match_frame_impl'
                        'inclusive'
                    [Var Names]
                        'self'
                        'filename'
                        'lineno'
                    [Free Vars]
                    [Cell Vars]
                    [Constants]
                        None
                    [Disassembly]
                        0       LOAD_FAST                       0: self
                        2       LOAD_METHOD                     0: _match_frame_impl
                        4       LOAD_FAST                       1: filename
                        6       LOAD_FAST                       2: lineno
                        8       CALL_METHOD                     2
                        10      LOAD_FAST                       0: self
                        12      LOAD_ATTR                       1: inclusive
                        14      UNARY_NOT                       
                        16      BINARY_XOR                      
                        18      RETURN_VALUE                    
                'Filter._match_frame'
                [Code]
                    File Name: tracemalloc.py
                    Object Name: _match_traceback
                    Arg Count: 2
                    Pos Only Arg Count: 0
                    KW Only Arg Count: 0
                    Locals: 4
                    Stack Size: 4
                    Flags: 0x00000003 (CO_OPTIMIZED | CO_NEWLOCALS)
                    [Names]
                        'all_frames'
                        'any'
                        'inclusive'
                        '_match_frame'
                    [Var Names]
                        'self'
                        'traceback'
                        'filename'
                        'lineno'
                    [Free Vars]
                    [Cell Vars]
                        'self'
                    [Constants]
                        None
                        [Code]
                            File Name: tracemalloc.py
                            Object Name: <genexpr>
                            Arg Count: 1
                            Pos Only Arg Count: 0
                            KW Only Arg Count: 0
                            Locals: 3
                            Stack Size: 5
                            Flags: 0x00000033 (CO_OPTIMIZED | CO_NEWLOCALS | CO_NESTED | CO_GENERATOR)
                            [Names]
                                '_match_frame_impl'
                            [Var Names]
                                '.0'
                                'filename'
                                'lineno'
                            [Free Vars]
                                'self'
                            [Cell Vars]
                            [Constants]
                                None
                            [Disassembly]
                                0       GEN_START                       0
                                2       LOAD_FAST                       0: .0
                                4       FOR_ITER                        11 (to 28)
                                6       UNPACK_SEQUENCE                 2
                                8       STORE_FAST                      1: filename
                                10      STORE_FAST                      2: lineno
                                12      LOAD_DEREF                      0: self
                                14      LOAD_METHOD                     0: _match_frame_impl
                                16      LOAD_FAST                       1: filename
                                18      LOAD_FAST                       2: lineno
                                20      CALL_METHOD                     2
                                22      YIELD_VALUE                     
                                24      POP_TOP                         
                                26      JUMP_ABSOLUTE                   2 (to 4)
                                28      LOAD_CONST                      0: None
                                30      RETURN_VALUE                    
                        'Filter._match_traceback.<locals>.<genexpr>'
                        0
                    [Disassembly]
                        0       LOAD_DEREF                      0: self
                        2       LOAD_ATTR                       0: all_frames
                        4       POP_JUMP_IF_FALSE               21 (to 42)
                        6       LOAD_GLOBAL                     1: any
                        8       LOAD_CLOSURE                    0: self
                        10      BUILD_TUPLE                     1
                        12      LOAD_CONST                      1: <CODE> <genexpr>
                        14      LOAD_CONST                      2: 'Filter._match_traceback.<locals>.<genexpr>'
                        16      MAKE_FUNCTION                   8
                        18      LOAD_FAST                       1: traceback
                        20      GET_ITER                        
                        22      CALL_FUNCTION                   1
                        24      CALL_FUNCTION                   1
                        26      POP_JUMP_IF_FALSE               17 (to 34)
                        28      LOAD_DEREF                      0: self
                        30      LOAD_ATTR                       2: inclusive
                        32      RETURN_VALUE                    
                        34      LOAD_DEREF                      0: self
                        36      LOAD_ATTR                       2: inclusive
                        38      UNARY_NOT                       
                        40      RETURN_VALUE                    
                        42      LOAD_FAST                       1: traceback
                        44      LOAD_CONST                      3: 0
                        46      BINARY_SUBSCR                   
                        48      UNPACK_SEQUENCE                 2
                        50      STORE_FAST                      2: filename
                        52      STORE_FAST                      3: lineno
                        54      LOAD_DEREF                      0: self
                        56      LOAD_METHOD                     3: _match_frame
                        58      LOAD_FAST                       2: filename
                        60      LOAD_FAST                       3: lineno
                        62      CALL_METHOD                     2
                        64      RETURN_VALUE                    
                'Filter._match_traceback'
                [Code]
                    File Name: tracemalloc.py
                    Object Name: _match
                    Arg Count: 2
                    Pos Only Arg Count: 0
                    KW Only Arg Count: 0
                    Locals: 7
                    Stack Size: 4
                    Flags: 0x00000043 (CO_OPTIMIZED | CO_NEWLOCALS | CO_NOFREE)
                    [Names]
                        '_match_traceback'
                        'domain'
                        'inclusive'
                    [Var Names]
                        'self'
                        'trace'
                        'domain'
                        'size'
                        'traceback'
                        'total_nframe'
                        'res'
                    [Free Vars]
                    [Cell Vars]
                    [Constants]
                        None
                    [Disassembly]
                        0       LOAD_FAST                       1: trace
                        2       UNPACK_SEQUENCE                 4
                        4       STORE_FAST                      2: domain
                        6       STORE_FAST                      3: size
                        8       STORE_FAST                      4: traceback
                        10      STORE_FAST                      5: total_nframe
                        12      LOAD_FAST                       0: self
                        14      LOAD_METHOD                     0: _match_traceback
                        16      LOAD_FAST                       4: traceback
                        18      CALL_METHOD                     1
                        20      STORE_FAST                      6: res
                        22      LOAD_FAST                       0: self
                        24      LOAD_ATTR                       1: domain
                        26      LOAD_CONST                      0: None
                        28      IS_OP                           1 (is not)
                        30      POP_JUMP_IF_FALSE               33 (to 66)
                        32      LOAD_FAST                       0: self
                        34      LOAD_ATTR                       2: inclusive
                        36      POP_JUMP_IF_FALSE               26 (to 52)
                        38      LOAD_FAST                       6: res
                        40      JUMP_IF_FALSE_OR_POP            25 (to 50)
                        42      LOAD_FAST                       2: domain
                        44      LOAD_FAST                       0: self
                        46      LOAD_ATTR                       1: domain
                        48      COMPARE_OP                      2 (==)
                        50      RETURN_VALUE                    
                        52      LOAD_FAST                       6: res
                        54      JUMP_IF_TRUE_OR_POP             32 (to 64)
                        56      LOAD_FAST                       2: domain
                        58      LOAD_FAST                       0: self
                        60      LOAD_ATTR                       1: domain
                        62      COMPARE_OP                      3 (!=)
                        64      RETURN_VALUE                    
                        66      LOAD_FAST                       6: res
                        68      RETURN_VALUE                    
                'Filter._match'
                (
                    None
                    False
                    None
                )
            [Disassembly]
                0       LOAD_NAME                       0: __name__
                2       STORE_NAME                      1: __module__
                4       LOAD_CONST                      0: 'Filter'
                6       STORE_NAME                      2: __qualname__
                8       NOP                             
                10      LOAD_CONST                      15: (None, False, None)
                12      LOAD_CLOSURE                    0: __class__
                14      BUILD_TUPLE                     1
                16      LOAD_CONST                      3: <CODE> __init__
                18      LOAD_CONST                      4: 'Filter.__init__'
                20      MAKE_FUNCTION                   9
                22      STORE_NAME                      3: __init__
                24      LOAD_NAME                       4: property
                26      LOAD_CONST                      5: <CODE> filename_pattern
                28      LOAD_CONST                      6: 'Filter.filename_pattern'
                30      MAKE_FUNCTION                   0
                32      CALL_FUNCTION                   1
                34      STORE_NAME                      5: filename_pattern
                36      LOAD_CONST                      7: <CODE> _match_frame_impl
                38      LOAD_CONST                      8: 'Filter._match_frame_impl'
                40      MAKE_FUNCTION                   0
                42      STORE_NAME                      6: _match_frame_impl
                44      LOAD_CONST                      9: <CODE> _match_frame
                46      LOAD_CONST                      10: 'Filter._match_frame'
                48      MAKE_FUNCTION                   0
                50      STORE_NAME                      7: _match_frame
                52      LOAD_CONST                      11: <CODE> _match_traceback
                54      LOAD_CONST                      12: 'Filter._match_traceback'
                56      MAKE_FUNCTION                   0
                58      STORE_NAME                      8: _match_traceback
                60      LOAD_CONST                      13: <CODE> _match
                62      LOAD_CONST                      14: 'Filter._match'
                64      MAKE_FUNCTION                   0
                66      STORE_NAME                      9: _match
                68      LOAD_CLOSURE                    0: __class__
                70      DUP_TOP                         
                72      STORE_NAME                      10: __classcell__
                74      RETURN_VALUE                    
        'Filter'
        [Code]
            File Name: tracemalloc.py
            Object Name: DomainFilter
            Arg Count: 0
            Pos Only Arg Count: 0
            KW Only Arg Count: 0
            Locals: 0
            Stack Size: 3
            Flags: 0x00000000
            [Names]
                '__name__'
                '__module__'
                '__qualname__'
                '__init__'
                'property'
                'domain'
                '_match'
                '__classcell__'
            [Var Names]
            [Free Vars]
            [Cell Vars]
                '__class__'
            [Constants]
                'DomainFilter'
                [Code]
                    File Name: tracemalloc.py
                    Object Name: __init__
                    Arg Count: 3
                    Pos Only Arg Count: 0
                    KW Only Arg Count: 0
                    Locals: 3
                    Stack Size: 3
                    Flags: 0x00000003 (CO_OPTIMIZED | CO_NEWLOCALS)
                    [Names]
                        'super'
                        '__init__'
                        '_domain'
                    [Var Names]
                        'self'
                        'inclusive'
                        'domain'
                    [Free Vars]
                        '__class__'
                    [Cell Vars]
                    [Constants]
                        None
                    [Disassembly]
                        0       LOAD_GLOBAL                     0: super
                        2       CALL_FUNCTION                   0
                        4       LOAD_METHOD                     1: __init__
                        6       LOAD_FAST                       1: inclusive
                        8       CALL_METHOD                     1
                        10      POP_TOP                         
                        12      LOAD_FAST                       2: domain
                        14      LOAD_FAST                       0: self
                        16      STORE_ATTR                      2: _domain
                        18      LOAD_CONST                      0: None
                        20      RETURN_VALUE                    
                'DomainFilter.__init__'
                [Code]
                    File Name: tracemalloc.py
                    Object Name: domain
                    Arg Count: 1
                    Pos Only Arg Count: 0
                    KW Only Arg Count: 0
                    Locals: 1
                    Stack Size: 1
                    Flags: 0x00000043 (CO_OPTIMIZED | CO_NEWLOCALS | CO_NOFREE)
                    [Names]
                        '_domain'
                    [Var Names]
                        'self'
                    [Free Vars]
                    [Cell Vars]
                    [Constants]
                        None
                    [Disassembly]
                        0       LOAD_FAST                       0: self
                        2       LOAD_ATTR                       0: _domain
                        4       RETURN_VALUE                    
                'DomainFilter.domain'
                [Code]
                    File Name: tracemalloc.py
                    Object Name: _match
                    Arg Count: 2
                    Pos Only Arg Count: 0
                    KW Only Arg Count: 0
                    Locals: 6
                    Stack Size: 4
                    Flags: 0x00000043 (CO_OPTIMIZED | CO_NEWLOCALS | CO_NOFREE)
                    [Names]
                        'domain'
                        'inclusive'
                    [Var Names]
                        'self'
                        'trace'
                        'domain'
                        'size'
                        'traceback'
                        'total_nframe'
                    [Free Vars]
                    [Cell Vars]
                    [Constants]
                        None
                    [Disassembly]
                        0       LOAD_FAST                       1: trace
                        2       UNPACK_SEQUENCE                 4
                        4       STORE_FAST                      2: domain
                        6       STORE_FAST                      3: size
                        8       STORE_FAST                      4: traceback
                        10      STORE_FAST                      5: total_nframe
                        12      LOAD_FAST                       2: domain
                        14      LOAD_FAST                       0: self
                        16      LOAD_ATTR                       0: domain
                        18      COMPARE_OP                      2 (==)
                        20      LOAD_FAST                       0: self
                        22      LOAD_ATTR                       1: inclusive
                        24      UNARY_NOT                       
                        26      BINARY_XOR                      
                        28      RETURN_VALUE                    
                'DomainFilter._match'
            [Disassembly]
                0       LOAD_NAME                       0: __name__
                2       STORE_NAME                      1: __module__
                4       LOAD_CONST                      0: 'DomainFilter'
                6       STORE_NAME                      2: __qualname__
                8       LOAD_CLOSURE                    0: __class__
                10      BUILD_TUPLE                     1
                12      LOAD_CONST                      1: <CODE> __init__
                14      LOAD_CONST                      2: 'DomainFilter.__init__'
                16      MAKE_FUNCTION                   8
                18      STORE_NAME                      3: __init__
                20      LOAD_NAME                       4: property
                22      LOAD_CONST                      3: <CODE> domain
                24      LOAD_CONST                      4: 'DomainFilter.domain'
                26      MAKE_FUNCTION                   0
                28      CALL_FUNCTION                   1
                30      STORE_NAME                      5: domain
                32      LOAD_CONST                      5: <CODE> _match
                34      LOAD_CONST                      6: 'DomainFilter._match'
                36      MAKE_FUNCTION                   0
                38      STORE_NAME                      6: _match
                40      LOAD_CLOSURE                    0: __class__
                42      DUP_TOP                         
                44      STORE_NAME                      7: __classcell__
                46      RETURN_VALUE                    
        'DomainFilter'
        [Code]
            File Name: tracemalloc.py
            Object Name: Snapshot
            Arg Count: 0
            Pos Only Arg Count: 0
            KW Only Arg Count: 0
            Locals: 0
            Stack Size: 3
            Flags: 0x00000040 (CO_NOFREE)
            [Names]
                '__name__'
                '__module__'
                '__qualname__'
                '__doc__'
                '__init__'
                'dump'
                'staticmethod'
                'load'
                '_filter_trace'
                'filter_traces'
                '_group_by'
                'statistics'
                'compare_to'
            [Var Names]
            [Free Vars]
            [Cell Vars]
            [Constants]
                'Snapshot'
                '\n    Snapshot of traces of memory blocks allocated by Python.\n    '
                [Code]
                    File Name: tracemalloc.py
                    Object Name: __init__
                    Arg Count: 3
                    Pos Only Arg Count: 0
                    KW Only Arg Count: 0
                    Locals: 3
                    Stack Size: 2
                    Flags: 0x00000043 (CO_OPTIMIZED | CO_NEWLOCALS | CO_NOFREE)
                    [Names]
                        '_Traces'
                        'traces'
                        'traceback_limit'
                    [Var Names]
                        'self'
                        'traces'
                        'traceback_limit'
                    [Free Vars]
                    [Cell Vars]
                    [Constants]
                        None
                    [Disassembly]
                        0       LOAD_GLOBAL                     0: _Traces
                        2       LOAD_FAST                       1: traces
                        4       CALL_FUNCTION                   1
                        6       LOAD_FAST                       0: self
                        8       STORE_ATTR                      1: traces
                        10      LOAD_FAST                       2: traceback_limit
                        12      LOAD_FAST                       0: self
                        14      STORE_ATTR                      2: traceback_limit
                        16      LOAD_CONST                      0: None
                        18      RETURN_VALUE                    
                'Snapshot.__init__'
                [Code]
                    File Name: tracemalloc.py
                    Object Name: dump
                    Arg Count: 2
                    Pos Only Arg Count: 0
                    KW Only Arg Count: 0
                    Locals: 3
                    Stack Size: 8
                    Flags: 0x00000043 (CO_OPTIMIZED | CO_NEWLOCALS | CO_NOFREE)
                    [Names]
                        'open'
                        'pickle'
                        'dump'
                        'HIGHEST_PROTOCOL'
                    [Var Names]
                        'self'
                        'filename'
                        'fp'
                    [Free Vars]
                    [Cell Vars]
                    [Constants]
                        '\n        Write the snapshot into a file.\n        '
                        'wb'
                        None
                    [Disassembly]
                        0       LOAD_GLOBAL                     0: open
                        2       LOAD_FAST                       1: filename
                        4       LOAD_CONST                      1: 'wb'
                        6       CALL_FUNCTION                   2
                        8       SETUP_WITH                      17 (to 44)
                        10      STORE_FAST                      2: fp
                        12      LOAD_GLOBAL                     1: pickle
                        14      LOAD_METHOD                     2: dump
                        16      LOAD_FAST                       0: self
                        18      LOAD_FAST                       2: fp
                        20      LOAD_GLOBAL                     1: pickle
                        22      LOAD_ATTR                       3: HIGHEST_PROTOCOL
                        24      CALL_METHOD                     3
                        26      POP_TOP                         
                        28      POP_BLOCK                       
                        30      LOAD_CONST                      2: None
                        32      DUP_TOP                         
                        34      DUP_TOP                         
                        36      CALL_FUNCTION                   3
                        38      POP_TOP                         
                        40      LOAD_CONST                      2: None
                        42      RETURN_VALUE                    
                        44      WITH_EXCEPT_START               
                        46      POP_JUMP_IF_TRUE                25 (to 50)
                        48      RERAISE                         1
                        50      POP_TOP                         
                        52      POP_TOP                         
                        54      POP_TOP                         
                        56      POP_EXCEPT                      
                        58      POP_TOP                         
                        60      LOAD_CONST                      2: None
                        62      RETURN_VALUE                    
                'Snapshot.dump'
                [Code]
                    File Name: tracemalloc.py
                    Object Name: load
                    Arg Count: 1
                    Pos Only Arg Count: 0
                    KW Only Arg Count: 0
                    Locals: 2
                    Stack Size: 8
                    Flags: 0x00000043 (CO_OPTIMIZED | CO_NEWLOCALS | CO_NOFREE)
                    [Names]
                        'open'
                        'pickle'
                        'load'
                    [Var Names]
                        'filename'
                        'fp'
                    [Free Vars]
                    [Cell Vars]
                    [Constants]
                        '\n        Load a snapshot from a file.\n        '
                        'rb'
                        None
                    [Disassembly]
                        0       LOAD_GLOBAL                     0: open
                        2       LOAD_FAST                       0: filename
                        4       LOAD_CONST                      1: 'rb'
                        6       CALL_FUNCTION                   2
                        8       SETUP_WITH                      13 (to 36)
                        10      STORE_FAST                      1: fp
                        12      LOAD_GLOBAL                     1: pickle
                        14      LOAD_METHOD                     2: load
                        16      LOAD_FAST                       1: fp
                        18      CALL_METHOD                     1
                        20      POP_BLOCK                       
                        22      ROT_TWO                         
                        24      LOAD_CONST                      2: None
                        26      DUP_TOP                         
                        28      DUP_TOP                         
                        30      CALL_FUNCTION                   3
                        32      POP_TOP                         
                        34      RETURN_VALUE                    
                        36      WITH_EXCEPT_START               
                        38      POP_JUMP_IF_TRUE                21 (to 42)
                        40      RERAISE                         1
                        42      POP_TOP                         
                        44      POP_TOP                         
                        46      POP_TOP                         
                        48      POP_EXCEPT                      
                        50      POP_TOP                         
                        52      LOAD_CONST                      2: None
                        54      RETURN_VALUE                    
                'Snapshot.load'
                [Code]
                    File Name: tracemalloc.py
                    Object Name: _filter_trace
                    Arg Count: 4
                    Pos Only Arg Count: 0
                    KW Only Arg Count: 0
                    Locals: 4
                    Stack Size: 4
                    Flags: 0x00000003 (CO_OPTIMIZED | CO_NEWLOCALS)
                    [Names]
                        'any'
                    [Var Names]
                        'self'
                        'include_filters'
                        'exclude_filters'
                        'trace'
                    [Free Vars]
                    [Cell Vars]
                        'trace'
                    [Constants]
                        None
                        [Code]
                            File Name: tracemalloc.py
                            Object Name: <genexpr>
                            Arg Count: 1
                            Pos Only Arg Count: 0
                            KW Only Arg Count: 0
                            Locals: 2
                            Stack Size: 4
                            Flags: 0x00000033 (CO_OPTIMIZED | CO_NEWLOCALS | CO_NESTED | CO_GENERATOR)
                            [Names]
                                '_match'
                            [Var Names]
                                '.0'
                                'trace_filter'
                            [Free Vars]
                                'trace'
                            [Cell Vars]
                            [Constants]
                                None
                            [Disassembly]
                                0       GEN_START                       0
                                2       LOAD_FAST                       0: .0
                                4       FOR_ITER                        8 (to 22)
                                6       STORE_FAST                      1: trace_filter
                                8       LOAD_FAST                       1: trace_filter
                                10      LOAD_METHOD                     0: _match
                                12      LOAD_DEREF                      0: trace
                                14      CALL_METHOD                     1
                                16      YIELD_VALUE                     
                                18      POP_TOP                         
                                20      JUMP_ABSOLUTE                   2 (to 4)
                                22      LOAD_CONST                      0: None
                                24      RETURN_VALUE                    
                        'Snapshot._filter_trace.<locals>.<genexpr>'
                        False
                        [Code]
                            File Name: tracemalloc.py
                            Object Name: <genexpr>
                            Arg Count: 1
                            Pos Only Arg Count: 0
                            KW Only Arg Count: 0
                            Locals: 2
                            Stack Size: 4
                            Flags: 0x00000033 (CO_OPTIMIZED | CO_NEWLOCALS | CO_NESTED | CO_GENERATOR)
                            [Names]
                                '_match'
                            [Var Names]
                                '.0'
                                'trace_filter'
                            [Free Vars]
                                'trace'
                            [Cell Vars]
                            [Constants]
                                None
                            [Disassembly]
                                0       GEN_START                       0
                                2       LOAD_FAST                       0: .0
                                4       FOR_ITER                        9 (to 24)
                                6       STORE_FAST                      1: trace_filter
                                8       LOAD_FAST                       1: trace_filter
                                10      LOAD_METHOD                     0: _match
                                12      LOAD_DEREF                      0: trace
                                14      CALL_METHOD                     1
                                16      UNARY_NOT                       
                                18      YIELD_VALUE                     
                                20      POP_TOP                         
                                22      JUMP_ABSOLUTE                   2 (to 4)
                                24      LOAD_CONST                      0: None
                                26      RETURN_VALUE                    
                        True
                    [Disassembly]
                        0       LOAD_FAST                       1: include_filters
                        2       POP_JUMP_IF_FALSE               15 (to 30)
                        4       LOAD_GLOBAL                     0: any
                        6       LOAD_CLOSURE                    0: trace
                        8       BUILD_TUPLE                     1
                        10      LOAD_CONST                      1: <CODE> <genexpr>
                        12      LOAD_CONST                      2: 'Snapshot._filter_trace.<locals>.<genexpr>'
                        14      MAKE_FUNCTION                   8
                        16      LOAD_FAST                       1: include_filters
                        18      GET_ITER                        
                        20      CALL_FUNCTION                   1
                        22      CALL_FUNCTION                   1
                        24      POP_JUMP_IF_TRUE                15 (to 30)
                        26      LOAD_CONST                      3: False
                        28      RETURN_VALUE                    
                        30      LOAD_FAST                       2: exclude_filters
                        32      POP_JUMP_IF_FALSE               30 (to 60)
                        34      LOAD_GLOBAL                     0: any
                        36      LOAD_CLOSURE                    0: trace
                        38      BUILD_TUPLE                     1
                        40      LOAD_CONST                      4: <CODE> <genexpr>
                        42      LOAD_CONST                      2: 'Snapshot._filter_trace.<locals>.<genexpr>'
                        44      MAKE_FUNCTION                   8
                        46      LOAD_FAST                       2: exclude_filters
                        48      GET_ITER                        
                        50      CALL_FUNCTION                   1
                        52      CALL_FUNCTION                   1
                        54      POP_JUMP_IF_FALSE               30 (to 60)
                        56      LOAD_CONST                      3: False
                        58      RETURN_VALUE                    
                        60      LOAD_CONST                      5: True
                        62      RETURN_VALUE                    
                'Snapshot._filter_trace'
                [Code]
                    File Name: tracemalloc.py
                    Object Name: filter_traces
                    Arg Count: 2
                    Pos Only Arg Count: 0
                    KW Only Arg Count: 0
                    Locals: 4
                    Stack Size: 4
                    Flags: 0x00000003 (CO_OPTIMIZED | CO_NEWLOCALS)
                    [Names]
                        'isinstance'
                        'Iterable'
                        'TypeError'
                        'type'
                        '__name__'
                        'inclusive'
                        'append'
                        'traces'
                        '_traces'
                        'copy'
                        'Snapshot'
                        'traceback_limit'
                    [Var Names]
                        'self'
                        'filters'
                        'trace_filter'
                        'new_traces'
                    [Free Vars]
                    [Cell Vars]
                        'exclude_filters'
                        'include_filters'
                        'self'
                    [Constants]
                        '\n        Create a new Snapshot instance with a filtered traces sequence, filters\n        is a list of Filter or DomainFilter instances.  If filters is an empty\n        list, return a new Snapshot instance with a copy of the traces.\n        '
                        'filters must be a list of filters, not %s'
                        [Code]
                            File Name: tracemalloc.py
                            Object Name: <listcomp>
                            Arg Count: 1
                            Pos Only Arg Count: 0
                            KW Only Arg Count: 0
                            Locals: 2
                            Stack Size: 7
                            Flags: 0x00000013 (CO_OPTIMIZED | CO_NEWLOCALS | CO_NESTED)
                            [Names]
                                '_filter_trace'
                            [Var Names]
                                '.0'
                                'trace'
                            [Free Vars]
                                'exclude_filters'
                                'include_filters'
                                'self'
                            [Cell Vars]
                            [Constants]
                            [Disassembly]
                                0       BUILD_LIST                      0
                                2       LOAD_FAST                       0: .0
                                4       FOR_ITER                        11 (to 28)
                                6       STORE_FAST                      1: trace
                                8       LOAD_DEREF                      2: self
                                10      LOAD_METHOD                     0: _filter_trace
                                12      LOAD_DEREF                      1: include_filters
                                14      LOAD_DEREF                      0: exclude_filters
                                16      LOAD_FAST                       1: trace
                                18      CALL_METHOD                     3
                                20      POP_JUMP_IF_FALSE               2 (to 4)
                                22      LOAD_FAST                       1: trace
                                24      LIST_APPEND                     2
                                26      JUMP_ABSOLUTE                   2 (to 4)
                                28      RETURN_VALUE                    
                        'Snapshot.filter_traces.<locals>.<listcomp>'
                    [Disassembly]
                        0       LOAD_GLOBAL                     0: isinstance
                        2       LOAD_FAST                       1: filters
                        4       LOAD_GLOBAL                     1: Iterable
                        6       CALL_FUNCTION                   2
                        8       POP_JUMP_IF_TRUE                14 (to 28)
                        10      LOAD_GLOBAL                     2: TypeError
                        12      LOAD_CONST                      1: 'filters must be a list of filters, not %s'
                        14      LOAD_GLOBAL                     3: type
                        16      LOAD_FAST                       1: filters
                        18      CALL_FUNCTION                   1
                        20      LOAD_ATTR                       4: __name__
                        22      BINARY_MODULO                   
                        24      CALL_FUNCTION                   1
                        26      RAISE_VARARGS                   1
                        28      LOAD_FAST                       1: filters
                        30      POP_JUMP_IF_FALSE               53 (to 106)
                        32      BUILD_LIST                      0
                        34      STORE_DEREF                     1: include_filters
                        36      BUILD_LIST                      0
                        38      STORE_DEREF                     0: exclude_filters
                        40      LOAD_FAST                       1: filters
                        42      GET_ITER                        
                        44      FOR_ITER                        16 (to 78)
                        46      STORE_FAST                      2: trace_filter
                        48      LOAD_FAST                       2: trace_filter
                        50      LOAD_ATTR                       5: inclusive
                        52      POP_JUMP_IF_FALSE               33 (to 66)
                        54      LOAD_DEREF                      1: include_filters
                        56      LOAD_METHOD                     6: append
                        58      LOAD_FAST                       2: trace_filter
                        60      CALL_METHOD                     1
                        62      POP_TOP                         
                        64      JUMP_ABSOLUTE                   22 (to 44)
                        66      LOAD_DEREF                      0: exclude_filters
                        68      LOAD_METHOD                     6: append
                        70      LOAD_FAST                       2: trace_filter
                        72      CALL_METHOD                     1
                        74      POP_TOP                         
                        76      JUMP_ABSOLUTE                   22 (to 44)
                        78      LOAD_CLOSURE                    0: exclude_filters
                        80      LOAD_CLOSURE                    1: include_filters
                        82      LOAD_CLOSURE                    2: self
                        84      BUILD_TUPLE                     3
                        86      LOAD_CONST                      2: <CODE> <listcomp>
                        88      LOAD_CONST                      3: 'Snapshot.filter_traces.<locals>.<listcomp>'
                        90      MAKE_FUNCTION                   8
                        92      LOAD_DEREF                      2: self
                        94      LOAD_ATTR                       7: traces
                        96      LOAD_ATTR                       8: _traces
                        98      GET_ITER                        
                        100     CALL_FUNCTION                   1
                        102     STORE_FAST                      3: new_traces
                        104     JUMP_FORWARD                    6 (to 118)
                        106     LOAD_DEREF                      2: self
                        108     LOAD_ATTR                       7: traces
                        110     LOAD_ATTR                       8: _traces
                        112     LOAD_METHOD                     9: copy
                        114     CALL_METHOD                     0
                        116     STORE_FAST                      3: new_traces
                        118     LOAD_GLOBAL                     10: Snapshot
                        120     LOAD_FAST                       3: new_traces
                        122     LOAD_DEREF                      2: self
                        124     LOAD_ATTR                       11: traceback_limit
                        126     CALL_FUNCTION                   2
                        128     RETURN_VALUE                    
                'Snapshot.filter_traces'
                [Code]
                    File Name: tracemalloc.py
                    Object Name: _group_by
                    Arg Count: 3
                    Pos Only Arg Count: 0
                    KW Only Arg Count: 0
                    Locals: 14
                    Stack Size: 10
                    Flags: 0x00000043 (CO_OPTIMIZED | CO_NEWLOCALS | CO_NOFREE)
                    [Names]
                        'ValueError'
                        'traces'
                        '_traces'
                        'KeyError'
                        'Traceback'
                        'size'
                        'count'
                        'Statistic'
                    [Var Names]
                        'self'
                        'key_type'
                        'cumulative'
                        'stats'
                        'tracebacks'
                        'trace'
                        'domain'
                        'size'
                        'trace_traceback'
                        'total_nframe'
                        'traceback'
                        'frames'
                        'stat'
                        'frame'
                    [Free Vars]
                    [Cell Vars]
                    [Constants]
                        None
                        (
                            'traceback'
                            'filename'
                            'lineno'
                        )
                        'unknown key_type: %r'
                        (
                            'lineno'
                            'filename'
                        )
                        'cumulative mode cannot by used with key type %r'
                        'traceback'
                        'lineno'
                        1
                        0
                    [Disassembly]
                        0       LOAD_FAST                       1: key_type
                        2       LOAD_CONST                      1: ('traceback', 'filename', 'lineno')
                        4       CONTAINS_OP                     1 (not in)
                        6       POP_JUMP_IF_FALSE               11 (to 22)
                        8       LOAD_GLOBAL                     0: ValueError
                        10      LOAD_CONST                      2: 'unknown key_type: %r'
                        12      LOAD_FAST                       1: key_type
                        14      BUILD_TUPLE                     1
                        16      BINARY_MODULO                   
                        18      CALL_FUNCTION                   1
                        20      RAISE_VARARGS                   1
                        22      LOAD_FAST                       2: cumulative
                        24      POP_JUMP_IF_FALSE               23 (to 46)
                        26      LOAD_FAST                       1: key_type
                        28      LOAD_CONST                      3: ('lineno', 'filename')
                        30      CONTAINS_OP                     1 (not in)
                        32      POP_JUMP_IF_FALSE               23 (to 46)
                        34      LOAD_GLOBAL                     0: ValueError
                        36      LOAD_CONST                      4: 'cumulative mode cannot by used with key type %r'
                        38      LOAD_FAST                       1: key_type
                        40      BINARY_MODULO                   
                        42      CALL_FUNCTION                   1
                        44      RAISE_VARARGS                   1
                        46      BUILD_MAP                       0
                        48      STORE_FAST                      3: stats
                        50      BUILD_MAP                       0
                        52      STORE_FAST                      4: tracebacks
                        54      LOAD_FAST                       2: cumulative
                        56      POP_JUMP_IF_TRUE                132 (to 264)
                        58      LOAD_FAST                       0: self
                        60      LOAD_ATTR                       1: traces
                        62      LOAD_ATTR                       2: _traces
                        64      GET_ITER                        
                        66      FOR_ITER                        96 (to 260)
                        68      STORE_FAST                      5: trace
                        70      LOAD_FAST                       5: trace
                        72      UNPACK_SEQUENCE                 4
                        74      STORE_FAST                      6: domain
                        76      STORE_FAST                      7: size
                        78      STORE_FAST                      8: trace_traceback
                        80      STORE_FAST                      9: total_nframe
                        82      SETUP_FINALLY                   6 (to 96)
                        84      LOAD_FAST                       4: tracebacks
                        86      LOAD_FAST                       8: trace_traceback
                        88      BINARY_SUBSCR                   
                        90      STORE_FAST                      10: traceback
                        92      POP_BLOCK                       
                        94      JUMP_FORWARD                    44 (to 184)
                        96      DUP_TOP                         
                        98      LOAD_GLOBAL                     3: KeyError
                        100     JUMP_IF_NOT_EXC_MATCH           91 (to 182)
                        102     POP_TOP                         
                        104     POP_TOP                         
                        106     POP_TOP                         
                        108     LOAD_FAST                       1: key_type
                        110     LOAD_CONST                      5: 'traceback'
                        112     COMPARE_OP                      2 (==)
                        114     POP_JUMP_IF_FALSE               61 (to 122)
                        116     LOAD_FAST                       8: trace_traceback
                        118     STORE_FAST                      11: frames
                        120     JUMP_FORWARD                    20 (to 162)
                        122     LOAD_FAST                       1: key_type
                        124     LOAD_CONST                      6: 'lineno'
                        126     COMPARE_OP                      2 (==)
                        128     POP_JUMP_IF_FALSE               72 (to 144)
                        130     LOAD_FAST                       8: trace_traceback
                        132     LOAD_CONST                      0: None
                        134     LOAD_CONST                      7: 1
                        136     BUILD_SLICE                     2
                        138     BINARY_SUBSCR                   
                        140     STORE_FAST                      11: frames
                        142     JUMP_FORWARD                    9 (to 162)
                        144     LOAD_FAST                       8: trace_traceback
                        146     LOAD_CONST                      8: 0
                        148     BINARY_SUBSCR                   
                        150     LOAD_CONST                      8: 0
                        152     BINARY_SUBSCR                   
                        154     LOAD_CONST                      8: 0
                        156     BUILD_TUPLE                     2
                        158     BUILD_TUPLE                     1
                        160     STORE_FAST                      11: frames
                        162     LOAD_GLOBAL                     4: Traceback
                        164     LOAD_FAST                       11: frames
                        166     CALL_FUNCTION                   1
                        168     STORE_FAST                      10: traceback
                        170     LOAD_FAST                       10: traceback
                        172     LOAD_FAST                       4: tracebacks
                        174     LOAD_FAST                       8: trace_traceback
                        176     STORE_SUBSCR                    
                        178     POP_EXCEPT                      
                        180     JUMP_FORWARD                    1 (to 184)
                        182     RERAISE                         0
                        184     SETUP_FINALLY                   20 (to 226)
                        186     LOAD_FAST                       3: stats
                        188     LOAD_FAST                       10: traceback
                        190     BINARY_SUBSCR                   
                        192     STORE_FAST                      12: stat
                        194     LOAD_FAST                       12: stat
                        196     DUP_TOP                         
                        198     LOAD_ATTR                       5: size
                        200     LOAD_FAST                       7: size
                        202     INPLACE_ADD                     
                        204     ROT_TWO                         
                        206     STORE_ATTR                      5: size
                        208     LOAD_FAST                       12: stat
                        210     DUP_TOP                         
                        212     LOAD_ATTR                       6: count
                        214     LOAD_CONST                      7: 1
                        216     INPLACE_ADD                     
                        218     ROT_TWO                         
                        220     STORE_ATTR                      6: count
                        222     POP_BLOCK                       
                        224     JUMP_ABSOLUTE                   33 (to 66)
                        226     DUP_TOP                         
                        228     LOAD_GLOBAL                     3: KeyError
                        230     JUMP_IF_NOT_EXC_MATCH           129 (to 258)
                        232     POP_TOP                         
                        234     POP_TOP                         
                        236     POP_TOP                         
                        238     LOAD_GLOBAL                     7: Statistic
                        240     LOAD_FAST                       10: traceback
                        242     LOAD_FAST                       7: size
                        244     LOAD_CONST                      7: 1
                        246     CALL_FUNCTION                   3
                        248     LOAD_FAST                       3: stats
                        250     LOAD_FAST                       10: traceback
                        252     STORE_SUBSCR                    
                        254     POP_EXCEPT                      
                        256     JUMP_ABSOLUTE                   33 (to 66)
                        258     RERAISE                         0
                        260     LOAD_FAST                       3: stats
                        262     RETURN_VALUE                    
                        264     LOAD_FAST                       0: self
                        266     LOAD_ATTR                       1: traces
                        268     LOAD_ATTR                       2: _traces
                        270     GET_ITER                        
                        272     FOR_ITER                        89 (to 452)
                        274     STORE_FAST                      5: trace
                        276     LOAD_FAST                       5: trace
                        278     UNPACK_SEQUENCE                 4
                        280     STORE_FAST                      6: domain
                        282     STORE_FAST                      7: size
                        284     STORE_FAST                      8: trace_traceback
                        286     STORE_FAST                      9: total_nframe
                        288     LOAD_FAST                       8: trace_traceback
                        290     GET_ITER                        
                        292     FOR_ITER                        78 (to 450)
                        294     STORE_FAST                      13: frame
                        296     SETUP_FINALLY                   6 (to 310)
                        298     LOAD_FAST                       4: tracebacks
                        300     LOAD_FAST                       13: frame
                        302     BINARY_SUBSCR                   
                        304     STORE_FAST                      10: traceback
                        306     POP_BLOCK                       
                        308     JUMP_FORWARD                    32 (to 374)
                        310     DUP_TOP                         
                        312     LOAD_GLOBAL                     3: KeyError
                        314     JUMP_IF_NOT_EXC_MATCH           186 (to 372)
                        316     POP_TOP                         
                        318     POP_TOP                         
                        320     POP_TOP                         
                        322     LOAD_FAST                       1: key_type
                        324     LOAD_CONST                      6: 'lineno'
                        326     COMPARE_OP                      2 (==)
                        328     POP_JUMP_IF_FALSE               169 (to 338)
                        330     LOAD_FAST                       13: frame
                        332     BUILD_TUPLE                     1
                        334     STORE_FAST                      11: frames
                        336     JUMP_FORWARD                    7 (to 352)
                        338     LOAD_FAST                       13: frame
                        340     LOAD_CONST                      8: 0
                        342     BINARY_SUBSCR                   
                        344     LOAD_CONST                      8: 0
                        346     BUILD_TUPLE                     2
                        348     BUILD_TUPLE                     1
                        350     STORE_FAST                      11: frames
                        352     LOAD_GLOBAL                     4: Traceback
                        354     LOAD_FAST                       11: frames
                        356     CALL_FUNCTION                   1
                        358     STORE_FAST                      10: traceback
                        360     LOAD_FAST                       10: traceback
                        362     LOAD_FAST                       4: tracebacks
                        364     LOAD_FAST                       13: frame
                        366     STORE_SUBSCR                    
                        368     POP_EXCEPT                      
                        370     JUMP_FORWARD                    1 (to 374)
                        372     RERAISE                         0
                        374     SETUP_FINALLY                   20 (to 416)
                        376     LOAD_FAST                       3: stats
                        378     LOAD_FAST                       10: traceback
                        380     BINARY_SUBSCR                   
                        382     STORE_FAST                      12: stat
                        384     LOAD_FAST                       12: stat
                        386     DUP_TOP                         
                        388     LOAD_ATTR                       5: size
                        390     LOAD_FAST                       7: size
                        392     INPLACE_ADD                     
                        394     ROT_TWO                         
                        396     STORE_ATTR                      5: size
                        398     LOAD_FAST                       12: stat
                        400     DUP_TOP                         
                        402     LOAD_ATTR                       6: count
                        404     LOAD_CONST                      7: 1
                        406     INPLACE_ADD                     
                        408     ROT_TWO                         
                        410     STORE_ATTR                      6: count
                        412     POP_BLOCK                       
                        414     JUMP_ABSOLUTE                   146 (to 292)
                        416     DUP_TOP                         
                        418     LOAD_GLOBAL                     3: KeyError
                        420     JUMP_IF_NOT_EXC_MATCH           224 (to 448)
                        422     POP_TOP                         
                        424     POP_TOP                         
                        426     POP_TOP                         
                        428     LOAD_GLOBAL                     7: Statistic
                        430     LOAD_FAST                       10: traceback
                        432     LOAD_FAST                       7: size
                        434     LOAD_CONST                      7: 1
                        436     CALL_FUNCTION                   3
                        438     LOAD_FAST                       3: stats
                        440     LOAD_FAST                       10: traceback
                        442     STORE_SUBSCR                    
                        444     POP_EXCEPT                      
                        446     JUMP_ABSOLUTE                   146 (to 292)
                        448     RERAISE                         0
                        450     JUMP_ABSOLUTE                   136 (to 272)
                        452     LOAD_FAST                       3: stats
                        454     RETURN_VALUE                    
                'Snapshot._group_by'
                False
                [Code]
                    File Name: tracemalloc.py
                    Object Name: statistics
                    Arg Count: 3
                    Pos Only Arg Count: 0
                    KW Only Arg Count: 0
                    Locals: 5
                    Stack Size: 4
                    Flags: 0x00000043 (CO_OPTIMIZED | CO_NEWLOCALS | CO_NOFREE)
                    [Names]
                        '_group_by'
                        'list'
                        'values'
                        'sort'
                        'Statistic'
                        '_sort_key'
                    [Var Names]
                        'self'
                        'key_type'
                        'cumulative'
                        'grouped'
                        'statistics'
                    [Free Vars]
                    [Cell Vars]
                    [Constants]
                        '\n        Group statistics by key_type. Return a sorted list of Statistic\n        instances.\n        '
                        True
                        (
                            'reverse'
                            'key'
                        )
                    [Disassembly]
                        0       LOAD_FAST                       0: self
                        2       LOAD_METHOD                     0: _group_by
                        4       LOAD_FAST                       1: key_type
                        6       LOAD_FAST                       2: cumulative
                        8       CALL_METHOD                     2
                        10      STORE_FAST                      3: grouped
                        12      LOAD_GLOBAL                     1: list
                        14      LOAD_FAST                       3: grouped
                        16      LOAD_METHOD                     2: values
                        18      CALL_METHOD                     0
                        20      CALL_FUNCTION                   1
                        22      STORE_FAST                      4: statistics
                        24      LOAD_FAST                       4: statistics
                        26      LOAD_ATTR                       3: sort
                        28      LOAD_CONST                      1: True
                        30      LOAD_GLOBAL                     4: Statistic
                        32      LOAD_ATTR                       5: _sort_key
                        34      LOAD_CONST                      2: ('reverse', 'key')
                        36      CALL_FUNCTION_KW                2
                        38      POP_TOP                         
                        40      LOAD_FAST                       4: statistics
                        42      RETURN_VALUE                    
                'Snapshot.statistics'
                [Code]
                    File Name: tracemalloc.py
                    Object Name: compare_to
                    Arg Count: 4
                    Pos Only Arg Count: 0
                    KW Only Arg Count: 0
                    Locals: 7
                    Stack Size: 4
                    Flags: 0x00000043 (CO_OPTIMIZED | CO_NEWLOCALS | CO_NOFREE)
                    [Names]
                        '_group_by'
                        '_compare_grouped_stats'
                        'sort'
                        'StatisticDiff'
                        '_sort_key'
                    [Var Names]
                        'self'
                        'old_snapshot'
                        'key_type'
                        'cumulative'
                        'new_group'
                        'old_group'
                        'statistics'
                    [Free Vars]
                    [Cell Vars]
                    [Constants]
                        '\n        Compute the differences with an old snapshot old_snapshot. Get\n        statistics as a sorted list of StatisticDiff instances, grouped by\n        group_by.\n        '
                        True
                        (
                            'reverse'
                            'key'
                        )
                    [Disassembly]
                        0       LOAD_FAST                       0: self
                        2       LOAD_METHOD                     0: _group_by
                        4       LOAD_FAST                       2: key_type
                        6       LOAD_FAST                       3: cumulative
                        8       CALL_METHOD                     2
                        10      STORE_FAST                      4: new_group
                        12      LOAD_FAST                       1: old_snapshot
                        14      LOAD_METHOD                     0: _group_by
                        16      LOAD_FAST                       2: key_type
                        18      LOAD_FAST                       3: cumulative
                        20      CALL_METHOD                     2
                        22      STORE_FAST                      5: old_group
                        24      LOAD_GLOBAL                     1: _compare_grouped_stats
                        26      LOAD_FAST                       5: old_group
                        28      LOAD_FAST                       4: new_group
                        30      CALL_FUNCTION                   2
                        32      STORE_FAST                      6: statistics
                        34      LOAD_FAST                       6: statistics
                        36      LOAD_ATTR                       2: sort
                        38      LOAD_CONST                      1: True
                        40      LOAD_GLOBAL                     3: StatisticDiff
                        42      LOAD_ATTR                       4: _sort_key
                        44      LOAD_CONST                      2: ('reverse', 'key')
                        46      CALL_FUNCTION_KW                2
                        48      POP_TOP                         
                        50      LOAD_FAST                       6: statistics
                        52      RETURN_VALUE                    
                'Snapshot.compare_to'
                None
                (
                    False
                )
            [Disassembly]
                0       LOAD_NAME                       0: __name__
                2       STORE_NAME                      1: __module__
                4       LOAD_CONST                      0: 'Snapshot'
                6       STORE_NAME                      2: __qualname__
                8       LOAD_CONST                      1: '\n    Snapshot of traces of memory blocks allocated by Python.\n    '
                10      STORE_NAME                      3: __doc__
                12      LOAD_CONST                      2: <CODE> __init__
                14      LOAD_CONST                      3: 'Snapshot.__init__'
                16      MAKE_FUNCTION                   0
                18      STORE_NAME                      4: __init__
                20      LOAD_CONST                      4: <CODE> dump
                22      LOAD_CONST                      5: 'Snapshot.dump'
                24      MAKE_FUNCTION                   0
                26      STORE_NAME                      5: dump
                28      LOAD_NAME                       6: staticmethod
                30      LOAD_CONST                      6: <CODE> load
                32      LOAD_CONST                      7: 'Snapshot.load'
                34      MAKE_FUNCTION                   0
                36      CALL_FUNCTION                   1
                38      STORE_NAME                      7: load
                40      LOAD_CONST                      8: <CODE> _filter_trace
                42      LOAD_CONST                      9: 'Snapshot._filter_trace'
                44      MAKE_FUNCTION                   0
                46      STORE_NAME                      8: _filter_trace
                48      LOAD_CONST                      10: <CODE> filter_traces
                50      LOAD_CONST                      11: 'Snapshot.filter_traces'
                52      MAKE_FUNCTION                   0
                54      STORE_NAME                      9: filter_traces
                56      LOAD_CONST                      12: <CODE> _group_by
                58      LOAD_CONST                      13: 'Snapshot._group_by'
                60      MAKE_FUNCTION                   0
                62      STORE_NAME                      10: _group_by
                64      LOAD_CONST                      20: (False,)
                66      LOAD_CONST                      15: <CODE> statistics
                68      LOAD_CONST                      16: 'Snapshot.statistics'
                70      MAKE_FUNCTION                   1
                72      STORE_NAME                      11: statistics
                74      LOAD_CONST                      20: (False,)
                76      LOAD_CONST                      17: <CODE> compare_to
                78      LOAD_CONST                      18: 'Snapshot.compare_to'
                80      MAKE_FUNCTION                   1
                82      STORE_NAME                      12: compare_to
                84      LOAD_CONST                      19: None
                86      RETURN_VALUE                    
        'Snapshot'
        [Code]
            File Name: tracemalloc.py
            Object Name: take_snapshot
            Arg Count: 0
            Pos Only Arg Count: 0
            KW Only Arg Count: 0
            Locals: 2
            Stack Size: 3
            Flags: 0x00000043 (CO_OPTIMIZED | CO_NEWLOCALS | CO_NOFREE)
            [Names]
                'is_tracing'
                'RuntimeError'
                '_get_traces'
                'get_traceback_limit'
                'Snapshot'
            [Var Names]
                'traces'
                'traceback_limit'
            [Free Vars]
            [Cell Vars]
            [Constants]
                '\n    Take a snapshot of traces of memory blocks allocated by Python.\n    '
                'the tracemalloc module must be tracing memory allocations to take a snapshot'
            [Disassembly]
                0       LOAD_GLOBAL                     0: is_tracing
                2       CALL_FUNCTION                   0
                4       POP_JUMP_IF_TRUE                7 (to 14)
                6       LOAD_GLOBAL                     1: RuntimeError
                8       LOAD_CONST                      1: 'the tracemalloc module must be tracing memory allocations to take a snapshot'
                10      CALL_FUNCTION                   1
                12      RAISE_VARARGS                   1
                14      LOAD_GLOBAL                     2: _get_traces
                16      CALL_FUNCTION                   0
                18      STORE_FAST                      0: traces
                20      LOAD_GLOBAL                     3: get_traceback_limit
                22      CALL_FUNCTION                   0
                24      STORE_FAST                      1: traceback_limit
                26      LOAD_GLOBAL                     4: Snapshot
                28      LOAD_FAST                       0: traces
                30      LOAD_FAST                       1: traceback_limit
                32      CALL_FUNCTION                   2
                34      RETURN_VALUE                    
        'take_snapshot'
    [Disassembly]
        0       LOAD_CONST                      0: 0
        2       LOAD_CONST                      1: ('Sequence', 'Iterable')
        4       IMPORT_NAME                     0: collections.abc
        6       IMPORT_FROM                     1: Sequence
        8       STORE_NAME                      1: Sequence
        10      IMPORT_FROM                     2: Iterable
        12      STORE_NAME                      2: Iterable
        14      POP_TOP                         
        16      LOAD_CONST                      0: 0
        18      LOAD_CONST                      2: ('total_ordering',)
        20      IMPORT_NAME                     3: functools
        22      IMPORT_FROM                     4: total_ordering
        24      STORE_NAME                      4: total_ordering
        26      POP_TOP                         
        28      LOAD_CONST                      0: 0
        30      LOAD_CONST                      3: None
        32      IMPORT_NAME                     5: fnmatch
        34      STORE_NAME                      5: fnmatch
        36      LOAD_CONST                      0: 0
        38      LOAD_CONST                      3: None
        40      IMPORT_NAME                     6: linecache
        42      STORE_NAME                      6: linecache
        44      LOAD_CONST                      0: 0
        46      LOAD_CONST                      3: None
        48      IMPORT_NAME                     7: os.path
        50      STORE_NAME                      8: os
        52      LOAD_CONST                      0: 0
        54      LOAD_CONST                      3: None
        56      IMPORT_NAME                     9: pickle
        58      STORE_NAME                      9: pickle
        60      LOAD_CONST                      0: 0
        62      LOAD_CONST                      4: ('*',)
        64      IMPORT_NAME                     10: _tracemalloc
        66      IMPORT_STAR                     
        68      LOAD_CONST                      0: 0
        70      LOAD_CONST                      5: ('_get_object_traceback', '_get_traces')
        72      IMPORT_NAME                     10: _tracemalloc
        74      IMPORT_FROM                     11: _get_object_traceback
        76      STORE_NAME                      11: _get_object_traceback
        78      IMPORT_FROM                     12: _get_traces
        80      STORE_NAME                      12: _get_traces
        82      POP_TOP                         
        84      LOAD_CONST                      6: <CODE> _format_size
        86      LOAD_CONST                      7: '_format_size'
        88      MAKE_FUNCTION                   0
        90      STORE_NAME                      13: _format_size
        92      LOAD_BUILD_CLASS                
        94      LOAD_CONST                      8: <CODE> Statistic
        96      LOAD_CONST                      9: 'Statistic'
        98      MAKE_FUNCTION                   0
        100     LOAD_CONST                      9: 'Statistic'
        102     CALL_FUNCTION                   2
        104     STORE_NAME                      14: Statistic
        106     LOAD_BUILD_CLASS                
        108     LOAD_CONST                      10: <CODE> StatisticDiff
        110     LOAD_CONST                      11: 'StatisticDiff'
        112     MAKE_FUNCTION                   0
        114     LOAD_CONST                      11: 'StatisticDiff'
        116     CALL_FUNCTION                   2
        118     STORE_NAME                      15: StatisticDiff
        120     LOAD_CONST                      12: <CODE> _compare_grouped_stats
        122     LOAD_CONST                      13: '_compare_grouped_stats'
        124     MAKE_FUNCTION                   0
        126     STORE_NAME                      16: _compare_grouped_stats
        128     LOAD_NAME                       4: total_ordering
        130     LOAD_BUILD_CLASS                
        132     LOAD_CONST                      14: <CODE> Frame
        134     LOAD_CONST                      15: 'Frame'
        136     MAKE_FUNCTION                   0
        138     LOAD_CONST                      15: 'Frame'
        140     CALL_FUNCTION                   2
        142     CALL_FUNCTION                   1
        144     STORE_NAME                      17: Frame
        146     LOAD_NAME                       4: total_ordering
        148     LOAD_BUILD_CLASS                
        150     LOAD_CONST                      16: <CODE> Traceback
        152     LOAD_CONST                      17: 'Traceback'
        154     MAKE_FUNCTION                   0
        156     LOAD_CONST                      17: 'Traceback'
        158     LOAD_NAME                       1: Sequence
        160     CALL_FUNCTION                   3
        162     CALL_FUNCTION                   1
        164     STORE_NAME                      18: Traceback
        166     LOAD_CONST                      18: <CODE> get_object_traceback
        168     LOAD_CONST                      19: 'get_object_traceback'
        170     MAKE_FUNCTION                   0
        172     STORE_NAME                      19: get_object_traceback
        174     LOAD_BUILD_CLASS                
        176     LOAD_CONST                      20: <CODE> Trace
        178     LOAD_CONST                      21: 'Trace'
        180     MAKE_FUNCTION                   0
        182     LOAD_CONST                      21: 'Trace'
        184     CALL_FUNCTION                   2
        186     STORE_NAME                      20: Trace
        188     LOAD_BUILD_CLASS                
        190     LOAD_CONST                      22: <CODE> _Traces
        192     LOAD_CONST                      23: '_Traces'
        194     MAKE_FUNCTION                   0
        196     LOAD_CONST                      23: '_Traces'
        198     LOAD_NAME                       1: Sequence
        200     CALL_FUNCTION                   3
        202     STORE_NAME                      21: _Traces
        204     LOAD_CONST                      24: <CODE> _normalize_filename
        206     LOAD_CONST                      25: '_normalize_filename'
        208     MAKE_FUNCTION                   0
        210     STORE_NAME                      22: _normalize_filename
        212     LOAD_BUILD_CLASS                
        214     LOAD_CONST                      26: <CODE> BaseFilter
        216     LOAD_CONST                      27: 'BaseFilter'
        218     MAKE_FUNCTION                   0
        220     LOAD_CONST                      27: 'BaseFilter'
        222     CALL_FUNCTION                   2
        224     STORE_NAME                      23: BaseFilter
        226     LOAD_BUILD_CLASS                
        228     LOAD_CONST                      28: <CODE> Filter
        230     LOAD_CONST                      29: 'Filter'
        232     MAKE_FUNCTION                   0
        234     LOAD_CONST                      29: 'Filter'
        236     LOAD_NAME                       23: BaseFilter
        238     CALL_FUNCTION                   3
        240     STORE_NAME                      24: Filter
        242     LOAD_BUILD_CLASS                
        244     LOAD_CONST                      30: <CODE> DomainFilter
        246     LOAD_CONST                      31: 'DomainFilter'
        248     MAKE_FUNCTION                   0
        250     LOAD_CONST                      31: 'DomainFilter'
        252     LOAD_NAME                       23: BaseFilter
        254     CALL_FUNCTION                   3
        256     STORE_NAME                      25: DomainFilter
        258     LOAD_BUILD_CLASS                
        260     LOAD_CONST                      32: <CODE> Snapshot
        262     LOAD_CONST                      33: 'Snapshot'
        264     MAKE_FUNCTION                   0
        266     LOAD_CONST                      33: 'Snapshot'
        268     CALL_FUNCTION                   2
        270     STORE_NAME                      26: Snapshot
        272     LOAD_CONST                      34: <CODE> take_snapshot
        274     LOAD_CONST                      35: 'take_snapshot'
        276     MAKE_FUNCTION                   0
        278     STORE_NAME                      27: take_snapshot
        280     LOAD_CONST                      3: None
        282     RETURN_VALUE                    
